Workbook

Sheet Notes
A1: KGR — WORKING PAPER SALES, SKU AND SEGMENT GROSS PROFIT — August 2026 (v7, rebuilt)
A3: Purpose | B3: Gross profit per segment (RPA, Trading) March–August 2026, with the 10 August invoices that have no SI moved to the segment of their items and re-costed; a GP-margin waterfall July→August per segment (NMG method); August sales split by vintage; SKU, form, karkas-size, by-product and batch economics; why the RPA loses money.
A4: FS basis | B4: Accounting team's FS_KGR_Aug_2026.xlsx (Agt 26 GL incl. the undated adjustment rows at the bottom; PL - Performance; TB Accurate). "Aug as booked" in Segment GP ties to PL - Performance to the rupiah.
A5: Sources | B5: inventory_valuation_terbaru.xls (1 Jul–31 Aug, printed 23 Sep 23.25; 95 items, 993 lines) + 25 dormant items from WP v6 · sales_details.xls via WP v6 (invoiced kg/revenue; invoices unchanged) · Dika's schedule of the 4 MJ invoices (item, kg, cost 31/8) · FS_KGR_Aug_2026.xlsx sheet Sheet1 (10 invoices) · GL live-bird PIs for batch cost.
A6: Colour code | B6: Blue = input from a source file. Black = formula. Green = link to another sheet. Yellow fill = assumption you may edit (segment of the 6 invoices, line prices, cost-of-sales overrides, kg-share override, benchmarks, lemak price).
A7: How the unbilled invoices are treated | B7: As booked, all 10 sit in RPA (4101013 in "Revenue - LB", all HPP in 5100004 and credited to 1104003). Adj-1 moves each line to the segment of its item code at the HPP booked; Adj-2 re-costs the 4 MJ invoices at the moving average on the SJ date (MA Engine replay B); Adj-3 is the knock-on on later DOs once those kg leave stock. The 6 invoices without item detail keep the HPP booked in Agt 26 (FS version of 24 Sep: 226 and 311 re-estimated) and follow Dika's segment tag in Agt 26 (201, 232 RPA; 226 Trading); untagged 243, 257, 311 sit in RPA — change per invoice in Unbilled column N.
A8: MA Engine | B8: Replays Accurate's moving average row by row. Replay A (as posted) reproduces Accurate's DO cost to Rp7 in total — proof the engine is Accurate's own method. Adjustments (IA) and job rows keep booked value. DO KGR26.00231 (JLB0822) left more than the stock on hand; Accurate's cost is kept. Changing a kg in Unbilled recalculates B. Changing an item code or SJ date needs the engine regenerated (row position).
A9: Vintage method | B9: Accurate keeps no lots. Point estimate = FIFO row by row in MA Engine (cols AE–AM): each outflow takes the stock on hand at 1 Jul first, then July receipts, then August receipts, and carries the HPP Accurate booked on that DO split by kg. Buckets therefore add up to booked HPP — no moving-average bar (NMG style, Dika 24 Sep). Lower bound = new stock first at the item's average booked HPP/kg. Revenue per item = its kg share of the invoiced revenue of its SKU-form (karkas: size-form) + its unbilled lines.
A10: Batch data | B10: Ops costing file 202608_Data_COGS_LB.xlsx (12 Pot_ISA sheets, Pot_ISA20 REV for 20 Aug) in I_Batch_Ops: output per item ties to Accurate receipts per batch; cost ties to GRN. Batch Economics shows output, yields on live-bird kg (ops definition) and on processed kg, value at the ops price list and at August realised prices, karkas size mix and cost/kg by product (ops allocation vs Accurate). 8 Aug: 323.8 kg usus discarded (limbah), not in stock.
A11: Waterfall method | B11: Bar = August revenue share of the bucket × (bucket product margin − July GP margin). Moving-average effect, cost of sales others and items outside the split (revenue with no SI, invoices without item) are separate bars. Consolidated: rate effect per segment + segment mix + unknown-segment invoices. Bars add exactly (Tally).
A12: Cost of sales others | B12: Expedition (5100002/07/10) and blasting (5100009) are inside Gross Profit in the accounting mapping. Segment GP shows them SEPARATELY at KGR level (Dika, 24 Sep): segment gross profit = revenue − product COGS. Sheet COS Others still attributes every journal line by vendor/narrative (shared lines by kg) as information; switch COS Others B3 to Yes to push that attribution into the segments. Storage, handling and packaging stay below GP as in the FS.
A13: What changed vs WP v6 | B13: (1) FS basis = accounting FS. (2) Accurate re-costed August: JLB DO −Rp31.7m, karkas/by-product split at GRN, TRD −Rp6.7m. (3) GR26080012 now has 5,641.6 kg karkas (1,577.7 kg Karkas 1.0 Fresh Premium posted) — its yield is normal; the old −Rp61m "short batch" driver is gone. (4) 10 unbilled invoices added (6 new by Dika). (5) Segment GP, vintage and waterfall added. (6) Stock Carry-over replaced by Vintage. (7) Months now tie to GL at SKU level: three GL-only rows in Data SKU — Apr RPA Rp22.1m SI COGS not matched to a DO (v6), Jul Trading Rp9.2m PI26070074 kulit posted straight to COGS (no GRN, no sale — for accounting), Jul RPA −Rp81k MJ26070009. Stock ties to GL at 30 Jun, 31 Jul and 31 Aug.
A14: KPI vs budget | B14: Sheet RPA KPI vs Budget: 19 driver KPIs (volume, live bird, process, output mix, prices, conversion, result per kg) with the budget value copied from KGR_-_Budget_Manufacturing_v3.xlsx (sheet!cell shown, blue) and August actual linked to this WP. Budget models the own plant from Sep-26; August was still maklon at ISA — conversion and utilisation are shown for direction only.
... A16: Sheet map | B16: MTM Bridge (KPI matrix, revenue bridge, customers, margin drivers, spread, opex/NIBT) → Segment GP → GP Waterfall → Vintage → Unbilled → RPA Loss Bridge → Batch Economics → SKU Summary → Karkas Detail → By-product → Fresh vs Frozen → Monthly by SKU → COS Others → Recon to FS → Deck Feed → Data SKU → MA Engine → I_Sales_Inv (invoice × customer) → I_Items → I_GL.

Sheet Tally
A1: TALLY — every total checked against its source
A2: Status OK = within tolerance. "OK (known)" = the difference equals a documented item (Expected column). BREAK = investigate.
A4: # | B4: Area | C4: Check | D4: WP value | E4: Reference | F4: Difference | G4: Expected (known item) | H4: Tol. | I4: Status | J4: Note
A5: 1 | B5: MA Engine | C5: Replay A reproduces Accurate DO cost (sum A − booked) | D5: ='MA Engine'!AB1111 -> -6.6701382 | E5: 0 | F5: =D5-E5 -> -6.6701382 | G5: 0 | H5: 10 | I5: =IF(ABS(F5-G5)<=H5,IF(G5=0,"OK","OK (known)"),"BREAK") -> OK | J5: Moving average replayed row by row; DO KGR26.00231 (JLB0822, stock negative in Accurate) kept at booked cost
A6: 2 | B6: MA Engine | C6: Closing kg per engine A = Accurate closing kg (sum of abs diff) | D6: =SUMPRODUCT(ABS(I_Items!$M$5:$M$133-I_Items!$K$5:$K$133)) -> 1.779768e-11 | E6: 0 | F6: =D6-E6 -> 1.779768e-11 | G6: 0 | H6: 0.05 | I6: =IF(ABS(F6-G6)<=H6,IF(G6=0,"OK","OK (known)"),"BREAK") -> OK
A7: 3 | B7: MA Engine | C7: Closing Rp per engine A = Accurate closing Rp (sum of abs diff) | D7: =SUMPRODUCT(ABS(I_Items!$N$5:$N$133-I_Items!$L$5:$L$133)) -> 12.561372 | E7: 0 | F7: =D7-E7 -> 12.561372 | G7: 0 | H7: 20 | I7: =IF(ABS(F7-G7)<=H7,IF(G7=0,"OK","OK (known)"),"BREAK") -> OK
A8: 4 | B8: MA Engine | C8: Aug DO cost RPA excl. DO 257 (engine A) = GL 5100004+05 less unbilled HPP | D8: =SUMIFS('MA Engine'!$S$6:$S$1110,'MA Engine'!$C$6:$C$1110,"RPA",'MA Engine'!$H$6:$H$1110,8,'MA Engine'!$I$6:$I$1110,"DO",'MA Engine'!$P$6:$P$1110,"<>Y") -> 2.1713713e+09 | E8: =I_GL!I19+I_GL!I20-Unbilled!L17 -> 2.1713713e+09 | F8: =D8-E8 -> 0.78266716 | G8: 0 | H8: 10 | I8: =IF(ABS(F8-G8)<=H8,IF(G8=0,"OK","OK (known)"),"BREAK") -> OK
A9: 5 | B9: MA Engine | C9: Aug DO cost Trading (engine A) = GL 5100011 | D9: =SUMIFS('MA Engine'!$S$6:$S$1110,'MA Engine'!$C$6:$C$1110,"Trading",'MA Engine'!$H$6:$H$1110,8,'MA Engine'!$I$6:$I$1110,"DO") -> 4.835721e+09 | E9: =I_GL!I26 -> 4.835721e+09 | F9: =D9-E9 -> -5.5488672 | G9: 0 | H9: 10 | I9: =IF(ABS(F9-G9)<=H9,IF(G9=0,"OK","OK (known)"),"BREAK") -> OK
A10: 6 | B10: MA Engine | C10: DO KGR26.00257 cost = GL 1104002 In Transit 31 Aug | D10: =SUMIFS('MA Engine'!$S$6:$S$1110,'MA Engine'!$P$6:$P$1110,"Y") -> 91185802 | E10: =I_GL!M6 -> 91185802 | F10: =D10-E10 -> -0.15293424 | G10: 0 | H10: 1 | I10: =IF(ABS(F10-G10)<=H10,IF(G10=0,"OK","OK (known)"),"BREAK") -> OK
A11: 7 | B11: MA Engine | C11: Aug receipts RPA (engine) = live-bird GRN value in GL (2103011) | D11: =SUMIFS('MA Engine'!$L$6:$L$1110,'MA Engine'!$C$6:$C$1110,"RPA",'MA Engine'!$H$6:$H$1110,8,'MA Engine'!$I$6:$I$1110,"Receipt") -> 3.8401048e+09 | E11: ='Batch Economics'!H18 -> 3.8401048e+09 | F11: =D11-E11 -> -0.009999752 | G11: 0 | H11: 1 | I11: =IF(ABS(F11-G11)<=H11,IF(G11=0,"OK","OK (known)"),"BREAK") -> OK
A12: 8 | B12: MA Engine | C12: Unbilled lines: stock goes negative after posting (count) | D12: =COUNTIF(Unbilled!$S$22:$S$38,"STOCK MINUS") -> 4 | E12: 0 | F12: =D12-E12 -> 4 | G12: 4 | H12: 0 | I12: =IF(ABS(F12-G12)<=H12,IF(G12=0,"OK","OK (known)"),"BREAK") -> OK (known) | J12: TRD0021, JLB1857, TRD0027, TRD0024 — item code to be confirmed (Unbilled open item 2)
A13: 9 | B13: Data SKU | C13: Aug invoiced kg = engine DO kg excl. DO 257 | D13: =SUMIFS('Data SKU'!$F$5:$F$116,'Data SKU'!$D$5:$D$116,8,'Data SKU'!$N$5:$N$116,"Invoiced") -> 236674.21 | E13: =SUMIFS('MA Engine'!$W$6:$W$1110,'MA Engine'!$H$6:$H$1110,8,'MA Engine'!$I$6:$I$1110,"DO",'MA Engine'!$P$6:$P$1110,"<>Y",'MA Engine'!$C$6:$C$1110,"<>Other") -> 236674.21 | F13: =D13-E13 -> 0 | G13: 0 | H13: 0.5 | I13: =IF(ABS(F13-G13)<=H13,IF(G13=0,"OK","OK (known)"),"BREAK") -> OK
A14: 10 | B14: Data SKU | C14: Aug invoiced revenue RPA = GL revenue RPA | D14: =SUMIFS('Data SKU'!$G$5:$G$116,'Data SKU'!$A$5:$A$116,"RPA",'Data SKU'!$D$5:$D$116,8,'Data SKU'!$N$5:$N$116,"Invoiced") -> 2104033270 | E14: =-SUMIFS(I_GL!$I$5:$I$29,I_GL!$C$5:$C$29,"Rev RPA") -> 2104662870 | F14: =D14-E14 -> -629600 | G14: -629600 | H14: 1 | I14: =IF(ABS(F14-G14)<=H14,IF(G14=0,"OK","OK (known)"),"BREAK") -> OK (known) | J14: Sampel usus/limbah April Rp629,600 reclassed from DP to 4101007 in Aug — no SI, so not in sales_details
A15: 11 | B15: Data SKU | C15: Aug invoiced revenue Trading = GL revenue Trading | D15: =SUMIFS('Data SKU'!$G$5:$G$116,'Data SKU'!$A$5:$A$116,"Trading",'Data SKU'!$D$5:$D$116,8,'Data SKU'!$N$5:$N$116,"Invoiced") -> 5.3173228e+09 | E15: =-SUMIFS(I_GL!$I$5:$I$29,I_GL!$C$5:$C$29,"Rev Trading") -> 5317322794 | F15: =D15-E15 -> -0.19999981 | G15: 0 | H15: 1 | I15: =IF(ABS(F15-G15)<=H15,IF(G15=0,"OK","OK (known)"),"BREAK") -> OK
A16: 12 | B16: Data SKU | C16: Mar-26 RPA: SKU revenue = Segment GP revenue | D16: =SUMIFS('Data SKU'!$G$5:$G$116,'Data SKU'!$A$5:$A$116,"RPA",'Data SKU'!$D$5:$D$116,3) -> 190035900 | E16: ='Segment GP'!D6 -> 190035900 | F16: =D16-E16 -> 0 | G16: 0 | H16: 1 | I16: =IF(ABS(F16-G16)<=H16,IF(G16=0,"OK","OK (known)"),"BREAK") -> OK
A17: 13 | B17: Data SKU | C17: Mar-26 RPA: SKU product cost = Segment GP COGS | D17: =SUMIFS('Data SKU'!$H$5:$H$116,'Data SKU'!$A$5:$A$116,"RPA",'Data SKU'!$D$5:$D$116,3) -> 1.7515188e+08 | E17: =-'Segment GP'!D13 -> 1.7515188e+08 | F17: =D17-E17 -> 0 | G17: 0 | H17: 10 | I17: =IF(ABS(F17-G17)<=H17,IF(G17=0,"OK","OK (known)"),"BREAK") -> OK
A18: 14 | B18: Data SKU | C18: Mar-26 Trading: SKU revenue = Segment GP revenue | D18: =SUMIFS('Data SKU'!$G$5:$G$116,'Data SKU'!$A$5:$A$116,"Trading",'Data SKU'!$D$5:$D$116,3) -> 0 | E18: ='Segment GP'!D7 -> 0 | F18: =D18-E18 -> 0 | G18: 0 | H18: 1 | I18: =IF(ABS(F18-G18)<=H18,IF(G18=0,"OK","OK (known)"),"BREAK") -> OK
A19: 15 | B19: Data SKU | C19: Mar-26 Trading: SKU product cost = Segment GP COGS | D19: =SUMIFS('Data SKU'!$H$5:$H$116,'Data SKU'!$A$5:$A$116,"Trading",'Data SKU'!$D$5:$D$116,3) -> 0 | E19: =-'Segment GP'!D14 -> 0 | F19: =D19-E19 -> 0 | G19: 0 | H19: 10 | I19: =IF(ABS(F19-G19)<=H19,IF(G19=0,"OK","OK (known)"),"BREAK") -> OK
A20: 16 | B20: Data SKU | C20: Apr-26 RPA: SKU revenue = Segment GP revenue | D20: =SUMIFS('Data SKU'!$G$5:$G$116,'Data SKU'!$A$5:$A$116,"RPA",'Data SKU'!$D$5:$D$116,4) -> 646041120 | E20: ='Segment GP'!E6 -> 646041120 | F20: =D20-E20 -> 0 | G20: 0 | H20: 1 | I20: =IF(ABS(F20-G20)<=H20,IF(G20=0,"OK","OK (known)"),"BREAK") -> OK
A21: 17 | B21: Data SKU | C21: Apr-26 RPA: SKU product cost = Segment GP COGS | D21: =SUMIFS('Data SKU'!$H$5:$H$116,'Data SKU'!$A$5:$A$116,"RPA",'Data SKU'!$D$5:$D$116,4) -> 5.6053189e+08 | E21: =-'Segment GP'!E13 -> 5.6053189e+08 | F21: =D21-E21 -> 0 | G21: 0 | H21: 10 | I21: =IF(ABS(F21-G21)<=H21,IF(G21=0,"OK","OK (known)"),"BREAK") -> OK
A22: 18 | B22: Data SKU | C22: Apr-26 Trading: SKU revenue = Segment GP revenue | D22: =SUMIFS('Data SKU'!$G$5:$G$116,'Data SKU'!$A$5:$A$116,"Trading",'Data SKU'!$D$5:$D$116,4) -> 149939860 | E22: ='Segment GP'!E7 -> 149939860 | F22: =D22-E22 -> 0 | G22: 0 | H22: 1 | I22: =IF(ABS(F22-G22)<=H22,IF(G22=0,"OK","OK (known)"),"BREAK") -> OK
A23: 19 | B23: Data SKU | C23: Apr-26 Trading: SKU product cost = Segment GP COGS | D23: =SUMIFS('Data SKU'!$H$5:$H$116,'Data SKU'!$A$5:$A$116,"Trading",'Data SKU'!$D$5:$D$116,4) -> 141127370 | E23: =-'Segment GP'!E14 -> 141127370 | F23: =D23-E23 -> 0 | G23: 0 | H23: 10 | I23: =IF(ABS(F23-G23)<=H23,IF(G23=0,"OK","OK (known)"),"BREAK") -> OK
A24: 20 | B24: Data SKU | C24: May-26 RPA: SKU revenue = Segment GP revenue | D24: =SUMIFS('Data SKU'!$G$5:$G$116,'Data SKU'!$A$5:$A$116,"RPA",'Data SKU'!$D$5:$D$116,5) -> 1402180774 | E24: ='Segment GP'!F6 -> 1402180774 | F24: =D24-E24 -> 0 | G24: 0 | H24: 1 | I24: =IF(ABS(F24-G24)<=H24,IF(G24=0,"OK","OK (known)"),"BREAK") -> OK
A25: 21 | B25: Data SKU | C25: May-26 RPA: SKU product cost = Segment GP COGS | D25: =SUMIFS('Data SKU'!$H$5:$H$116,'Data SKU'!$A$5:$A$116,"RPA",'Data SKU'!$D$5:$D$116,5) -> 1.5619249e+09 | E25: =-'Segment GP'!F13 -> 1.5619249e+09 | F25: =D25-E25 -> 0.65999985 | G25: 0 | H25: 10 | I25: =IF(ABS(F25-G25)<=H25,IF(G25=0,"OK","OK (known)"),"BREAK") -> OK
A26: 22 | B26: Data SKU | C26: May-26 Trading: SKU revenue = Segment GP revenue | D26: =SUMIFS('Data SKU'!$G$5:$G$116,'Data SKU'!$A$5:$A$116,"Trading",'Data SKU'!$D$5:$D$116,5) -> 44220195 | E26: ='Segment GP'!F7 -> 44220195 | F26: =D26-E26 -> 0 | G26: 0 | H26: 1 | I26: =IF(ABS(F26-G26)<=H26,IF(G26=0,"OK","OK (known)"),"BREAK") -> OK
A27: 23 | B27: Data SKU | C27: May-26 Trading: SKU product cost = Segment GP COGS | D27: =SUMIFS('Data SKU'!$H$5:$H$116,'Data SKU'!$A$5:$A$116,"Trading",'Data SKU'!$D$5:$D$116,5) -> 40506060 | E27: =-'Segment GP'!F14 -> 40506060 | F27: =D27-E27 -> 0 | G27: 0 | H27: 10 | I27: =IF(ABS(F27-G27)<=H27,IF(G27=0,"OK","OK (known)"),"BREAK") -> OK
A28: 24 | B28: Data SKU | C28: Jun-26 RPA: SKU revenue = Segment GP revenue | D28: =SUMIFS('Data SKU'!$G$5:$G$116,'Data SKU'!$A$5:$A$116,"RPA",'Data SKU'!$D$5:$D$116,6) -> 5.0030944e+08 | E28: ='Segment GP'!G6 -> 5.0030944e+08 | F28: =D28-E28 -> 0 | G28: 0 | H28: 1 | I28: =IF(ABS(F28-G28)<=H28,IF(G28=0,"OK","OK (known)"),"BREAK") -> OK
A29: 25 | B29: Data SKU | C29: Jun-26 RPA: SKU product cost = Segment GP COGS | D29: =SUMIFS('Data SKU'!$H$5:$H$116,'Data SKU'!$A$5:$A$116,"RPA",'Data SKU'!$D$5:$D$116,6) -> 4.8423077e+08 | E29: =-'Segment GP'!G13 -> 4.8423077e+08 | F29: =D29-E29 -> 0.0099999905 | G29: 0 | H29: 10 | I29: =IF(ABS(F29-G29)<=H29,IF(G29=0,"OK","OK (known)"),"BREAK") -> OK
A30: 26 | B30: Data SKU | C30: Jun-26 Trading: SKU revenue = Segment GP revenue | D30: =SUMIFS('Data SKU'!$G$5:$G$116,'Data SKU'!$A$5:$A$116,"Trading",'Data SKU'!$D$5:$D$116,6) -> 922384240 | E30: ='Segment GP'!G7 -> 922384240 | F30: =D30-E30 -> 0 | G30: 0 | H30: 1 | I30: =IF(ABS(F30-G30)<=H30,IF(G30=0,"OK","OK (known)"),"BREAK") -> OK
A31: 27 | B31: Data SKU | C31: Jun-26 Trading: SKU product cost = Segment GP COGS | D31: =SUMIFS('Data SKU'!$H$5:$H$116,'Data SKU'!$A$5:$A$116,"Trading",'Data SKU'!$D$5:$D$116,6) -> 8.077824e+08 | E31: =-'Segment GP'!G14 -> 8.077824e+08 | F31: =D31-E31 -> -0.19000006 | G31: 0 | H31: 10 | I31: =IF(ABS(F31-G31)<=H31,IF(G31=0,"OK","OK (known)"),"BREAK") -> OK
A32: 28 | B32: Data SKU | C32: Jul-26 RPA: SKU revenue = Segment GP revenue | D32: =SUMIFS('Data SKU'!$G$5:$G$116,'Data SKU'!$A$5:$A$116,"RPA",'Data SKU'!$D$5:$D$116,7) -> 246532160 | E32: ='Segment GP'!H6 -> 246532160 | F32: =D32-E32 -> 0 | G32: 0 | H32: 1 | I32: =IF(ABS(F32-G32)<=H32,IF(G32=0,"OK","OK (known)"),"BREAK") -> OK
A33: 29 | B33: Data SKU | C33: Jul-26 RPA: SKU product cost = Segment GP COGS | D33: =SUMIFS('Data SKU'!$H$5:$H$116,'Data SKU'!$A$5:$A$116,"RPA",'Data SKU'!$D$5:$D$116,7) -> 2.4804879e+08 | E33: =-'Segment GP'!H13 -> 2.4804879e+08 | F33: =D33-E33 -> 0.079999954 | G33: 0 | H33: 10 | I33: =IF(ABS(F33-G33)<=H33,IF(G33=0,"OK","OK (known)"),"BREAK") -> OK
A34: 30 | B34: Data SKU | C34: Jul-26 Trading: SKU revenue = Segment GP revenue | D34: =SUMIFS('Data SKU'!$G$5:$G$116,'Data SKU'!$A$5:$A$116,"Trading",'Data SKU'!$D$5:$D$116,7) -> 2.8764258e+09 | E34: ='Segment GP'!H7 -> 2.8764258e+09 | F34: =D34-E34 -> 0 | G34: 0 | H34: 1 | I34: =IF(ABS(F34-G34)<=H34,IF(G34=0,"OK","OK (known)"),"BREAK") -> OK
A35: 31 | B35: Data SKU | C35: Jul-26 Trading: SKU product cost = Segment GP COGS | D35: =SUMIFS('Data SKU'!$H$5:$H$116,'Data SKU'!$A$5:$A$116,"Trading",'Data SKU'!$D$5:$D$116,7) -> 2.3922533e+09 | E35: =-'Segment GP'!H14 -> 2.3922533e+09 | F35: =D35-E35 -> -0.61000013 | G35: 0 | H35: 10 | I35: =IF(ABS(F35-G35)<=H35,IF(G35=0,"OK","OK (known)"),"BREAK") -> OK
A36: 32 | B36: Data SKU | C36: Aug-26 RPA: SKU revenue = Segment GP revenue (corrected) | D36: =SUMIFS('Data SKU'!$G$5:$G$116,'Data SKU'!$A$5:$A$116,"RPA",'Data SKU'!$D$5:$D$116,8) -> 2.691687e+09 | E36: ='Segment GP'!M6 -> 2.691687e+09 | F36: =D36-E36 -> 0 | G36: 0 | H36: 1 | I36: =IF(ABS(F36-G36)<=H36,IF(G36=0,"OK","OK (known)"),"BREAK") -> OK
A37: 33 | B37: Data SKU | C37: Aug-26 RPA: SKU product cost = Segment GP COGS (corrected) | D37: =SUMIFS('Data SKU'!$H$5:$H$116,'Data SKU'!$A$5:$A$116,"RPA",'Data SKU'!$D$5:$D$116,8) -> 2.7551492e+09 | E37: =-'Segment GP'!M13 -> 2.7551492e+09 | F37: =D37-E37 -> 0.78266764 | G37: 0 | H37: 10 | I37: =IF(ABS(F37-G37)<=H37,IF(G37=0,"OK","OK (known)"),"BREAK") -> OK | J37: Aug: MA replay reproduces Accurate within Rp7
A38: 34 | B38: Data SKU | C38: Aug-26 Trading: SKU revenue = Segment GP revenue (corrected) | D38: =SUMIFS('Data SKU'!$G$5:$G$116,'Data SKU'!$A$5:$A$116,"Trading",'Data SKU'!$D$5:$D$116,8) -> 5.6700739e+09 | E38: ='Segment GP'!M7 -> 5.6700739e+09 | F38: =D38-E38 -> -0.19999981 | G38: 0 | H38: 1 | I38: =IF(ABS(F38-G38)<=H38,IF(G38=0,"OK","OK (known)"),"BREAK") -> OK
A39: 35 | B39: Data SKU | C39: Aug-26 Trading: SKU product cost = Segment GP COGS (corrected) | D39: =SUMIFS('Data SKU'!$H$5:$H$116,'Data SKU'!$A$5:$A$116,"Trading",'Data SKU'!$D$5:$D$116,8) -> 5.2001277e+09 | E39: =-'Segment GP'!M14 -> 5.2001277e+09 | F39: =D39-E39 -> -5.5488672 | G39: 0 | H39: 10 | I39: =IF(ABS(F39-G39)<=H39,IF(G39=0,"OK","OK (known)"),"BREAK") -> OK | J39: Aug: MA replay reproduces Accurate within Rp7
A40: 36 | B40: Recon to FS | C40: Inventory 30 Jun: GL − subledger, RPA | D40: ='Recon to FS'!C43 -> 1 | E40: 0 | F40: =D40-E40 -> 1 | G40: 0 | H40: 1 | I40: =IF(ABS(F40-G40)<=H40,IF(G40=0,"OK","OK (known)"),"BREAK") -> OK
A41: 37 | B41: Recon to FS | C41: Inventory 30 Jun: GL − subledger, Trading + packaging | D41: ='Recon to FS'!D43+'Recon to FS'!E43 -> 0 | E41: 0 | F41: =D41-E41 -> 0 | G41: 0 | H41: 5 | I41: =IF(ABS(F41-G41)<=H41,IF(G41=0,"OK","OK (known)"),"BREAK") -> OK | J41: Rupiah rounding of the moving average
A42: 38 | B42: Recon to FS | C42: Inventory 31 Jul: GL − subledger, RPA | D42: ='Recon to FS'!C47 -> 81362 | E42: 0 | F42: =D42-E42 -> 81362 | G42: 81362 | H42: 1 | I42: =IF(ABS(F42-G42)<=H42,IF(G42=0,"OK","OK (known)"),"BREAK") -> OK (known) | J42: MJ26070009
A43: 39 | B43: Recon to FS | C43: Inventory 31 Jul: GL − subledger, Trading + packaging | D43: ='Recon to FS'!D47+'Recon to FS'!E47 -> -2 | E43: 0 | F43: =D43-E43 -> -2 | G43: 0 | H43: 5 | I43: =IF(ABS(F43-G43)<=H43,IF(G43=0,"OK","OK (known)"),"BREAK") -> OK | J43: Rupiah rounding of the moving average
A44: 40 | B44: Data SKU | C44: Aug corrected cost − as booked = unbilled re-cost + DO re-cost | D44: ='Data SKU'!H117-'Data SKU'!O117 -> 571620.34 | E44: =Unbilled!Q39-'Segment GP'!L34 -> 571620.34 | F44: =D44-E44 -> -2.3283064e-08 | G44: 0 | H44: 1 | I44: =IF(ABS(F44-G44)<=H44,IF(G44=0,"OK","OK (known)"),"BREAK") -> OK
A45: 41 | B45: Unbilled | C45: Σ invoice value = GL 4101013 Unbilled Revenue | D45: =Unbilled!H17 -> 939775239 | E45: =-SUMIFS(I_GL!$I$5:$I$29,I_GL!$C$5:$C$29,"Rev Unbilled") -> 939775239 | F45: =D45-E45 -> 0 | G45: 0 | H45: 1 | I45: =IF(ABS(F45-G45)<=H45,IF(G45=0,"OK","OK (known)"),"BREAK") -> OK
A46: 42 | B46: Unbilled | C46: Σ HPP booked = MJ26080015–18 + undated adj rows on 5100004 | D46: =Unbilled!L17 -> 947613074 | E46: =525580657.48+I_GL!J19 -> 947613074 | F46: =D46-E46 -> 0 | G46: 0 | H46: 1 | I46: =IF(ABS(F46-G46)<=H46,IF(G46=0,"OK","OK (known)"),"BREAK") -> OK
A47: 43 | B47: Unbilled | C47: Σ short-paid = GL 1103123 Unbilled AR remaining 31 Aug | D47: =Unbilled!J17 -> 2377756 | E47: 2377756 | F47: =D47-E47 -> 0 | G47: 0 | H47: 1 | I47: =IF(ABS(F47-G47)<=H47,IF(G47=0,"OK","OK (known)"),"BREAK") -> OK | J47: GL 1103123 balance per Agt 26
A48: 44 | B48: Unbilled | C48: Item lines kg = ops kg for the 4 MJ invoices | D48: =SUM(Unbilled!O7:O10) -> 15717.46 | E48: =Unbilled!G18 -> 15717.46 | F48: =D48-E48 -> 0 | G48: 0 | H48: 0.01 | I48: =IF(ABS(F48-G48)<=H48,IF(G48=0,"OK","OK (known)"),"BREAK") -> OK
A49: 45 | B49: Unbilled | C49: Item line revenue = invoice value (4 MJ) | D49: =Unbilled!U39 -> 531755505 | E49: =Unbilled!H18 -> 531755505 | F49: =D49-E49 -> 0 | G49: 0 | H49: 1 | I49: =IF(ABS(F49-G49)<=H49,IF(G49=0,"OK","OK (known)"),"BREAK") -> OK
A50: 46 | B50: Segment GP | C50: Adj-1 nets to nil — revenue | D50: ='Segment GP'!J9 -> 0 | E50: 0 | F50: =D50-E50 -> 0 | G50: 0 | H50: 1 | I50: =IF(ABS(F50-G50)<=H50,IF(G50=0,"OK","OK (known)"),"BREAK") -> OK
A51: 47 | B51: Segment GP | C51: Adj-1 nets to nil — COGS | D51: ='Segment GP'!J16 -> 0.38989997 | E51: 0 | F51: =D51-E51 -> 0.38989997 | G51: 0 | H51: 1 | I51: =IF(ABS(F51-G51)<=H51,IF(G51=0,"OK","OK (known)"),"BREAK") -> OK
A52: 48 | B52: Segment GP | C52: GP as booked = PL - Performance, Mar–Aug (sum of abs diff) | D52: =SUMPRODUCT(ABS('Segment GP'!D55:I55)) -> 0 | E52: 0 | F52: =D52-E52 -> 0 | G52: 0 | H52: 6 | I52: =IF(ABS(F52-G52)<=H52,IF(G52=0,"OK","OK (known)"),"BREAK") -> OK
A53: 49 | B53: Segment GP | C53: Aug corrected GP = as booked + Adj-2 + Adj-3 | D53: ='Segment GP'!M34 -> 3.0613814e+08 | E53: ='Segment GP'!I34+'Segment GP'!K34+'Segment GP'!L34 -> 3.0613814e+08 | F53: =D53-E53 -> 0.38990027 | G53: 0 | H53: 1 | I53: =IF(ABS(F53-G53)<=H53,IF(G53=0,"OK","OK (known)"),"BREAK") -> OK
A54: 50 | B54: Segment GP | C54: RPA + Trading + not in a segment = total GP, Mar–Aug | D54: =SUMPRODUCT(ABS('Segment GP'!D57:N57)) -> 0 | E54: 0 | F54: =D54-E54 -> 0 | G54: 0 | H54: 1 | I54: =IF(ABS(F54-G54)<=H54,IF(G54=0,"OK","OK (known)"),"BREAK") -> OK
A55: 51 | B55: Segment GP | C55: Aug corrected revenue = accounting revenue (reclass only) | D55: ='Segment GP'!M9 -> 8361760903 | E55: ='Segment GP'!I9 -> 8361760903 | F55: =D55-E55 -> 0 | G55: 0 | H55: 1 | I55: =IF(ABS(F55-G55)<=H55,IF(G55=0,"OK","OK (known)"),"BREAK") -> OK
A56: 52 | B56: COS Others | C56: Journal lines = GL 5100002/07/09/10, Mar–Aug | D56: =SUMPRODUCT(ABS('COS Others'!B20:G20)) -> 0 | E56: 0 | F56: =D56-E56 -> 0 | G56: 0 | H56: 1 | I56: =IF(ABS(F56-G56)<=H56,IF(G56=0,"OK","OK (known)"),"BREAK") -> OK
A57: 53 | B57: COS Others | C57: RPA + Trading = total, Mar–Aug | D57: =SUMPRODUCT(ABS('COS Others'!B18:G18)) -> 0 | E57: 0 | F57: =D57-E57 -> 0 | G57: 0 | H57: 1 | I57: =IF(ABS(F57-G57)<=H57,IF(G57=0,"OK","OK (known)"),"BREAK") -> OK
A58: 54 | B58: Vintage | C58: RPA: vintage kg = sales kg with item detail | D58: =Vintage!H10 -> 86484.24 | E58: =SUMIFS(Vintage!$P$36:$P$127,Vintage!$C$36:$C$127,"RPA") -> 86484.24 | F58: =D58-E58 -> 0 | G58: 0 | H58: 0.5 | I58: =IF(ABS(F58-G58)<=H58,IF(G58=0,"OK","OK (known)"),"BREAK") -> OK
A59: 55 | B59: Vintage | C59: RPA: vintage revenue = Data SKU Aug revenue with item detail | D59: =Vintage!I10 -> 2.3735642e+09 | E59: =SUMIFS('Data SKU'!$G$5:$G$116,'Data SKU'!$A$5:$A$116,"RPA",'Data SKU'!$D$5:$D$116,8,'Data SKU'!$B$5:$B$116,"<>Belum ada detail item",'Data SKU'!$N$5:$N$116,"<>GL only (no DO)") -> 2.3735642e+09 | F59: =D59-E59 -> 0 | G59: 0 | H59: 1 | I59: =IF(ABS(F59-G59)<=H59,IF(G59=0,"OK","OK (known)"),"BREAK") -> OK
A60: 56 | B60: Vintage | C60: RPA: layer cost + MA effect = Data SKU Aug cost with item detail | D60: =Vintage!J10 -> 2.442288e+09 | E60: =SUMIFS('Data SKU'!$H$5:$H$116,'Data SKU'!$A$5:$A$116,"RPA",'Data SKU'!$D$5:$D$116,8,'Data SKU'!$B$5:$B$116,"<>Belum ada detail item",'Data SKU'!$N$5:$N$116,"<>GL only (no DO)") -> 2.442288e+09 | F60: =D60-E60 -> 0 | G60: 0 | H60: 1 | I60: =IF(ABS(F60-G60)<=H60,IF(G60=0,"OK","OK (known)"),"BREAK") -> OK
A61: 57 | B61: Vintage | C61: Trading: vintage kg = sales kg with item detail | D61: =Vintage!H16 -> 165907.43 | E61: =SUMIFS(Vintage!$P$36:$P$127,Vintage!$C$36:$C$127,"Trading") -> 165907.43 | F61: =D61-E61 -> 0 | G61: 0 | H61: 0.5 | I61: =IF(ABS(F61-G61)<=H61,IF(G61=0,"OK","OK (known)"),"BREAK") -> OK
A62: 58 | B62: Vintage | C62: Trading: vintage revenue = Data SKU Aug revenue with item detail | D62: =Vintage!I16 -> 5.5795474e+09 | E62: =SUMIFS('Data SKU'!$G$5:$G$116,'Data SKU'!$A$5:$A$116,"Trading",'Data SKU'!$D$5:$D$116,8,'Data SKU'!$B$5:$B$116,"<>Belum ada detail item",'Data SKU'!$N$5:$N$116,"<>GL only (no DO)") -> 5.5795474e+09 | F62: =D62-E62 -> 0.19999981 | G62: 0 | H62: 1 | I62: =IF(ABS(F62-G62)<=H62,IF(G62=0,"OK","OK (known)"),"BREAK") -> OK
A63: 59 | B63: Vintage | C63: Trading: layer cost + MA effect = Data SKU Aug cost with item detail | D63: =Vintage!J16 -> 5.0909565e+09 | E63: =SUMIFS('Data SKU'!$H$5:$H$116,'Data SKU'!$A$5:$A$116,"Trading",'Data SKU'!$D$5:$D$116,8,'Data SKU'!$B$5:$B$116,"<>Belum ada detail item",'Data SKU'!$N$5:$N$116,"<>GL only (no DO)") -> 5.0909565e+09 | F63: =D63-E63 -> 0 | G63: 0 | H63: 1 | I63: =IF(ABS(F63-G63)<=H63,IF(G63=0,"OK","OK (known)"),"BREAK") -> OK
A64: 60 | B64: GP Waterfall | C64: RPA: bars add to corrected Aug margin (FIFO) | D64: ='GP Waterfall'!C23 -> 0 | E64: 0 | F64: =D64-E64 -> 0 | G64: 0 | H64: 1e-07 | I64: =IF(ABS(F64-G64)<=H64,IF(G64=0,"OK","OK (known)"),"BREAK") -> OK
A65: 61 | B65: GP Waterfall | C65: RPA: bars add to corrected Aug margin (lower bound) | D65: ='GP Waterfall'!D23 -> 0 | E65: 0 | F65: =D65-E65 -> 0 | G65: 0 | H65: 1e-07 | I65: =IF(ABS(F65-G65)<=H65,IF(G65=0,"OK","OK (known)"),"BREAK") -> OK
A66: 62 | B66: GP Waterfall | C66: Trading: bars add to corrected Aug margin (FIFO) | D66: ='GP Waterfall'!C55 -> 0 | E66: 0 | F66: =D66-E66 -> 0 | G66: 0 | H66: 1e-07 | I66: =IF(ABS(F66-G66)<=H66,IF(G66=0,"OK","OK (known)"),"BREAK") -> OK
A67: 63 | B67: GP Waterfall | C67: Trading: bars add to corrected Aug margin (lower bound) | D67: ='GP Waterfall'!D55 -> 0 | E67: 0 | F67: =D67-E67 -> 0 | G67: 0 | H67: 1e-07 | I67: =IF(ABS(F67-G67)<=H67,IF(G67=0,"OK","OK (known)"),"BREAK") -> OK
A68: 64 | B68: GP Waterfall | C68: RPA: product-group breakdown adds to the vintage bars | D68: =ABS('GP Waterfall'!C33)+ABS('GP Waterfall'!D33)+ABS('GP Waterfall'!E33) -> 0 | E68: 0 | F68: =D68-E68 -> 0 | G68: 0 | H68: 1e-06 | I68: =IF(ABS(F68-G68)<=H68,IF(G68=0,"OK","OK (known)"),"BREAK") -> OK
A69: 65 | B69: GP Waterfall | C69: Trading: product-group breakdown adds to the vintage bars | D69: =ABS('GP Waterfall'!C66)+ABS('GP Waterfall'!D66)+ABS('GP Waterfall'!E66) -> 0 | E69: 0 | F69: =D69-E69 -> 0 | G69: 0 | H69: 1e-06 | I69: =IF(ABS(F69-G69)<=H69,IF(G69=0,"OK","OK (known)"),"BREAK") -> OK
A70: 66 | B70: GP Waterfall | C70: KGR: bars add to corrected Aug margin | D70: ='GP Waterfall'!C77 -> 0 | E70: 0 | F70: =D70-E70 -> 0 | G70: 0 | H70: 1e-07 | I70: =IF(ABS(F70-G70)<=H70,IF(G70=0,"OK","OK (known)"),"BREAK") -> OK
A71: 67 | B71: Karkas Detail | C71: Karkas kg (RPA + Trading, invoiced + unbilled) = Data SKU karkas Aug | D71: ='Karkas Detail'!J27+'Karkas Detail'!J42 -> 151997.96 | E71: =SUMIFS('Data SKU'!$F$5:$F$116,'Data SKU'!$B$5:$B$116,"Karkas",'Data SKU'!$D$5:$D$116,8) -> 151997.8 | F71: =D71-E71 -> 0.16 | G71: 0 | H71: 0.5 | I71: =IF(ABS(F71-G71)<=H71,IF(G71=0,"OK","OK (known)"),"BREAK") -> OK
A72: 68 | B72: Karkas Detail | C72: Karkas revenue = Data SKU karkas Aug | D72: ='Karkas Detail'!K27+'Karkas Detail'!K42 -> 4.9865981e+09 | E72: =SUMIFS('Data SKU'!$G$5:$G$116,'Data SKU'!$B$5:$B$116,"Karkas",'Data SKU'!$D$5:$D$116,8) -> 4.9865981e+09 | F72: =D72-E72 -> 0.19999981 | G72: 0 | H72: 1 | I72: =IF(ABS(F72-G72)<=H72,IF(G72=0,"OK","OK (known)"),"BREAK") -> OK
A73: 69 | B73: Karkas Detail | C73: Karkas cost = Data SKU karkas Aug | D73: ='Karkas Detail'!L27+'Karkas Detail'!L42 -> 4.8845427e+09 | E73: =SUMIFS('Data SKU'!$H$5:$H$116,'Data SKU'!$B$5:$B$116,"Karkas",'Data SKU'!$D$5:$D$116,8) -> 4.8845427e+09 | F73: =D73-E73 -> 0 | G73: 0 | H73: 1 | I73: =IF(ABS(F73-G73)<=H73,IF(G73=0,"OK","OK (known)"),"BREAK") -> OK
A74: 70 | B74: By-product | C74: Restated main-product GP = RPA product GP | D74: ='By-product'!E18 -> 0 | E74: 0 | F74: =D74-E74 -> 0 | G74: 0 | H74: 1 | I74: =IF(ABS(F74-G74)<=H74,IF(G74=0,"OK","OK (known)"),"BREAK") -> OK
A75: 71 | B75: Batch Economics | C75: GRN value per batch = engine receipts (sum of abs diff) | D75: =SUMPRODUCT(ABS('Batch Economics'!S6:S17)) -> 0 | E75: 0 | F75: =D75-E75 -> 0 | G75: 0 | H75: 1 | I75: =IF(ABS(F75-G75)<=H75,IF(G75=0,"OK","OK (known)"),"BREAK") -> OK
A76: 72 | B76: Batch Economics | C76: Ops batch cost = GRN value per batch (sum of abs diff) | D76: =SUMPRODUCT(ABS('Batch Economics'!AZ6:AZ17)) -> 0 | E76: 0 | F76: =D76-E76 -> 0 | G76: 0 | H76: 1 | I76: =IF(ABS(F76-G76)<=H76,IF(G76=0,"OK","OK (known)"),"BREAK") -> OK
A77: 73 | B77: Batch Economics | C77: Ops output stocked = Accurate receipts per batch (sum of abs diff) | D77: =SUMPRODUCT(ABS('Batch Economics'!AO6:AO17)) -> 0 | E77: 0 | F77: =D77-E77 -> 0 | G77: 0 | H77: 0.5 | I77: =IF(ABS(F77-G77)<=H77,IF(G77=0,"OK","OK (known)"),"BREAK") -> OK
A78: 74 | B78: Batch Economics | C78: Ops output lines = ops batch header output | D78: =I_Batch_Ops!J343 -> 121109.8 | E78: =I_Batch_Ops!L17 -> 121109.8 | F78: =D78-E78 -> 0 | G78: 0 | H78: 0.5 | I78: =IF(ABS(F78-G78)<=H78,IF(G78=0,"OK","OK (known)"),"BREAK") -> OK
A79: 75 | B79: Batch Economics | C79: Cost per product at goods receipt = ops allocation (sum of abs diff) | D79: =SUM('Batch Economics'!N82:N95) -> 0 | E79: 0 | F79: =D79-E79 -> 0 | G79: 0 | H79: 5 | I79: =IF(ABS(F79-G79)<=H79,IF(G79=0,"OK","OK (known)"),"BREAK") -> OK
A80: 76 | B80: Batch Economics | C80: Unit economics: per kg bought and per kg processed give the same cost per kg output | D80: ='Batch Economics'!C55 -> 0 | E80: 0 | F80: =D80-E80 -> 0 | G80: 0 | H80: 0.01 | I80: =IF(ABS(F80-G80)<=H80,IF(G80=0,"OK","OK (known)"),"BREAK") -> OK
A81: 77 | B81: Batch Economics | C81: Unit economics: cost per kg output in stock = batch table Rp/kg output | D81: ='Batch Economics'!C54 -> 31792.632 | E81: ='Batch Economics'!AI18 -> 31792.632 | F81: =D81-E81 -> 0 | G81: 0 | H81: 0.01 | I81: =IF(ABS(F81-G81)<=H81,IF(G81=0,"OK","OK (known)"),"BREAK") -> OK
A82: 78 | B82: Batch Ops KPI | C82: Summary: driver shares + other = 100% of the production loss | D82: ='Batch Ops KPI'!I24 -> 1 | E82: 1 | F82: =D82-E82 -> 0 | G82: 0 | H82: 1e-09 | I82: =IF(ABS(F82-G82)<=H82,IF(G82=0,"OK","OK (known)"),"BREAK") -> OK
A83: 79 | B83: RPA KPI vs Budget | C83: Contribution per kg LB = breakeven − LB price (identity) | D83: ='RPA KPI vs Budget'!I30 -> -2766.9971 | E83: ='RPA KPI vs Budget'!I31-'RPA KPI vs Budget'!I11 -> -2766.9971 | F83: =D83-E83 -> 0 | G83: 0 | H83: 0.01 | I83: =IF(ABS(F83-G83)<=H83,IF(G83=0,"OK","OK (known)"),"BREAK") -> OK
A84: 80 | B84: RPA KPI vs Budget | C84: By-product yields add to the by-product yield KPI | D84: ='RPA KPI vs Budget'!I48 -> 0.18160828 | E84: ='RPA KPI vs Budget'!I17 -> 0.18160828 | F84: =D84-E84 -> 0 | G84: 0 | H84: 1e-09 | I84: =IF(ABS(F84-G84)<=H84,IF(G84=0,"OK","OK (known)"),"BREAK") -> OK
A85: 81 | B85: Batch Ops KPI | C85: Total row live bird kg and gap = Batch Economics | D85: ='Batch Ops KPI'!D46+'Batch Ops KPI'!P46*1000000 -> -3.8922846e+08 | E85: ='Batch Economics'!G18+'Batch Economics'!AH18 -> -3.8922846e+08 | F85: =D85-E85 -> 0 | G85: 0 | H85: 1 | I85: =IF(ABS(F85-G85)<=H85,IF(G85=0,"OK","OK (known)"),"BREAK") -> OK
A86: 82 | B86: Batch Economics | C86: Karkas size mix total = karkas kg received | D86: ='Batch Economics'!T77 -> 97158.9 | E86: ='Batch Economics'!V18 -> 97158.9 | F86: =D86-E86 -> 0 | G86: 0 | H86: 0.5 | I86: =IF(ABS(F86-G86)<=H86,IF(G86=0,"OK","OK (known)"),"BREAK") -> OK
A87: 83 | B87: Vintage | C87: RPA: moving-average effect nil (buckets carry booked HPP) | D87: =Vintage!J9 -> 0 | E87: 0 | F87: =D87-E87 -> 0 | G87: 0 | H87: 1 | I87: =IF(ABS(F87-G87)<=H87,IF(G87=0,"OK","OK (known)"),"BREAK") -> OK
A88: 84 | B88: Vintage | C88: Trading: moving-average effect nil (buckets carry booked HPP) | D88: =Vintage!J15 -> 0 | E88: 0 | F88: =D88-E88 -> 0 | G88: 0 | H88: 1 | I88: =IF(ABS(F88-G88)<=H88,IF(G88=0,"OK","OK (known)"),"BREAK") -> OK
A89: 85 | B89: Batch Economics | C89: Output kg = engine JLB receipts kg Aug | D89: ='Batch Economics'!AC18 -> 120786 | E89: =SUMIFS('MA Engine'!$K$6:$K$1110,'MA Engine'!$C$6:$C$1110,"RPA",'MA Engine'!$H$6:$H$1110,8,'MA Engine'!$I$6:$I$1110,"Receipt") -> 120786 | F89: =D89-E89 -> 0 | G89: 0 | H89: 0.5 | I89: =IF(ABS(F89-G89)<=H89,IF(G89=0,"OK","OK (known)"),"BREAK") -> OK
A90: 86 | B90: RPA Loss Bridge | C90: Sales-basis bridge = Vintage RPA product GP | D90: ='RPA Loss Bridge'!C17 -> 0 | E90: 0 | F90: =D90-E90 -> 0 | G90: 0 | H90: 1 | I90: =IF(ABS(F90-G90)<=H90,IF(G90=0,"OK","OK (known)"),"BREAK") -> OK
A91: 87 | B91: RPA Loss Bridge | C91: Production drivers add back to the loss | D91: ='RPA Loss Bridge'!C37 -> 0 | E91: 0 | F91: =D91-E91 -> 0 | G91: 0 | H91: 1 | I91: =IF(ABS(F91-G91)<=H91,IF(G91=0,"OK","OK (known)"),"BREAK") -> OK
A92: 88 | B92: I_Sales_Inv | C92: Jul SI revenue = GL revenue (RPA + Trading) | D92: =SUMIFS(I_Sales_Inv!$E$5:$E$228,I_Sales_Inv!$A$5:$A$228,7)+SUMIFS(I_Sales_Inv!$F$5:$F$228,I_Sales_Inv!$A$5:$A$228,7) -> 3.1229579e+09 | E92: =-SUMIFS(I_GL!$H$5:$H$29,I_GL!$C$5:$C$29,"Rev RPA")-SUMIFS(I_GL!$H$5:$H$29,I_GL!$C$5:$C$29,"Rev Trading") -> 3.1229579e+09 | F92: =D92-E92 -> 0 | G92: 0 | H92: 1 | I92: =IF(ABS(F92-G92)<=H92,IF(G92=0,"OK","OK (known)"),"BREAK") -> OK
A93: 89 | B93: I_Sales_Inv | C93: Aug SI + unbilled revenue = GL revenue less sampel without SI | D93: =SUMIFS(I_Sales_Inv!$E$5:$E$228,I_Sales_Inv!$A$5:$A$228,8)+SUMIFS(I_Sales_Inv!$F$5:$F$228,I_Sales_Inv!$A$5:$A$228,8) -> 8361131303 | E93: =-SUMIFS(I_GL!$I$5:$I$29,I_GL!$C$5:$C$29,"Rev RPA")-SUMIFS(I_GL!$I$5:$I$29,I_GL!$C$5:$C$29,"Rev Trading")-SUMIFS(I_GL!$I$5:$I$29,I_GL!$C$5:$C$29,"Rev Unbilled")-629600 -> 8361131303 | F93: =D93-E93 -> 0 | G93: 0 | H93: 1 | I93: =IF(ABS(F93-G93)<=H93,IF(G93=0,"OK","OK (known)"),"BREAK") -> OK
A94: 90 | B94: I_Sales_Inv | C94: Jul DO kg per SI = Data SKU Jul kg | D94: =SUMIFS(I_Sales_Inv!$H$5:$H$228,I_Sales_Inv!$A$5:$A$228,7)+SUMIFS(I_Sales_Inv!$I$5:$I$228,I_Sales_Inv!$A$5:$A$228,7) -> 99522.71 | E94: =SUMIFS('Data SKU'!$F$5:$F$116,'Data SKU'!$D$5:$D$116,7) -> 99522.71 | F94: =D94-E94 -> 0 | G94: 0 | H94: 0.5 | I94: =IF(ABS(F94-G94)<=H94,IF(G94=0,"OK","OK (known)"),"BREAK") -> OK
A95: 91 | B95: I_Sales_Inv | C95: Aug cost per SI (+unbilled) = Segment GP product COGS less GL-only | D95: =SUMIFS(I_Sales_Inv!$K$5:$K$228,I_Sales_Inv!$A$5:$A$228,8)+SUMIFS(I_Sales_Inv!$L$5:$L$228,I_Sales_Inv!$A$5:$A$228,8) -> 7.9552769e+09 | E95: =-'Segment GP'!M16 -> 7.9552769e+09 | F95: =D95-E95 -> -4.7661982 | G95: 0 | H95: 10 | I95: =IF(ABS(F95-G95)<=H95,IF(G95=0,"OK","OK (known)"),"BREAK") -> OK
A96: 92 | B96: MTM Bridge | C96: Revenue bridge RPA / Trading ties (sum of |Aug total − Segment GP|) | D96: =ABS('MTM Bridge'!I55-'Segment GP'!M6)+ABS('MTM Bridge'!I65-'Segment GP'!M7) -> 0.19999981 | E96: 0 | F96: =D96-E96 -> 0.19999981 | G96: 0 | H96: 1 | I96: =IF(ABS(F96-G96)<=H96,IF(G96=0,"OK","OK (known)"),"BREAK") -> OK
A97: 93 | B97: MTM Bridge | C97: GP margin bridge RPA ties to Segment GP | D97: ='MTM Bridge'!L244-('Segment GP'!M35-'Segment GP'!H35) -> 3.3728981e-11 | E97: 0 | F97: =D97-E97 -> 3.3728981e-11 | G97: 0 | H97: 1e-07 | I97: =IF(ABS(F97-G97)<=H97,IF(G97=0,"OK","OK (known)"),"BREAK") -> OK
A98: 94 | B98: MTM Bridge | C98: GP margin bridge Trading ties to Segment GP | D98: ='MTM Bridge'!L272-('Segment GP'!M36-'Segment GP'!H36) -> 7.3420517e-10 | E98: 0 | F98: =D98-E98 -> 7.3420517e-10 | G98: 0 | H98: 1e-07 | I98: =IF(ABS(F98-G98)<=H98,IF(G98=0,"OK","OK (known)"),"BREAK") -> OK
A99: 95 | B99: MTM Bridge | C99: RPA timing bridge: same-month + carried stock + MA + outside + COS = Aug margin | D99: ='MTM Bridge'!D130 -> 0 | E99: 0 | F99: =D99-E99 -> 0 | G99: 0 | H99: 1e-07 | I99: =IF(ABS(F99-G99)<=H99,IF(G99=0,"OK","OK (known)"),"BREAK") -> OK
A100: 96 | B100: MTM Bridge | C100: RPA same-month economics by SKU = step (a) | D100: ='MTM Bridge'!O147 -> 0 | E100: 0 | F100: =D100-E100 -> 0 | G100: 0 | H100: 1e-07 | I100: =IF(ABS(F100-G100)<=H100,IF(G100=0,"OK","OK (known)"),"BREAK") -> OK
A101: 97 | B101: Vintage | C101: RPA July: vintage revenue = Data SKU Jul invoiced revenue | D101: =Vintage!I24 -> 246532160 | E101: =SUMIFS('Data SKU'!$G$5:$G$116,'Data SKU'!$A$5:$A$116,"RPA",'Data SKU'!$D$5:$D$116,7,'Data SKU'!$N$5:$N$116,"Invoiced") -> 246532160 | F101: =D101-E101 -> 0 | G101: 0 | H101: 1 | I101: =IF(ABS(F101-G101)<=H101,IF(G101=0,"OK","OK (known)"),"BREAK") -> OK
...

Sheet MTM Bridge
A1: KGR — JULY vs AUGUST 2026 (MTM): KPI matrix, revenue bridge, customers, GP-margin drivers, opex and NIBT — the numbers behind the script
A2: Aug = corrected (unbilled at item segment, moving average on SJ date; 6 invoices without item detail in RPA). Opex/NIBT = accounting PL - Performance.
B4: A. KEY FINANCIAL AND PERFORMANCE MATRIX
B5: Description | C5: Unit | D5: Jul-26 | E5: Aug-26 | F5: Variance | G5: Var % | H5: YTD Mar–Aug | N5: Note
B6: Revenue — RPA | C6: IDR mn | D6: ='Segment GP'!H6/1000000 -> 246.53216 | E6: ='Segment GP'!M6/1000000 -> 2691.687 | F6: =IFERROR(E6-D6,0) -> 2445.1548 | G6: =IFERROR(F6/ABS(D6),0) -> 9.9181982 | H6: ='Segment GP'!N6/1000000 -> 5676.7864
B7: Revenue — Trading | C7: IDR mn | D7: ='Segment GP'!H7/1000000 -> 2876.4258 | E7: ='Segment GP'!M7/1000000 -> 5670.0739 | F7: =IFERROR(E7-D7,0) -> 2793.6481 | G7: =IFERROR(F7/ABS(D7),0) -> 0.97122204 | H7: ='Segment GP'!N7/1000000 -> 9663.044
B8: Revenue — total | C8: IDR mn | D8: ='Segment GP'!H9/1000000 -> 3122.9579 | E8: ='Segment GP'!M9/1000000 -> 8361.7609 | F8: =IFERROR(E8-D8,0) -> 5238.803 | G8: =IFERROR(F8/ABS(D8),0) -> 1.6775131 | H8: ='Segment GP'!N9/1000000 -> 15339.83
B9: Gross profit — total | C9: IDR mn | D9: ='Segment GP'!H34/1000000 -> 363.05137 | E9: ='Segment GP'!M34/1000000 -> 306.13814 | F9: =IFERROR(E9-D9,0) -> -56.913236 | G9: =IFERROR(F9/ABS(D9),0) -> -0.15676359 | H9: ='Segment GP'!N34/1000000 -> 389.84162
B10: GP margin — RPA | C10: % | D10: ='Segment GP'!H35 -> -0.0061518649 | E10: ='Segment GP'!M35 -> -0.023577126 | F10: =IFERROR(E10-D10,0) -> -0.017425261 | H10: ='Segment GP'!N35 -> -0.019069074
B11: GP margin — Trading | C11: % | D11: ='Segment GP'!H36 -> 0.16832434 | E11: ='Segment GP'!M36 -> 0.082881853 | F11: =IFERROR(E11-D11,0) -> -0.085442491 | H11: ='Segment GP'!N36 -> 0.11189509
B12: GP margin — total | C12: % | D12: ='Segment GP'!H38 -> 0.11625241 | E12: ='Segment GP'!M38 -> 0.036611683 | F12: =IFERROR(E12-D12,0) -> -0.079640723 | H12: ='Segment GP'!N38 -> 0.025413685
B13: Volume sold — RPA | C13: ton | D13: ='Segment GP'!H40/1000 -> 12.57601 | E13: ='Segment GP'!M40/1000 -> 95.54572 | F13: =IFERROR(E13-D13,0) -> 82.96971 | G13: =IFERROR(F13/ABS(D13),0) -> 6.597459 | H13: ='Segment GP'!N40/1000 -> 239.68339
B14: Volume sold — Trading | C14: ton | D14: ='Segment GP'!H41/1000 -> 86.9467 | E14: ='Segment GP'!M41/1000 -> 168.92498 | F14: =IFERROR(E14-D14,0) -> 81.97828 | G14: =IFERROR(F14/ABS(D14),0) -> 0.94285672 | H14: ='Segment GP'!N41/1000 -> 288.43437
B15: ASP — RPA | C15: Rp/kg | D15: ='Segment GP'!H44 -> 19603.369 | E15: ='Segment GP'!M44 -> 28171.717 | F15: =IFERROR(E15-D15,0) -> 8568.3484 | G15: =IFERROR(F15/ABS(D15),0) -> 0.43708551 | H15: ='Segment GP'!N44 -> 23684.521
B16: ASP — Trading | C16: Rp/kg | D16: ='Segment GP'!H48 -> 33082.633 | E16: ='Segment GP'!M48 -> 33565.633 | F16: =IFERROR(E16-D16,0) -> 482.99993 | G16: =IFERROR(F16/ABS(D16),0) -> 0.014599803 | H16: ='Segment GP'!N48 -> 33501.708
B17: Product cost — Trading | C17: Rp/kg | D17: =-'Segment GP'!H49 -> 27514.021 | E17: =-'Segment GP'!M49 -> 30783.651 | F17: =IFERROR(E17-D17,0) -> 3269.6306 | G17: =IFERROR(F17/ABS(D17),0) -> 0.11883507
B18: Revenue share — RPA | C18: % | D18: ='Segment GP'!H6/'Segment GP'!H9 -> 0.078941876 | E18: ='Segment GP'!M6/'Segment GP'!M9 -> 0.32190432 | F18: =IFERROR(E18-D18,0) -> 0.24296245
B19: RPA: live bird bought | C19: ton | D19: 4.1017 | E19: ='Batch Economics'!G18/1000 -> 140.71904 | F19: =IFERROR(E19-D19,0) -> 136.61734 | G19: =IFERROR(F19/ABS(D19),0) -> 33.307492 | N19: Jul: 1 batch, PI26070053 Deni Jakaria (boneless run)
B20: RPA: live bird price | C20: Rp/kg | D20: 12350 | E20: ='Batch Economics'!L18 -> 24472.12 | F20: =IFERROR(E20-D20,0) -> 12122.12 | G20: =IFERROR(F20/ABS(D20),0) -> 0.98154821 | N20: Jul batch Rp12,350/kg — not a normal broiler price; July GRN output 4,492 kg > 4,102 kg bought (incl. HJA 1,300 kg at Rp0): not usable as a base
B21: RPA: batches slaughtered | C21: # | D21: 1 | E21: 12 | F21: =IFERROR(E21-D21,0) -> 11
B22: RPA: shrink bought → slaughtered | C22: % | D22: n/m | E22: ='Batch Economics'!O18 -> 0.062797756
B23: RPA: karkas yield on slaughter weight | C23: % | D23: n/m | E23: ='Batch Economics'!AD18 -> 0.73670973
B24: RPA: karkas received fresh | C24: % | D24: n/m | E24: ='Batch Economics'!AF18 -> 0.59320762
B25: RPA: inbound freight | C25: Rp/kg LB | D25: n/m | E25: ='Batch Economics'!AK18 -> 1289.0935
B26: RPA: live bird share of batch cost | C26: % | D26: n/m | E26: ='Batch Economics'!K18/'Batch Economics'!H18 -> 0.89677065
B27: Trading: purchases | C27: ton | D27: =SUMIFS('MA Engine'!$K$6:$K$1110,'MA Engine'!$C$6:$C$1110,"Trading",'MA Engine'!$H$6:$H$1110,7,'MA Engine'!$I$6:$I$1110,"Receipt")/1000 -> 106.94875 | E27: =SUMIFS('MA Engine'!$K$6:$K$1110,'MA Engine'!$C$6:$C$1110,"Trading",'MA Engine'!$H$6:$H$1110,8,'MA Engine'!$I$6:$I$1110,"Receipt")/1000 -> 159.27977 | F27: =IFERROR(E27-D27,0) -> 52.33102 | G27: =IFERROR(F27/ABS(D27),0) -> 0.48930932 | N27: Goods receipts into TRD items (MA Engine)
B28: Trading: average purchase price | C28: Rp/kg | D28: =SUMIFS('MA Engine'!$L$6:$L$1110,'MA Engine'!$C$6:$C$1110,"Trading",'MA Engine'!$H$6:$H$1110,7,'MA Engine'!$I$6:$I$1110,"Receipt")/SUMIFS('MA Engine'!$K$6:$K$1110,'MA Engine'!$C$6:$C$1110,"Trading",'MA Engine'!$H$6:$H$1110,7,'MA Engine'!$I$6:$I$1110,"Receipt") -> 26671.872 | E28: =SUMIFS('MA Engine'!$L$6:$L$1110,'MA Engine'!$C$6:$C$1110,"Trading",'MA Engine'!$H$6:$H$1110,8,'MA Engine'!$I$6:$I$1110,"Receipt")/SUMIFS('MA Engine'!$K$6:$K$1110,'MA Engine'!$C$6:$C$1110,"Trading",'MA Engine'!$H$6:$H$1110,8,'MA Engine'!$I$6:$I$1110,"Receipt") -> 29711.405 | F28: =IFERROR(E28-D28,0) -> 3039.5329 | G28: =IFERROR(F28/ABS(D28),0) -> 0.11396024
B29: Trading: karkas share of kg sold | C29: % | D29: =SUMIFS('Data SKU'!$F$5:$F$116,'Data SKU'!$A$5:$A$116,"Trading",'Data SKU'!$B$5:$B$116,"Karkas",'Data SKU'!$D$5:$D$116,7)/'Segment GP'!H41 -> 0.16089696 | E29: =SUMIFS('Data SKU'!$F$5:$F$116,'Data SKU'!$A$5:$A$116,"Trading",'Data SKU'!$B$5:$B$116,"Karkas",'Data SKU'!$D$5:$D$116,8)/'Segment GP'!M41 -> 0.54989268 | F29: =IFERROR(E29-D29,0) -> 0.38899572
B30: Active customers (with SI / unbilled) | C30: # | D30: =SUMPRODUCT((I_Sales_Inv!$A$5:$A$228=7)/COUNTIFS(I_Sales_Inv!$D$5:$D$228,I_Sales_Inv!$D$5:$D$228,I_Sales_Inv!$A$5:$A$228,I_Sales_Inv!$A$5:$A$228)) -> 22 | E30: =SUMPRODUCT((I_Sales_Inv!$A$5:$A$228=8)/COUNTIFS(I_Sales_Inv!$D$5:$D$228,I_Sales_Inv!$D$5:$D$228,I_Sales_Inv!$A$5:$A$228,I_Sales_Inv!$A$5:$A$228)) -> 26 | F30: =IFERROR(E30-D30,0) -> 4
B32: B. REVENUE BRIDGE Jul → Aug by segment and SKU (IDR)
B33: SKU | C33: Form | D33: Jul revenue | E33: Volume effect | F33: Price effect | G33: New / dropped | H33: Other (no kg) | I33: Aug revenue | J33: Jul kg | K33: Aug kg | L33: Jul ASP | M33: Aug ASP | N33: Note
B34: BLD | C34: Fresh | D34: ='SKU Summary'!F6 -> 0 | E34: =IF(AND(J34>0,K34>0),(K34-J34)*L34,0) -> 0 | F34: =IF(AND(J34>0,K34>0),(M34-L34)*K34,0) -> 0 | G34: =IF(AND(J34>0,K34>0),0,IF(J34>0,-D34,0)+IF(K34>0,I34,0)) -> 9281170 | H34: =I34-D34-E34-F34-G34 -> 0 | I34: ='SKU Summary'!L6 -> 9281170 | J34: ='SKU Summary'!E6 -> 0 | K34: ='SKU Summary'!K6 -> 226.37 | L34: ='SKU Summary'!G6 -> 0 | M34: ='SKU Summary'!M6 -> 41000
B35: BLD | C35: Frozen | D35: ='SKU Summary'!F7 -> 46002000 | E35: =IF(AND(J35>0,K35>0),(K35-J35)*L35,0) -> 18343400 | F35: =IF(AND(J35>0,K35>0),(M35-L35)*K35,0) -> 0 | G35: =IF(AND(J35>0,K35>0),0,IF(J35>0,-D35,0)+IF(K35>0,I35,0)) -> 0 | H35: =I35-D35-E35-F35-G35 -> 0 | I35: ='SKU Summary'!L7 -> 64345400 | J35: ='SKU Summary'!E7 -> 1122 | K35: ='SKU Summary'!K7 -> 1569.4 | L35: ='SKU Summary'!G7 -> 41000 | M35: ='SKU Summary'!M7 -> 41000
B36: BLP | C36: Fresh | D36: ='SKU Summary'!F8 -> 0 | E36: =IF(AND(J36>0,K36>0),(K36-J36)*L36,0) -> 0 | F36: =IF(AND(J36>0,K36>0),(M36-L36)*K36,0) -> 0 | G36: =IF(AND(J36>0,K36>0),0,IF(J36>0,-D36,0)+IF(K36>0,I36,0)) -> 10982800 | H36: =I36-D36-E36-F36-G36 -> 0 | I36: ='SKU Summary'!L8 -> 10982800 | J36: ='SKU Summary'!E8 -> 0 | K36: ='SKU Summary'!K8 -> 274.57 | L36: ='SKU Summary'!G8 -> 0 | M36: ='SKU Summary'!M8 -> 40000
B37: BLP | C37: Frozen | D37: ='SKU Summary'!F9 -> 0 | E37: =IF(AND(J37>0,K37>0),(K37-J37)*L37,0) -> 0 | F37: =IF(AND(J37>0,K37>0),(M37-L37)*K37,0) -> 0 | G37: =IF(AND(J37>0,K37>0),0,IF(J37>0,-D37,0)+IF(K37>0,I37,0)) -> 96460400 | H37: =I37-D37-E37-F37-G37 -> 0 | I37: ='SKU Summary'!L9 -> 96460400 | J37: ='SKU Summary'!E9 -> 0 | K37: ='SKU Summary'!K9 -> 2411.51 | L37: ='SKU Summary'!G9 -> 0 | M37: ='SKU Summary'!M9 -> 40000
B38: Belum ada detail item | C38: n/a | D38: ='SKU Summary'!F10 -> 0 | E38: =IF(AND(J38>0,K38>0),(K38-J38)*L38,0) -> 0 | F38: =IF(AND(J38>0,K38>0),(M38-L38)*K38,0) -> 0 | G38: =IF(AND(J38>0,K38>0),0,IF(J38>0,-D38,0)+IF(K38>0,I38,0)) -> 317493234 | H38: =I38-D38-E38-F38-G38 -> 0 | I38: ='SKU Summary'!L10 -> 317493234 | J38: ='SKU Summary'!E10 -> 0 | K38: ='SKU Summary'!K10 -> 9061.48 | L38: ='SKU Summary'!G10 -> 0 | M38: ='SKU Summary'!M10 -> 35037.68
B39: Ceker | C39: Fresh | D39: ='SKU Summary'!F11 -> 0 | E39: =IF(AND(J39>0,K39>0),(K39-J39)*L39,0) -> 0 | F39: =IF(AND(J39>0,K39>0),(M39-L39)*K39,0) -> 0 | G39: =IF(AND(J39>0,K39>0),0,IF(J39>0,-D39,0)+IF(K39>0,I39,0)) -> 11370200 | H39: =I39-D39-E39-F39-G39 -> 0 | I39: ='SKU Summary'!L11 -> 11370200 | J39: ='SKU Summary'!E11 -> 0 | K39: ='SKU Summary'!K11 -> 3666.8 | L39: ='SKU Summary'!G11 -> 0 | M39: ='SKU Summary'!M11 -> 3100.8509
B40: Ceker | C40: Frozen | D40: ='SKU Summary'!F12 -> 2311000 | E40: =IF(AND(J40>0,K40>0),(K40-J40)*L40,0) -> 0 | F40: =IF(AND(J40>0,K40>0),(M40-L40)*K40,0) -> 0 | G40: =IF(AND(J40>0,K40>0),0,IF(J40>0,-D40,0)+IF(K40>0,I40,0)) -> -2311000 | H40: =I40-D40-E40-F40-G40 -> 0 | I40: ='SKU Summary'!L12 -> 0 | J40: ='SKU Summary'!E12 -> 462.2 | K40: ='SKU Summary'!K12 -> 0 | L40: ='SKU Summary'!G12 -> 5000 | M40: ='SKU Summary'!M12 -> 0
B41: GL adjustment | C41: n/a | D41: ='SKU Summary'!F13 -> 0 | E41: =IF(AND(J41>0,K41>0),(K41-J41)*L41,0) -> 0 | F41: =IF(AND(J41>0,K41>0),(M41-L41)*K41,0) -> 0 | G41: =IF(AND(J41>0,K41>0),0,IF(J41>0,-D41,0)+IF(K41>0,I41,0)) -> 0 | H41: =I41-D41-E41-F41-G41 -> 0 | I41: ='SKU Summary'!L13 -> 0 | J41: ='SKU Summary'!E13 -> 0 | K41: ='SKU Summary'!K13 -> 0 | L41: ='SKU Summary'!G13 -> 0 | M41: ='SKU Summary'!M13 -> 0
B42: HJA (Hati/Jantung/Ampela) | C42: Fresh | D42: ='SKU Summary'!F14 -> 1837500 | E42: =IF(AND(J42>0,K42>0),(K42-J42)*L42,0) -> 31734500 | F42: =IF(AND(J42>0,K42>0),(M42-L42)*K42,0) -> -3254350 | G42: =IF(AND(J42>0,K42>0),0,IF(J42>0,-D42,0)+IF(K42>0,I42,0)) -> 0 | H42: =I42-D42-E42-F42-G42 -> 0 | I42: ='SKU Summary'!L14 -> 30317650 | J42: ='SKU Summary'!E14 -> 367.5 | K42: ='SKU Summary'!K14 -> 6714.4 | L42: ='SKU Summary'!G14 -> 5000 | M42: ='SKU Summary'!M14 -> 4515.3178
B43: HJA (Hati/Jantung/Ampela) | C43: Frozen | D43: ='SKU Summary'!F15 -> 1300000 | E43: =IF(AND(J43>0,K43>0),(K43-J43)*L43,0) -> -1078500 | F43: =IF(AND(J43>0,K43>0),(M43-L43)*K43,0) -> 886000 | G43: =IF(AND(J43>0,K43>0),0,IF(J43>0,-D43,0)+IF(K43>0,I43,0)) -> 0 | H43: =I43-D43-E43-F43-G43 -> 0 | I43: ='SKU Summary'!L15 -> 1107500 | J43: ='SKU Summary'!E15 -> 1300 | K43: ='SKU Summary'!K15 -> 221.5 | L43: ='SKU Summary'!G15 -> 1000 | M43: ='SKU Summary'!M15 -> 5000
B44: KRK (Kerangka) | C44: Frozen | D44: ='SKU Summary'!F16 -> 13229600 | E44: =IF(AND(J44>0,K44>0),(K44-J44)*L44,0) -> 0 | F44: =IF(AND(J44>0,K44>0),(M44-L44)*K44,0) -> 0 | G44: =IF(AND(J44>0,K44>0),0,IF(J44>0,-D44,0)+IF(K44>0,I44,0)) -> -13229600 | H44: =I44-D44-E44-F44-G44 -> 0 | I44: ='SKU Summary'!L16 -> 0 | J44: ='SKU Summary'!E16 -> 2645.92 | K44: ='SKU Summary'!K16 -> 0 | L44: ='SKU Summary'!G16 -> 5000 | M44: ='SKU Summary'!M16 -> 0
B45: Karkas | C45: Fresh | D45: ='SKU Summary'!F17 -> 2502700 | E45: =IF(AND(J45>0,K45>0),(K45-J45)*L45,0) -> 1204707270 | F45: =IF(AND(J45>0,K45>0),(M45-L45)*K45,0) -> 324456600 | G45: =IF(AND(J45>0,K45>0),0,IF(J45>0,-D45,0)+IF(K45>0,I45,0)) -> 0 | H45: =I45-D45-E45-F45-G45 -> 0 | I45: ='SKU Summary'!L17 -> 1531666570 | J45: ='SKU Summary'!E17 -> 86.3 | K45: ='SKU Summary'!K17 -> 41627.93 | L45: ='SKU Summary'!G17 -> 29000 | M45: ='SKU Summary'!M17 -> 36794.205
... B54: Usus | C54: Fresh | D54: ='SKU Summary'!F26 -> 0 | E54: =IF(AND(J54>0,K54>0),(K54-J54)*L54,0) -> 0 | F54: =IF(AND(J54>0,K54>0),(M54-L54)*K54,0) -> 0 | G54: =IF(AND(J54>0,K54>0),0,IF(J54>0,-D54,0)+IF(K54>0,I54,0)) -> 8166150 | H54: =I54-D54-E54-F54-G54 -> 0 | I54: ='SKU Summary'!L26 -> 8166150 | J54: ='SKU Summary'!E26 -> 0 | K54: ='SKU Summary'!K26 -> 5444.1 | L54: ='SKU Summary'!G26 -> 0 | M54: ='SKU Summary'!M26 -> 1500
B55: RPA total | D55: =SUM(D34:D54) -> 246532160 | E55: =SUM(E34:E54) -> 1.5544428e+09 | F55: =SUM(F34:F54) -> 3.7588138e+08 | G55: =SUM(G34:G54) -> 5.142011e+08 | H55: =SUM(H34:H54) -> 629600 | I55: =SUM(I34:I54) -> 2.691687e+09 | J55: =SUM(J34:J54) -> 12576.01 | K55: =SUM(K34:K54) -> 95545.72 | L55: =IFERROR(D55/J55,0) -> 19603.369 | M55: =IFERROR(I55/K55,0) -> 28171.717 | N55: =IF(ROUND(I55-'Segment GP'!M6,0)=0,"ties to Segment GP","CHECK") -> ties to Segment GP
B57: BLD | C57: Frozen | D57: ='SKU Summary'!F29 -> 1921787190 | E57: =IF(AND(J57>0,K57>0),(K57-J57)*L57,0) -> -1.0235027e+09 | F57: =IF(AND(J57>0,K57>0),(M57-L57)*K57,0) -> 1.0671261e+08 | G57: =IF(AND(J57>0,K57>0),0,IF(J57>0,-D57,0)+IF(K57>0,I57,0)) -> 0 | H57: =I57-D57-E57-F57-G57 -> 0 | I57: ='SKU Summary'!L29 -> 1004997085 | J57: ='SKU Summary'!E29 -> 51091.07 | K57: ='SKU Summary'!K29 -> 23881.06 | L57: ='SKU Summary'!G29 -> 37614.933 | M57: ='SKU Summary'!M29 -> 42083.437
B58: BLP | C58: Frozen | D58: ='SKU Summary'!F30 -> 5.3684636e+08 | E58: =IF(AND(J58>0,K58>0),(K58-J58)*L58,0) -> 6.3065968e+08 | F58: =IF(AND(J58>0,K58>0),(M58-L58)*K58,0) -> 3.3947497e+08 | G58: =IF(AND(J58>0,K58>0),0,IF(J58>0,-D58,0)+IF(K58>0,I58,0)) -> 0 | H58: =I58-D58-E58-F58-G58 -> 0 | I58: ='SKU Summary'!L30 -> 1.506981e+09 | J58: ='SKU Summary'!E30 -> 16076.61 | K58: ='SKU Summary'!K30 -> 34962.59 | L58: ='SKU Summary'!G30 -> 33393.008 | M58: ='SKU Summary'!M30 -> 43102.671
B59: Belum ada detail item | C59: n/a | D59: ='SKU Summary'!F31 -> 0 | E59: =IF(AND(J59>0,K59>0),(K59-J59)*L59,0) -> 0 | F59: =IF(AND(J59>0,K59>0),(M59-L59)*K59,0) -> 0 | G59: =IF(AND(J59>0,K59>0),0,IF(J59>0,-D59,0)+IF(K59>0,I59,0)) -> 90526500 | H59: =I59-D59-E59-F59-G59 -> 0 | I59: ='SKU Summary'!L31 -> 90526500 | J59: ='SKU Summary'!E31 -> 0 | K59: ='SKU Summary'!K31 -> 3017.55 | L59: ='SKU Summary'!G31 -> 0 | M59: ='SKU Summary'!M31 -> 30000
B60: KRK (Kerangka) | C60: Not stated in item master | D60: ='SKU Summary'!F32 -> 33741005 | E60: =IF(AND(J60>0,K60>0),(K60-J60)*L60,0) -> 46496424 | F60: =IF(AND(J60>0,K60>0),(M60-L60)*K60,0) -> 69877371 | G60: =IF(AND(J60>0,K60>0),0,IF(J60>0,-D60,0)+IF(K60>0,I60,0)) -> 0 | H60: =I60-D60-E60-F60-G60 -> 0 | I60: ='SKU Summary'!L32 -> 150114800 | J60: ='SKU Summary'!E32 -> 5789.56 | K60: ='SKU Summary'!K32 -> 13767.8 | L60: ='SKU Summary'!G32 -> 5827.9049 | M60: ='SKU Summary'!M32 -> 10903.325
B61: Karkas | C61: Not stated in item master | D61: ='SKU Summary'!F33 -> 384051230 | E61: =IF(AND(J61>0,K61>0),(K61-J61)*L61,0) -> 2.1660653e+09 | F61: =IF(AND(J61>0,K61>0),(M61-L61)*K61,0) -> 3.5498227e+08 | G61: =IF(AND(J61>0,K61>0),0,IF(J61>0,-D61,0)+IF(K61>0,I61,0)) -> 0 | H61: =I61-D61-E61-F61-G61 -> 0 | I61: ='SKU Summary'!L33 -> 2.9050988e+09 | J61: ='SKU Summary'!E33 -> 13989.46 | K61: ='SKU Summary'!K33 -> 92890.61 | L61: ='SKU Summary'!G33 -> 27452.899 | M61: ='SKU Summary'!M33 -> 31274.407
B62: Kulit | C62: Frozen | D62: ='SKU Summary'!F34 -> 0 | E62: =IF(AND(J62>0,K62>0),(K62-J62)*L62,0) -> 0 | F62: =IF(AND(J62>0,K62>0),(M62-L62)*K62,0) -> 0 | G62: =IF(AND(J62>0,K62>0),0,IF(J62>0,-D62,0)+IF(K62>0,I62,0)) -> 3055730 | H62: =I62-D62-E62-F62-G62 -> 0 | I62: ='SKU Summary'!L34 -> 3055730 | J62: ='SKU Summary'!E34 -> 0 | K62: ='SKU Summary'!K34 -> 105.37 | L62: ='SKU Summary'!G34 -> 0 | M62: ='SKU Summary'!M34 -> 29000
B63: Kulit | C63: n/a | D63: ='SKU Summary'!F35 -> 0 | E63: =IF(AND(J63>0,K63>0),(K63-J63)*L63,0) -> 0 | F63: =IF(AND(J63>0,K63>0),(M63-L63)*K63,0) -> 0 | G63: =IF(AND(J63>0,K63>0),0,IF(J63>0,-D63,0)+IF(K63>0,I63,0)) -> 0 | H63: =I63-D63-E63-F63-G63 -> 0 | I63: ='SKU Summary'!L35 -> 0 | J63: ='SKU Summary'!E35 -> 0 | K63: ='SKU Summary'!K35 -> 0 | L63: ='SKU Summary'!G35 -> 0 | M63: ='SKU Summary'!M35 -> 0
B64: Sayap | C64: Not stated in item master | D64: ='SKU Summary'!F36 -> 0 | E64: =IF(AND(J64>0,K64>0),(K64-J64)*L64,0) -> 0 | F64: =IF(AND(J64>0,K64>0),(M64-L64)*K64,0) -> 0 | G64: =IF(AND(J64>0,K64>0),0,IF(J64>0,-D64,0)+IF(K64>0,I64,0)) -> 9300000 | H64: =I64-D64-E64-F64-G64 -> 0 | I64: ='SKU Summary'!L36 -> 9300000 | J64: ='SKU Summary'!E36 -> 0 | K64: ='SKU Summary'!K36 -> 300 | L64: ='SKU Summary'!G36 -> 0 | M64: ='SKU Summary'!M36 -> 31000
B65: Trading total | D65: =SUM(D57:D64) -> 2.8764258e+09 | E65: =SUM(E57:E64) -> 1.8197187e+09 | F65: =SUM(F57:F64) -> 8.7104722e+08 | G65: =SUM(G57:G64) -> 102882230 | H65: =SUM(H57:H64) -> 0 | I65: =SUM(I57:I64) -> 5.6700739e+09 | J65: =SUM(J57:J64) -> 86946.7 | K65: =SUM(K57:K64) -> 168924.98 | L65: =IFERROR(D65/J65,0) -> 33082.633 | M65: =IFERROR(I65/K65,0) -> 33565.633 | N65: =IF(ROUND(I65-'Segment GP'!M7,0)=0,"ties to Segment GP","CHECK") -> ties to Segment GP
B67: C. REVENUE AND PRODUCT GP BY CUSTOMER — Jul vs Aug (IDR; Aug incl. unbilled at item segment)
B68: Customer | D68: Jul revenue RPA | E68: Jul revenue Trading | F68: Aug revenue RPA | G68: Aug revenue Trading | H68: Aug revenue total | I68: Variance vs Jul | J68: Aug kg | K68: Aug ASP Rp/kg | L68: Aug product GP | M68: Aug GP % | N68: Share of Aug revenue
B69: RIZKI RAMADHAN | D69: =SUMIFS(I_Sales_Inv!$E$5:$E$228,I_Sales_Inv!$D$5:$D$228,$B69,I_Sales_Inv!$A$5:$A$228,7) -> 0 | E69: =SUMIFS(I_Sales_Inv!$F$5:$F$228,I_Sales_Inv!$D$5:$D$228,$B69,I_Sales_Inv!$A$5:$A$228,7) -> 183187190 | F69: =SUMIFS(I_Sales_Inv!$E$5:$E$228,I_Sales_Inv!$D$5:$D$228,$B69,I_Sales_Inv!$A$5:$A$228,8) -> 450862780 | G69: =SUMIFS(I_Sales_Inv!$F$5:$F$228,I_Sales_Inv!$D$5:$D$228,$B69,I_Sales_Inv!$A$5:$A$228,8) -> 1090890480 | H69: =F69+G69 -> 1541753260 | I69: =H69-D69-E69 -> 1358566070 | J69: =SUMIFS(I_Sales_Inv!$H$5:$H$228,I_Sales_Inv!$D$5:$D$228,$B69,I_Sales_Inv!$A$5:$A$228,8)+SUMIFS(I_Sales_Inv!$I$5:$I$228,I_Sales_Inv!$D$5:$D$228,$B69,I_Sales_Inv!$A$5:$A$228,8) -> 49090.79 | K69: =IFERROR(H69/J69,0) -> 31406.161 | L69: =H69-SUMIFS(I_Sales_Inv!$K$5:$K$228,I_Sales_Inv!$D$5:$D$228,$B69,I_Sales_Inv!$A$5:$A$228,8)-SUMIFS(I_Sales_Inv!$L$5:$L$228,I_Sales_Inv!$D$5:$D$228,$B69,I_Sales_Inv!$A$5:$A$228,8) -> 16389131 | M69: =IFERROR(L69/H69,0) -> 0.010630191 | N69: =IFERROR(H69/$H$104,0) -> 0.18439529
B70: MUHAMAD HARISUDDIN | D70: =SUMIFS(I_Sales_Inv!$E$5:$E$228,I_Sales_Inv!$D$5:$D$228,$B70,I_Sales_Inv!$A$5:$A$228,7) -> 0 | E70: =SUMIFS(I_Sales_Inv!$F$5:$F$228,I_Sales_Inv!$D$5:$D$228,$B70,I_Sales_Inv!$A$5:$A$228,7) -> 0 | F70: =SUMIFS(I_Sales_Inv!$E$5:$E$228,I_Sales_Inv!$D$5:$D$228,$B70,I_Sales_Inv!$A$5:$A$228,8) -> 1035040175 | G70: =SUMIFS(I_Sales_Inv!$F$5:$F$228,I_Sales_Inv!$D$5:$D$228,$B70,I_Sales_Inv!$A$5:$A$228,8) -> 0 | H70: =F70+G70 -> 1035040175 | I70: =H70-D70-E70 -> 1035040175 | J70: =SUMIFS(I_Sales_Inv!$H$5:$H$228,I_Sales_Inv!$D$5:$D$228,$B70,I_Sales_Inv!$A$5:$A$228,8)+SUMIFS(I_Sales_Inv!$I$5:$I$228,I_Sales_Inv!$D$5:$D$228,$B70,I_Sales_Inv!$A$5:$A$228,8) -> 27923.4 | K70: =IFERROR(H70/J70,0) -> 37067.126 | L70: =H70-SUMIFS(I_Sales_Inv!$K$5:$K$228,I_Sales_Inv!$D$5:$D$228,$B70,I_Sales_Inv!$A$5:$A$228,8)-SUMIFS(I_Sales_Inv!$L$5:$L$228,I_Sales_Inv!$D$5:$D$228,$B70,I_Sales_Inv!$A$5:$A$228,8) -> -10908600 | M70: =IFERROR(L70/H70,0) -> -0.010539301 | N70: =IFERROR(H70/$H$104,0) -> 0.12379188
B71: HARTINI | D71: =SUMIFS(I_Sales_Inv!$E$5:$E$228,I_Sales_Inv!$D$5:$D$228,$B71,I_Sales_Inv!$A$5:$A$228,7) -> 0 | E71: =SUMIFS(I_Sales_Inv!$F$5:$F$228,I_Sales_Inv!$D$5:$D$228,$B71,I_Sales_Inv!$A$5:$A$228,7) -> 0 | F71: =SUMIFS(I_Sales_Inv!$E$5:$E$228,I_Sales_Inv!$D$5:$D$228,$B71,I_Sales_Inv!$A$5:$A$228,8) -> 0 | G71: =SUMIFS(I_Sales_Inv!$F$5:$F$228,I_Sales_Inv!$D$5:$D$228,$B71,I_Sales_Inv!$A$5:$A$228,8) -> 806360640 | H71: =F71+G71 -> 806360640 | I71: =H71-D71-E71 -> 806360640 | J71: =SUMIFS(I_Sales_Inv!$H$5:$H$228,I_Sales_Inv!$D$5:$D$228,$B71,I_Sales_Inv!$A$5:$A$228,8)+SUMIFS(I_Sales_Inv!$I$5:$I$228,I_Sales_Inv!$D$5:$D$228,$B71,I_Sales_Inv!$A$5:$A$228,8) -> 20038.35 | K71: =IFERROR(H71/J71,0) -> 40240.87 | L71: =H71-SUMIFS(I_Sales_Inv!$K$5:$K$228,I_Sales_Inv!$D$5:$D$228,$B71,I_Sales_Inv!$A$5:$A$228,8)-SUMIFS(I_Sales_Inv!$L$5:$L$228,I_Sales_Inv!$D$5:$D$228,$B71,I_Sales_Inv!$A$5:$A$228,8) -> 52424154 | M71: =IFERROR(L71/H71,0) -> 0.065013285 | N71: =IFERROR(H71/$H$104,0) -> 0.096441571
B72: ERWIN ALAMSYAH | D72: =SUMIFS(I_Sales_Inv!$E$5:$E$228,I_Sales_Inv!$D$5:$D$228,$B72,I_Sales_Inv!$A$5:$A$228,7) -> 54507200 | E72: =SUMIFS(I_Sales_Inv!$F$5:$F$228,I_Sales_Inv!$D$5:$D$228,$B72,I_Sales_Inv!$A$5:$A$228,7) -> 440916045 | F72: =SUMIFS(I_Sales_Inv!$E$5:$E$228,I_Sales_Inv!$D$5:$D$228,$B72,I_Sales_Inv!$A$5:$A$228,8) -> 197633740 | G72: =SUMIFS(I_Sales_Inv!$F$5:$F$228,I_Sales_Inv!$D$5:$D$228,$B72,I_Sales_Inv!$A$5:$A$228,8) -> 571763670 | H72: =F72+G72 -> 769397410 | I72: =H72-D72-E72 -> 273974165 | J72: =SUMIFS(I_Sales_Inv!$H$5:$H$228,I_Sales_Inv!$D$5:$D$228,$B72,I_Sales_Inv!$A$5:$A$228,8)+SUMIFS(I_Sales_Inv!$I$5:$I$228,I_Sales_Inv!$D$5:$D$228,$B72,I_Sales_Inv!$A$5:$A$228,8) -> 31750.83 | K72: =IFERROR(H72/J72,0) -> 24232.356 | L72: =H72-SUMIFS(I_Sales_Inv!$K$5:$K$228,I_Sales_Inv!$D$5:$D$228,$B72,I_Sales_Inv!$A$5:$A$228,8)-SUMIFS(I_Sales_Inv!$L$5:$L$228,I_Sales_Inv!$D$5:$D$228,$B72,I_Sales_Inv!$A$5:$A$228,8) -> 15340542 | M72: =IFERROR(L72/H72,0) -> 0.019938385 | N72: =IFERROR(H72/$H$104,0) -> 0.09202073
B73: PT NUSANTARA ONE SATU | D73: =SUMIFS(I_Sales_Inv!$E$5:$E$228,I_Sales_Inv!$D$5:$D$228,$B73,I_Sales_Inv!$A$5:$A$228,7) -> 1596300 | E73: =SUMIFS(I_Sales_Inv!$F$5:$F$228,I_Sales_Inv!$D$5:$D$228,$B73,I_Sales_Inv!$A$5:$A$228,7) -> 38178050 | F73: =SUMIFS(I_Sales_Inv!$E$5:$E$228,I_Sales_Inv!$D$5:$D$228,$B73,I_Sales_Inv!$A$5:$A$228,8) -> 0 | G73: =SUMIFS(I_Sales_Inv!$F$5:$F$228,I_Sales_Inv!$D$5:$D$228,$B73,I_Sales_Inv!$A$5:$A$228,8) -> 556983784 | H73: =F73+G73 -> 556983784 | I73: =H73-D73-E73 -> 517209434 | J73: =SUMIFS(I_Sales_Inv!$H$5:$H$228,I_Sales_Inv!$D$5:$D$228,$B73,I_Sales_Inv!$A$5:$A$228,8)+SUMIFS(I_Sales_Inv!$I$5:$I$228,I_Sales_Inv!$D$5:$D$228,$B73,I_Sales_Inv!$A$5:$A$228,8) -> 16776.62 | K73: =IFERROR(H73/J73,0) -> 33200 | L73: =H73-SUMIFS(I_Sales_Inv!$K$5:$K$228,I_Sales_Inv!$D$5:$D$228,$B73,I_Sales_Inv!$A$5:$A$228,8)-SUMIFS(I_Sales_Inv!$L$5:$L$228,I_Sales_Inv!$D$5:$D$228,$B73,I_Sales_Inv!$A$5:$A$228,8) -> 72810982 | M73: =IFERROR(L73/H73,0) -> 0.1307237 | N73: =IFERROR(H73/$H$104,0) -> 0.06661584
B74: JOKO PURNOMO | D74: =SUMIFS(I_Sales_Inv!$E$5:$E$228,I_Sales_Inv!$D$5:$D$228,$B74,I_Sales_Inv!$A$5:$A$228,7) -> 0 | E74: =SUMIFS(I_Sales_Inv!$F$5:$F$228,I_Sales_Inv!$D$5:$D$228,$B74,I_Sales_Inv!$A$5:$A$228,7) -> 0 | F74: =SUMIFS(I_Sales_Inv!$E$5:$E$228,I_Sales_Inv!$D$5:$D$228,$B74,I_Sales_Inv!$A$5:$A$228,8) -> 112011040 | G74: =SUMIFS(I_Sales_Inv!$F$5:$F$228,I_Sales_Inv!$D$5:$D$228,$B74,I_Sales_Inv!$A$5:$A$228,8) -> 312902130 | H74: =F74+G74 -> 424913170 | I74: =H74-D74-E74 -> 424913170 | J74: =SUMIFS(I_Sales_Inv!$H$5:$H$228,I_Sales_Inv!$D$5:$D$228,$B74,I_Sales_Inv!$A$5:$A$228,8)+SUMIFS(I_Sales_Inv!$I$5:$I$228,I_Sales_Inv!$D$5:$D$228,$B74,I_Sales_Inv!$A$5:$A$228,8) -> 11732.62 | K74: =IFERROR(H74/J74,0) -> 36216.392 | L74: =H74-SUMIFS(I_Sales_Inv!$K$5:$K$228,I_Sales_Inv!$D$5:$D$228,$B74,I_Sales_Inv!$A$5:$A$228,8)-SUMIFS(I_Sales_Inv!$L$5:$L$228,I_Sales_Inv!$D$5:$D$228,$B74,I_Sales_Inv!$A$5:$A$228,8) -> 31393535 | M74: =IFERROR(L74/H74,0) -> 0.073882235 | N74: =IFERROR(H74/$H$104,0) -> 0.050820057
B75: NATALIA PRIHATI | D75: =SUMIFS(I_Sales_Inv!$E$5:$E$228,I_Sales_Inv!$D$5:$D$228,$B75,I_Sales_Inv!$A$5:$A$228,7) -> 0 | E75: =SUMIFS(I_Sales_Inv!$F$5:$F$228,I_Sales_Inv!$D$5:$D$228,$B75,I_Sales_Inv!$A$5:$A$228,7) -> 0 | F75: =SUMIFS(I_Sales_Inv!$E$5:$E$228,I_Sales_Inv!$D$5:$D$228,$B75,I_Sales_Inv!$A$5:$A$228,8) -> 36464190 | G75: =SUMIFS(I_Sales_Inv!$F$5:$F$228,I_Sales_Inv!$D$5:$D$228,$B75,I_Sales_Inv!$A$5:$A$228,8) -> 379607190 | H75: =F75+G75 -> 416071380 | I75: =H75-D75-E75 -> 416071380 | J75: =SUMIFS(I_Sales_Inv!$H$5:$H$228,I_Sales_Inv!$D$5:$D$228,$B75,I_Sales_Inv!$A$5:$A$228,8)+SUMIFS(I_Sales_Inv!$I$5:$I$228,I_Sales_Inv!$D$5:$D$228,$B75,I_Sales_Inv!$A$5:$A$228,8) -> 13137.07 | K75: =IFERROR(H75/J75,0) -> 31671.551 | L75: =H75-SUMIFS(I_Sales_Inv!$K$5:$K$228,I_Sales_Inv!$D$5:$D$228,$B75,I_Sales_Inv!$A$5:$A$228,8)-SUMIFS(I_Sales_Inv!$L$5:$L$228,I_Sales_Inv!$D$5:$D$228,$B75,I_Sales_Inv!$A$5:$A$228,8) -> 8399466.5 | M75: =IFERROR(L75/H75,0) -> 0.020187561 | N75: =IFERROR(H75/$H$104,0) -> 0.04976257
B76: PT SINAR HORECA SUKSES | D76: =SUMIFS(I_Sales_Inv!$E$5:$E$228,I_Sales_Inv!$D$5:$D$228,$B76,I_Sales_Inv!$A$5:$A$228,7) -> 0 | E76: =SUMIFS(I_Sales_Inv!$F$5:$F$228,I_Sales_Inv!$D$5:$D$228,$B76,I_Sales_Inv!$A$5:$A$228,7) -> 145134000 | F76: =SUMIFS(I_Sales_Inv!$E$5:$E$228,I_Sales_Inv!$D$5:$D$228,$B76,I_Sales_Inv!$A$5:$A$228,8) -> 181069770 | G76: =SUMIFS(I_Sales_Inv!$F$5:$F$228,I_Sales_Inv!$D$5:$D$228,$B76,I_Sales_Inv!$A$5:$A$228,8) -> 117285930 | H76: =F76+G76 -> 298355700 | I76: =H76-D76-E76 -> 153221700 | J76: =SUMIFS(I_Sales_Inv!$H$5:$H$228,I_Sales_Inv!$D$5:$D$228,$B76,I_Sales_Inv!$A$5:$A$228,8)+SUMIFS(I_Sales_Inv!$I$5:$I$228,I_Sales_Inv!$D$5:$D$228,$B76,I_Sales_Inv!$A$5:$A$228,8) -> 7359.5 | K76: =IFERROR(H76/J76,0) -> 40540.213 | L76: =H76-SUMIFS(I_Sales_Inv!$K$5:$K$228,I_Sales_Inv!$D$5:$D$228,$B76,I_Sales_Inv!$A$5:$A$228,8)-SUMIFS(I_Sales_Inv!$L$5:$L$228,I_Sales_Inv!$D$5:$D$228,$B76,I_Sales_Inv!$A$5:$A$228,8) -> 52487110 | M76: =IFERROR(L76/H76,0) -> 0.17592126 | N76: =IFERROR(H76/$H$104,0) -> 0.035683652
B77: AGUS DUDI | D77: =SUMIFS(I_Sales_Inv!$E$5:$E$228,I_Sales_Inv!$D$5:$D$228,$B77,I_Sales_Inv!$A$5:$A$228,7) -> 0 | E77: =SUMIFS(I_Sales_Inv!$F$5:$F$228,I_Sales_Inv!$D$5:$D$228,$B77,I_Sales_Inv!$A$5:$A$228,7) -> 96205750 | F77: =SUMIFS(I_Sales_Inv!$E$5:$E$228,I_Sales_Inv!$D$5:$D$228,$B77,I_Sales_Inv!$A$5:$A$228,8) -> 0 | G77: =SUMIFS(I_Sales_Inv!$F$5:$F$228,I_Sales_Inv!$D$5:$D$228,$B77,I_Sales_Inv!$A$5:$A$228,8) -> 297727500 | H77: =F77+G77 -> 297727500 | I77: =H77-D77-E77 -> 201521750 | J77: =SUMIFS(I_Sales_Inv!$H$5:$H$228,I_Sales_Inv!$D$5:$D$228,$B77,I_Sales_Inv!$A$5:$A$228,8)+SUMIFS(I_Sales_Inv!$I$5:$I$228,I_Sales_Inv!$D$5:$D$228,$B77,I_Sales_Inv!$A$5:$A$228,8) -> 6786.5 | K77: =IFERROR(H77/J77,0) -> 43870.552 | L77: =H77-SUMIFS(I_Sales_Inv!$K$5:$K$228,I_Sales_Inv!$D$5:$D$228,$B77,I_Sales_Inv!$A$5:$A$228,8)-SUMIFS(I_Sales_Inv!$L$5:$L$228,I_Sales_Inv!$D$5:$D$228,$B77,I_Sales_Inv!$A$5:$A$228,8) -> 57610411 | M77: =IFERROR(L77/H77,0) -> 0.19350047 | N77: =IFERROR(H77/$H$104,0) -> 0.035608519
B78: YULIANA | D78: =SUMIFS(I_Sales_Inv!$E$5:$E$228,I_Sales_Inv!$D$5:$D$228,$B78,I_Sales_Inv!$A$5:$A$228,7) -> 46002000 | E78: =SUMIFS(I_Sales_Inv!$F$5:$F$228,I_Sales_Inv!$D$5:$D$228,$B78,I_Sales_Inv!$A$5:$A$228,7) -> 252474310 | F78: =SUMIFS(I_Sales_Inv!$E$5:$E$228,I_Sales_Inv!$D$5:$D$228,$B78,I_Sales_Inv!$A$5:$A$228,8) -> 0 | G78: =SUMIFS(I_Sales_Inv!$F$5:$F$228,I_Sales_Inv!$D$5:$D$228,$B78,I_Sales_Inv!$A$5:$A$228,8) -> 296885900 | H78: =F78+G78 -> 296885900 | I78: =H78-D78-E78 -> -1590410 | J78: =SUMIFS(I_Sales_Inv!$H$5:$H$228,I_Sales_Inv!$D$5:$D$228,$B78,I_Sales_Inv!$A$5:$A$228,8)+SUMIFS(I_Sales_Inv!$I$5:$I$228,I_Sales_Inv!$D$5:$D$228,$B78,I_Sales_Inv!$A$5:$A$228,8) -> 7551.8 | K78: =IFERROR(H78/J78,0) -> 39313.263 | L78: =H78-SUMIFS(I_Sales_Inv!$K$5:$K$228,I_Sales_Inv!$D$5:$D$228,$B78,I_Sales_Inv!$A$5:$A$228,8)-SUMIFS(I_Sales_Inv!$L$5:$L$228,I_Sales_Inv!$D$5:$D$228,$B78,I_Sales_Inv!$A$5:$A$228,8) -> 68592532 | M78: =IFERROR(L78/H78,0) -> 0.23104005 | N78: =IFERROR(H78/$H$104,0) -> 0.035507862
B79: PT KHARISMA MAKMUR SEJAHTERA | D79: =SUMIFS(I_Sales_Inv!$E$5:$E$228,I_Sales_Inv!$D$5:$D$228,$B79,I_Sales_Inv!$A$5:$A$228,7) -> 0 | E79: =SUMIFS(I_Sales_Inv!$F$5:$F$228,I_Sales_Inv!$D$5:$D$228,$B79,I_Sales_Inv!$A$5:$A$228,7) -> 127785000 | F79: =SUMIFS(I_Sales_Inv!$E$5:$E$228,I_Sales_Inv!$D$5:$D$228,$B79,I_Sales_Inv!$A$5:$A$228,8) -> 0 | G79: =SUMIFS(I_Sales_Inv!$F$5:$F$228,I_Sales_Inv!$D$5:$D$228,$B79,I_Sales_Inv!$A$5:$A$228,8) -> 292966300 | H79: =F79+G79 -> 292966300 | I79: =H79-D79-E79 -> 165181300 | J79: =SUMIFS(I_Sales_Inv!$H$5:$H$228,I_Sales_Inv!$D$5:$D$228,$B79,I_Sales_Inv!$A$5:$A$228,8)+SUMIFS(I_Sales_Inv!$I$5:$I$228,I_Sales_Inv!$D$5:$D$228,$B79,I_Sales_Inv!$A$5:$A$228,8) -> 5938.5 | K79: =IFERROR(H79/J79,0) -> 49333.384 | L79: =H79-SUMIFS(I_Sales_Inv!$K$5:$K$228,I_Sales_Inv!$D$5:$D$228,$B79,I_Sales_Inv!$A$5:$A$228,8)-SUMIFS(I_Sales_Inv!$L$5:$L$228,I_Sales_Inv!$D$5:$D$228,$B79,I_Sales_Inv!$A$5:$A$228,8) -> 28716922 | M79: =IFERROR(L79/H79,0) -> 0.098021246 | N79: =IFERROR(H79/$H$104,0) -> 0.035039074
B80: PT JAGAD FROZEN FOODS | D80: =SUMIFS(I_Sales_Inv!$E$5:$E$228,I_Sales_Inv!$D$5:$D$228,$B80,I_Sales_Inv!$A$5:$A$228,7) -> 0 | E80: =SUMIFS(I_Sales_Inv!$F$5:$F$228,I_Sales_Inv!$D$5:$D$228,$B80,I_Sales_Inv!$A$5:$A$228,7) -> 0 | F80: =SUMIFS(I_Sales_Inv!$E$5:$E$228,I_Sales_Inv!$D$5:$D$228,$B80,I_Sales_Inv!$A$5:$A$228,8) -> 7204550 | G80: =SUMIFS(I_Sales_Inv!$F$5:$F$228,I_Sales_Inv!$D$5:$D$228,$B80,I_Sales_Inv!$A$5:$A$228,8) -> 254667520 | H80: =F80+G80 -> 261872070 | I80: =H80-D80-E80 -> 261872070 | J80: =SUMIFS(I_Sales_Inv!$H$5:$H$228,I_Sales_Inv!$D$5:$D$228,$B80,I_Sales_Inv!$A$5:$A$228,8)+SUMIFS(I_Sales_Inv!$I$5:$I$228,I_Sales_Inv!$D$5:$D$228,$B80,I_Sales_Inv!$A$5:$A$228,8) -> 8455.51 | K80: =IFERROR(H80/J80,0) -> 30970.582 | L80: =H80-SUMIFS(I_Sales_Inv!$K$5:$K$228,I_Sales_Inv!$D$5:$D$228,$B80,I_Sales_Inv!$A$5:$A$228,8)-SUMIFS(I_Sales_Inv!$L$5:$L$228,I_Sales_Inv!$D$5:$D$228,$B80,I_Sales_Inv!$A$5:$A$228,8) -> 6838760.7 | M80: =IFERROR(L80/H80,0) -> 0.026114891 | N80: =IFERROR(H80/$H$104,0) -> 0.031320172
... B103: TOMI HANDRIANTO | D103: =SUMIFS(I_Sales_Inv!$E$5:$E$228,I_Sales_Inv!$D$5:$D$228,$B103,I_Sales_Inv!$A$5:$A$228,7) -> 0 | E103: =SUMIFS(I_Sales_Inv!$F$5:$F$228,I_Sales_Inv!$D$5:$D$228,$B103,I_Sales_Inv!$A$5:$A$228,7) -> 1000008.2 | F103: =SUMIFS(I_Sales_Inv!$E$5:$E$228,I_Sales_Inv!$D$5:$D$228,$B103,I_Sales_Inv!$A$5:$A$228,8) -> 0 | G103: =SUMIFS(I_Sales_Inv!$F$5:$F$228,I_Sales_Inv!$D$5:$D$228,$B103,I_Sales_Inv!$A$5:$A$228,8) -> 0 | H103: =F103+G103 -> 0 | I103: =H103-D103-E103 -> -1000008.2 | J103: =SUMIFS(I_Sales_Inv!$H$5:$H$228,I_Sales_Inv!$D$5:$D$228,$B103,I_Sales_Inv!$A$5:$A$228,8)+SUMIFS(I_Sales_Inv!$I$5:$I$228,I_Sales_Inv!$D$5:$D$228,$B103,I_Sales_Inv!$A$5:$A$228,8) -> 0 | K103: =IFERROR(H103/J103,0) -> 0 | L103: =H103-SUMIFS(I_Sales_Inv!$K$5:$K$228,I_Sales_Inv!$D$5:$D$228,$B103,I_Sales_Inv!$A$5:$A$228,8)-SUMIFS(I_Sales_Inv!$L$5:$L$228,I_Sales_Inv!$D$5:$D$228,$B103,I_Sales_Inv!$A$5:$A$228,8) -> 0 | M103: =IFERROR(L103/H103,0) -> 0 | N103: =IFERROR(H103/$H$104,0) -> 0
B104: TOTAL | D104: =SUM(D69:D103) -> 246532160 | E104: =SUM(E69:E103) -> 2.8764258e+09 | F104: =SUM(F69:F103) -> 2.6910574e+09 | G104: =SUM(G69:G103) -> 5.6700739e+09 | H104: =SUM(H69:H103) -> 8361131303 | I104: =SUM(I69:I103) -> 5.2381734e+09 | J104: =SUM(J69:J103) -> 264470.7 | K104: =IFERROR(H104/J104,0) -> 31614.585 | L104: =SUM(L69:L103) -> 4.0585439e+08 | M104: =IFERROR(L104/H104,0) -> 0.048540607
B105: Check: customer revenue = Segment GP revenue less revenue without SI (Jul / Aug) | D105: =ROUND(D104+E104-'Segment GP'!H9,0) -> 0 | H105: =ROUND(H104-('Segment GP'!M9-629600),0) -> 0
B107: D1. RPA — GP MARGIN Jul-26 → Aug-26: SAME-MONTH ECONOMICS vs INVENTORY TIMING
B108: Unlike BMG, KGR does not sell in the month what it produced in the month. Each month's margin = margin on goods produced and sold in that month + the effect of stock carried in from earlier months.
B109: Line | D109: Jul-26 | E109: Aug-26 | F109: Δ | N109: Source / formula
B110: Revenue | D110: ='Segment GP'!H6 -> 246532160 | E110: ='Segment GP'!M6 -> 2.691687e+09 | F110: =E110-D110 -> 2.4451548e+09 | N110: Segment GP
B111: sold from goods produced in the same month | D111: =Vintage!I22 -> 2908421.9 | E111: =Vintage!I8 -> 1.7504327e+09 | F111: =E111-D111 -> 1.7475243e+09 | N111: Vintage (FIFO by DO)
B112: sold from stock carried in from earlier months | D112: =Vintage!I21 -> 2.4362374e+08 | E112: =Vintage!I6+Vintage!I7 -> 6.2313146e+08 | F112: =E112-D112 -> 3.7950772e+08 | N112: Vintage (FIFO by DO) — Aug: pre-Jul + Jul stock
B113: outside the split (GL-only rows, revenue without SI, invoices without item) | D113: =D110-D111-D112 -> 0 | E113: =E110-E111-E112 -> 318122834 | F113: =E113-D113 -> 318122834
B114: HPP booked — goods produced in the same month | D114: =Vintage!J22+Vintage!J23 -> 5342548.2 | E114: =Vintage!J8+Vintage!J9 -> 1.8665731e+09 | F114: =E114-D114 -> 1.8612305e+09 | N114: HPP on the DOs that shipped them
B115: HPP booked — carried stock | D115: =Vintage!J21 -> 2.3578761e+08 | E115: =Vintage!J6+Vintage!J7 -> 5.7571491e+08 | F115: =E115-D115 -> 3.399273e+08 | N115: HPP on the DOs that shipped them
B116: HPP — outside the split | D116: =-'Segment GP'!H13-D114-D115 -> 6918638.9 | E116: =-'Segment GP'!M13-E114-E115 -> 3.1286126e+08 | F116: =E116-D116 -> 3.0594262e+08 | N116: rest of product COGS
B117: Cost of sales others | D117: =-'Segment GP'!H27 -> 0 | E117: =-'Segment GP'!M27 -> 0 | F117: =E117-D117 -> 0 | N117: nil unless allocated (COS Others B3)
B118: Share of revenue from carried stock | D118: =IF(D110=0,0,D112/D110) -> 0.98820267 | E118: =IF(E110=0,0,E112/E110) -> 0.2315022 | F118: =(E118-D118)*100 -> -75.670047
B119: Product margin — same-month goods | D119: =IF(D111=0,0,(D111-D114)/D111) -> -0.83692341 | E119: =IF(E111=0,0,(E111-E114)/E111) -> -0.06634952 | F119: =(E119-D119)*100 -> 77.057389
B120: Product margin — carried stock | D120: =IF(D112=0,0,(D112-D115)/D112) -> 0.032164898 | E120: =IF(E112=0,0,(E112-E115)/E112) -> 0.076093977 | F120: =(E120-D120)*100 -> 4.392908
B121: GP margin (segment) | D121: ='Segment GP'!H35 -> -0.0061518649 | E121: ='Segment GP'!M35 -> -0.023577126 | F121: =(E121-D121)*100 -> -1.7425261 | N121: Segment GP
B123: Bridge Jul → Aug | D123: pp | E123: Cumulative | N123: How it is computed
B124: GP margin Jul-26 | D124: =D121 -> -0.0061518649 | E124: =D124 -> -0.0061518649 | N124: Segment GP
B125: (a) Same-month economics — margin on goods produced and sold in the month | D125: =E119-D119 -> 0.77057389 | E125: =E124+D125 -> 0.76442202 | N125: Δ product margin of same-month goods — detail in the table below (price vs cost per SKU)
B126: (b) Inventory timing — stock carried in from earlier months | D126: =E118*(E120-E119)-D118*(D120-D119) -> -0.8258594 | E126: =E125+D126 -> -0.061437376 | N126: Δ [share of carried stock × (its margin − same-month margin)]
B127: (c) Items outside the split | D127: =((E113-E116)/E110-E113/E110*E119)-((D113-D116)/D110-D113/D110*D119) -> 0.03786025 | E127: =E126+D127 -> -0.023577126 | N127: GL-only rows, revenue without SI, invoices without item, net of the same-month margin
B128: (d) Cost of sales others (nil unless allocated — COS Others B3) | D128: =-(E117/E110-D117/D110) -> 0 | E128: =E127+D128 -> -0.023577126 | N128: Δ (expedition + blasting ÷ revenue)
B129: GP margin Aug-26 (corrected) | D129: =SUM(D124:D128) -> -0.023577126 | E129: =D129 -> -0.023577126
B130: check: − Segment GP Aug margin (nil) | D130: =ROUND(D129-E121,8) -> 0
B132: (a) by SKU — goods produced and sold in the same month | C132: kg Jul | D132: kg Aug | E132: Sell Jul Rp/kg | F132: Sell Aug Rp/kg | G132: Cost Jul Rp/kg | H132: Cost Aug Rp/kg | I132: Margin Jul | J132: Margin Aug | K132: Selling price effect pp | L132: Cost effect pp | M132: Mix effect pp | N132: New / dropped pp | O132: Total pp | P132: Rev Jul | Q132: Rev Aug | R132: Cost Jul | S132: Cost Aug
B133: BLD | C133: =SUMIFS(Vintage!$BH$36:$BH$127,Vintage!$C$36:$C$127,"RPA",Vintage!$D$36:$D$127,"BLD") -> 0 | D133: =SUMIFS(Vintage!$AC$36:$AC$127,Vintage!$C$36:$C$127,"RPA",Vintage!$D$36:$D$127,"BLD") -> 0 | E133: =IF(C133=0,0,P133/C133) -> 0 | F133: =IF(D133=0,0,Q133/D133) -> 0 | G133: =IF(C133=0,0,R133/C133) -> 0 | H133: =IF(D133=0,0,S133/D133) -> 0 | I133: =IF(P133=0,0,1-R133/P133) -> 0 | J133: =IF(Q133=0,0,1-S133/Q133) -> 0 | K133: =IF(AND(P133<>0,Q133<>0,E133<>0,F133<>0),(Q133/$Q$146)*(G133/E133-G133/F133),0) -> 0 | L133: =IF(AND(P133<>0,Q133<>0,E133<>0,F133<>0),(Q133/$Q$146)*(G133/F133-H133/F133),0) -> 0 | M133: =IF(AND(P133<>0,Q133<>0,E133<>0,F133<>0),((Q133/$Q$146)-(P133/$P$146))*I133,0) -> 0 | N133: =IF(AND(P133<>0,Q133<>0,E133<>0,F133<>0),0,(Q133/$Q$146)*J133-(P133/$P$146)*I133) -> 0 | O133: =SUM(K133:N133) -> 0 | P133: =SUMIFS(Vintage!$BQ$36:$BQ$127,Vintage!$C$36:$C$127,"RPA",Vintage!$D$36:$D$127,"BLD") -> 0 | Q133: =SUMIFS(Vintage!$AP$36:$AP$127,Vintage!$C$36:$C$127,"RPA",Vintage!$D$36:$D$127,"BLD") -> 0 | R133: =SUMIFS(Vintage!$BM$36:$BM$127,Vintage!$C$36:$C$127,"RPA",Vintage!$D$36:$D$127,"BLD") -> 0 | S133: =SUMIFS(Vintage!$AK$36:$AK$127,Vintage!$C$36:$C$127,"RPA",Vintage!$D$36:$D$127,"BLD") -> 0
B134: BLP | C134: =SUMIFS(Vintage!$BH$36:$BH$127,Vintage!$C$36:$C$127,"RPA",Vintage!$D$36:$D$127,"BLP") -> 0 | D134: =SUMIFS(Vintage!$AC$36:$AC$127,Vintage!$C$36:$C$127,"RPA",Vintage!$D$36:$D$127,"BLP") -> 0 | E134: =IF(C134=0,0,P134/C134) -> 0 | F134: =IF(D134=0,0,Q134/D134) -> 0 | G134: =IF(C134=0,0,R134/C134) -> 0 | H134: =IF(D134=0,0,S134/D134) -> 0 | I134: =IF(P134=0,0,1-R134/P134) -> 0 | J134: =IF(Q134=0,0,1-S134/Q134) -> 0 | K134: =IF(AND(P134<>0,Q134<>0,E134<>0,F134<>0),(Q134/$Q$146)*(G134/E134-G134/F134),0) -> 0 | L134: =IF(AND(P134<>0,Q134<>0,E134<>0,F134<>0),(Q134/$Q$146)*(G134/F134-H134/F134),0) -> 0 | M134: =IF(AND(P134<>0,Q134<>0,E134<>0,F134<>0),((Q134/$Q$146)-(P134/$P$146))*I134,0) -> 0 | N134: =IF(AND(P134<>0,Q134<>0,E134<>0,F134<>0),0,(Q134/$Q$146)*J134-(P134/$P$146)*I134) -> 0 | O134: =SUM(K134:N134) -> 0 | P134: =SUMIFS(Vintage!$BQ$36:$BQ$127,Vintage!$C$36:$C$127,"RPA",Vintage!$D$36:$D$127,"BLP") -> 0 | Q134: =SUMIFS(Vintage!$AP$36:$AP$127,Vintage!$C$36:$C$127,"RPA",Vintage!$D$36:$D$127,"BLP") -> 0 | R134: =SUMIFS(Vintage!$BM$36:$BM$127,Vintage!$C$36:$C$127,"RPA",Vintage!$D$36:$D$127,"BLP") -> 0 | S134: =SUMIFS(Vintage!$AK$36:$AK$127,Vintage!$C$36:$C$127,"RPA",Vintage!$D$36:$D$127,"BLP") -> 0
B135: Ceker | C135: =SUMIFS(Vintage!$BH$36:$BH$127,Vintage!$C$36:$C$127,"RPA",Vintage!$D$36:$D$127,"Ceker") -> 0 | D135: =SUMIFS(Vintage!$AC$36:$AC$127,Vintage!$C$36:$C$127,"RPA",Vintage!$D$36:$D$127,"Ceker") -> 2249.86 | E135: =IF(C135=0,0,P135/C135) -> 0 | F135: =IF(D135=0,0,Q135/D135) -> 3100.8509 | G135: =IF(C135=0,0,R135/C135) -> 0 | H135: =IF(D135=0,0,S135/D135) -> 15556.921 | I135: =IF(P135=0,0,1-R135/P135) -> 0 | J135: =IF(Q135=0,0,1-S135/Q135) -> -4.0169847 | K135: =IF(AND(P135<>0,Q135<>0,E135<>0,F135<>0),(Q135/$Q$146)*(G135/E135-G135/F135),0) -> 0 | L135: =IF(AND(P135<>0,Q135<>0,E135<>0,F135<>0),(Q135/$Q$146)*(G135/F135-H135/F135),0) -> 0 | M135: =IF(AND(P135<>0,Q135<>0,E135<>0,F135<>0),((Q135/$Q$146)-(P135/$P$146))*I135,0) -> 0 | N135: =IF(AND(P135<>0,Q135<>0,E135<>0,F135<>0),0,(Q135/$Q$146)*J135-(P135/$P$146)*I135) -> -0.016009993 | O135: =SUM(K135:N135) -> -0.016009993 | P135: =SUMIFS(Vintage!$BQ$36:$BQ$127,Vintage!$C$36:$C$127,"RPA",Vintage!$D$36:$D$127,"Ceker") -> 0 | Q135: =SUMIFS(Vintage!$AP$36:$AP$127,Vintage!$C$36:$C$127,"RPA",Vintage!$D$36:$D$127,"Ceker") -> 6976480.4 | R135: =SUMIFS(Vintage!$BM$36:$BM$127,Vintage!$C$36:$C$127,"RPA",Vintage!$D$36:$D$127,"Ceker") -> 0 | S135: =SUMIFS(Vintage!$AK$36:$AK$127,Vintage!$C$36:$C$127,"RPA",Vintage!$D$36:$D$127,"Ceker") -> 35000895
B136: HJA (Hati/Jantung/Ampela) | C136: =SUMIFS(Vintage!$BH$36:$BH$127,Vintage!$C$36:$C$127,"RPA",Vintage!$D$36:$D$127,"HJA (Hati/Jantung/Ampela)") -> 0 | D136: =SUMIFS(Vintage!$AC$36:$AC$127,Vintage!$C$36:$C$127,"RPA",Vintage!$D$36:$D$127,"HJA (Hati/Jantung/Ampela)") -> 1444 | E136: =IF(C136=0,0,P136/C136) -> 0 | F136: =IF(D136=0,0,Q136/D136) -> 4515.3178 | G136: =IF(C136=0,0,R136/C136) -> 0 | H136: =IF(D136=0,0,S136/D136) -> 4003.5336 | I136: =IF(P136=0,0,1-R136/P136) -> 0 | J136: =IF(Q136=0,0,1-S136/Q136) -> 0.11334401 | K136: =IF(AND(P136<>0,Q136<>0,E136<>0,F136<>0),(Q136/$Q$146)*(G136/E136-G136/F136),0) -> 0 | L136: =IF(AND(P136<>0,Q136<>0,E136<>0,F136<>0),(Q136/$Q$146)*(G136/F136-H136/F136),0) -> 0 | M136: =IF(AND(P136<>0,Q136<>0,E136<>0,F136<>0),((Q136/$Q$146)-(P136/$P$146))*I136,0) -> 0 | N136: =IF(AND(P136<>0,Q136<>0,E136<>0,F136<>0),0,(Q136/$Q$146)*J136-(P136/$P$146)*I136) -> 0.00042219073 | O136: =SUM(K136:N136) -> 0.00042219073 | P136: =SUMIFS(Vintage!$BQ$36:$BQ$127,Vintage!$C$36:$C$127,"RPA",Vintage!$D$36:$D$127,"HJA (Hati/Jantung/Ampela)") -> 0 | Q136: =SUMIFS(Vintage!$AP$36:$AP$127,Vintage!$C$36:$C$127,"RPA",Vintage!$D$36:$D$127,"HJA (Hati/Jantung/Ampela)") -> 6520118.9 | R136: =SUMIFS(Vintage!$BM$36:$BM$127,Vintage!$C$36:$C$127,"RPA",Vintage!$D$36:$D$127,"HJA (Hati/Jantung/Ampela)") -> 0 | S136: =SUMIFS(Vintage!$AK$36:$AK$127,Vintage!$C$36:$C$127,"RPA",Vintage!$D$36:$D$127,"HJA (Hati/Jantung/Ampela)") -> 5781102.5
B137: KRK (Kerangka) | C137: =SUMIFS(Vintage!$BH$36:$BH$127,Vintage!$C$36:$C$127,"RPA",Vintage!$D$36:$D$127,"KRK (Kerangka)") -> 563 | D137: =SUMIFS(Vintage!$AC$36:$AC$127,Vintage!$C$36:$C$127,"RPA",Vintage!$D$36:$D$127,"KRK (Kerangka)") -> 0 | E137: =IF(C137=0,0,P137/C137) -> 5000 | F137: =IF(D137=0,0,Q137/D137) -> 0 | G137: =IF(C137=0,0,R137/C137) -> 9344.9005 | H137: =IF(D137=0,0,S137/D137) -> 0 | I137: =IF(P137=0,0,1-R137/P137) -> -0.86898009 | J137: =IF(Q137=0,0,1-S137/Q137) -> 0 | K137: =IF(AND(P137<>0,Q137<>0,E137<>0,F137<>0),(Q137/$Q$146)*(G137/E137-G137/F137),0) -> 0 | L137: =IF(AND(P137<>0,Q137<>0,E137<>0,F137<>0),(Q137/$Q$146)*(G137/F137-H137/F137),0) -> 0 | M137: =IF(AND(P137<>0,Q137<>0,E137<>0,F137<>0),((Q137/$Q$146)-(P137/$P$146))*I137,0) -> 0 | N137: =IF(AND(P137<>0,Q137<>0,E137<>0,F137<>0),0,(Q137/$Q$146)*J137-(P137/$P$146)*I137) -> 0.84106745 | O137: =SUM(K137:N137) -> 0.84106745 | P137: =SUMIFS(Vintage!$BQ$36:$BQ$127,Vintage!$C$36:$C$127,"RPA",Vintage!$D$36:$D$127,"KRK (Kerangka)") -> 2815000 | Q137: =SUMIFS(Vintage!$AP$36:$AP$127,Vintage!$C$36:$C$127,"RPA",Vintage!$D$36:$D$127,"KRK (Kerangka)") -> 0 | R137: =SUMIFS(Vintage!$BM$36:$BM$127,Vintage!$C$36:$C$127,"RPA",Vintage!$D$36:$D$127,"KRK (Kerangka)") -> 5261179 | S137: =SUMIFS(Vintage!$AK$36:$AK$127,Vintage!$C$36:$C$127,"RPA",Vintage!$D$36:$D$127,"KRK (Kerangka)") -> 0
...

Sheet Batch Ops KPI
A1: RPA — BATCH OPS KPI, AUGUST 2026
A2: Source: Batch Economics (Accurate goods receipts = ops Pot_ISA sheets; cost = GRN). Value at the price RPA realised in August per form. All cells link to the WP.
B4: A. RPA OPS KPI — AUGUST 2026: input → process → output → sales → stock
B5: # | C5: Data | D5: Agustus | E5: Satuan | F5: Pembanding | G5: Keterangan pembanding | H5: Selisih | I5: Porsi dari rugi produksi Agustus | J5: Kenapa perlu
B6: 1 | C6: Live bird — harga beli | D6: ='Batch Economics'!L18 -> 24472.12 | E6: Rp/kg | F6: ='Batch Economics'!AL18 -> 21705.123 | G6: Harga breakeven (di harga jual Agustus) | H6: =D6-F6 -> 2766.9971 | J6: Ayam dibeli di atas titik impas
C7: Live bird — volume | D7: ='Batch Economics'!G18/1000 -> 140.71904 | E7: ="ton, "&COUNT('Batch Economics'!B6:B17)&" batch" -> ton, 12 batch
B8: 2 | C8: Shrink (dibeli vs diproses) — rata-rata | D8: ='Batch Economics'!O18 -> 0.062797756 | E8: % dari kg dibeli | F8: ='RPA Loss Bridge'!C22 -> 0.02 | G8: Normal | H8: =D8-F8 -> 0.042797756 | I8: ='RPA Loss Bridge'!E32 -> 0.37478745 | J8: Driver #2 rugi produksi
C9: Shrink — batch tertinggi | D9: =MAX('Batch Economics'!O6:O17) -> 0.097179102 | E9: % (terendah di kolom Pembanding) | F9: =MIN('Batch Economics'!O6:O17) -> 0.043254441 | G9: Batch terendah | J9: Variasi antar batch besar
B10: 3 | C10: Freight per kg live bird | D10: ='Batch Economics'!AK18 -> 1289.0935 | E10: Rp/kg LB | F10: ='RPA Loss Bridge'!C23 -> 1000 | G10: Benchmark (batch terbaik) | H10: =D10-F10 -> 289.0935 | I10: ='RPA Loss Bridge'!E34 -> 0.10447915 | J10: Driver #4 rugi produksi
B11: 4 | C11: Yield — karkas ÷ kg diproses | D11: ='Batch Economics'!AD18 -> 0.73670973 | E11: % | F11: ='RPA Loss Bridge'!C24 -> 0.737 | G11: Benchmark | H11: =D11-F11 -> -0.00029026965 | I11: ='RPA Loss Bridge'!E33 -> 0.003617476 | J11: Membuktikan masalahnya bukan yield
C12: Yield — output ÷ kg live bird | D12: ='Batch Economics'!AP18 -> 0.8606497 | E12: % (ops, incl. usus limbah)
C13: Yield — karkas ÷ kg live bird | D13: ='Batch Economics'!AQ18 -> 0.69044601 | E13: %
B14: 5 | C14: Karkas diproduksi fresh | D14: ='Batch Economics'!AF18 -> 0.59320762 | E14: % dari karkas diproduksi | J14: Sisanya keluar frozen
C15: Karkas dari produksi Agustus yang terjual — porsi fresh | D15: =IFERROR(SUMIFS(Vintage!$AC$36:$AC$127,Vintage!$C$36:$C$127,"RPA",Vintage!$BB$36:$BB$127,"Karkas fresh")/(SUMIFS(Vintage!$AC$36:$AC$127,Vintage!$C$36:$C$127,"RPA",Vintage!$BB$36:$BB$127,"Karkas fresh")+SUMIFS(Vintage!$AC$36:$AC$127,Vintage!$C$36:$C$127,"RPA",Vintage!$BB$36:$BB$127,"Karkas frozen")+SUMIFS(Vintage!$AC$36:$AC$127,Vintage!$C$36:$C$127,"RPA",Vintage!$BB$36:$BB$127,"Karkas mix")),0) -> 0.87659448 | E15: % dari karkas terjual | J15: Yang laku terutama fresh
C16: Harga laku karkas fresh | D16: ='Batch Economics'!D23 -> 36794.205 | E16: Rp/kg | F16: ='Batch Economics'!D24 -> 31657.785 | G16: Harga laku karkas frozen | H16: =D16-F16 -> 5136.4193 | I16: ='RPA Loss Bridge'!E31 -> 0.52137991 | J16: Driver #1 rugi produksi (karkas keluar frozen)
B17: 6 | C17: Cost per kg output | D17: ='Batch Economics'!AI18 -> 31792.632 | E17: Rp/kg | F17: ='Batch Economics'!AJ18 -> 28569.003 | G17: Nilai output per kg (harga laku Agustus) | H17: =D17-F17 -> 3223.6284 | J17: Biaya per kg di atas nilai per kg
C18: Cost karkas per kg — as booked | D18: ='Batch Economics'!C58 -> 37149.487 | E18: Rp/kg | F18: ='Batch Economics'!D23 -> 36794.205 | G18: Harga laku karkas fresh | H18: =D18-F18 -> 355.28218 | J18: Karkas fresh pun belum menutup biaya
C19: Cost karkas per kg — kredit by-product | D19: ='Batch Economics'!C59 -> 38712.299 | E19: Rp/kg | F19: ='Batch Economics'!D23 -> 36794.205 | G19: Harga laku karkas fresh | H19: =D19-F19 -> 1918.0941 | J19: By-product dinilai di harga lakunya
B20: 7 | C20: Sisa stok karkas frozen produksi Agustus, 31 Agu | D20: =F58/1000 -> 33.72738 | E20: ton | J20: Risiko margin September
C21: Sisa stok karkas fresh produksi Agustus, 31 Agu | D21: =F59/1000 -> 12.11286 | E21: ton | J21: Aging stok fresh
C22: Sisa stok by-product produksi Agustus, 31 Agu | D22: =F61/1000 -> 14.22802 | E22: ton
C23: Driver lain: maklon tanpa kg (Rp4m) dan sisa spread harga LB vs karkas | D23: =('RPA Loss Bridge'!C35+'RPA Loss Bridge'!C36)/1000000 -> 1.6602658 | E23: Rp mn | I23: ='RPA Loss Bridge'!E35+'RPA Loss Bridge'!E36 -> -0.0042639888 | J23: Kecil — bukan penjelas utama
C24: Rugi produksi Agustus (seluruh output, di harga laku) | D24: ='RPA Loss Bridge'!C30/1000000 -> -389.36918 | E24: Rp mn | I24: =SUM(I8,I10,I11,I16)+I23 -> 1 | J24: Total yang dijelaskan driver di atas
B25: Porsi dari rugi = driver ÷ rugi produksi Agustus (RPA Loss Bridge). Pembanding shrink, freight dan yield = benchmark di RPA Loss Bridge (sel kuning). Semua angka link ke Batch Economics / Vintage.
B32: B. PER BATCH
B33: Cut date | C33: Supplier | D33: Live bird kg | E33: Live bird Rp/kg | F33: Shrink % | G33: Freight Rp/kg LB | H33: Output % of LB | I33: Karkas % of LB | J33: Karkas % of processed | K33: Karkas fresh % | L33: Avg size (Uk) | M33: Cost Rp/kg output | N33: Value Rp/kg output | O33: Gap Rp/kg output | P33: Gap Rp mn | Q33: Breakeven LB Rp/kg | R33: LB price − breakeven
B34: =I_Batch_Ops!B5 -> 46242 | C34: =I_Batch_Ops!E5 -> Priyono | D34: ='Batch Economics'!G6 -> 7000 | E34: ='Batch Economics'!L6 -> 24100 | F34: ='Batch Economics'!O6 -> 0.062428571 | G34: ='Batch Economics'!AK6 -> 1285.7143 | H34: ='Batch Economics'!AP6 -> 0.87044286 | I34: ='Batch Economics'!AQ6 -> 0.68865714 | J34: ='Batch Economics'!AD6 -> 0.73451166 | K34: ='Batch Economics'!AF6 -> 0.94467494 | L34: ='Batch Economics'!U65 -> 1.0786583 | M34: ='Batch Economics'!AI6 -> 32621.081 | N34: ='Batch Economics'!AJ6 -> 31167.436 | O34: =N34-M34 -> -1453.6447 | P34: ='Batch Economics'!AH6/1000000 -> -8.3865124 | Q34: ='Batch Economics'!AL6 -> 22901.927 | R34: =E34-Q34 -> 1198.0732
B35: =I_Batch_Ops!B6 -> 46244 | C35: =I_Batch_Ops!E6 -> Alberus | D35: ='Batch Economics'!G7 -> 11241.1 | E35: ='Batch Economics'!L7 -> 21700 | F35: ='Batch Economics'!O7 -> 0.097179102 | G35: ='Batch Economics'!AK7 -> 2135.0224 | H35: ='Batch Economics'!AP7 -> 0.84487283 | I35: ='Batch Economics'!AQ7 -> 0.67005008 | J35: ='Batch Economics'!AD7 -> 0.74217387 | K35: ='Batch Economics'!AF7 -> 0.83080416 | L35: ='Batch Economics'!U66 -> 1.0634126 | M35: ='Batch Economics'!AI7 -> 29921.113 | N35: ='Batch Economics'!AJ7 -> 29178.046 | O35: =N35-M35 -> -743.06688 | P35: ='Batch Economics'!AH7/1000000 -> -7.0571291 | Q35: ='Batch Economics'!AL7 -> 21072.203 | R35: =E35-Q35 -> 627.79702
B36: =I_Batch_Ops!B7 -> 46245 | C36: =I_Batch_Ops!E7 -> PT Bounty Segar Distribution | D36: ='Batch Economics'!G8 -> 7000 | E36: ='Batch Economics'!L8 -> 24000 | F36: ='Batch Economics'!O8 -> 0.057757143 | G36: ='Batch Economics'!AK8 -> 1000 | H36: ='Batch Economics'!AP8 -> 0.84498571 | I36: ='Batch Economics'!AQ8 -> 0.65964286 | J36: ='Batch Economics'!AD8 -> 0.70007732 | K36: ='Batch Economics'!AF8 -> 0.56591229 | L36: ='Batch Economics'!U67 -> 1.5516665 | M36: ='Batch Economics'!AI8 -> 31370.458 | N36: ='Batch Economics'!AJ8 -> 27716.417 | O36: =N36-M36 -> -3654.0402 | P36: ='Batch Economics'!AH8/1000000 -> -21.613282 | Q36: ='Batch Economics'!AL8 -> 20912.388 | R36: =E36-Q36 -> 3087.6117
B37: =I_Batch_Ops!B8 -> 46248 | C37: =I_Batch_Ops!E8 -> Alberus & Priyono | D37: ='Batch Economics'!G9 -> 15388.94 | E37: ='Batch Economics'!L9 -> 25377.978 | F37: ='Batch Economics'!O9 -> 0.043254441 | G37: ='Batch Economics'!AK9 -> 1169.6712 | H37: ='Batch Economics'!AP9 -> 0.87391334 | I37: ='Batch Economics'!AQ9 -> 0.69555148 | J37: ='Batch Economics'!AD9 -> 0.72699734 | K37: ='Batch Economics'!AF9 -> 0.70315215 | L37: ='Batch Economics'!U68 -> 1.2832181 | M37: ='Batch Economics'!AI9 -> 32129.55 | N37: ='Batch Economics'!AJ9 -> 28743.151 | O37: =N37-M37 -> -3386.3984 | P37: ='Batch Economics'!AH9/1000000 -> -45.542318 | Q37: ='Batch Economics'!AL9 -> 22418.559 | R37: =E37-Q37 -> 2959.4188
B38: =I_Batch_Ops!B9 -> 46253 | C38: =I_Batch_Ops!E9 -> Alberus | D38: ='Batch Economics'!G10 -> 16862.7 | E38: ='Batch Economics'!L10 -> 24435.713 | F38: ='Batch Economics'!O10 -> 0.076025785 | G38: ='Batch Economics'!AK10 -> 1482.5621 | H38: ='Batch Economics'!AP10 -> 0.84772308 | I38: ='Batch Economics'!AQ10 -> 0.6842202 | J38: ='Batch Economics'!AD10 -> 0.74051872 | K38: ='Batch Economics'!AF10 -> 0.7320113 | L38: ='Batch Economics'!U69 -> 1.2523679 | M38: ='Batch Economics'!AI10 -> 32317.904 | N38: ='Batch Economics'!AJ10 -> 29230.453 | O38: =N38-M38 -> -3087.4517 | P38: ='Batch Economics'!AH10/1000000 -> -44.134814 | Q38: ='Batch Economics'!AL10 -> 21818.408 | R38: =E38-Q38 -> 2617.3041
B39: =I_Batch_Ops!B10 -> 46254 | C39: =I_Batch_Ops!E10 -> Alberus | D39: ='Batch Economics'!G11 -> 8177.6 | E39: ='Batch Economics'!L11 -> 25100 | F39: ='Batch Economics'!O11 -> 0.049525533 | G39: ='Batch Economics'!AK11 -> 1100.5674 | H39: ='Batch Economics'!AP11 -> 0.87157601 | I39: ='Batch Economics'!AQ11 -> 0.68988456 | J39: ='Batch Economics'!AD11 -> 0.72583177 | K39: ='Batch Economics'!AF11 -> 0.27965471 | L39: ='Batch Economics'!U70 -> 0.9688794 | M39: ='Batch Economics'!AI11 -> 31805.977 | N39: ='Batch Economics'!AJ11 -> 26881.523 | O39: =N39-M39 -> -4924.4544 | P39: ='Batch Economics'!AH11/1000000 -> -35.098556 | Q39: ='Batch Economics'!AL11 -> 20807.964 | R39: =E39-Q39 -> 4292.0363
B40: =I_Batch_Ops!B11 -> 46255 | C40: =I_Batch_Ops!E11 -> Alberus | D40: ='Batch Economics'!G12 -> 7780.6 | E40: ='Batch Economics'!L12 -> 25100 | F40: ='Batch Economics'!O12 -> 0.061306326 | G40: ='Batch Economics'!AK12 -> 1156.7231 | H40: ='Batch Economics'!AP12 -> 0.85571807 | I40: ='Batch Economics'!AQ12 -> 0.68589826 | J40: ='Batch Economics'!AD12 -> 0.73069445 | K40: ='Batch Economics'!AF12 -> 0.23656942 | L40: ='Batch Economics'!U71 -> 1.0239174 | M40: ='Batch Economics'!AI12 -> 32438.994 | N40: ='Batch Economics'!AJ12 -> 27011.781 | O40: =N40-M40 -> -5427.2123 | P40: ='Batch Economics'!AH12/1000000 -> -36.13438 | Q40: ='Batch Economics'!AL12 -> 20455.836 | R40: =E40-Q40 -> 4644.1636
B41: =I_Batch_Ops!B12 -> 46259 | C41: =I_Batch_Ops!E12 -> Alberus | D41: ='Batch Economics'!G13 -> 12211.6 | E41: ='Batch Economics'!L13 -> 23659.91 | F41: ='Batch Economics'!O13 -> 0.044613318 | G41: ='Batch Economics'!AK13 -> 2088.1785 | H41: ='Batch Economics'!AP13 -> 0.85950244 | I41: ='Batch Economics'!AQ13 -> 0.70221756 | J41: ='Batch Economics'!AD13 -> 0.73500874 | K41: ='Batch Economics'!AF13 -> 0.72141758 | L41: ='Batch Economics'!U72 -> 1.2880539 | M41: ='Batch Economics'!AI13 -> 31735.462 | N41: ='Batch Economics'!AJ13 -> 29491.401 | O41: =N41-M41 -> -2244.0615 | P41: ='Batch Economics'!AH13/1000000 -> -23.553445 | Q41: ='Batch Economics'!AL13 -> 21731.134 | R41: =E41-Q41 -> 1928.7763
B42: =I_Batch_Ops!B13 -> 46260 | C42: =I_Batch_Ops!E13 -> Alberus | D42: ='Batch Economics'!G14 -> 12089.6 | E42: ='Batch Economics'!L14 -> 24148.141 | F42: ='Batch Economics'!O14 -> 0.081747949 | G42: ='Batch Economics'!AK14 -> 1116.6623 | H42: ='Batch Economics'!AP14 -> 0.84611567 | I42: ='Batch Economics'!AQ14 -> 0.67985707 | J42: ='Batch Economics'!AD14 -> 0.74038176 | K42: ='Batch Economics'!AF14 -> 0.60890354 | L42: ='Batch Economics'!U73 -> 1.2514405 | M42: ='Batch Economics'!AI14 -> 31987.197 | N42: ='Batch Economics'!AJ14 -> 28603.238 | O42: =N42-M42 -> -3383.9595 | P42: ='Batch Economics'!AH14/1000000 -> -34.615198 | Q42: ='Batch Economics'!AL14 -> 21284.919 | R42: =E42-Q42 -> 2863.2212
B43: =I_Batch_Ops!B14 -> 46261 | C43: =I_Batch_Ops!E14 -> Alberus | D43: ='Batch Economics'!G15 -> 11681.4 | E43: ='Batch Economics'!L15 -> 24600 | F43: ='Batch Economics'!O15 -> 0.064238875 | G43: ='Batch Economics'!AK15 -> 1232.729 | H43: ='Batch Economics'!AP15 -> 0.86254216 | I43: ='Batch Economics'!AQ15 -> 0.69582413 | J43: ='Batch Economics'!AD15 -> 0.74359162 | K43: ='Batch Economics'!AF15 -> 0.67556162 | L43: ='Batch Economics'!U74 -> 1.2210083 | M43: ='Batch Economics'!AI15 -> 31685.346 | N43: ='Batch Economics'!AJ15 -> 28979.874 | O43: =N43-M43 -> -2705.472 | P43: ='Batch Economics'!AH15/1000000 -> -27.259524 | Q43: ='Batch Economics'!AL15 -> 22266.416 | R43: =E43-Q43 -> 2333.5837
B44: =I_Batch_Ops!B15 -> 46262 | C44: =I_Batch_Ops!E15 -> Alberus | D44: ='Batch Economics'!G16 -> 15537.2 | E44: ='Batch Economics'!L16 -> 25412.043 | F44: ='Batch Economics'!O16 -> 0.055795124 | G44: ='Batch Economics'!AK16 -> 965.42492 | H44: ='Batch Economics'!AP16 -> 0.87102567 | I44: ='Batch Economics'!AQ16 -> 0.70322194 | J44: ='Batch Economics'!AD16 -> 0.74477686 | K44: ='Batch Economics'!AF16 -> 0.42209022 | L44: ='Batch Economics'!U75 -> 1.223356 | M44: ='Batch Economics'!AI16 -> 32017.651 | N44: ='Batch Economics'!AJ16 -> 27945.367 | O44: =N44-M44 -> -4072.2844 | P44: ='Batch Economics'!AH16/1000000 -> -55.111447 | Q44: ='Batch Economics'!AL16 -> 21864.979 | R44: =E44-Q44 -> 3547.0643
B45: =I_Batch_Ops!B16 -> 46265 | C45: =I_Batch_Ops!E16 -> Alberus | D45: ='Batch Economics'!G17 -> 15748.3 | E45: ='Batch Economics'!L17 -> 25200 | F45: ='Batch Economics'!O17 -> 0.058615851 | G45: ='Batch Economics'!AK17 -> 761.98701 | H45: ='Batch Economics'!AP17 -> 0.87257037 | I45: ='Batch Economics'!AQ17 -> 0.70611431 | J45: ='Batch Economics'!AD17 -> 0.75008094 | K45: ='Batch Economics'!AF17 -> 0.3690974 | L45: ='Batch Economics'!U76 -> 1.3639922 | M45: ='Batch Economics'!AI17 -> 31479.641 | N45: ='Batch Economics'!AJ17 -> 27778.256 | O45: =N45-M45 -> -3701.3843 | P45: ='Batch Economics'!AH17/1000000 -> -50.862572 | Q45: ='Batch Economics'!AL17 -> 21970.282 | R45: =E45-Q45 -> 3229.7183
B46: TOTAL | C46: Agustus — total | D46: ='Batch Economics'!G18 -> 140719.04 | E46: ='Batch Economics'!L18 -> 24472.12 | F46: ='Batch Economics'!O18 -> 0.062797756 | G46: ='Batch Economics'!AK18 -> 1289.0935 | H46: ='Batch Economics'!AP18 -> 0.8606497 | I46: ='Batch Economics'!AQ18 -> 0.69044601 | J46: ='Batch Economics'!AD18 -> 0.73670973 | K46: ='Batch Economics'!AF18 -> 0.59320762 | L46: ='Batch Economics'!U77 -> 1.2276753 | M46: ='Batch Economics'!AI18 -> 31792.632 | N46: ='Batch Economics'!AJ18 -> 28569.003 | O46: =N46-M46 -> -3223.6284 | P46: ='Batch Economics'!AH18/1000000 -> -389.36918 | Q46: ='Batch Economics'!AL18 -> 21705.123 | R46: =E46-Q46 -> 2766.9971
B47: Benchmark | F47: ='RPA Loss Bridge'!C22 -> 0.02 | G47: ='RPA Loss Bridge'!C23 -> 1000 | J47: ='RPA Loss Bridge'!C24 -> 0.737 | O47: 0
B49: Shrink = live bird bought (PI) − kg processed (maklon) ÷ bought. Output and karkas % = kg received in stock ÷ live bird bought (8 Aug excludes 323.8 kg usus discarded). Fresh % = karkas received fresh ÷ all karkas.
B50: Avg size = kg-weighted Uk band of the karkas received. Cost per kg output = batch cost (live bird + inbound freight + maklon) ÷ output in stock. Value = output × RPA realised August price per form (karkas fresh / frozen, by-products).
B51: Breakeven LB price = (value of output − freight − maklon) ÷ live bird kg: the most RPA could pay per kg live bird at August selling prices. Blasting, packaging, storage and handling are not in these costs.
B53: Memo — where August production went (kg)
B54: Karkas produced (received) in August | F54: ='Batch Economics'!V18 -> 97158.9
B55: sold in August (invoiced + unbilled) | F55: =(SUMIFS('MA Engine'!$AJ$6:$AJ$1110,'MA Engine'!$C$6:$C$1110,"RPA",'MA Engine'!$D$6:$D$1110,"Karkas",'MA Engine'!$H$6:$H$1110,8,'MA Engine'!$I$6:$I$1110,"DO",'MA Engine'!$P$6:$P$1110,"<>Y")+SUMIFS('MA Engine'!$AJ$6:$AJ$1110,'MA Engine'!$C$6:$C$1110,"RPA",'MA Engine'!$D$6:$D$1110,"Karkas",'MA Engine'!$H$6:$H$1110,8,'MA Engine'!$I$6:$I$1110,"Unbilled")) -> 47397.07 | H55: =IFERROR(F55/F54,0) -> 0.48783045
B56: other outflow (DO 257 in transit, IA recodes) | F56: =SUMIFS('MA Engine'!$AJ$6:$AJ$1110,'MA Engine'!$C$6:$C$1110,"RPA",'MA Engine'!$D$6:$D$1110,"Karkas",'MA Engine'!$H$6:$H$1110,8)-(SUMIFS('MA Engine'!$AJ$6:$AJ$1110,'MA Engine'!$C$6:$C$1110,"RPA",'MA Engine'!$D$6:$D$1110,"Karkas",'MA Engine'!$H$6:$H$1110,8,'MA Engine'!$I$6:$I$1110,"DO",'MA Engine'!$P$6:$P$1110,"<>Y")+SUMIFS('MA Engine'!$AJ$6:$AJ$1110,'MA Engine'!$C$6:$C$1110,"RPA",'MA Engine'!$D$6:$D$1110,"Karkas",'MA Engine'!$H$6:$H$1110,8,'MA Engine'!$I$6:$I$1110,"Unbilled")) -> 4121.43 | H56: =IFERROR(F56/F54,0) -> 0.04241948
B57: still in stock at 31 Aug | F57: ='Batch Economics'!V18-SUMIFS('MA Engine'!$AJ$6:$AJ$1110,'MA Engine'!$C$6:$C$1110,"RPA",'MA Engine'!$D$6:$D$1110,"Karkas",'MA Engine'!$H$6:$H$1110,8) -> 45640.4 | H57: =IFERROR(F57/F54,0) -> 0.46975007
B58: of which frozen | F58: ='Batch Economics'!U18-SUMIFS('MA Engine'!$AJ$6:$AJ$1110,'MA Engine'!$C$6:$C$1110,"RPA",'MA Engine'!$D$6:$D$1110,"Karkas",'MA Engine'!$E$6:$E$1110,"Frozen",'MA Engine'!$H$6:$H$1110,8) -> 33727.38
B59: of which fresh | F59: ='Batch Economics'!T18-SUMIFS('MA Engine'!$AJ$6:$AJ$1110,'MA Engine'!$C$6:$C$1110,"RPA",'MA Engine'!$D$6:$D$1110,"Karkas",'MA Engine'!$E$6:$E$1110,"Fresh",'MA Engine'!$H$6:$H$1110,8) -> 12112.86
B60: By-products produced in August | F60: ='Batch Economics'!AB18 -> 23627.1
B61: still in stock at 31 Aug | F61: ='Batch Economics'!AB18-(SUMIFS('MA Engine'!$AJ$6:$AJ$1110,'MA Engine'!$C$6:$C$1110,"RPA",'MA Engine'!$H$6:$H$1110,8)-SUMIFS('MA Engine'!$AJ$6:$AJ$1110,'MA Engine'!$C$6:$C$1110,"RPA",'MA Engine'!$D$6:$D$1110,"Karkas",'MA Engine'!$H$6:$H$1110,8)) -> 14228.02 | H61: =IFERROR(F61/F60,0) -> 0.6021907
B62: FIFO by DO (MA Engine): August outflows take older stock first, so what is left at 31 Aug is August production. Karkas mix sold from stock without an August receipt makes fresh + frozen differ slightly from the total.

Sheet RPA KPI vs Budget
A1: RPA — KPI PENGGERAK UTAMA: BUDGET vs AKTUAL AGUSTUS 2026
A2: Budget = KGR_-_Budget_Manufacturing_v3.xlsx (bulan pertama Sep-26 atau kartu biaya standar; nilai biru disalin dari sel yang disebut). Aktual = WP ini (Batch Economics, Accurate = ops). Budget memodelkan pabrik sendiri; Agustus masih maklon di ISA.
B5: # | C5: KPI | D5: Definisi | E5: Satuan | F5: Budget | G5: Sumber budget | H5: Target KPI (B_KPI) | I5: Aktual Agustus | J5: Selisih aktual − budget | K5: Status | L5: Dampak vs budget Rp mn (indikatif) | M5: Pemilik | N5: Catatan
B6: A. VOLUME DAN KAPASITAS
B7: 1 | C7: Live bird diterima | D7: kg diterima (PI) per bulan | E7: ton | F7: 432.28664 | G7: O_Produksi!I14 (Sep-26) | H7: — | I7: ='Batch Economics'!G18/1000 -> 140.71904 | J7: =IF(ISNUMBER(I7),I7-F7,"") -> -291.5676 | K7: =IF(ISNUMBER(I7),IF(I7>=F7,"On","Off"),"—") -> Off | M7: Direktur Operasional | N7: Agustus 12 batch; budget mengasumsikan potong setiap hari
B8: 2 | C8: kg masuk lini per hari potong | D8: kg diproses ÷ hari potong | E8: kg/hari | F8: 14265.459 | G8: O_Produksi!I22 (Sep-26) | H8: =20000 -> 20000 | I8: ='Batch Economics'!M18/COUNT('Batch Economics'!B6:B17) -> 10990.183 | J8: =IF(ISNUMBER(I8),I8-F8,"") -> -3275.2756 | K8: =IF(ISNUMBER(I8),IF(I8>=F8,"On","Off"),"—") -> Off | M8: Manajer Operasional | N8: Target volume 20 t/hari (Assumptions!G55)
B9: 3 | C9: Utilisasi vs volume normal | D9: kg masuk lini ÷ volume normal bulanan | E9: % | F9: 0.41084563 | G9: O_Produksi!I25 (Sep-26) | H9: ≥ 95% | I9: ='Batch Economics'!M18/1041665.625 -> 0.12660704 | J9: =IF(ISNUMBER(I9),I9-F9,"") -> -0.28423859 | K9: =IF(ISNUMBER(I9),IF(I9>=F9,"On","Off"),"—") -> Off | M9: Manajer Operasional | N9: Volume normal 1,041,666 kg/bln (Assumptions!G24). Di bawah 95% overhead tak terserap jadi beban periode (PSAK 14)
B10: B. BAHAN BAKU
B11: 4 | C11: Harga live bird | D11: Rp per kg diterima | E11: Rp/kg | F11: 24805.388 | G11: O_Weekly RPA!H15 (rata-rata rencana) | H11: ≤ Rp 20.000 | I11: ='Batch Economics'!L18 -> 24472.12 | J11: =IF(ISNUMBER(I11),I11-F11,"") -> -333.26765 | K11: =IF(ISNUMBER(I11),IF(I11<=F11,"On","Off"),"—") -> On | L11: =(F11-I11)*'Batch Economics'!G18/1000000 -> 46.897103 | M11: Manajer Operasional | N11: B_KPI: di atas Rp22.000 pabrik tidak BEP di volume berapa pun
B12: 5 | C12: Ongkos angkut live bird | D12: freight inbound ÷ kg diterima | E12: Rp/kg LB | F12: 0 | G12: tidak dimodelkan | H12: — | I12: ='Batch Economics'!AK18 -> 1289.0935 | J12: =IF(ISNUMBER(I12),I12-F12,"") -> 1289.0935 | K12: =IF(ISNUMBER(I12),IF(I12<=F12,"On","Off"),"—") -> Off | L12: =(F12-I12)*'Batch Economics'!G18/1000000 -> -181.4 | M12: Manajer Operasional | N12: Budget menganggap harga LB sudah sampai pabrik. Aktual Rp181m di Agustus — perlu masuk budget
B13: C. PROSES
B14: 6 | C14: Susut penerimaan s.d. masuk lini | D14: (kg diterima − kg diproses) ÷ kg diterima | E14: % | F14: 0.01 | G14: I_Model Details!G25:G27 (DOA + mortalitas + susut holding) | H14: ≤ 2% (akurasi terima) | I14: ='Batch Economics'!O18 -> 0.062797756 | J14: =IF(ISNUMBER(I14),I14-F14,"") -> 0.052797756 | K14: =IF(ISNUMBER(I14),IF(I14<=F14,"On","Off"),"—") -> Off | L14: =(F14-I14)*'Batch Economics'!G18*'Batch Economics'!L18/1000000 -> -181.81928 | M14: Supervisor Produksi | N14: Aktual = kg PI vs kg tagihan maklon; belum dipisah DOA / mati / susut timbang
B15: 7 | C15: Yield total | D15: kg output ÷ kg masuk lini | E15: % | F15: 0.8879778 | G15: O_Produksi!I44 (Sep-26) | H15: 89,2% (indikatif) | I15: ='Batch Economics'!AC18/'Batch Economics'!M18 -> 0.91586279 | J15: =IF(ISNUMBER(I15),I15-F15,"") -> 0.027884993 | K15: =IF(ISNUMBER(I15),IF(I15>=F15,"On","Off"),"—") -> On | M15: PPIC | N15: Output di stok Accurate (tanpa usus limbah 8 Agu)
B16: 8 | C16: Yield karkas | D16: kg karkas ÷ kg masuk lini | E16: % | F16: 0.69416 | G16: O_Costing!E35 (kartu standar) | H16: — | I16: ='Batch Economics'!AD18 -> 0.73670973 | J16: =IF(ISNUMBER(I16),I16-F16,"") -> 0.04254973 | K16: =IF(ISNUMBER(I16),IF(I16>=F16,"On","Off"),"—") -> On | L16: =(I16-F16)*'Batch Economics'!M18*(('Batch Economics'!T18*'Batch Economics'!D23+'Batch Economics'!U18*'Batch Economics'!D24)/'Batch Economics'!V18)/1000000 -> 194.7475 | M16: PPIC | N16: Dampak dinilai di harga laku karkas Agustus
B17: 9 | C17: Yield by-product | D17: kg by-product (termasuk limbah) ÷ kg masuk lini | E17: % | F17: =SUM(F42:F47) -> 0.19828 | G17: O_Costing!E36:E41 | H17: ≤ 5% deviasi relatif | I17: =('Batch Economics'!AB18+'Batch Economics'!AN18)/'Batch Economics'!M18 -> 0.18160828 | J17: =IF(ISNUMBER(I17),I17-F17,"") -> -0.016671716 | K17: =IF(ISNUMBER(I17),IF(I17>=F17,"On","Off"),"—") -> Off | L17: =(I17-F17)*'Batch Economics'!M18*(('Batch Economics'!W18*'Batch Economics'!D25+'Batch Economics'!X18*'Batch Economics'!D26+'Batch Economics'!Y18*'Batch Economics'!D27+'Batch Economics'!Z18*'Batch Economics'!D28+'Batch Economics'!AA18*'Batch Economics'!D29)/'Batch Economics'!AB18)/1000000 -> -7.3386361 | M17: PPIC | N17: Budget termasuk kerongkongan 3,9% (tidak ada di Agustus — karkas dijual utuh). Rincian per produk di bawah
B18: 10 | C18: Kondemnasi post-mortem | D18: kg dikondemnasi ÷ kg masuk lini | E18: % | F18: 0.005 | G18: I_Model Details!G28 | H18: ≤ 0,5% | I18: n/a | K18: =IF(ISNUMBER(I18),"info","—") -> — | M18: Dokter Hewan | N18: Belum dicatat — perlu kolom di Yield Report
B19: D. BAURAN OUTPUT
B20: 11 | C20: Karkas dijual utuh | D20: kg karkas utuh ÷ karkas total | E20: % | F20: 0.81328512 | G20: Assumptions!G77 | H20: — | I20: ='Batch Economics'!V18/('Batch Economics'!V18+SUMIFS('MA Engine'!$K$6:$K$1110,'MA Engine'!$C$6:$C$1110,"RPA",'MA Engine'!$H$6:$H$1110,8,'MA Engine'!$I$6:$I$1110,"Receipt",'MA Engine'!$D$6:$D$1110,"BLD")+SUMIFS('MA Engine'!$K$6:$K$1110,'MA Engine'!$C$6:$C$1110,"RPA",'MA Engine'!$H$6:$H$1110,8,'MA Engine'!$I$6:$I$1110,"Receipt",'MA Engine'!$D$6:$D$1110,"BLP")) -> 1 | J20: =IF(ISNUMBER(I20),I20-F20,"") -> 0.18671488 | K20: =IF(ISNUMBER(I20),"info","—") -> info | M20: PPIC | N20: Agustus tanpa cut-up
B21: 12 | C21: Porsi output dibekukan | D21: kg produk beku ÷ total output | E21: % | F21: 0.6 | G21: I_Model Details!G29 | H21: — | I21: =SUMIFS('MA Engine'!$K$6:$K$1110,'MA Engine'!$C$6:$C$1110,"RPA",'MA Engine'!$H$6:$H$1110,8,'MA Engine'!$I$6:$I$1110,"Receipt",'MA Engine'!$E$6:$E$1110,"Frozen")/'Batch Economics'!AC18 -> 0.33036113 | J21: =IF(ISNUMBER(I21),I21-F21,"") -> -0.26963887 | K21: =IF(ISNUMBER(I21),"info","—") -> info | L21: ='RPA Loss Bridge'!C31/1000000 -> -203.00927 | M21: Manajer Sales | N21: Budget butuh premium harga beku +Rp1.122/kg (B_UnitEcon); aktual frozen DISKON Rp5,136/kg. Dampak = driver #1 Loss Bridge
B22: E. HARGA JUAL
B23: 13 | C23: Harga karkas (bauran fresh + frozen) | D23: nilai karkas ÷ kg, di harga laku Agustus | E23: Rp/kg | F23: 37150.028 | G23: I_Model Details!I120 (Sep-26) | H23: — | I23: =(('Batch Economics'!T18*'Batch Economics'!D23+'Batch Economics'!U18*'Batch Economics'!D24)/'Batch Economics'!V18) -> 34704.748 | J23: =IF(ISNUMBER(I23),I23-F23,"") -> -2445.2798 | K23: =IF(ISNUMBER(I23),IF(I23>=F23,"On","Off"),"—") -> Off | L23: =(I23-F23)*'Batch Economics'!V18/1000000 -> -237.58069 | M23: Manajer Sales | N23: Fresh Rp36,794, frozen Rp31,658. Harga pasar acuan budget Rp33.106 (Assumptions!G56)
B24: 14 | C24: Harga by-product (bauran aktual) | D24: nilai by-product ÷ kg | E24: Rp/kg | F24: =('Batch Economics'!W18*F50+'Batch Economics'!X18*F51+'Batch Economics'!Y18*F52+'Batch Economics'!Z18*F53+'Batch Economics'!AA18*F54)/'Batch Economics'!AB18 -> 7429.7511 | G24: I_Model Details!I128:I132 (Sep-26), dibobot bauran aktual | H24: — | I24: =(('Batch Economics'!W18*'Batch Economics'!D25+'Batch Economics'!X18*'Batch Economics'!D26+'Batch Economics'!Y18*'Batch Economics'!D27+'Batch Economics'!Z18*'Batch Economics'!D28+'Batch Economics'!AA18*'Batch Economics'!D29)/'Batch Economics'!AB18) -> 3337.712 | J24: =IF(ISNUMBER(I24),I24-F24,"") -> -4092.0391 | K24: =IF(ISNUMBER(I24),IF(I24>=F24,"On","Off"),"—") -> Off | L24: =(I24-F24)*'Batch Economics'!AB18/1000000 -> -96.683017 | M24: Manajer Sales | N24: Budget kepala/ceker Rp11,6rb, usus Rp7,0rb; laku Agustus Rp4,0rb / Rp3,1rb / Rp1,5rb
B25: F. BIAYA KONVERSI
B26: 15 | C26: Biaya potong per kg masuk lini | D26: maklon ÷ kg diproses (budget: Pool A tenaga + overhead) | E26: Rp/kg | F26: 1232.5107 | G26: I_Model Details!I179 (Sep-26, pabrik sendiri) | H26: — | I26: ='Batch Economics'!J18/'Batch Economics'!M18 -> 1630.3301 | J26: =IF(ISNUMBER(I26),I26-F26,"") -> 397.81941 | K26: =IF(ISNUMBER(I26),IF(I26<=F26,"On","Off"),"—") -> Off | L26: =(F26-I26)*'Batch Economics'!M18/1000000 -> -52.465299 | M26: Manajer Accounting | N26: Di volume Agustus, Pool A pabrik sendiri ≈ Rp4,000/kg — maklon masih lebih murah
B27: G. HASIL PER KG
B28: 16 | C28: Nilai output per kg | D28: nilai output di harga laku ÷ kg output | E28: Rp/kg | F28: 27816.022 | G28: B_RPA_Summary!G89 | H28: — | I28: ='Batch Economics'!AJ18 -> 28569.003 | J28: =IF(ISNUMBER(I28),I28-F28,"") -> 752.98128 | K28: =IF(ISNUMBER(I28),IF(I28>=F28,"On","Off"),"—") -> On | M28: Manajer Sales
B29: 17 | C29: Biaya per kg output | D29: biaya batch ÷ kg output | E29: Rp/kg | F29: 30471.5 | G29: B_RPA_Summary!H52 (20 t/hari) | H29: — | I29: ='Batch Economics'!AI18 -> 31792.632 | J29: =IF(ISNUMBER(I29),I29-F29,"") -> 1321.1317 | K29: =IF(ISNUMBER(I29),IF(I29<=F29,"On","Off"),"—") -> Off | M29: Manajer Accounting | N29: Budget termasuk storage, kemasan, G&A (Rp2.255/kg); aktual hanya LB + angkut + maklon
B30: 18 | C30: Kontribusi per kg live bird | D30: (nilai output − LB − angkut − maklon) ÷ kg LB | E30: Rp/kg | F30: 1835 | G30: B_KPI!F26 (kartu standar) | H30: Rp 1.835 | I30: =('Batch Economics'!AG18-'Batch Economics'!H18)/'Batch Economics'!G18 -> -2766.9971 | J30: =IF(ISNUMBER(I30),I30-F30,"") -> -4601.9971 | K30: =IF(ISNUMBER(I30),IF(I30>=F30,"On","Off"),"—") -> Off | L30: =(I30-F30)*'Batch Economics'!G18/1000000 -> -647.58862 | M30: Manajer Accounting | N30: Selisih total terhadap kartu standar — bukan jumlah dari baris lain
B31: 19 | C31: Harga breakeven live bird | D31: harga LB maksimum agar kontribusi = 0 | E31: Rp/kg | F31: 21912.653 | G31: B_Summary!G362 (ambang own = maklon) | H31: — | I31: ='Batch Economics'!AL18 -> 21705.123 | J31: =IF(ISNUMBER(I31),I31-F31,"") -> -207.53003 | K31: =IF(ISNUMBER(I31),IF(I31>=F31,"On","Off"),"—") -> Off | M31: Manajer Operasional | N31: Aktual: harga beli Rp2.767/kg di atas breakeven
B32: Status: On = aktual sama atau lebih baik dari budget. Dampak = (aktual − budget) × volume Agustus, di harga laku Agustus; indikatif, antar baris tumpang tindih sehingga tidak dijumlah. Kontribusi per kg (#18) adalah selisih totalnya.
B40: H. YIELD DAN HARGA PER BY-PRODUCT — budget (kartu standar / Sep-26) vs aktual Agustus
C41: Produk | E41: Satuan | F41: Yield budget ÷ kg masuk lini | G41: Sumber | I41: Yield aktual ÷ kg masuk lini | J41: Selisih | K41: Status
C42: Kerongkongan | E42: % | F42: 0.03906 | G42: O_Costing!E36 | I42: 0 | J42: =I42-F42 -> -0.03906 | K42: =IF(ABS(I42/F42-1)<=5%,"On","Off") -> Off
C43: Kepala | E43: % | F43: 0.05267 | G43: O_Costing!E37 | I43: ='Batch Economics'!X18/'Batch Economics'!M18 -> 0.046732614 | J43: =I43-F43 -> -0.0059373856 | K43: =IF(ABS(I43/F43-1)<=5%,"On","Off") -> Off
C44: Ceker | E44: % | F44: 0.03026 | G44: O_Costing!E38 | I44: ='Batch Economics'!Z18/'Batch Economics'!M18 -> 0.029439151 | J44: =I44-F44 -> -0.000820849 | K44: =IF(ABS(I44/F44-1)<=5%,"On","Off") -> On
C45: Usus (incl. limbah) | E45: % | F45: 0.04192 | G45: O_Costing!E39 | I45: =('Batch Economics'!Y18+'Batch Economics'!AN18)/'Batch Economics'!M18 -> 0.046029714 | J45: =I45-F45 -> 0.0041097144 | K45: =IF(ABS(I45/F45-1)<=5%,"On","Off") -> Off
C46: HJA / giblet | E46: % | F46: 0.03193 | G46: O_Costing!E40 | I46: ='Batch Economics'!W18/'Batch Economics'!M18 -> 0.056040921 | J46: =I46-F46 -> 0.024110921 | K46: =IF(ABS(I46/F46-1)<=5%,"On","Off") -> Off
C47: Lemak | E47: % | F47: 0.00244 | G47: O_Costing!E41 | I47: ='Batch Economics'!AA18/'Batch Economics'!M18 -> 0.0033658826 | J47: =I47-F47 -> 0.00092588258 | K47: =IF(ABS(I47/F47-1)<=5%,"On","Off") -> Off
C48: Total by-product | F48: =SUM(F42:F47) -> 0.19828 | I48: =SUM(I42:I47) -> 0.18160828 | J48: =I48-F48 -> -0.016671716
C49: Produk | E49: Satuan | F49: Harga budget Sep-26 | G49: Sumber | I49: Harga laku Agustus | J49: Selisih | K49: Status
C50: HJA / giblet | E50: Rp/kg | F50: 812.65686 | G50: I_Model Details!I131 | I50: ='Batch Economics'!D25 -> 4515.3178 | J50: =I50-F50 -> 3702.661 | K50: =IF(I50=0,"no sale",IF(I50>=F50,"On","Off")) -> On
C51: Kepala | E51: Rp/kg | F51: 11609.384 | G51: I_Model Details!I128 | I51: ='Batch Economics'!D26 -> 4028.6768 | J51: =I51-F51 -> -7580.707 | K51: =IF(I51=0,"no sale",IF(I51>=F51,"On","Off")) -> Off
C52: Usus | E52: Rp/kg | F52: 6965.6303 | G52: I_Model Details!I130 | I52: ='Batch Economics'!D27 -> 1500 | J52: =I52-F52 -> -5465.6303 | K52: =IF(I52=0,"no sale",IF(I52>=F52,"On","Off")) -> Off
C53: Ceker | E53: Rp/kg | F53: 11609.384 | G53: I_Model Details!I129 | I53: ='Batch Economics'!D28 -> 3100.8509 | J53: =I53-F53 -> -8508.5329 | K53: =IF(I53=0,"no sale",IF(I53>=F53,"On","Off")) -> Off
C54: Lemak | E54: Rp/kg | F54: 29023.459 | G54: I_Model Details!I132 | I54: ='Batch Economics'!D29 -> 0 | J54: =I54-F54 -> -29023.459 | K54: =IF(I54=0,"no sale",IF(I54>=F54,"On","Off")) -> no sale
B55: B_KPI sudah memberi peringatan: benchmark by-product memicu 4 dari 5 kategori. Harga by-product di budget ~3x harga laku — ini yang sama membuat HPP by-product di Accurate terlalu tinggi.

Sheet Segment GP
A1: GROSS PROFIT BY SEGMENT — RPA and Trading, March to August 2026 (Rp)
A2: Mar–Jul and "Aug as booked" follow the accounting mapping (PL - Performance): unbilled revenue and all its HPP sit in RPA. Columns J–L move the 10 unbilled invoices to the segment of their items and re-cost them; M is the corrected August.
B4: Line | C4: Source / basis | D4: Mar-26 | E4: Apr-26 | F4: May-26 | G4: Jun-26 | H4: Jul-26 | I4: Aug-26 as booked | J4: Adj-1 unbilled to item segment | K4: Adj-2 HPP at MA on SJ date | L4: Adj-3 later DOs re-costed | M4: Aug-26 CORRECTED | N4: YTD Mar–Aug corrected
B5: A. REVENUE
B6: Revenue — RPA | C6: GL 4101006/07/10 (+4101013 as booked) | D6: =-(SUMIFS(I_GL!$D$5:$D$29,I_GL!$C$5:$C$29,"Rev RPA")+SUMIFS(I_GL!$D$5:$D$29,I_GL!$C$5:$C$29,"Rev Unbilled")) -> 190035900 | E6: =-(SUMIFS(I_GL!$E$5:$E$29,I_GL!$C$5:$C$29,"Rev RPA")+SUMIFS(I_GL!$E$5:$E$29,I_GL!$C$5:$C$29,"Rev Unbilled")) -> 646041120 | F6: =-(SUMIFS(I_GL!$F$5:$F$29,I_GL!$C$5:$C$29,"Rev RPA")+SUMIFS(I_GL!$F$5:$F$29,I_GL!$C$5:$C$29,"Rev Unbilled")) -> 1402180774 | G6: =-(SUMIFS(I_GL!$G$5:$G$29,I_GL!$C$5:$C$29,"Rev RPA")+SUMIFS(I_GL!$G$5:$G$29,I_GL!$C$5:$C$29,"Rev Unbilled")) -> 5.0030944e+08 | H6: =-(SUMIFS(I_GL!$H$5:$H$29,I_GL!$C$5:$C$29,"Rev RPA")+SUMIFS(I_GL!$H$5:$H$29,I_GL!$C$5:$C$29,"Rev Unbilled")) -> 246532160 | I6: =-(SUMIFS(I_GL!$I$5:$I$29,I_GL!$C$5:$C$29,"Rev RPA")+SUMIFS(I_GL!$I$5:$I$29,I_GL!$C$5:$C$29,"Rev Unbilled")) -> 3044438109 | J6: =SUMIFS(I_GL!$I$5:$I$29,I_GL!$C$5:$C$29,"Rev Unbilled")+Unbilled!J44 -> -3.5275112e+08 | K6: 0 | L6: 0 | M6: =SUM(I6:L6) -> 2.691687e+09 | N6: =SUM(D6:H6)+M6 -> 5.6767864e+09
B7: Revenue — Trading | C7: GL 4101012 less 4101004 | D7: =-SUMIFS(I_GL!$D$5:$D$29,I_GL!$C$5:$C$29,"Rev Trading") -> 0 | E7: =-SUMIFS(I_GL!$E$5:$E$29,I_GL!$C$5:$C$29,"Rev Trading") -> 149939860 | F7: =-SUMIFS(I_GL!$F$5:$F$29,I_GL!$C$5:$C$29,"Rev Trading") -> 44220195 | G7: =-SUMIFS(I_GL!$G$5:$G$29,I_GL!$C$5:$C$29,"Rev Trading") -> 922384240 | H7: =-SUMIFS(I_GL!$H$5:$H$29,I_GL!$C$5:$C$29,"Rev Trading") -> 2.8764258e+09 | I7: =-SUMIFS(I_GL!$I$5:$I$29,I_GL!$C$5:$C$29,"Rev Trading") -> 5317322794 | J7: =Unbilled!J45 -> 3.5275112e+08 | K7: 0 | L7: 0 | M7: =SUM(I7:L7) -> 5.6700739e+09 | N7: =SUM(D7:H7)+M7 -> 9.663044e+09
B8: Revenue — unbilled, segment not yet known | C8: 6 invoices without item detail | D8: 0 | E8: 0 | F8: 0 | G8: 0 | H8: 0 | I8: 0 | J8: =Unbilled!J46 -> 0 | K8: 0 | L8: 0 | M8: =SUM(I8:L8) -> 0 | N8: =SUM(D8:H8)+M8 -> 0
B9: TOTAL REVENUE | D9: =SUM(D6:D8) -> 190035900 | E9: =SUM(E6:E8) -> 795980980 | F9: =SUM(F6:F8) -> 1446400969 | G9: =SUM(G6:G8) -> 1.4226937e+09 | H9: =SUM(H6:H8) -> 3.1229579e+09 | I9: =SUM(I6:I8) -> 8361760903 | J9: =SUM(J6:J8) -> 0 | K9: =SUM(K6:K8) -> 0 | ... N9: =SUM(N6:N8) -> 1.533983e+10
B10: B. PRODUCT COGS (live bird + inbound freight + maklon for RPA; purchase cost for Trading)
B11: COGS — RPA per GL | C11: GL 5100004/05/06 (maklon expensed until Jul) | D11: =-SUMIFS(I_GL!$D$5:$D$29,I_GL!$C$5:$C$29,"COGS RPA") -> -1.7515188e+08 | E11: =-SUMIFS(I_GL!$E$5:$E$29,I_GL!$C$5:$C$29,"COGS RPA") -> -6.3689426e+08 | F11: =-SUMIFS(I_GL!$F$5:$F$29,I_GL!$C$5:$C$29,"COGS RPA") -> -1.4855625e+09 | G11: =-SUMIFS(I_GL!$G$5:$G$29,I_GL!$C$5:$C$29,"COGS RPA") -> -4.8423077e+08 | H11: =-SUMIFS(I_GL!$H$5:$H$29,I_GL!$C$5:$C$29,"COGS RPA") -> -2.4804879e+08 | I11: =-SUMIFS(I_GL!$I$5:$I$29,I_GL!$C$5:$C$29,"COGS RPA") -> -3.1189843e+09 | J11: =Unbilled!L17-Unbilled!K44 -> 3.6442167e+08 | K11: =-(Unbilled!F44-Unbilled!E44) -> -3023524.4 | L11: =-SUMIFS('MA Engine'!$AC$6:$AC$1110,'MA Engine'!$C$6:$C$1110,"RPA",'MA Engine'!$H$6:$H$1110,8,'MA Engine'!$P$6:$P$1110,"<>Y") -> 2436949.6 | M11: =SUM(I11:L11) -> -2.7551492e+09 | N11: =SUM(D11:H11)+M11 -> -5.7850374e+09
B12: Performance adjustment — maklon timing | C12: PL - Performance Apr/May | D12: 0 | E12: 76362362 | F12: -76362362 | G12: 0 | H12: 0 | I12: 0 | J12: 0 | K12: 0 | L12: 0 | M12: =SUM(I12:L12) -> 0 | N12: =SUM(D12:H12)+M12 -> 0
B13: COGS — RPA | D13: =D11+D12 -> -1.7515188e+08 | E13: =E11+E12 -> -5.6053189e+08 | F13: =F11+F12 -> -1.5619249e+09 | G13: =G11+G12 -> -4.8423077e+08 | H13: =H11+H12 -> -2.4804879e+08 | I13: =I11+I12 -> -3.1189843e+09 | J13: =J11+J12 -> 3.6442167e+08 | K13: =K11+K12 -> -3023524.4 | L13: =L11+L12 -> 2436949.6 | M13: =SUM(I13:L13) -> -2.7551492e+09 | N13: =SUM(D13:H13)+M13 -> -5.7850374e+09
B14: COGS — Trading | C14: GL 5100011 | D14: =-SUMIFS(I_GL!$D$5:$D$29,I_GL!$C$5:$C$29,"COGS Trading") -> 0 | E14: =-SUMIFS(I_GL!$E$5:$E$29,I_GL!$C$5:$C$29,"COGS Trading") -> -141127370 | F14: =-SUMIFS(I_GL!$F$5:$F$29,I_GL!$C$5:$C$29,"COGS Trading") -> -40506060 | G14: =-SUMIFS(I_GL!$G$5:$G$29,I_GL!$C$5:$C$29,"COGS Trading") -> -8.077824e+08 | H14: =-SUMIFS(I_GL!$H$5:$H$29,I_GL!$C$5:$C$29,"COGS Trading") -> -2.3922533e+09 | I14: =-SUMIFS(I_GL!$I$5:$I$29,I_GL!$C$5:$C$29,"COGS Trading") -> -4.835721e+09 | J14: =-Unbilled!K45 -> -3.6442167e+08 | K14: =-(Unbilled!F45-Unbilled!E45) -> 14954.501 | L14: =-SUMIFS('MA Engine'!$AC$6:$AC$1110,'MA Engine'!$C$6:$C$1110,"Trading",'MA Engine'!$H$6:$H$1110,8,'MA Engine'!$P$6:$P$1110,"<>Y") -> 0 | M14: =SUM(I14:L14) -> -5.2001277e+09 | N14: =SUM(D14:H14)+M14 -> -8.5817968e+09
B15: COGS — unbilled, segment not yet known | C15: estimate booked | D15: 0 | E15: 0 | F15: 0 | G15: 0 | H15: 0 | I15: 0 | J15: =-Unbilled!K46 -> 0 | K15: 0 | L15: 0 | M15: =SUM(I15:L15) -> 0 | N15: =SUM(D15:H15)+M15 -> 0
B16: TOTAL PRODUCT COGS | D16: =D13+D14+D15 -> -1.7515188e+08 | E16: =E13+E14+E15 -> -7.0165926e+08 | F16: =F13+F14+F15 -> -1.6024309e+09 | G16: =G13+G14+G15 -> -1.2920132e+09 | H16: =H13+H14+H15 -> -2.6403021e+09 | I16: =I13+I14+I15 -> -7.9547053e+09 | J16: =J13+J14+J15 -> 0.38989997 | K16: =K13+K14+K15 -> -3008569.9 | ... N16: =N13+N14+N15 -> -1.4366834e+10
B17: C. PRODUCT GROSS PROFIT
B18: Product GP — RPA | D18: =D6+D13 -> 14884021 | E18: =E6+E13 -> 85509227 | F18: =F6+F13 -> -1.597441e+08 | G18: =G6+G13 -> 16078670 | H18: =H6+H13 -> -1516632.5 | I18: =I6+I13 -> -74546222 | J18: =J6+J13 -> 11670554 | K18: =K6+K13 -> -3023524.4 | ... N18: =N6+N13 -> -1.0825106e+08
B19: Product GP — Trading | D19: =D7+D14 -> 0 | E19: =E7+E14 -> 8812490 | F19: =F7+F14 -> 3714135 | G19: =G7+G14 -> 1.1460184e+08 | H19: =H7+H14 -> 4.8417248e+08 | I19: =I7+I14 -> 4.8160183e+08 | J19: =J7+J14 -> -11670553 | K19: =K7+K14 -> 14954.501 | ... N19: =N7+N14 -> 1.0812472e+09
B20: Product GP — unbilled, segment not known | D20: =D8+D15 -> 0 | E20: =E8+E15 -> 0 | F20: =F8+F15 -> 0 | G20: =G8+G15 -> 0 | H20: =H8+H15 -> 0 | I20: =I8+I15 -> 0 | J20: =J8+J15 -> 0 | K20: =K8+K15 -> 0 | ... N20: =N8+N15 -> 0
B21: PRODUCT GP — TOTAL | D21: =D9+D16 -> 14884021 | E21: =E9+E16 -> 94321717 | F21: =F9+F16 -> -1.5602997e+08 | G21: =G9+G16 -> 1.3068051e+08 | H21: =H9+H16 -> 4.8265585e+08 | I21: =I9+I16 -> 4.0705561e+08 | J21: =J9+J16 -> 0.38989997 | K21: =K9+K16 -> -3008569.9 | ... N21: =N9+N16 -> 9.7299612e+08
B22: Product GP % — RPA | D22: =IF(D6=0,0,D18/D6) -> 0.078322154 | E22: =IF(E6=0,0,E18/E6) -> 0.1323588 | F22: =IF(F6=0,0,F18/F6) -> -0.11392547 | G22: =IF(G6=0,0,G18/G6) -> 0.03213745 | H22: =IF(H6=0,0,H18/H6) -> -0.0061518649 | I22: =IF(I6=0,0,I18/I6) -> -0.024486036 | M22: =IF(M6=0,0,M18/M6) -> -0.023577126 | N22: =IF(N6=0,0,N18/N6) -> -0.019069074
B23: Product GP % — Trading | D23: =IF(D7=0,0,D19/D7) -> 0 | E23: =IF(E7=0,0,E19/E7) -> 0.058773498 | F23: =IF(F7=0,0,F19/F7) -> 0.083991828 | G23: =IF(G7=0,0,G19/G7) -> 0.12424523 | H23: =IF(H7=0,0,H19/H7) -> 0.16832434 | I23: =IF(I7=0,0,I19/I7) -> 0.090572239 | M23: =IF(M7=0,0,M19/M7) -> 0.082881853 | N23: =IF(N7=0,0,N19/N7) -> 0.11189509
B24: Product GP % — unbilled, not known | D24: =IF(D8=0,0,D20/D8) -> 0 | E24: =IF(E8=0,0,E20/E8) -> 0 | F24: =IF(F8=0,0,F20/F8) -> 0 | G24: =IF(G8=0,0,G20/G8) -> 0 | H24: =IF(H8=0,0,H20/H8) -> 0 | I24: =IF(I8=0,0,I20/I8) -> 0 | M24: =IF(M8=0,0,M20/M8) -> 0 | N24: =IF(N8=0,0,N20/N8) -> 0
B25: Product GP % — total | D25: =IF(D9=0,0,D21/D9) -> 0.078322154 | E25: =IF(E9=0,0,E21/E9) -> 0.11849745 | F25: =IF(F9=0,0,F21/F9) -> -0.10787463 | G25: =IF(G9=0,0,G21/G9) -> 0.091854284 | H25: =IF(H9=0,0,H21/H9) -> 0.15455086 | I25: =IF(I9=0,0,I21/I9) -> 0.048680608 | M25: =IF(M9=0,0,M21/M9) -> 0.048612247 | N25: =IF(N9=0,0,N21/N9) -> 0.063429392
B26: D. COST OF SALES — OTHERS (expedition + blasting) — kept separate unless the switch on COS Others B3 = Yes
B27: Cost of sales others — allocated to RPA | C27: only if COS Others B3 = Yes | D27: =IF('COS Others'!$B$3="Yes",-'COS Others'!B16,0) -> 0 | E27: =IF('COS Others'!$B$3="Yes",-'COS Others'!C16,0) -> 0 | F27: =IF('COS Others'!$B$3="Yes",-'COS Others'!D16,0) -> 0 | G27: =IF('COS Others'!$B$3="Yes",-'COS Others'!E16,0) -> 0 | H27: =IF('COS Others'!$B$3="Yes",-'COS Others'!F16,0) -> 0 | I27: =IF('COS Others'!$B$3="Yes",-'COS Others'!G16,0) -> 0 | J27: 0 | K27: 0 | L27: 0 | M27: =SUM(I27:L27) -> 0 | N27: =SUM(D27:H27)+M27 -> 0
B28: Cost of sales others — allocated to Trading | C28: only if COS Others B3 = Yes | D28: =IF('COS Others'!$B$3="Yes",-'COS Others'!B17,0) -> 0 | E28: =IF('COS Others'!$B$3="Yes",-'COS Others'!C17,0) -> 0 | F28: =IF('COS Others'!$B$3="Yes",-'COS Others'!D17,0) -> 0 | G28: =IF('COS Others'!$B$3="Yes",-'COS Others'!E17,0) -> 0 | H28: =IF('COS Others'!$B$3="Yes",-'COS Others'!F17,0) -> 0 | I28: =IF('COS Others'!$B$3="Yes",-'COS Others'!G17,0) -> 0 | J28: 0 | K28: 0 | L28: 0 | M28: =SUM(I28:L28) -> 0 | N28: =SUM(D28:H28)+M28 -> 0
B29: Cost of sales others — total (GL) | C29: GL 5100002/07/09/10 | D29: =-'COS Others'!B12 -> -784000 | E29: =-'COS Others'!C12 -> -45272146 | F29: =-'COS Others'!D12 -> -1.244876e+08 | G29: =-'COS Others'!E12 -> -1.9266042e+08 | H29: =-'COS Others'!F12 -> -1.1960448e+08 | I29: =-'COS Others'!G12 -> -100345850 | J29: 0 | K29: 0 | L29: 0 | M29: =SUM(I29:L29) -> -100345850 | N29: =SUM(D29:H29)+M29 -> -5.831545e+08
B30: E. GROSS PROFIT — segments, then what is not in a segment, then the Gross Profit line of the slide P&L
B31: Gross profit — RPA | D31: =D18+D27 -> 14884021 | E31: =E18+E27 -> 85509227 | F31: =F18+F27 -> -1.597441e+08 | G31: =G18+G27 -> 16078670 | H31: =H18+H27 -> -1516632.5 | I31: =I18+I27 -> -74546222 | J31: =J18+J27 -> 11670554 | K31: =K18+K27 -> -3023524.4 | ... N31: =N18+N27 -> -1.0825106e+08
B32: Gross profit — Trading | D32: =D19+D28 -> 0 | E32: =E19+E28 -> 8812490 | F32: =F19+F28 -> 3714135 | G32: =G19+G28 -> 1.1460184e+08 | H32: =H19+H28 -> 4.8417248e+08 | I32: =I19+I28 -> 4.8160183e+08 | J32: =J19+J28 -> -11670553 | K32: =K19+K28 -> 14954.501 | ... N32: =N19+N28 -> 1.0812472e+09
B33: Not in a segment: cost of sales others not allocated (+ unbilled without segment) | D33: =D20+D29-D27-D28 -> -784000 | E33: =E20+E29-E27-E28 -> -45272146 | F33: =F20+F29-F27-F28 -> -1.244876e+08 | G33: =G20+G29-G27-G28 -> -1.9266042e+08 | H33: =H20+H29-H27-H28 -> -1.1960448e+08 | I33: =I20+I29-I27-I28 -> -100345850 | J33: =J20+J29-J27-J28 -> 0 | K33: =K20+K29-K27-K28 -> 0 | ... N33: =N20+N29-N27-N28 -> -5.831545e+08
B34: GROSS PROFIT — TOTAL | D34: =D21+D29 -> 14100021 | E34: =E21+E29 -> 49049571 | F34: =F21+F29 -> -2.8051756e+08 | G34: =G21+G29 -> -61979915 | H34: =H21+H29 -> 3.6305137e+08 | I34: =I21+I29 -> 3.0670976e+08 | J34: =J21+J29 -> 0.38989997 | K34: =K21+K29 -> -3008569.9 | ... N34: =N21+N29 -> 3.8984162e+08
B35: GP margin — RPA | D35: =IF(D6=0,0,D31/D6) -> 0.078322154 | E35: =IF(E6=0,0,E31/E6) -> 0.1323588 | F35: =IF(F6=0,0,F31/F6) -> -0.11392547 | G35: =IF(G6=0,0,G31/G6) -> 0.03213745 | H35: =IF(H6=0,0,H31/H6) -> -0.0061518649 | I35: =IF(I6=0,0,I31/I6) -> -0.024486036 | M35: =IF(M6=0,0,M31/M6) -> -0.023577126 | N35: =IF(N6=0,0,N31/N6) -> -0.019069074
B36: GP margin — Trading | D36: =IF(D7=0,0,D32/D7) -> 0 | E36: =IF(E7=0,0,E32/E7) -> 0.058773498 | F36: =IF(F7=0,0,F32/F7) -> 0.083991828 | G36: =IF(G7=0,0,G32/G7) -> 0.12424523 | H36: =IF(H7=0,0,H32/H7) -> 0.16832434 | I36: =IF(I7=0,0,I32/I7) -> 0.090572239 | M36: =IF(M7=0,0,M32/M7) -> 0.082881853 | N36: =IF(N7=0,0,N32/N7) -> 0.11189509
B37: Not in a segment ÷ total revenue | D37: =IF(D9=0,0,D33/D9) -> -0.0041255363 | E37: =IF(E9=0,0,E33/E9) -> -0.056875914 | F37: =IF(F9=0,0,F33/F9) -> -0.086067143 | G37: =IF(G9=0,0,G33/G9) -> -0.13541947 | H37: =IF(H9=0,0,H33/H9) -> -0.038298459 | I37: =IF(I9=0,0,I33/I9) -> -0.012000564 | M37: =IF(M9=0,0,M33/M9) -> -0.012000564 | N37: =IF(N9=0,0,N33/N9) -> -0.038015707
B38: GP MARGIN — TOTAL | D38: =IF(D9=0,0,D34/D9) -> 0.074196618 | E38: =IF(E9=0,0,E34/E9) -> 0.061621536 | F38: =IF(F9=0,0,F34/F9) -> -0.19394177 | G38: =IF(G9=0,0,G34/G9) -> -0.043565186 | H38: =IF(H9=0,0,H34/H9) -> 0.11625241 | I38: =IF(I9=0,0,I34/I9) -> 0.036680044 | M38: =IF(M9=0,0,M34/M9) -> 0.036611683 | N38: =IF(N9=0,0,N34/N9) -> 0.025413685
B39: F. VOLUME AND PER KG
B40: kg sold — RPA | C40: Data SKU invoiced (+ all unbilled kg as booked) | D40: =SUMIFS('Data SKU'!$F$5:$F$116,'Data SKU'!$A$5:$A$116,"RPA",'Data SKU'!$D$5:$D$116,3,'Data SKU'!$N$5:$N$116,"Invoiced") -> 7865.7 | E40: =SUMIFS('Data SKU'!$F$5:$F$116,'Data SKU'!$A$5:$A$116,"RPA",'Data SKU'!$D$5:$D$116,4,'Data SKU'!$N$5:$N$116,"Invoiced") -> 39093.41 | F40: =SUMIFS('Data SKU'!$F$5:$F$116,'Data SKU'!$A$5:$A$116,"RPA",'Data SKU'!$D$5:$D$116,5,'Data SKU'!$N$5:$N$116,"Invoiced") -> 69041.25 | G40: =SUMIFS('Data SKU'!$F$5:$F$116,'Data SKU'!$A$5:$A$116,"RPA",'Data SKU'!$D$5:$D$116,6,'Data SKU'!$N$5:$N$116,"Invoiced") -> 15561.3 | H40: =SUMIFS('Data SKU'!$F$5:$F$116,'Data SKU'!$A$5:$A$116,"RPA",'Data SKU'!$D$5:$D$116,7,'Data SKU'!$N$5:$N$116,"Invoiced") -> 12576.01 | I40: =SUMIFS('Data SKU'!$F$5:$F$116,'Data SKU'!$A$5:$A$116,"RPA",'Data SKU'!$D$5:$D$116,8,'Data SKU'!$N$5:$N$116,"Invoiced")+Unbilled!G17 -> 106896.28 | J40: =-Unbilled!G17+Unbilled!C44+Unbilled!G44 -> -11350.56 | K40: 0 | L40: 0 | M40: =SUM(I40:L40) -> 95545.72 | N40: =SUM(D40:H40)+M40 -> 239683.39
B41: kg sold — Trading | C41: Data SKU invoiced | D41: =SUMIFS('Data SKU'!$F$5:$F$116,'Data SKU'!$A$5:$A$116,"Trading",'Data SKU'!$D$5:$D$116,3,'Data SKU'!$N$5:$N$116,"Invoiced") -> 0 | E41: =SUMIFS('Data SKU'!$F$5:$F$116,'Data SKU'!$A$5:$A$116,"Trading",'Data SKU'!$D$5:$D$116,4,'Data SKU'!$N$5:$N$116,"Invoiced") -> 3550.57 | F41: =SUMIFS('Data SKU'!$F$5:$F$116,'Data SKU'!$A$5:$A$116,"Trading",'Data SKU'!$D$5:$D$116,5,'Data SKU'!$N$5:$N$116,"Invoiced") -> 1598.33 | G41: =SUMIFS('Data SKU'!$F$5:$F$116,'Data SKU'!$A$5:$A$116,"Trading",'Data SKU'!$D$5:$D$116,6,'Data SKU'!$N$5:$N$116,"Invoiced") -> 27413.79 | H41: =SUMIFS('Data SKU'!$F$5:$F$116,'Data SKU'!$A$5:$A$116,"Trading",'Data SKU'!$D$5:$D$116,7,'Data SKU'!$N$5:$N$116,"Invoiced") -> 86946.7 | I41: =SUMIFS('Data SKU'!$F$5:$F$116,'Data SKU'!$A$5:$A$116,"Trading",'Data SKU'!$D$5:$D$116,8,'Data SKU'!$N$5:$N$116,"Invoiced") -> 157574.42 | J41: =Unbilled!C45+Unbilled!G45 -> 11350.56 | K41: 0 | L41: 0 | M41: =SUM(I41:L41) -> 168924.98 | N41: =SUM(D41:H41)+M41 -> 288434.37
B42: kg sold — unbilled, segment not known | D42: 0 | E42: 0 | F42: 0 | G42: 0 | H42: 0 | I42: 0 | J42: =Unbilled!C46+Unbilled!G46 -> 0 | K42: 0 | L42: 0 | M42: =SUM(I42:L42) -> 0 | N42: =SUM(D42:H42)+M42 -> 0
B43: kg sold — total | D43: =SUM(D40:D42) -> 7865.7 | E43: =SUM(E40:E42) -> 42643.98 | F43: =SUM(F40:F42) -> 70639.58 | G43: =SUM(G40:G42) -> 42975.09 | H43: =SUM(H40:H42) -> 99522.71 | I43: =SUM(I40:I42) -> 264470.7 | J43: =SUM(J40:J42) -> 0 | K43: =SUM(K40:K42) -> 0 | ... N43: =SUM(N40:N42) -> 528117.76
B44: RPA — ASP (Rp/kg) | D44: =IF(D40=0,0,D6/D40) -> 24160.075 | E44: =IF(E40=0,0,E6/E40) -> 16525.576 | F44: =IF(F40=0,0,F6/F40) -> 20309.319 | G44: =IF(G40=0,0,G6/G40) -> 32150.877 | H44: =IF(H40=0,0,H6/H40) -> 19603.369 | I44: =IF(I40=0,0,I6/I40) -> 28480.3 | M44: =IF(M40=0,0,M6/M40) -> 28171.717 | N44: =IF(N40=0,0,N6/N40) -> 23684.521
B45: RPA — product cost (Rp/kg) | D45: =IF(D40=0,0,D13/D40) -> -22267.806 | E45: =IF(E40=0,0,E13/E40) -> -14338.271 | F45: =IF(F40=0,0,F13/F40) -> -22623.068 | G45: =IF(G40=0,0,G13/G40) -> -31117.63 | H45: =IF(H40=0,0,H13/H40) -> -19723.966 | I45: =IF(I40=0,0,I13/I40) -> -29177.67 | M45: =IF(M40=0,0,M13/M40) -> -28835.925 | N45: =IF(N40=0,0,N13/N40) -> -24136.163
B46: RPA — product GP (Rp/kg) | D46: =IF(D40=0,0,D18/D40) -> 1892.2691 | E46: =IF(E40=0,0,E18/E40) -> 2187.3054 | F46: =IF(F40=0,0,F18/F40) -> -2313.7487 | G46: =IF(G40=0,0,G18/G40) -> 1033.2472 | H46: =IF(H40=0,0,H18/H40) -> -120.59727 | I46: =IF(I40=0,0,I18/I40) -> -697.36965 | M46: =IF(M40=0,0,M18/M40) -> -664.20812 | N46: =IF(N40=0,0,N18/N40) -> -451.64189
B47: RPA — gross profit (Rp/kg) | D47: =IF(D40=0,0,D31/D40) -> 1892.2691 | E47: =IF(E40=0,0,E31/E40) -> 2187.3054 | F47: =IF(F40=0,0,F31/F40) -> -2313.7487 | G47: =IF(G40=0,0,G31/G40) -> 1033.2472 | H47: =IF(H40=0,0,H31/H40) -> -120.59727 | I47: =IF(I40=0,0,I31/I40) -> -697.36965 | M47: =IF(M40=0,0,M31/M40) -> -664.20812 | N47: =IF(N40=0,0,N31/N40) -> -451.64189
B48: Trading — ASP (Rp/kg) | D48: =IF(D41=0,0,D7/D41) -> 0 | E48: =IF(E41=0,0,E7/E41) -> 42229.8 | F48: =IF(F41=0,0,F7/F41) -> 27666.499 | G48: =IF(G41=0,0,G7/G41) -> 33646.725 | H48: =IF(H41=0,0,H7/H41) -> 33082.633 | I48: =IF(I41=0,0,I7/I41) -> 33744.835 | M48: =IF(M41=0,0,M7/M41) -> 33565.633 | N48: =IF(N41=0,0,N7/N41) -> 33501.708
B49: Trading — product cost (Rp/kg) | D49: =IF(D41=0,0,D14/D41) -> 0 | E49: =IF(E41=0,0,E14/E41) -> -39747.807 | F49: =IF(F41=0,0,F14/F41) -> -25342.739 | G49: =IF(G41=0,0,G14/G41) -> -29466.28 | H49: =IF(H41=0,0,H14/H41) -> -27514.021 | I49: =IF(I41=0,0,I14/I41) -> -30688.49 | M49: =IF(M41=0,0,M14/M41) -> -30783.651 | N49: =IF(N41=0,0,N14/N41) -> -29753.031
B50: Trading — product GP (Rp/kg) | D50: =IF(D41=0,0,D19/D41) -> 0 | E50: =IF(E41=0,0,E19/E41) -> 2481.993 | F50: =IF(F41=0,0,F19/F41) -> 2323.7598 | G50: =IF(G41=0,0,G19/G41) -> 4180.4449 | H50: =IF(H41=0,0,H19/H41) -> 5568.6125 | I50: =IF(I41=0,0,I19/I41) -> 3056.3452 | M50: =IF(M41=0,0,M19/M41) -> 2781.9819 | N50: =IF(N41=0,0,N19/N41) -> 3748.6766
B51: Trading — gross profit (Rp/kg) | D51: =IF(D41=0,0,D32/D41) -> 0 | E51: =IF(E41=0,0,E32/E41) -> 2481.993 | F51: =IF(F41=0,0,F32/F41) -> 2323.7598 | G51: =IF(G41=0,0,G32/G41) -> 4180.4449 | H51: =IF(H41=0,0,H32/H41) -> 5568.6125 | I51: =IF(I41=0,0,I32/I41) -> 3056.3452 | M51: =IF(M41=0,0,M32/M41) -> 2781.9819 | N51: =IF(N41=0,0,N32/N41) -> 3748.6766
B53: G. TIE-OUT TO THE ACCOUNTING TEAM'S FS (sheet PL - Performance)
B54: Gross profit per PL - Performance | C54: FS_KGR_Aug_2026.xlsx, Performance columns | D54: 14100021 | E54: 49049571 | F54: -2.8051756e+08 | G54: -61979915 | H54: 3.6305137e+08 | I54: 3.0670976e+08
B55: Difference: as booked − accounting (nil) | D55: =ROUND(D34-D54,0) -> 0 | E55: =ROUND(E34-E54,0) -> 0 | F55: =ROUND(F34-F54,0) -> 0 | G55: =ROUND(G34-G54,0) -> 0 | H55: =ROUND(H34-H54,0) -> 0 | I55: =ROUND(I34-I54,0) -> 0
B56: Adj-1 nets to nil across segments (revenue / COGS) | J56: =ROUND(J9,0)&" / "&ROUND(J16,0) -> 0 / 0
B57: Check: RPA + Trading + not in a segment − total GP (nil) | D57: =ROUND(D31+D32+D33-D34,0) -> 0 | E57: =ROUND(E31+E32+E33-E34,0) -> 0 | F57: =ROUND(F31+F32+F33-F34,0) -> 0 | G57: =ROUND(G31+G32+G33-G34,0) -> 0 | H57: =ROUND(H31+H32+H33-H34,0) -> 0 | I57: =ROUND(I31+I32+I33-I34,0) -> 0 | J57: =ROUND(J31+J32+J33-J34,0) -> 0 | K57: =ROUND(K31+K32+K33-K34,0) -> 0 | ... N57: =ROUND(N31+N32+N33-N34,0) -> 0
B59: Reading: RPA and Trading gross profit in the Aug-26 CORRECTED column are what the business earned per segment once the 10 unbilled invoices are put where their items came from and costed at the moving average on the day the goods left. The 6 invoices without item detail stay in their own line until their items are known (or pick a segment for each in Unbilled column N).

Sheet GP Waterfall
A1: GP MARGIN WATERFALL — July to August 2026, by segment (same method as the NMG slide)
A2: Each bar = revenue share of the bucket in August × (bucket margin − July margin). Buckets carry the HPP booked on the DOs that shipped them (FIFO by DO), so there is no moving-average bar. Bars add exactly from the July margin to the corrected August margin.
B4: RPA — GROSS PROFIT CONTEXT, August 2026 vs July 2026 (Rp)
C5: Jul-26 | D5: Stok pra-Juli | E5: Produksi Juli | F5: Produksi Agustus | G5: Lain-lain* | H5: Total Aug-26 (corrected) | I5: Variance Aug − Jul | J5: Variance %
B6: Pendapatan | C6: ='Segment GP'!H6 -> 246532160 | D6: =Vintage!I6 -> 5.4166332e+08 | E6: =Vintage!I7 -> 81468140 | F6: =Vintage!I8 -> 1.7504327e+09 | G6: =H6-SUM(D6:F6) -> 318122834 | H6: ='Segment GP'!M6 -> 2.691687e+09 | I6: =H6-C6 -> 2.4451548e+09 | J6: =IF(C6=0,0,I6/ABS(C6)) -> 9.9181982
B7: HPP produk (as booked) | C7: ='Segment GP'!H13 -> -2.4804879e+08 | D7: =-Vintage!J6 -> -5.0466641e+08 | E7: =-Vintage!J7 -> -71048495 | F7: =-Vintage!J8-Vintage!J9 -> -1.8665731e+09 | G7: =H7-SUM(D7:F7) -> -3.1286126e+08 | H7: ='Segment GP'!M13 -> -2.7551492e+09 | I7: =H7-C7 -> -2.5071004e+09 | J7: =IF(C7=0,0,I7/ABS(C7)) -> -10.107287
B8: Laba kotor produk | C8: =C6+C7 -> -1516632.5 | D8: =D6+D7 -> 36996907 | E8: =E6+E7 -> 10419645 | F8: =F6+F7 -> -1.1614037e+08 | G8: =G6+G7 -> 5261574.3 | H8: =H6+H7 -> -63462243 | I8: =H8-C8 -> -61945610 | J8: =IF(C8=0,0,I8/ABS(C8)) -> -40.844179
B9: Cost of sales others (only if allocated — COS Others B3) | C9: ='Segment GP'!H27 -> 0 | G9: =H9 -> 0 | H9: ='Segment GP'!M27 -> 0 | I9: =H9-C9 -> 0 | J9: =IF(C9=0,0,I9/ABS(C9)) -> 0
B10: Laba kotor | C10: =C8+N(C9) -> -1516632.5 | D10: =D8+N(D9) -> 36996907 | E10: =E8+N(E9) -> 10419645 | F10: =F8+N(F9) -> -1.1614037e+08 | G10: =G8+N(G9) -> 5261574.3 | H10: =H8+N(H9) -> -63462243 | I10: =H10-C10 -> -61945610 | J10: =IF(C10=0,0,I10/ABS(C10)) -> -40.844179
B11: GP margin | C11: =IF(C6=0,0,C10/C6) -> -0.0061518649 | D11: =IF(D6=0,0,D10/D6) -> 0.068302403 | E11: =IF(E6=0,0,E10/E6) -> 0.1278984 | F11: =IF(F6=0,0,F10/F6) -> -0.06634952 | H11: =IF(H6=0,0,H10/H6) -> -0.023577126 | I11: =H11-C11 -> -0.017425261
B12: Each vintage carries the HPP Accurate booked on the DOs that shipped it (FIFO by DO), so the buckets add up to booked HPP — no moving-average bar. *Lain-lain = revenue/cost outside the item-level split (revenue without SI, invoices without item detail).
B14: RPA — GP MARGIN WATERFALL Jul → Aug (percentage points)
B15: Step | C15: FIFO point estimate | D15: Lower bound (new stock first) | E15: Revenue share Aug | F15: Bucket margin | G15: How it is computed
B16: GP margin Jul-26 | C16: =C11 -> -0.0061518649 | D16: =C11 -> -0.0061518649 | G16: July gross profit ÷ July revenue (Segment GP)
B17: Stok pra-Juli | C17: =E17*(F17-$C$16) -> 0.014982851 | D17: =IF(Vintage!Q6=0,0,Vintage!Q6/$H$6*((Vintage!Q6-Vintage!R6)/Vintage!Q6-$C$16)) -> 0.015076938 | E17: =D6/$H$6 -> 0.20123563 | F17: =D11 -> 0.068302403 | G17: share × (bucket margin − July margin)
B18: Produksi Juli | C18: =E18*(F18-$C$16) -> 0.0040572421 | D18: =IF(Vintage!Q7=0,0,Vintage!Q7/$H$6*((Vintage!Q7-Vintage!R7)/Vintage!Q7-$C$16)) -> 0.0037235399 | E18: =E6/$H$6 -> 0.030266573 | F18: =E11 -> 0.1278984 | G18: share × (bucket margin − July margin)
B19: Produksi Agustus | C19: =E19*(F19-$C$16) -> -0.039147176 | D19: =IF(Vintage!Q8=0,0,Vintage!Q8/$H$6*((Vintage!Q8-(Vintage!R8+Vintage!R9))/Vintage!Q8-$C$16)) -> -0.03890756 | E19: =F6/$H$6 -> 0.65031064 | F19: =F11 -> -0.06634952 | G19: share × (bucket margin − July margin)
B20: Cost of sales others | C20: =H9/H6 -> 0 | D20: =H9/H6 -> 0 | G20: nil unless allocated (COS Others B3); otherwise at KGR level
B21: Lain-lain | C21: =(G6+G7)/H6-G6/H6*C11 -> 0.0026818211 | D21: =(G6+G7)/H6-G6/H6*C11 -> 0.0026818211 | G21: items outside the split, net of their share of the July margin
B22: GP margin Aug-26 (corrected) | C22: =SUM(C16:C21) -> -0.023577126 | D22: =SUM(D16:D21) -> -0.023577126
B23: Check: waterfall − Segment GP corrected margin (nil) | C23: =ROUND(C22-'Segment GP'!M35,8) -> 0 | D23: =ROUND(D22-'Segment GP'!M35,8) -> 0
B25: RPA — WHAT IS INSIDE EACH BAR, by product group (percentage points; rows add up to the bars above)
B26: Product group | C26: Stok pra-Juli | D26: Produksi Juli | E26: Produksi Agustus | F26: Total vintage bars | G26: Revenue from produksi agustus (Rp) | H26: Margin of produksi agustus
B27: Boneless & parting (from earlier boneless runs) | C27: =(SUMIFS(Vintage!$AN$36:$AN$127,Vintage!$C$36:$C$127,"RPA",Vintage!$BB$36:$BB$127,"Boneless & parting (from earlier boneless runs)")-SUMIFS(Vintage!$AI$36:$AI$127,Vintage!$C$36:$C$127,"RPA",Vintage!$BB$36:$BB$127,"Boneless & parting (from earlier boneless runs)")-$C$11*SUMIFS(Vintage!$AN$36:$AN$127,Vintage!$C$36:$C$127,"RPA",Vintage!$BB$36:$BB$127,"Boneless & parting (from earlier boneless runs)"))/$H$6 -> 0.006022082 | D27: =(SUMIFS(Vintage!$AO$36:$AO$127,Vintage!$C$36:$C$127,"RPA",Vintage!$BB$36:$BB$127,"Boneless & parting (from earlier boneless runs)")-SUMIFS(Vintage!$AJ$36:$AJ$127,Vintage!$C$36:$C$127,"RPA",Vintage!$BB$36:$BB$127,"Boneless & parting (from earlier boneless runs)")-$C$11*SUMIFS(Vintage!$AO$36:$AO$127,Vintage!$C$36:$C$127,"RPA",Vintage!$BB$36:$BB$127,"Boneless & parting (from earlier boneless runs)"))/$H$6 -> 0.0038842374 | E27: =(SUMIFS(Vintage!$AP$36:$AP$127,Vintage!$C$36:$C$127,"RPA",Vintage!$BB$36:$BB$127,"Boneless & parting (from earlier boneless runs)")-SUMIFS(Vintage!$AK$36:$AK$127,Vintage!$C$36:$C$127,"RPA",Vintage!$BB$36:$BB$127,"Boneless & parting (from earlier boneless runs)")-$C$11*SUMIFS(Vintage!$AP$36:$AP$127,Vintage!$C$36:$C$127,"RPA",Vintage!$BB$36:$BB$127,"Boneless & parting (from earlier boneless runs)"))/$H$6 -> 0 | F27: =SUM(C27:E27) -> 0.0099063194 | G27: =SUMIFS(Vintage!$AP$36:$AP$127,Vintage!$C$36:$C$127,"RPA",Vintage!$BB$36:$BB$127,"Boneless & parting (from earlier boneless runs)") -> 0 | H27: =IFERROR((G27-SUMIFS(Vintage!$AK$36:$AK$127,Vintage!$C$36:$C$127,"RPA",Vintage!$BB$36:$BB$127,"Boneless & parting (from earlier boneless runs)"))/G27,0) -> 0
B28: By-product (kepala, ceker, usus, HJA, lemak) | C28: =(SUMIFS(Vintage!$AN$36:$AN$127,Vintage!$C$36:$C$127,"RPA",Vintage!$BB$36:$BB$127,"By-product (kepala, ceker, usus, HJA, lemak)")-SUMIFS(Vintage!$AI$36:$AI$127,Vintage!$C$36:$C$127,"RPA",Vintage!$BB$36:$BB$127,"By-product (kepala, ceker, usus, HJA, lemak)")-$C$11*SUMIFS(Vintage!$AN$36:$AN$127,Vintage!$C$36:$C$127,"RPA",Vintage!$BB$36:$BB$127,"By-product (kepala, ceker, usus, HJA, lemak)"))/$H$6 -> -0.004516844 | D28: =(SUMIFS(Vintage!$AO$36:$AO$127,Vintage!$C$36:$C$127,"RPA",Vintage!$BB$36:$BB$127,"By-product (kepala, ceker, usus, HJA, lemak)")-SUMIFS(Vintage!$AJ$36:$AJ$127,Vintage!$C$36:$C$127,"RPA",Vintage!$BB$36:$BB$127,"By-product (kepala, ceker, usus, HJA, lemak)")-$C$11*SUMIFS(Vintage!$AO$36:$AO$127,Vintage!$C$36:$C$127,"RPA",Vintage!$BB$36:$BB$127,"By-product (kepala, ceker, usus, HJA, lemak)"))/$H$6 -> 0.00031225537 | E28: =(SUMIFS(Vintage!$AP$36:$AP$127,Vintage!$C$36:$C$127,"RPA",Vintage!$BB$36:$BB$127,"By-product (kepala, ceker, usus, HJA, lemak)")-SUMIFS(Vintage!$AK$36:$AK$127,Vintage!$C$36:$C$127,"RPA",Vintage!$BB$36:$BB$127,"By-product (kepala, ceker, usus, HJA, lemak)")-$C$11*SUMIFS(Vintage!$AP$36:$AP$127,Vintage!$C$36:$C$127,"RPA",Vintage!$BB$36:$BB$127,"By-product (kepala, ceker, usus, HJA, lemak)"))/$H$6 -> -0.026701966 | F28: =SUM(C28:E28) -> -0.030906555 | G28: =SUMIFS(Vintage!$AP$36:$AP$127,Vintage!$C$36:$C$127,"RPA",Vintage!$BB$36:$BB$127,"By-product (kepala, ceker, usus, HJA, lemak)") -> 34378441 | H28: =IFERROR((G28-SUMIFS(Vintage!$AK$36:$AK$127,Vintage!$C$36:$C$127,"RPA",Vintage!$BB$36:$BB$127,"By-product (kepala, ceker, usus, HJA, lemak)"))/G28,0) -> -2.0968032
B29: Karkas fresh | C29: =(SUMIFS(Vintage!$AN$36:$AN$127,Vintage!$C$36:$C$127,"RPA",Vintage!$BB$36:$BB$127,"Karkas fresh")-SUMIFS(Vintage!$AI$36:$AI$127,Vintage!$C$36:$C$127,"RPA",Vintage!$BB$36:$BB$127,"Karkas fresh")-$C$11*SUMIFS(Vintage!$AN$36:$AN$127,Vintage!$C$36:$C$127,"RPA",Vintage!$BB$36:$BB$127,"Karkas fresh"))/$H$6 -> 3.6500733e-05 | D29: =(SUMIFS(Vintage!$AO$36:$AO$127,Vintage!$C$36:$C$127,"RPA",Vintage!$BB$36:$BB$127,"Karkas fresh")-SUMIFS(Vintage!$AJ$36:$AJ$127,Vintage!$C$36:$C$127,"RPA",Vintage!$BB$36:$BB$127,"Karkas fresh")-$C$11*SUMIFS(Vintage!$AO$36:$AO$127,Vintage!$C$36:$C$127,"RPA",Vintage!$BB$36:$BB$127,"Karkas fresh"))/$H$6 -> 0 | E29: =(SUMIFS(Vintage!$AP$36:$AP$127,Vintage!$C$36:$C$127,"RPA",Vintage!$BB$36:$BB$127,"Karkas fresh")-SUMIFS(Vintage!$AK$36:$AK$127,Vintage!$C$36:$C$127,"RPA",Vintage!$BB$36:$BB$127,"Karkas fresh")-$C$11*SUMIFS(Vintage!$AP$36:$AP$127,Vintage!$C$36:$C$127,"RPA",Vintage!$BB$36:$BB$127,"Karkas fresh"))/$H$6 -> -0.0068626895 | F29: =SUM(C29:E29) -> -0.0068261888 | G29: =SUMIFS(Vintage!$AP$36:$AP$127,Vintage!$C$36:$C$127,"RPA",Vintage!$BB$36:$BB$127,"Karkas fresh") -> 1.5287451e+09 | H29: =IFERROR((G29-SUMIFS(Vintage!$AK$36:$AK$127,Vintage!$C$36:$C$127,"RPA",Vintage!$BB$36:$BB$127,"Karkas fresh"))/G29,0) -> -0.018235117
B30: Karkas frozen | C30: =(SUMIFS(Vintage!$AN$36:$AN$127,Vintage!$C$36:$C$127,"RPA",Vintage!$BB$36:$BB$127,"Karkas frozen")-SUMIFS(Vintage!$AI$36:$AI$127,Vintage!$C$36:$C$127,"RPA",Vintage!$BB$36:$BB$127,"Karkas frozen")-$C$11*SUMIFS(Vintage!$AN$36:$AN$127,Vintage!$C$36:$C$127,"RPA",Vintage!$BB$36:$BB$127,"Karkas frozen"))/$H$6 -> 0.012429137 | D30: =(SUMIFS(Vintage!$AO$36:$AO$127,Vintage!$C$36:$C$127,"RPA",Vintage!$BB$36:$BB$127,"Karkas frozen")-SUMIFS(Vintage!$AJ$36:$AJ$127,Vintage!$C$36:$C$127,"RPA",Vintage!$BB$36:$BB$127,"Karkas frozen")-$C$11*SUMIFS(Vintage!$AO$36:$AO$127,Vintage!$C$36:$C$127,"RPA",Vintage!$BB$36:$BB$127,"Karkas frozen"))/$H$6 -> -0.00013925073 | E30: =(SUMIFS(Vintage!$AP$36:$AP$127,Vintage!$C$36:$C$127,"RPA",Vintage!$BB$36:$BB$127,"Karkas frozen")-SUMIFS(Vintage!$AK$36:$AK$127,Vintage!$C$36:$C$127,"RPA",Vintage!$BB$36:$BB$127,"Karkas frozen")-$C$11*SUMIFS(Vintage!$AP$36:$AP$127,Vintage!$C$36:$C$127,"RPA",Vintage!$BB$36:$BB$127,"Karkas frozen"))/$H$6 -> -0.0057492688 | F30: =SUM(C30:E30) -> 0.0065406177 | G30: =SUMIFS(Vintage!$AP$36:$AP$127,Vintage!$C$36:$C$127,"RPA",Vintage!$BB$36:$BB$127,"Karkas frozen") -> 1.8148093e+08 | H30: =IFERROR((G30-SUMIFS(Vintage!$AK$36:$AK$127,Vintage!$C$36:$C$127,"RPA",Vintage!$BB$36:$BB$127,"Karkas frozen"))/G30,0) -> -0.091423812
B31: Karkas mix | C31: =(SUMIFS(Vintage!$AN$36:$AN$127,Vintage!$C$36:$C$127,"RPA",Vintage!$BB$36:$BB$127,"Karkas mix")-SUMIFS(Vintage!$AI$36:$AI$127,Vintage!$C$36:$C$127,"RPA",Vintage!$BB$36:$BB$127,"Karkas mix")-$C$11*SUMIFS(Vintage!$AN$36:$AN$127,Vintage!$C$36:$C$127,"RPA",Vintage!$BB$36:$BB$127,"Karkas mix"))/$H$6 -> 0.0010119754 | D31: =(SUMIFS(Vintage!$AO$36:$AO$127,Vintage!$C$36:$C$127,"RPA",Vintage!$BB$36:$BB$127,"Karkas mix")-SUMIFS(Vintage!$AJ$36:$AJ$127,Vintage!$C$36:$C$127,"RPA",Vintage!$BB$36:$BB$127,"Karkas mix")-$C$11*SUMIFS(Vintage!$AO$36:$AO$127,Vintage!$C$36:$C$127,"RPA",Vintage!$BB$36:$BB$127,"Karkas mix"))/$H$6 -> 0 | E31: =(SUMIFS(Vintage!$AP$36:$AP$127,Vintage!$C$36:$C$127,"RPA",Vintage!$BB$36:$BB$127,"Karkas mix")-SUMIFS(Vintage!$AK$36:$AK$127,Vintage!$C$36:$C$127,"RPA",Vintage!$BB$36:$BB$127,"Karkas mix")-$C$11*SUMIFS(Vintage!$AP$36:$AP$127,Vintage!$C$36:$C$127,"RPA",Vintage!$BB$36:$BB$127,"Karkas mix"))/$H$6 -> 0.00016674898 | F31: =SUM(C31:E31) -> 0.0011787244 | G31: =SUMIFS(Vintage!$AP$36:$AP$127,Vintage!$C$36:$C$127,"RPA",Vintage!$BB$36:$BB$127,"Karkas mix") -> 5828258 | H31: =IFERROR((G31-SUMIFS(Vintage!$AK$36:$AK$127,Vintage!$C$36:$C$127,"RPA",Vintage!$BB$36:$BB$127,"Karkas mix"))/G31,0) -> 0.070858463
B32: Total = the vintage bars above | C32: =SUM(C27:C31) -> 0.014982851 | D32: =SUM(D27:D31) -> 0.0040572421 | E32: =SUM(E27:E31) -> -0.039147176 | F32: =SUM(F27:F31) -> -0.020107082 | G32: =SUM(G27:G31) -> 1.7504327e+09
B33: Check: − bars (nil) | C33: =ROUND(C32-C17,8) -> 0 | D33: =ROUND(D32-C18,8) -> 0 | E33: =ROUND(E32-C19,8) -> 0
B36: Trading — GROSS PROFIT CONTEXT, August 2026 vs July 2026 (Rp)
C37: Jul-26 | D37: Stok pra-Juli | E37: Pembelian Juli | F37: Pembelian Agustus | G37: Lain-lain* | H37: Total Aug-26 (corrected) | I37: Variance Aug − Jul | J37: Variance %
B38: Pendapatan | C38: ='Segment GP'!H7 -> 2.8764258e+09 | D38: =Vintage!I12 -> 3.2032434e+08 | E38: =Vintage!I13 -> 2.3065773e+09 | F38: =Vintage!I14 -> 2.9526457e+09 | G38: =H38-SUM(D38:F38) -> 90526500 | H38: ='Segment GP'!M7 -> 5.6700739e+09 | I38: =H38-C38 -> 2.7936481e+09 | J38: =IF(C38=0,0,I38/ABS(C38)) -> 0.97122204
B39: HPP produk (as booked) | C39: ='Segment GP'!H14 -> -2.3922533e+09 | D39: =-Vintage!J12 -> -2.8398518e+08 | E39: =-Vintage!J13 -> -1.9368902e+09 | F39: =-Vintage!J14-Vintage!J15 -> -2.8700811e+09 | G39: =H39-SUM(D39:F39) -> -1.0917116e+08 | H39: ='Segment GP'!M14 -> -5.2001277e+09 | I39: =H39-C39 -> -2.8078744e+09 | J39: =IF(C39=0,0,I39/ABS(C39)) -> -1.1737362
B40: Laba kotor produk | C40: =C38+C39 -> 4.8417248e+08 | D40: =D38+D39 -> 36339163 | E40: =E38+E39 -> 3.6968711e+08 | F40: =F38+F39 -> 82564615 | G40: =G38+G39 -> -18644662 | H40: =H38+H39 -> 4.6994623e+08 | I40: =H40-C40 -> -14226253 | J40: =IF(C40=0,0,I40/ABS(C40)) -> -0.029382614
B41: Cost of sales others (only if allocated — COS Others B3) | C41: ='Segment GP'!H28 -> 0 | G41: =H41 -> 0 | H41: ='Segment GP'!M28 -> 0 | I41: =H41-C41 -> 0 | J41: =IF(C41=0,0,I41/ABS(C41)) -> 0
B42: Laba kotor | C42: =C40+N(C41) -> 4.8417248e+08 | D42: =D40+N(D41) -> 36339163 | E42: =E40+N(E41) -> 3.6968711e+08 | F42: =F40+N(F41) -> 82564615 | G42: =G40+N(G41) -> -18644662 | H42: =H40+N(H41) -> 4.6994623e+08 | I42: =H42-C42 -> -14226253 | J42: =IF(C42=0,0,I42/ABS(C42)) -> -0.029382614
B43: GP margin | C43: =IF(C38=0,0,C42/C38) -> 0.16832434 | D43: =IF(D38=0,0,D42/D38) -> 0.1134449 | E43: =IF(E38=0,0,E42/E38) -> 0.16027519 | F43: =IF(F38=0,0,F42/F38) -> 0.027962926 | H43: =IF(H38=0,0,H42/H38) -> 0.082881853 | I43: =H43-C43 -> -0.085442491
B44: Each vintage carries the HPP Accurate booked on the DOs that shipped it (FIFO by DO), so the buckets add up to booked HPP — no moving-average bar. *Lain-lain = revenue/cost outside the item-level split (revenue without SI, invoices without item detail).
B46: Trading — GP MARGIN WATERFALL Jul → Aug (percentage points)
B47: Step | C47: FIFO point estimate | D47: Lower bound (new stock first) | E47: Revenue share Aug | F47: Bucket margin | G47: How it is computed
B48: GP margin Jul-26 | C48: =C43 -> 0.16832434 | D48: =C43 -> 0.16832434 | G48: July gross profit ÷ July revenue (Segment GP)
B49: Stok pra-Juli | C49: =E49*(F49-$C$48) -> -0.0031003514 | D49: =IF(Vintage!Q12=0,0,Vintage!Q12/$H$38*((Vintage!Q12-Vintage!R12)/Vintage!Q12-$C$48)) -> -4.6808449e-05 | E49: =D38/$H$38 -> 0.056493857 | F49: =D43 -> 0.1134449 | G49: share × (bucket margin − July margin)
B50: Pembelian Juli | C50: =E50*(F50-$C$48) -> -0.0032743844 | D50: =IF(Vintage!Q13=0,0,Vintage!Q13/$H$38*((Vintage!Q13-Vintage!R13)/Vintage!Q13-$C$48)) -> -0.019428789 | E50: =E38/$H$38 -> 0.40679846 | F50: =E43 -> 0.16027519 | G50: share × (bucket margin − July margin)
B51: Pembelian Agustus | C51: =E51*(F51-$C$48) -> -0.073092088 | D51: =IF(Vintage!Q14=0,0,Vintage!Q14/$H$38*((Vintage!Q14-(Vintage!R14+Vintage!R15))/Vintage!Q14-$C$48)) -> -0.059991227 | E51: =F38/$H$38 -> 0.52074202 | F51: =F43 -> 0.027962926 | G51: share × (bucket margin − July margin)
B52: Cost of sales others | C52: =H41/H38 -> 0 | D52: =H41/H38 -> 0 | G52: nil unless allocated (COS Others B3); otherwise at KGR level
B53: Lain-lain | C53: =(G38+G39)/H38-G38/H38*C43 -> -0.0059756673 | D53: =(G38+G39)/H38-G38/H38*C43 -> -0.0059756673 | G53: items outside the split, net of their share of the July margin
B54: GP margin Aug-26 (corrected) | C54: =SUM(C48:C53) -> 0.082881853 | D54: =SUM(D48:D53) -> 0.082881853
B55: Check: waterfall − Segment GP corrected margin (nil) | C55: =ROUND(C54-'Segment GP'!M36,8) -> 0 | D55: =ROUND(D54-'Segment GP'!M36,8) -> 0
B57: Trading — WHAT IS INSIDE EACH BAR, by product group (percentage points; rows add up to the bars above)
B58: Product group | C58: Stok pra-Juli | D58: Pembelian Juli | E58: Pembelian Agustus | F58: Total vintage bars | G58: Revenue from pembelian agustus (Rp) | H58: Margin of pembelian agustus
B59: BLD | C59: =(SUMIFS(Vintage!$AN$36:$AN$127,Vintage!$C$36:$C$127,"Trading",Vintage!$BB$36:$BB$127,"BLD")-SUMIFS(Vintage!$AI$36:$AI$127,Vintage!$C$36:$C$127,"Trading",Vintage!$BB$36:$BB$127,"BLD")-$C$43*SUMIFS(Vintage!$AN$36:$AN$127,Vintage!$C$36:$C$127,"Trading",Vintage!$BB$36:$BB$127,"BLD"))/$H$38 -> 0 | D59: =(SUMIFS(Vintage!$AO$36:$AO$127,Vintage!$C$36:$C$127,"Trading",Vintage!$BB$36:$BB$127,"BLD")-SUMIFS(Vintage!$AJ$36:$AJ$127,Vintage!$C$36:$C$127,"Trading",Vintage!$BB$36:$BB$127,"BLD")-$C$43*SUMIFS(Vintage!$AO$36:$AO$127,Vintage!$C$36:$C$127,"Trading",Vintage!$BB$36:$BB$127,"BLD"))/$H$38 -> 0.0054929406 | E59: =(SUMIFS(Vintage!$AP$36:$AP$127,Vintage!$C$36:$C$127,"Trading",Vintage!$BB$36:$BB$127,"BLD")-SUMIFS(Vintage!$AK$36:$AK$127,Vintage!$C$36:$C$127,"Trading",Vintage!$BB$36:$BB$127,"BLD")-$C$43*SUMIFS(Vintage!$AP$36:$AP$127,Vintage!$C$36:$C$127,"Trading",Vintage!$BB$36:$BB$127,"BLD"))/$H$38 -> -0.00771088 | F59: =SUM(C59:E59) -> -0.0022179395 | G59: =SUMIFS(Vintage!$AP$36:$AP$127,Vintage!$C$36:$C$127,"Trading",Vintage!$BB$36:$BB$127,"BLD") -> 4.4008165e+08 | H59: =IFERROR((G59-SUMIFS(Vintage!$AK$36:$AK$127,Vintage!$C$36:$C$127,"Trading",Vintage!$BB$36:$BB$127,"BLD"))/G59,0) -> 0.068976281
B60: BLP | C60: =(SUMIFS(Vintage!$AN$36:$AN$127,Vintage!$C$36:$C$127,"Trading",Vintage!$BB$36:$BB$127,"BLP")-SUMIFS(Vintage!$AI$36:$AI$127,Vintage!$C$36:$C$127,"Trading",Vintage!$BB$36:$BB$127,"BLP")-$C$43*SUMIFS(Vintage!$AN$36:$AN$127,Vintage!$C$36:$C$127,"Trading",Vintage!$BB$36:$BB$127,"BLP"))/$H$38 -> 0 | D60: =(SUMIFS(Vintage!$AO$36:$AO$127,Vintage!$C$36:$C$127,"Trading",Vintage!$BB$36:$BB$127,"BLP")-SUMIFS(Vintage!$AJ$36:$AJ$127,Vintage!$C$36:$C$127,"Trading",Vintage!$BB$36:$BB$127,"BLP")-$C$43*SUMIFS(Vintage!$AO$36:$AO$127,Vintage!$C$36:$C$127,"Trading",Vintage!$BB$36:$BB$127,"BLP"))/$H$38 -> 0.0082639982 | E60: =(SUMIFS(Vintage!$AP$36:$AP$127,Vintage!$C$36:$C$127,"Trading",Vintage!$BB$36:$BB$127,"BLP")-SUMIFS(Vintage!$AK$36:$AK$127,Vintage!$C$36:$C$127,"Trading",Vintage!$BB$36:$BB$127,"BLP")-$C$43*SUMIFS(Vintage!$AP$36:$AP$127,Vintage!$C$36:$C$127,"Trading",Vintage!$BB$36:$BB$127,"BLP"))/$H$38 -> -0.016143142 | F60: =SUM(C60:E60) -> -0.0078791436 | G60: =SUMIFS(Vintage!$AP$36:$AP$127,Vintage!$C$36:$C$127,"Trading",Vintage!$BB$36:$BB$127,"BLP") -> 8.0359111e+08 | H60: =IFERROR((G60-SUMIFS(Vintage!$AK$36:$AK$127,Vintage!$C$36:$C$127,"Trading",Vintage!$BB$36:$BB$127,"BLP"))/G60,0) -> 0.05441964
B61: KRK (Kerangka) | C61: =(SUMIFS(Vintage!$AN$36:$AN$127,Vintage!$C$36:$C$127,"Trading",Vintage!$BB$36:$BB$127,"KRK (Kerangka)")-SUMIFS(Vintage!$AI$36:$AI$127,Vintage!$C$36:$C$127,"Trading",Vintage!$BB$36:$BB$127,"KRK (Kerangka)")-$C$43*SUMIFS(Vintage!$AN$36:$AN$127,Vintage!$C$36:$C$127,"Trading",Vintage!$BB$36:$BB$127,"KRK (Kerangka)"))/$H$38 -> 0 | D61: =(SUMIFS(Vintage!$AO$36:$AO$127,Vintage!$C$36:$C$127,"Trading",Vintage!$BB$36:$BB$127,"KRK (Kerangka)")-SUMIFS(Vintage!$AJ$36:$AJ$127,Vintage!$C$36:$C$127,"Trading",Vintage!$BB$36:$BB$127,"KRK (Kerangka)")-$C$43*SUMIFS(Vintage!$AO$36:$AO$127,Vintage!$C$36:$C$127,"Trading",Vintage!$BB$36:$BB$127,"KRK (Kerangka)"))/$H$38 -> -0.00042286852 | E61: =(SUMIFS(Vintage!$AP$36:$AP$127,Vintage!$C$36:$C$127,"Trading",Vintage!$BB$36:$BB$127,"KRK (Kerangka)")-SUMIFS(Vintage!$AK$36:$AK$127,Vintage!$C$36:$C$127,"Trading",Vintage!$BB$36:$BB$127,"KRK (Kerangka)")-$C$43*SUMIFS(Vintage!$AP$36:$AP$127,Vintage!$C$36:$C$127,"Trading",Vintage!$BB$36:$BB$127,"KRK (Kerangka)"))/$H$38 -> -0.0023452494 | F61: =SUM(C61:E61) -> -0.0027681179 | G61: =SUMIFS(Vintage!$AP$36:$AP$127,Vintage!$C$36:$C$127,"Trading",Vintage!$BB$36:$BB$127,"KRK (Kerangka)") -> 1.1665969e+08 | H61: =IFERROR((G61-SUMIFS(Vintage!$AK$36:$AK$127,Vintage!$C$36:$C$127,"Trading",Vintage!$BB$36:$BB$127,"KRK (Kerangka)"))/G61,0) -> 0.054336922
B62: Karkas | C62: =(SUMIFS(Vintage!$AN$36:$AN$127,Vintage!$C$36:$C$127,"Trading",Vintage!$BB$36:$BB$127,"Karkas")-SUMIFS(Vintage!$AI$36:$AI$127,Vintage!$C$36:$C$127,"Trading",Vintage!$BB$36:$BB$127,"Karkas")-$C$43*SUMIFS(Vintage!$AN$36:$AN$127,Vintage!$C$36:$C$127,"Trading",Vintage!$BB$36:$BB$127,"Karkas"))/$H$38 -> -0.0031003514 | D62: =(SUMIFS(Vintage!$AO$36:$AO$127,Vintage!$C$36:$C$127,"Trading",Vintage!$BB$36:$BB$127,"Karkas")-SUMIFS(Vintage!$AJ$36:$AJ$127,Vintage!$C$36:$C$127,"Trading",Vintage!$BB$36:$BB$127,"Karkas")-$C$43*SUMIFS(Vintage!$AO$36:$AO$127,Vintage!$C$36:$C$127,"Trading",Vintage!$BB$36:$BB$127,"Karkas"))/$H$38 -> -0.016566412 | E62: =(SUMIFS(Vintage!$AP$36:$AP$127,Vintage!$C$36:$C$127,"Trading",Vintage!$BB$36:$BB$127,"Karkas")-SUMIFS(Vintage!$AK$36:$AK$127,Vintage!$C$36:$C$127,"Trading",Vintage!$BB$36:$BB$127,"Karkas")-$C$43*SUMIFS(Vintage!$AP$36:$AP$127,Vintage!$C$36:$C$127,"Trading",Vintage!$BB$36:$BB$127,"Karkas"))/$H$38 -> -0.046741981 | F62: =SUM(C62:E62) -> -0.066408744 | G62: =SUMIFS(Vintage!$AP$36:$AP$127,Vintage!$C$36:$C$127,"Trading",Vintage!$BB$36:$BB$127,"Karkas") -> 1.5830133e+09 | H62: =IFERROR((G62-SUMIFS(Vintage!$AK$36:$AK$127,Vintage!$C$36:$C$127,"Trading",Vintage!$BB$36:$BB$127,"Karkas"))/G62,0) -> 0.00090282709
B63: Kulit | C63: =(SUMIFS(Vintage!$AN$36:$AN$127,Vintage!$C$36:$C$127,"Trading",Vintage!$BB$36:$BB$127,"Kulit")-SUMIFS(Vintage!$AI$36:$AI$127,Vintage!$C$36:$C$127,"Trading",Vintage!$BB$36:$BB$127,"Kulit")-$C$43*SUMIFS(Vintage!$AN$36:$AN$127,Vintage!$C$36:$C$127,"Trading",Vintage!$BB$36:$BB$127,"Kulit"))/$H$38 -> 0 | D63: =(SUMIFS(Vintage!$AO$36:$AO$127,Vintage!$C$36:$C$127,"Trading",Vintage!$BB$36:$BB$127,"Kulit")-SUMIFS(Vintage!$AJ$36:$AJ$127,Vintage!$C$36:$C$127,"Trading",Vintage!$BB$36:$BB$127,"Kulit")-$C$43*SUMIFS(Vintage!$AO$36:$AO$127,Vintage!$C$36:$C$127,"Trading",Vintage!$BB$36:$BB$127,"Kulit"))/$H$38 -> -4.2042613e-05 | E63: =(SUMIFS(Vintage!$AP$36:$AP$127,Vintage!$C$36:$C$127,"Trading",Vintage!$BB$36:$BB$127,"Kulit")-SUMIFS(Vintage!$AK$36:$AK$127,Vintage!$C$36:$C$127,"Trading",Vintage!$BB$36:$BB$127,"Kulit")-$C$43*SUMIFS(Vintage!$AP$36:$AP$127,Vintage!$C$36:$C$127,"Trading",Vintage!$BB$36:$BB$127,"Kulit"))/$H$38 -> 0 | F63: =SUM(C63:E63) -> -4.2042613e-05 | G63: =SUMIFS(Vintage!$AP$36:$AP$127,Vintage!$C$36:$C$127,"Trading",Vintage!$BB$36:$BB$127,"Kulit") -> 0 | H63: =IFERROR((G63-SUMIFS(Vintage!$AK$36:$AK$127,Vintage!$C$36:$C$127,"Trading",Vintage!$BB$36:$BB$127,"Kulit"))/G63,0) -> 0
B64: Sayap | C64: =(SUMIFS(Vintage!$AN$36:$AN$127,Vintage!$C$36:$C$127,"Trading",Vintage!$BB$36:$BB$127,"Sayap")-SUMIFS(Vintage!$AI$36:$AI$127,Vintage!$C$36:$C$127,"Trading",Vintage!$BB$36:$BB$127,"Sayap")-$C$43*SUMIFS(Vintage!$AN$36:$AN$127,Vintage!$C$36:$C$127,"Trading",Vintage!$BB$36:$BB$127,"Sayap"))/$H$38 -> 0 | D64: =(SUMIFS(Vintage!$AO$36:$AO$127,Vintage!$C$36:$C$127,"Trading",Vintage!$BB$36:$BB$127,"Sayap")-SUMIFS(Vintage!$AJ$36:$AJ$127,Vintage!$C$36:$C$127,"Trading",Vintage!$BB$36:$BB$127,"Sayap")-$C$43*SUMIFS(Vintage!$AO$36:$AO$127,Vintage!$C$36:$C$127,"Trading",Vintage!$BB$36:$BB$127,"Sayap"))/$H$38 -> 0 | E64: =(SUMIFS(Vintage!$AP$36:$AP$127,Vintage!$C$36:$C$127,"Trading",Vintage!$BB$36:$BB$127,"Sayap")-SUMIFS(Vintage!$AK$36:$AK$127,Vintage!$C$36:$C$127,"Trading",Vintage!$BB$36:$BB$127,"Sayap")-$C$43*SUMIFS(Vintage!$AP$36:$AP$127,Vintage!$C$36:$C$127,"Trading",Vintage!$BB$36:$BB$127,"Sayap"))/$H$38 -> -0.00015083609 | F64: =SUM(C64:E64) -> -0.00015083609 | G64: =SUMIFS(Vintage!$AP$36:$AP$127,Vintage!$C$36:$C$127,"Trading",Vintage!$BB$36:$BB$127,"Sayap") -> 9300000 | H64: =IFERROR((G64-SUMIFS(Vintage!$AK$36:$AK$127,Vintage!$C$36:$C$127,"Trading",Vintage!$BB$36:$BB$127,"Sayap"))/G64,0) -> 0.076361787
B65: Total = the vintage bars above | C65: =SUM(C59:C64) -> -0.0031003514 | D65: =SUM(D59:D64) -> -0.0032743844 | E65: =SUM(E59:E64) -> -0.073092088 | F65: =SUM(F59:F64) -> -0.079466824 | G65: =SUM(G59:G64) -> 2.9526457e+09
B66: Check: − bars (nil) | C66: =ROUND(C65-C49,8) -> 0 | D66: =ROUND(D65-C50,8) -> 0 | E66: =ROUND(E65-C51,8) -> 0
B69: KGR TOTAL — GP MARGIN WATERFALL Jul → Aug (percentage points)
B70: Step | C70: Value | D70: How it is computed
B71: GP margin Jul-26 — KGR | C71: ='Segment GP'!H38 -> 0.11625241 | D71: Segment GP
B72: RPA — margin change | C72: ='Segment GP'!M6/'Segment GP'!M9*('Segment GP'!M35-'Segment GP'!H35) -> -0.0056092669 | D72: Aug revenue share × (Aug − Jul RPA margin)
B73: Trading — margin change | C73: ='Segment GP'!M7/'Segment GP'!M9*('Segment GP'!M36-'Segment GP'!H36) -> -0.057938184 | D73: Aug revenue share × (Aug − Jul Trading margin)
B74: Segment mix | C74: =('Segment GP'!M6/'Segment GP'!M9-'Segment GP'!H6/'Segment GP'!H9)*'Segment GP'!H35+('Segment GP'!M7/'Segment GP'!M9-'Segment GP'!H7/'Segment GP'!H9)*'Segment GP'!H36 -> -0.042391167 | D74: change in revenue share × July margin of the segment
B75: Not in a segment (cost of sales others not allocated + unbilled without segment) | C75: ='Segment GP'!M33/'Segment GP'!M9-'Segment GP'!H33/'Segment GP'!H9 -> 0.026297895 | D75: change in (not-in-a-segment ÷ revenue); Segment GP row 33
B76: GP margin Aug-26 — KGR (corrected) | C76: =SUM(C71:C75) -> 0.036611683
B77: Check vs Segment GP (nil) | C77: =ROUND(C76-'Segment GP'!M38,8) -> 0

Sheet Vintage
A1: VINTAGE — August sales split by when the goods were produced (RPA) or bought (Trading)
A2: Point estimate: FIFO row by row in MA Engine (oldest stock leaves first). Each bucket carries the HPP Accurate actually booked on the DOs that shipped it, so buckets add up to booked HPP with no moving-average bar (NMG style). Lower bound: new stock first, at the item average booked HPP/kg. Layer costs (cols AE–AG) are kept for information and for the RPA Loss Bridge.
A4: SUMMARY — August sales by vintage, product level (sales with item detail; the 6 invoices without items are excluded)
A5: Segment | B5: Bucket | H5: kg sold | I5: Revenue | J5: Product cost | K5: Product GP | L5: GP % | M5: Revenue Rp/kg | N5: Cost Rp/kg | P5: LB: kg | Q5: LB: revenue | R5: LB: cost | S5: LB: GP | T5: LB: GP %
A6: RPA | B6: Stok pra-Juli | H6: =SUMIFS($AA$36:$AA$127,$C$36:$C$127,$A6) -> 26511.85 | I6: =SUMIFS($AN$36:$AN$127,$C$36:$C$127,$A6) -> 5.4166332e+08 | J6: =SUMIFS($AI$36:$AI$127,$C$36:$C$127,$A6) -> 5.0466641e+08 | K6: =I6-J6 -> 36996907 | L6: =IF(I6=0,0,K6/I6) -> 0.068302403 | M6: =IF(H6=0,0,I6/H6) -> 20430.989 | N6: =IF(H6=0,0,J6/H6) -> 19035.504 | P6: =SUMIFS($AR$36:$AR$127,$C$36:$C$127,$A6) -> 13153.564 | Q6: =SUMIFS($AV$36:$AV$127,$C$36:$C$127,$A6) -> 4.3153276e+08 | R6: =SUMPRODUCT(($C$36:$C$127=$A6)*$AR$36:$AR$127*$BA$36:$BA$127) -> 3.936051e+08 | S6: =Q6-R6 -> 37927667 | T6: =IF(Q6=0,0,S6/Q6) -> 0.087890585
A7: RPA | B7: Produksi Juli | H7: =SUMIFS($AB$36:$AB$127,$C$36:$C$127,$A7) -> 3176.24 | I7: =SUMIFS($AO$36:$AO$127,$C$36:$C$127,$A7) -> 81468140 | J7: =SUMIFS($AJ$36:$AJ$127,$C$36:$C$127,$A7) -> 71048495 | K7: =I7-J7 -> 10419645 | L7: =IF(I7=0,0,K7/I7) -> 0.1278984 | M7: =IF(H7=0,0,I7/H7) -> 25649.239 | N7: =IF(H7=0,0,J7/H7) -> 22368.743 | P7: =SUMIFS($AS$36:$AS$127,$C$36:$C$127,$A7) -> 1967.7637 | Q7: =SUMIFS($AW$36:$AW$127,$C$36:$C$127,$A7) -> 74005648 | R7: =SUMPRODUCT(($C$36:$C$127=$A7)*$AS$36:$AS$127*$BA$36:$BA$127) -> 64438317 | S7: =Q7-R7 -> 9567331.1 | T7: =IF(Q7=0,0,S7/Q7) -> 0.12927839
A8: RPA | B8: Produksi Agustus | H8: =SUMIFS($AC$36:$AC$127,$C$36:$C$127,$A8) -> 56796.15 | I8: =SUMIFS($AP$36:$AP$127,$C$36:$C$127,$A8) -> 1.7504327e+09 | J8: =SUMIFS($AK$36:$AK$127,$C$36:$C$127,$A8) -> 1.8665731e+09 | K8: =I8-J8 -> -1.1614037e+08 | L8: =IF(I8=0,0,K8/I8) -> -0.06634952 | M8: =IF(H8=0,0,I8/H8) -> 30819.566 | N8: =IF(H8=0,0,J8/H8) -> 32864.429 | P8: =SUMIFS($AT$36:$AT$127,$C$36:$C$127,$A8) -> 71362.912 | Q8: =SUMIFS($AX$36:$AX$127,$C$36:$C$127,$A8) -> 1.8680257e+09 | R8: =SUMPRODUCT(($C$36:$C$127=$A8)*$AT$36:$AT$127*$BA$36:$BA$127) -> 1.9842446e+09 | S8: =Q8-R8 -> -1.1621882e+08 | T8: =IF(Q8=0,0,S8/Q8) -> -0.062214782
A9: RPA | B9: Efek moving average (cost only) | H9: 0 | I9: 0 | J9: =SUMIFS($AL$36:$AL$127,$C$36:$C$127,$A9) -> 0 | K9: =I9-J9 -> 0 | L9: =IF(I9=0,0,K9/I9) -> 0 | M9: =IF(H9=0,0,I9/H9) -> 0 | N9: =IF(H9=0,0,J9/H9) -> 0 | P9: 0 | Q9: 0 | R9: =SUMIFS($AY$36:$AY$127,$C$36:$C$127,$A9) -> 0 | S9: =Q9-R9 -> 0 | T9: =IF(Q9=0,0,S9/Q9) -> 0
A10: RPA | B10: Total — sales with item detail | H10: =SUM(H6:H9) -> 86484.24 | I10: =SUM(I6:I9) -> 2.3735642e+09 | J10: =SUM(J6:J9) -> 2.442288e+09 | K10: =I10-J10 -> -68723817 | L10: =IF(I10=0,0,K10/I10) -> -0.028953849 | M10: =IF(H10=0,0,I10/H10) -> 27445.048 | N10: =IF(H10=0,0,J10/H10) -> 28239.688 | P10: =SUM(P6:P9) -> 86484.24 | Q10: =SUM(Q6:Q9) -> 2.3735642e+09 | R10: =SUM(R6:R9) -> 2.442288e+09 | S10: =Q10-R10 -> -68723817 | T10: =IF(Q10=0,0,S10/Q10) -> -0.028953849
A12: Trading | B12: Stok pra-Juli | H12: =SUMIFS($AA$36:$AA$127,$C$36:$C$127,$A12) -> 10408.05 | I12: =SUMIFS($AN$36:$AN$127,$C$36:$C$127,$A12) -> 3.2032434e+08 | J12: =SUMIFS($AI$36:$AI$127,$C$36:$C$127,$A12) -> 2.8398518e+08 | K12: =I12-J12 -> 36339163 | L12: =IF(I12=0,0,K12/I12) -> 0.1134449 | M12: =IF(H12=0,0,I12/H12) -> 30776.595 | N12: =IF(H12=0,0,J12/H12) -> 27285.147 | P12: =SUMIFS($AR$36:$AR$127,$C$36:$C$127,$A12) -> 2525.05 | Q12: =SUMIFS($AV$36:$AV$127,$C$36:$C$127,$A12) -> 70379206 | R12: =SUMPRODUCT(($C$36:$C$127=$A12)*$AR$36:$AR$127*$BA$36:$BA$127) -> 58798080 | S12: =Q12-R12 -> 11581126 | T12: =IF(Q12=0,0,S12/Q12) -> 0.16455324
A13: Trading | B13: Pembelian Juli | H13: =SUMIFS($AB$36:$AB$127,$C$36:$C$127,$A13) -> 64495.18 | I13: =SUMIFS($AO$36:$AO$127,$C$36:$C$127,$A13) -> 2.3065773e+09 | J13: =SUMIFS($AJ$36:$AJ$127,$C$36:$C$127,$A13) -> 1.9368902e+09 | K13: =I13-J13 -> 3.6968711e+08 | L13: =IF(I13=0,0,K13/I13) -> 0.16027519 | M13: =IF(H13=0,0,I13/H13) -> 35763.561 | N13: =IF(H13=0,0,J13/H13) -> 30031.55 | P13: =SUMIFS($AS$36:$AS$127,$C$36:$C$127,$A13) -> 54865.03 | Q13: =SUMIFS($AW$36:$AW$127,$C$36:$C$127,$A13) -> 2.0031104e+09 | R13: =SUMPRODUCT(($C$36:$C$127=$A13)*$AS$36:$AS$127*$BA$36:$BA$127) -> 1.7761008e+09 | S13: =Q13-R13 -> 2.2700957e+08 | T13: =IF(Q13=0,0,S13/Q13) -> 0.11332854
A14: Trading | B14: Pembelian Agustus | H14: =SUMIFS($AC$36:$AC$127,$C$36:$C$127,$A14) -> 91004.2 | I14: =SUMIFS($AP$36:$AP$127,$C$36:$C$127,$A14) -> 2.9526457e+09 | J14: =SUMIFS($AK$36:$AK$127,$C$36:$C$127,$A14) -> 2.8700811e+09 | K14: =I14-J14 -> 82564615 | L14: =IF(I14=0,0,K14/I14) -> 0.027962926 | M14: =IF(H14=0,0,I14/H14) -> 32445.159 | N14: =IF(H14=0,0,J14/H14) -> 31537.897 | P14: =SUMIFS($AT$36:$AT$127,$C$36:$C$127,$A14) -> 108517.35 | Q14: =SUMIFS($AX$36:$AX$127,$C$36:$C$127,$A14) -> 3.5060578e+09 | R14: =SUMPRODUCT(($C$36:$C$127=$A14)*$AT$36:$AT$127*$BA$36:$BA$127) -> 3.2560576e+09 | S14: =Q14-R14 -> 2.5000019e+08 | T14: =IF(Q14=0,0,S14/Q14) -> 0.071305211
A15: Trading | B15: Efek moving average (cost only) | H15: 0 | I15: 0 | J15: =SUMIFS($AL$36:$AL$127,$C$36:$C$127,$A15) -> 0 | K15: =I15-J15 -> 0 | L15: =IF(I15=0,0,K15/I15) -> 0 | M15: =IF(H15=0,0,I15/H15) -> 0 | N15: =IF(H15=0,0,J15/H15) -> 0 | P15: 0 | Q15: 0 | R15: =SUMIFS($AY$36:$AY$127,$C$36:$C$127,$A15) -> 0 | S15: =Q15-R15 -> 0 | T15: =IF(Q15=0,0,S15/Q15) -> 0
A16: Trading | B16: Total — sales with item detail | H16: =SUM(H12:H15) -> 165907.43 | I16: =SUM(I12:I15) -> 5.5795474e+09 | J16: =SUM(J12:J15) -> 5.0909565e+09 | K16: =I16-J16 -> 4.8859089e+08 | L16: =IF(I16=0,0,K16/I16) -> 0.087568194 | M16: =IF(H16=0,0,I16/H16) -> 33630.485 | N16: =IF(H16=0,0,J16/H16) -> 30685.525 | P16: =SUM(P12:P15) -> 165907.43 | Q16: =SUM(Q12:Q15) -> 5.5795474e+09 | R16: =SUM(R12:R15) -> 5.0909565e+09 | S16: =Q16-R16 -> 4.8859089e+08 | T16: =IF(Q16=0,0,S16/Q16) -> 0.087568194
A19: SUMMARY — JULY sales by vintage (same method) — needed to compare like with like
A20: Segment | B20: Bucket | H20: kg sold | I20: Revenue | J20: Product cost | K20: Product GP | L20: GP % | M20: Revenue Rp/kg | N20: Cost Rp/kg
A21: RPA | B21: Stok pra-Juli (on hand 1 Jul) | H21: =SUMIFS($BG$36:$BG$127,$C$36:$C$127,$A21) -> 12009.71 | I21: =SUMIFS($BP$36:$BP$127,$C$36:$C$127,$A21) -> 2.4362374e+08 | J21: =SUMIFS($BL$36:$BL$127,$C$36:$C$127,$A21) -> 2.3578761e+08 | K21: =I21-J21 -> 7836132.7 | L21: =IF(I21=0,0,K21/I21) -> 0.032164898 | M21: =IF(H21=0,0,I21/H21) -> 20285.564 | N21: =IF(H21=0,0,J21/H21) -> 19633.081
A22: RPA | B22: Produksi Juli | H22: =SUMIFS($BH$36:$BH$127,$C$36:$C$127,$A22) -> 566.3 | I22: =SUMIFS($BQ$36:$BQ$127,$C$36:$C$127,$A22) -> 2908421.9 | J22: =SUMIFS($BM$36:$BM$127,$C$36:$C$127,$A22) -> 5342548.2 | K22: =I22-J22 -> -2434126.3 | L22: =IF(I22=0,0,K22/I22) -> -0.83692341 | M22: =IF(H22=0,0,I22/H22) -> 5135.8324 | N22: =IF(H22=0,0,J22/H22) -> 9434.1307
A23: RPA | B23: Efek moving average (cost only) | H23: 0 | I23: 0 | J23: =SUMIFS($BN$36:$BN$127,$C$36:$C$127,$A23) -> -1.1641532e-09 | K23: =I23-J23 -> 1.1641532e-09 | L23: =IF(I23=0,0,K23/I23) -> 0 | M23: =IF(H23=0,0,I23/H23) -> 0 | N23: =IF(H23=0,0,J23/H23) -> 0
A24: RPA | B24: Total — July sales (invoiced) | H24: =SUM(H21:H23) -> 12576.01 | I24: =SUM(I21:I23) -> 246532160 | J24: =SUM(J21:J23) -> 2.4113015e+08 | K24: =I24-J24 -> 5402006.3 | L24: =IF(I24=0,0,K24/I24) -> 0.021911974 | M24: =IF(H24=0,0,I24/H24) -> 19603.369 | N24: =IF(H24=0,0,J24/H24) -> 19173.82
A25: Trading | B25: Stok pra-Juli (on hand 1 Jul) | H25: =SUMIFS($BG$36:$BG$127,$C$36:$C$127,$A25) -> 45482.37 | I25: =SUMIFS($BP$36:$BP$127,$C$36:$C$127,$A25) -> 1.5413062e+09 | J25: =SUMIFS($BL$36:$BL$127,$C$36:$C$127,$A25) -> 1.2866639e+09 | K25: =I25-J25 -> 2.5464236e+08 | L25: =IF(I25=0,0,K25/I25) -> 0.16521205 | M25: =IF(H25=0,0,I25/H25) -> 33887.993 | N25: =IF(H25=0,0,J25/H25) -> 28289.288
A26: Trading | B26: Pembelian Juli | H26: =SUMIFS($BH$36:$BH$127,$C$36:$C$127,$A26) -> 41464.33 | I26: =SUMIFS($BQ$36:$BQ$127,$C$36:$C$127,$A26) -> 1.3351196e+09 | J26: =SUMIFS($BM$36:$BM$127,$C$36:$C$127,$A26) -> 1.0963714e+09 | K26: =I26-J26 -> 2.3874812e+08 | L26: =IF(I26=0,0,K26/I26) -> 0.17882153 | M26: =IF(H26=0,0,I26/H26) -> 32199.231 | N26: =IF(H26=0,0,J26/H26) -> 26441.315
A27: Trading | B27: Efek moving average (cost only) | H27: 0 | I27: 0 | J27: =SUMIFS($BN$36:$BN$127,$C$36:$C$127,$A27) -> 0 | K27: =I27-J27 -> 0 | L27: =IF(I27=0,0,K27/I27) -> 0 | M27: =IF(H27=0,0,I27/H27) -> 0 | N27: =IF(H27=0,0,J27/H27) -> 0
A28: Trading | B28: Total — July sales (invoiced) | H28: =SUM(H25:H27) -> 86946.7 | I28: =SUM(I25:I27) -> 2.8764258e+09 | J28: =SUM(J25:J27) -> 2.3830353e+09 | K28: =I28-J28 -> 4.9339049e+08 | L28: =IF(I28=0,0,K28/I28) -> 0.17152902 | M28: =IF(H28=0,0,I28/H28) -> 33082.633 | N28: =IF(H28=0,0,J28/H28) -> 27408.002
A29: Case (column G): A = no August production/purchase of the item, all sales from old stock; B = old stock and August production both present; C = no stock at 1 Aug, all from August. Pre-July layer cost = 1 Aug book value less the July layer at July receipt cost (falls back to the 1 Aug average if that would go negative).
A35: Item | B35: Description | C35: Segment | D35: SKU | E35: Form | F35: Size | G35: Case | H35: Open 1 Jul kg | I35: Jul in kg | J35: Jul out kg | K35: Open 1 Aug kg | L35: Open 1 Aug Rp | M35: Aug in kg | N35: Aug in Rp | O35: Aug out kg (all) | P35: Sales kg (inv+unb) | Q35: of which invoiced | R35: of which unbilled | S35: DO 257 transit | T35: Other out (IA/Job) | U35: Pre-Jul left 1 Aug | V35: Jul left 1 Aug | W35: Aug out from pre-Jul | X35: from Jul | Y35: from Aug | Z35: Sales share | AA35: Sales kg pre-Jul | AB35: Sales kg Jul | AC35: Sales kg Aug | AD35: Jul in Rp | AE35: Cost/kg Jul layer | AF35: Cost/kg pre-Jul layer | AG35: Cost/kg Aug layer | AH35: COGS booked (replay B) | AI35: Cost pre-Jul | AJ35: Cost Jul | AK35: Cost Aug | AL35: MA effect | AM35: Sales revenue | AN35: Revenue pre-Jul | AO35: Revenue Jul | AP35: Revenue Aug | AQ35: LB: old kg out | AR35: LB: sales kg pre-Jul | AS35: LB: sales kg Jul | AT35: LB: sales kg Aug | AU35: LB: cost old+new | AV35: LB: revenue pre-Jul | AW35: LB: revenue Jul | AX35: LB: revenue Aug | AY35: LB: MA effect | AZ35: Sales at Aug layer cost | BA35: Booked HPP/kg of sales | BB35: Product group (waterfall) | BC35: JUL: sales kg (DO Jul) | BD35: JUL: pre-Jul stock used | BE35: JUL: Jul layer used | BF35: JUL: sales share | BG35: JUL: sales kg pre-Jul | BH35: JUL: sales kg Jul layer | BI35: JUL: cost/kg 1 Jul stock | BJ35: JUL: cost/kg Jul receipts | BK35: JUL: COGS booked | BL35: JUL: cost pre-Jul | BM35: JUL: cost Jul layer | BN35: JUL: MA effect | BO35: JUL: sales revenue | BP35: JUL: revenue pre-Jul | BQ35: JUL: revenue Jul layer
A36: JLB0078 | B36: =INDEX(I_Items!$B$5:$B$133,MATCH($A36,I_Items!$A$5:$A$133,0))&"" -> Boneless BL Fresh Ceker | C36: =INDEX(I_Items!$C$5:$C$133,MATCH($A36,I_Items!$A$5:$A$133,0))&"" -> RPA | D36: =INDEX(I_Items!$D$5:$D$133,MATCH($A36,I_Items!$A$5:$A$133,0))&"" -> Ceker | E36: =INDEX(I_Items!$F$5:$F$133,MATCH($A36,I_Items!$A$5:$A$133,0))&"" -> Fresh | F36: =INDEX(I_Items!$E$5:$E$133,MATCH($A36,I_Items!$A$5:$A$133,0))&"" | G36: =IF(P36=0,"-",IF(M36=0,"A",IF(K36<=0,"C","B"))) -> B | H36: =SUMIFS('MA Engine'!$K$6:$K$1110,'MA Engine'!$B$6:$B$1110,$A36,'MA Engine'!$I$6:$I$1110,"Opening") -> 1416.94 | I36: =SUMIFS('MA Engine'!$K$6:$K$1110,'MA Engine'!$B$6:$B$1110,$A36,'MA Engine'!$H$6:$H$1110,7,'MA Engine'!$I$6:$I$1110,"<>Opening") -> 0 | J36: =SUMIFS('MA Engine'!$W$6:$W$1110,'MA Engine'!$B$6:$B$1110,$A36,'MA Engine'!$H$6:$H$1110,7) -> 0 | K36: =H36+I36-J36 -> 1416.94 | L36: =SUMIFS('MA Engine'!$L$6:$L$1110,'MA Engine'!$B$6:$B$1110,$A36,'MA Engine'!$I$6:$I$1110,"Opening")+SUMIFS('MA Engine'!$L$6:$L$1110,'MA Engine'!$B$6:$B$1110,$A36,'MA Engine'!$H$6:$H$1110,7,'MA Engine'!$I$6:$I$1110,"<>Opening")-SUMIFS('MA Engine'!$X$6:$X$1110,'MA Engine'!$B$6:$B$1110,$A36,'MA Engine'!$H$6:$H$1110,7) -> 12528306 | M36: =SUMIFS('MA Engine'!$K$6:$K$1110,'MA Engine'!$B$6:$B$1110,$A36,'MA Engine'!$H$6:$H$1110,8) -> 3882.5 | N36: =SUMIFS('MA Engine'!$L$6:$L$1110,'MA Engine'!$B$6:$B$1110,$A36,'MA Engine'!$H$6:$H$1110,8) -> 65077534 | O36: =SUMIFS('MA Engine'!$W$6:$W$1110,'MA Engine'!$B$6:$B$1110,$A36,'MA Engine'!$H$6:$H$1110,8) -> 3666.8 | P36: =Q36+R36 -> 3666.8 | Q36: =SUMIFS('MA Engine'!$W$6:$W$1110,'MA Engine'!$B$6:$B$1110,$A36,'MA Engine'!$H$6:$H$1110,8,'MA Engine'!$I$6:$I$1110,"DO",'MA Engine'!$P$6:$P$1110,"<>Y") -> 3666.8 | R36: =SUMIFS('MA Engine'!$W$6:$W$1110,'MA Engine'!$B$6:$B$1110,$A36,'MA Engine'!$H$6:$H$1110,8,'MA Engine'!$I$6:$I$1110,"Unbilled") -> 0 | S36: =SUMIFS('MA Engine'!$W$6:$W$1110,'MA Engine'!$B$6:$B$1110,$A36,'MA Engine'!$H$6:$H$1110,8,'MA Engine'!$P$6:$P$1110,"Y") -> 0 | T36: =O36-P36-S36 -> 0 | U36: =MAX(0,H36-J36) -> 1416.94 | V36: =MAX(0,K36-U36) -> 0 | W36: =MIN(U36,O36) -> 1416.94 | X36: =MIN(V36,O36-W36) -> 0 | Y36: =O36-W36-X36 -> 2249.86 | Z36: =IF(O36=0,0,P36/O36) -> 1 | AA36: =SUMIFS('MA Engine'!$AH$6:$AH$1110,'MA Engine'!$B$6:$B$1110,$A36,'MA Engine'!$H$6:$H$1110,8,'MA Engine'!$I$6:$I$1110,"DO",'MA Engine'!$P$6:$P$1110,"<>Y")+SUMIFS('MA Engine'!$AH$6:$AH$1110,'MA Engine'!$B$6:$B$1110,$A36,'MA Engine'!$H$6:$H$1110,8,'MA Engine'!$I$6:$I$1110,"Unbilled") -> 1416.94 | AB36: =SUMIFS('MA Engine'!$AI$6:$AI$1110,'MA Engine'!$B$6:$B$1110,$A36,'MA Engine'!$H$6:$H$1110,8,'MA Engine'!$I$6:$I$1110,"DO",'MA Engine'!$P$6:$P$1110,"<>Y")+SUMIFS('MA Engine'!$AI$6:$AI$1110,'MA Engine'!$B$6:$B$1110,$A36,'MA Engine'!$H$6:$H$1110,8,'MA Engine'!$I$6:$I$1110,"Unbilled") -> 0 | AC36: =SUMIFS('MA Engine'!$AJ$6:$AJ$1110,'MA Engine'!$B$6:$B$1110,$A36,'MA Engine'!$H$6:$H$1110,8,'MA Engine'!$I$6:$I$1110,"DO",'MA Engine'!$P$6:$P$1110,"<>Y")+SUMIFS('MA Engine'!$AJ$6:$AJ$1110,'MA Engine'!$B$6:$B$1110,$A36,'MA Engine'!$H$6:$H$1110,8,'MA Engine'!$I$6:$I$1110,"Unbilled") -> 2249.86 | AD36: =SUMIFS('MA Engine'!$L$6:$L$1110,'MA Engine'!$B$6:$B$1110,$A36,'MA Engine'!$H$6:$H$1110,7,'MA Engine'!$I$6:$I$1110,"<>Opening") -> 0 | AE36: =IF(AND(U36>0.0001,(L36-V36*IF(I36>0,AD36/I36,IF(K36>0,L36/K36,0)))<0),IF(K36>0,L36/K36,0),IF(I36>0,AD36/I36,IF(K36>0,L36/K36,0))) -> 8841.804 | AF36: =IF(U36<=0.0001,IF(K36>0,L36/K36,0),IF((L36-V36*IF(I36>0,AD36/I36,IF(K36>0,L36/K36,0)))<0,IF(K36>0,L36/K36,0),(L36-V36*IF(I36>0,AD36/I36,IF(K36>0,L36/K36,0)))/U36)) -> 8841.804 | AG36: =IF(M36>0,N36/M36,IF(K36>0,L36/K36,0)) -> 16761.76 | AH36: =SUMIFS('MA Engine'!$X$6:$X$1110,'MA Engine'!$B$6:$B$1110,$A36,'MA Engine'!$H$6:$H$1110,8,'MA Engine'!$I$6:$I$1110,"DO",'MA Engine'!$P$6:$P$1110,"<>Y")+SUMIFS('MA Engine'!$X$6:$X$1110,'MA Engine'!$B$6:$B$1110,$A36,'MA Engine'!$H$6:$H$1110,8,'MA Engine'!$I$6:$I$1110,"Unbilled") -> 50747541 | AI36: =SUMIFS('MA Engine'!$AK$6:$AK$1110,'MA Engine'!$B$6:$B$1110,$A36,'MA Engine'!$H$6:$H$1110,8,'MA Engine'!$I$6:$I$1110,"DO",'MA Engine'!$P$6:$P$1110,"<>Y")+SUMIFS('MA Engine'!$AK$6:$AK$1110,'MA Engine'!$B$6:$B$1110,$A36,'MA Engine'!$H$6:$H$1110,8,'MA Engine'!$I$6:$I$1110,"Unbilled") -> 15746646 | AJ36: =SUMIFS('MA Engine'!$AL$6:$AL$1110,'MA Engine'!$B$6:$B$1110,$A36,'MA Engine'!$H$6:$H$1110,8,'MA Engine'!$I$6:$I$1110,"DO",'MA Engine'!$P$6:$P$1110,"<>Y")+SUMIFS('MA Engine'!$AL$6:$AL$1110,'MA Engine'!$B$6:$B$1110,$A36,'MA Engine'!$H$6:$H$1110,8,'MA Engine'!$I$6:$I$1110,"Unbilled") -> 0 | AK36: =SUMIFS('MA Engine'!$AM$6:$AM$1110,'MA Engine'!$B$6:$B$1110,$A36,'MA Engine'!$H$6:$H$1110,8,'MA Engine'!$I$6:$I$1110,"DO",'MA Engine'!$P$6:$P$1110,"<>Y")+SUMIFS('MA Engine'!$AM$6:$AM$1110,'MA Engine'!$B$6:$B$1110,$A36,'MA Engine'!$H$6:$H$1110,8,'MA Engine'!$I$6:$I$1110,"Unbilled") -> 35000895 | AL36: =AH36-AI36-AJ36-AK36 -> 0 | AM36: =IF(Q36=0,0,IF($D36="Karkas",SUMIFS('Karkas Detail'!$E$6:$E$42,'Karkas Detail'!$A$6:$A$42,$C36,'Karkas Detail'!$B$6:$B$42,$F36,'Karkas Detail'!$C$6:$C$42,$E36)/SUMIFS($Q$36:$Q$127,$C$36:$C$127,$C36,$D$36:$D$127,"Karkas",$F$36:$F$127,$F36,$E$36:$E$127,$E36),SUMIFS('Data SKU'!$G$5:$G$116,'Data SKU'!$A$5:$A$116,$C36,'Data SKU'!$B$5:$B$116,$D36,'Data SKU'!$C$5:$C$116,$E36,'Data SKU'!$D$5:$D$116,8,'Data SKU'!$N$5:$N$116,"Invoiced")/SUMIFS($Q$36:$Q$127,$C$36:$C$127,$C36,$D$36:$D$127,$D36,$E$36:$E$127,$E36))*Q36)+SUMIFS(Unbilled!$U$22:$U$38,Unbilled!$E$22:$E$38,$A36) -> 11370200 | AN36: =IF(P36=0,0,AM36*AA36/P36) -> 4393719.6 | AO36: =IF(P36=0,0,AM36*AB36/P36) -> 0 | AP36: =IF(P36=0,0,AM36*AC36/P36) -> 6976480.4 | AQ36: =MIN(U36+V36,MAX(0,O36-M36)) -> 0 | AR36: =MAX(0,AQ36-V36)*Z36 -> 0 | AS36: =MIN(V36,AQ36)*Z36 -> 0 | AT36: =(O36-AQ36)*Z36 -> 3666.8 | AU36: =(AR36+AS36+AT36)*BA36 -> 50747541 | AV36: =IF(P36=0,0,AM36*AR36/P36) -> 0 | AW36: =IF(P36=0,0,AM36*AS36/P36) -> 0 | AX36: =IF(P36=0,0,AM36*AT36/P36) -> 11370200 | AY36: =AH36-AU36 -> 0 | AZ36: =IF(M36>0,P36*AG36,0) -> 61462023 | BA36: =IF(P36=0,0,AH36/P36) -> 13839.735 | BB36: By-product (kepala, ceker, usus, HJA, lemak) | BC36: =SUMIFS('MA Engine'!$W$6:$W$1110,'MA Engine'!$B$6:$B$1110,$A36,'MA Engine'!$H$6:$H$1110,7,'MA Engine'!$I$6:$I$1110,"DO") -> 0 | BD36: =MIN(MAX(0,H36),J36) -> 0 | BE36: =J36-BD36 -> 0 | BF36: =IF(J36=0,0,BC36/J36) -> 0 | BG36: =SUMIFS('MA Engine'!$AH$6:$AH$1110,'MA Engine'!$B$6:$B$1110,$A36,'MA Engine'!$H$6:$H$1110,7,'MA Engine'!$I$6:$I$1110,"DO") -> 0 | BH36: =SUMIFS('MA Engine'!$AI$6:$AI$1110,'MA Engine'!$B$6:$B$1110,$A36,'MA Engine'!$H$6:$H$1110,7,'MA Engine'!$I$6:$I$1110,"DO")+SUMIFS('MA Engine'!$AJ$6:$AJ$1110,'MA Engine'!$B$6:$B$1110,$A36,'MA Engine'!$H$6:$H$1110,7,'MA Engine'!$I$6:$I$1110,"DO") -> 0 | BI36: =IF(H36>0,SUMIFS('MA Engine'!$L$6:$L$1110,'MA Engine'!$B$6:$B$1110,$A36,'MA Engine'!$I$6:$I$1110,"Opening")/H36,0) -> 8841.804 | BJ36: =IF(I36>0,AD36/I36,BI36) -> 8841.804 | BK36: =SUMIFS('MA Engine'!$X$6:$X$1110,'MA Engine'!$B$6:$B$1110,$A36,'MA Engine'!$H$6:$H$1110,7,'MA Engine'!$I$6:$I$1110,"DO") -> 0 | BL36: =SUMIFS('MA Engine'!$AK$6:$AK$1110,'MA Engine'!$B$6:$B$1110,$A36,'MA Engine'!$H$6:$H$1110,7,'MA Engine'!$I$6:$I$1110,"DO") -> 0 | BM36: =SUMIFS('MA Engine'!$AL$6:$AL$1110,'MA Engine'!$B$6:$B$1110,$A36,'MA Engine'!$H$6:$H$1110,7,'MA Engine'!$I$6:$I$1110,"DO")+SUMIFS('MA Engine'!$AM$6:$AM$1110,'MA Engine'!$B$6:$B$1110,$A36,'MA Engine'!$H$6:$H$1110,7,'MA Engine'!$I$6:$I$1110,"DO") -> 0 | BN36: =BK36-BL36-BM36 -> 0 | BO36: =IF(BC36=0,0,SUMIFS('Data SKU'!$G$5:$G$116,'Data SKU'!$A$5:$A$116,$C36,'Data SKU'!$B$5:$B$116,$D36,'Data SKU'!$C$5:$C$116,$E36,'Data SKU'!$D$5:$D$116,7,'Data SKU'!$N$5:$N$116,"Invoiced")/SUMIFS($BC$36:$BC$127,$C$36:$C$127,$C36,$D$36:$D$127,$D36,$E$36:$E$127,$E36)*BC36) -> 0 | BP36: =IF(BC36=0,0,BO36*BG36/BC36) -> 0 | BQ36: =IF(BC36=0,0,BO36*BH36/BC36) -> 0
A37: JLB0080 | B37: =INDEX(I_Items!$B$5:$B$133,MATCH($A37,I_Items!$A$5:$A$133,0))&"" -> Boneless BL Fresh HJA | C37: =INDEX(I_Items!$C$5:$C$133,MATCH($A37,I_Items!$A$5:$A$133,0))&"" -> RPA | D37: =INDEX(I_Items!$D$5:$D$133,MATCH($A37,I_Items!$A$5:$A$133,0))&"" -> HJA (Hati/Jantung/Ampela) | E37: =INDEX(I_Items!$F$5:$F$133,MATCH($A37,I_Items!$A$5:$A$133,0))&"" -> Fresh | F37: =INDEX(I_Items!$E$5:$E$133,MATCH($A37,I_Items!$A$5:$A$133,0))&"" | G37: =IF(P37=0,"-",IF(M37=0,"A",IF(K37<=0,"C","B"))) -> B | H37: =SUMIFS('MA Engine'!$K$6:$K$1110,'MA Engine'!$B$6:$B$1110,$A37,'MA Engine'!$I$6:$I$1110,"Opening") -> 4337.9 | I37: =SUMIFS('MA Engine'!$K$6:$K$1110,'MA Engine'!$B$6:$B$1110,$A37,'MA Engine'!$H$6:$H$1110,7,'MA Engine'!$I$6:$I$1110,"<>Opening") -> 1300 | J37: =SUMIFS('MA Engine'!$W$6:$W$1110,'MA Engine'!$B$6:$B$1110,$A37,'MA Engine'!$H$6:$H$1110,7) -> 367.5 | K37: =H37+I37-J37 -> 5270.4 | L37: =SUMIFS('MA Engine'!$L$6:$L$1110,'MA Engine'!$B$6:$B$1110,$A37,'MA Engine'!$I$6:$I$1110,"Opening")+SUMIFS('MA Engine'!$L$6:$L$1110,'MA Engine'!$B$6:$B$1110,$A37,'MA Engine'!$H$6:$H$1110,7,'MA Engine'!$I$6:$I$1110,"<>Opening")-SUMIFS('MA Engine'!$X$6:$X$1110,'MA Engine'!$B$6:$B$1110,$A37,'MA Engine'!$H$6:$H$1110,7) -> 2672933.4 | M37: =SUMIFS('MA Engine'!$K$6:$K$1110,'MA Engine'!$B$6:$B$1110,$A37,'MA Engine'!$H$6:$H$1110,8) -> 7390.8 | N37: =SUMIFS('MA Engine'!$L$6:$L$1110,'MA Engine'!$B$6:$B$1110,$A37,'MA Engine'!$H$6:$H$1110,8) -> 42224515 | O37: =SUMIFS('MA Engine'!$W$6:$W$1110,'MA Engine'!$B$6:$B$1110,$A37,'MA Engine'!$H$6:$H$1110,8) -> 6714.4 | P37: =Q37+R37 -> 6714.4 | Q37: =SUMIFS('MA Engine'!$W$6:$W$1110,'MA Engine'!$B$6:$B$1110,$A37,'MA Engine'!$H$6:$H$1110,8,'MA Engine'!$I$6:$I$1110,"DO",'MA Engine'!$P$6:$P$1110,"<>Y") -> 6714.4 | R37: =SUMIFS('MA Engine'!$W$6:$W$1110,'MA Engine'!$B$6:$B$1110,$A37,'MA Engine'!$H$6:$H$1110,8,'MA Engine'!$I$6:$I$1110,"Unbilled") -> 0 | S37: =SUMIFS('MA Engine'!$W$6:$W$1110,'MA Engine'!$B$6:$B$1110,$A37,'MA Engine'!$H$6:$H$1110,8,'MA Engine'!$P$6:$P$1110,"Y") -> 0 | T37: =O37-P37-S37 -> 0 | U37: =MAX(0,H37-J37) -> 3970.4 | V37: =MAX(0,K37-U37) -> 1300 | W37: =MIN(U37,O37) -> 3970.4 | X37: =MIN(V37,O37-W37) -> 1300 | Y37: =O37-W37-X37 -> 1444 | Z37: =IF(O37=0,0,P37/O37) -> 1 | AA37: =SUMIFS('MA Engine'!$AH$6:$AH$1110,'MA Engine'!$B$6:$B$1110,$A37,'MA Engine'!$H$6:$H$1110,8,'MA Engine'!$I$6:$I$1110,"DO",'MA Engine'!$P$6:$P$1110,"<>Y")+SUMIFS('MA Engine'!$AH$6:$AH$1110,'MA Engine'!$B$6:$B$1110,$A37,'MA Engine'!$H$6:$H$1110,8,'MA Engine'!$I$6:$I$1110,"Unbilled") -> 3970.4 | AB37: =SUMIFS('MA Engine'!$AI$6:$AI$1110,'MA Engine'!$B$6:$B$1110,$A37,'MA Engine'!$H$6:$H$1110,8,'MA Engine'!$I$6:$I$1110,"DO",'MA Engine'!$P$6:$P$1110,"<>Y")+SUMIFS('MA Engine'!$AI$6:$AI$1110,'MA Engine'!$B$6:$B$1110,$A37,'MA Engine'!$H$6:$H$1110,8,'MA Engine'!$I$6:$I$1110,"Unbilled") -> 1300 | AC37: =SUMIFS('MA Engine'!$AJ$6:$AJ$1110,'MA Engine'!$B$6:$B$1110,$A37,'MA Engine'!$H$6:$H$1110,8,'MA Engine'!$I$6:$I$1110,"DO",'MA Engine'!$P$6:$P$1110,"<>Y")+SUMIFS('MA Engine'!$AJ$6:$AJ$1110,'MA Engine'!$B$6:$B$1110,$A37,'MA Engine'!$H$6:$H$1110,8,'MA Engine'!$I$6:$I$1110,"Unbilled") -> 1444 | AD37: =SUMIFS('MA Engine'!$L$6:$L$1110,'MA Engine'!$B$6:$B$1110,$A37,'MA Engine'!$H$6:$H$1110,7,'MA Engine'!$I$6:$I$1110,"<>Opening") -> 0 | AE37: =IF(AND(U37>0.0001,(L37-V37*IF(I37>0,AD37/I37,IF(K37>0,L37/K37,0)))<0),IF(K37>0,L37/K37,0),IF(I37>0,AD37/I37,IF(K37>0,L37/K37,0))) -> 0 | AF37: =IF(U37<=0.0001,IF(K37>0,L37/K37,0),IF((L37-V37*IF(I37>0,AD37/I37,IF(K37>0,L37/K37,0)))<0,IF(K37>0,L37/K37,0),(L37-V37*IF(I37>0,AD37/I37,IF(K37>0,L37/K37,0)))/U37)) -> 673.21514 | AG37: =IF(M37>0,N37/M37,IF(K37>0,L37/K37,0)) -> 5713.1184 | AH37: =SUMIFS('MA Engine'!$X$6:$X$1110,'MA Engine'!$B$6:$B$1110,$A37,'MA Engine'!$H$6:$H$1110,8,'MA Engine'!$I$6:$I$1110,"DO",'MA Engine'!$P$6:$P$1110,"<>Y")+SUMIFS('MA Engine'!$X$6:$X$1110,'MA Engine'!$B$6:$B$1110,$A37,'MA Engine'!$H$6:$H$1110,8,'MA Engine'!$I$6:$I$1110,"Unbilled") -> 20555649 | AI37: =SUMIFS('MA Engine'!$AK$6:$AK$1110,'MA Engine'!$B$6:$B$1110,$A37,'MA Engine'!$H$6:$H$1110,8,'MA Engine'!$I$6:$I$1110,"DO",'MA Engine'!$P$6:$P$1110,"<>Y")+SUMIFS('MA Engine'!$AK$6:$AK$1110,'MA Engine'!$B$6:$B$1110,$A37,'MA Engine'!$H$6:$H$1110,8,'MA Engine'!$I$6:$I$1110,"Unbilled") -> 9709016.4 | AJ37: =SUMIFS('MA Engine'!$AL$6:$AL$1110,'MA Engine'!$B$6:$B$1110,$A37,'MA Engine'!$H$6:$H$1110,8,'MA Engine'!$I$6:$I$1110,"DO",'MA Engine'!$P$6:$P$1110,"<>Y")+SUMIFS('MA Engine'!$AL$6:$AL$1110,'MA Engine'!$B$6:$B$1110,$A37,'MA Engine'!$H$6:$H$1110,8,'MA Engine'!$I$6:$I$1110,"Unbilled") -> 5065530.4 | AK37: =SUMIFS('MA Engine'!$AM$6:$AM$1110,'MA Engine'!$B$6:$B$1110,$A37,'MA Engine'!$H$6:$H$1110,8,'MA Engine'!$I$6:$I$1110,"DO",'MA Engine'!$P$6:$P$1110,"<>Y")+SUMIFS('MA Engine'!$AM$6:$AM$1110,'MA Engine'!$B$6:$B$1110,$A37,'MA Engine'!$H$6:$H$1110,8,'MA Engine'!$I$6:$I$1110,"Unbilled") -> 5781102.5 | AL37: =AH37-AI37-AJ37-AK37 -> 0 | AM37: =IF(Q37=0,0,IF($D37="Karkas",SUMIFS('Karkas Detail'!$E$6:$E$42,'Karkas Detail'!$A$6:$A$42,$C37,'Karkas Detail'!$B$6:$B$42,$F37,'Karkas Detail'!$C$6:$C$42,$E37)/SUMIFS($Q$36:$Q$127,$C$36:$C$127,$C37,$D$36:$D$127,"Karkas",$F$36:$F$127,$F37,$E$36:$E$127,$E37),SUMIFS('Data SKU'!$G$5:$G$116,'Data SKU'!$A$5:$A$116,$C37,'Data SKU'!$B$5:$B$116,$D37,'Data SKU'!$C$5:$C$116,$E37,'Data SKU'!$D$5:$D$116,8,'Data SKU'!$N$5:$N$116,"Invoiced")/SUMIFS($Q$36:$Q$127,$C$36:$C$127,$C37,$D$36:$D$127,$D37,$E$36:$E$127,$E37))*Q37)+SUMIFS(Unbilled!$U$22:$U$38,Unbilled!$E$22:$E$38,$A37) -> 30317650 | AN37: =IF(P37=0,0,AM37*AA37/P37) -> 17927618 | AO37: =IF(P37=0,0,AM37*AB37/P37) -> 5869913.2 | AP37: =IF(P37=0,0,AM37*AC37/P37) -> 6520118.9 | AQ37: =MIN(U37+V37,MAX(0,O37-M37)) -> 0 | AR37: =MAX(0,AQ37-V37)*Z37 -> 0 | AS37: =MIN(V37,AQ37)*Z37 -> 0 | AT37: =(O37-AQ37)*Z37 -> 6714.4 | AU37: =(AR37+AS37+AT37)*BA37 -> 20555649 | AV37: =IF(P37=0,0,AM37*AR37/P37) -> 0 | AW37: =IF(P37=0,0,AM37*AS37/P37) -> 0 | AX37: =IF(P37=0,0,AM37*AT37/P37) -> 30317650 | AY37: =AH37-AU37 -> 0 | AZ37: =IF(M37>0,P37*AG37,0) -> 38360162 | BA37: =IF(P37=0,0,AH37/P37) -> 3061.4276 | BB37: By-product (kepala, ceker, usus, HJA, lemak) | BC37: =SUMIFS('MA Engine'!$W$6:$W$1110,'MA Engine'!$B$6:$B$1110,$A37,'MA Engine'!$H$6:$H$1110,7,'MA Engine'!$I$6:$I$1110,"DO") -> 367.5 | BD37: =MIN(MAX(0,H37),J37) -> 367.5 | BE37: =J37-BD37 -> 0 | BF37: =IF(J37=0,0,BC37/J37) -> 1 | BG37: =SUMIFS('MA Engine'!$AH$6:$AH$1110,'MA Engine'!$B$6:$B$1110,$A37,'MA Engine'!$H$6:$H$1110,7,'MA Engine'!$I$6:$I$1110,"DO") -> 367.5 | BH37: =SUMIFS('MA Engine'!$AI$6:$AI$1110,'MA Engine'!$B$6:$B$1110,$A37,'MA Engine'!$H$6:$H$1110,7,'MA Engine'!$I$6:$I$1110,"DO")+SUMIFS('MA Engine'!$AJ$6:$AJ$1110,'MA Engine'!$B$6:$B$1110,$A37,'MA Engine'!$H$6:$H$1110,7,'MA Engine'!$I$6:$I$1110,"DO") -> 0 | BI37: =IF(H37>0,SUMIFS('MA Engine'!$L$6:$L$1110,'MA Engine'!$B$6:$B$1110,$A37,'MA Engine'!$I$6:$I$1110,"Opening")/H37,0) -> 659.14717 | BJ37: =IF(I37>0,AD37/I37,BI37) -> 0 | BK37: =SUMIFS('MA Engine'!$X$6:$X$1110,'MA Engine'!$B$6:$B$1110,$A37,'MA Engine'!$H$6:$H$1110,7,'MA Engine'!$I$6:$I$1110,"DO") -> 186381.11 | BL37: =SUMIFS('MA Engine'!$AK$6:$AK$1110,'MA Engine'!$B$6:$B$1110,$A37,'MA Engine'!$H$6:$H$1110,7,'MA Engine'!$I$6:$I$1110,"DO") -> 186381.11 | BM37: =SUMIFS('MA Engine'!$AL$6:$AL$1110,'MA Engine'!$B$6:$B$1110,$A37,'MA Engine'!$H$6:$H$1110,7,'MA Engine'!$I$6:$I$1110,"DO")+SUMIFS('MA Engine'!$AM$6:$AM$1110,'MA Engine'!$B$6:$B$1110,$A37,'MA Engine'!$H$6:$H$1110,7,'MA Engine'!$I$6:$I$1110,"DO") -> 0 | BN37: =BK37-BL37-BM37 -> 0 | BO37: =IF(BC37=0,0,SUMIFS('Data SKU'!$G$5:$G$116,'Data SKU'!$A$5:$A$116,$C37,'Data SKU'!$B$5:$B$116,$D37,'Data SKU'!$C$5:$C$116,$E37,'Data SKU'!$D$5:$D$116,7,'Data SKU'!$N$5:$N$116,"Invoiced")/SUMIFS($BC$36:$BC$127,$C$36:$C$127,$C37,$D$36:$D$127,$D37,$E$36:$E$127,$E37)*BC37) -> 1837500 | BP37: =IF(BC37=0,0,BO37*BG37/BC37) -> 1837500 | BQ37: =IF(BC37=0,0,BO37*BH37/BC37) -> 0
A38: JLB0092 | B38: =INDEX(I_Items!$B$5:$B$133,MATCH($A38,I_Items!$A$5:$A$133,0))&"" -> Boneless BL Fresh Kepala | C38: =INDEX(I_Items!$C$5:$C$133,MATCH($A38,I_Items!$A$5:$A$133,0))&"" -> RPA | D38: =INDEX(I_Items!$D$5:$D$133,MATCH($A38,I_Items!$A$5:$A$133,0))&"" -> Kepala | E38: =INDEX(I_Items!$F$5:$F$133,MATCH($A38,I_Items!$A$5:$A$133,0))&"" -> Fresh | F38: =INDEX(I_Items!$E$5:$E$133,MATCH($A38,I_Items!$A$5:$A$133,0))&"" | G38: =IF(P38=0,"-",IF(M38=0,"A",IF(K38<=0,"C","B"))) -> B | H38: =SUMIFS('MA Engine'!$K$6:$K$1110,'MA Engine'!$B$6:$B$1110,$A38,'MA Engine'!$I$6:$I$1110,"Opening") -> 768.5 | I38: =SUMIFS('MA Engine'!$K$6:$K$1110,'MA Engine'!$B$6:$B$1110,$A38,'MA Engine'!$H$6:$H$1110,7,'MA Engine'!$I$6:$I$1110,"<>Opening") -> 0 | J38: =SUMIFS('MA Engine'!$W$6:$W$1110,'MA Engine'!$B$6:$B$1110,$A38,'MA Engine'!$H$6:$H$1110,7) -> 0 | K38: =H38+I38-J38 -> 768.5 | L38: =SUMIFS('MA Engine'!$L$6:$L$1110,'MA Engine'!$B$6:$B$1110,$A38,'MA Engine'!$I$6:$I$1110,"Opening")+SUMIFS('MA Engine'!$L$6:$L$1110,'MA Engine'!$B$6:$B$1110,$A38,'MA Engine'!$H$6:$H$1110,7,'MA Engine'!$I$6:$I$1110,"<>Opening")-SUMIFS('MA Engine'!$X$6:$X$1110,'MA Engine'!$B$6:$B$1110,$A38,'MA Engine'!$H$6:$H$1110,7) -> 9341548.3 | M38: =SUMIFS('MA Engine'!$K$6:$K$1110,'MA Engine'!$B$6:$B$1110,$A38,'MA Engine'!$H$6:$H$1110,8) -> 6163.2 | N38: =SUMIFS('MA Engine'!$L$6:$L$1110,'MA Engine'!$B$6:$B$1110,$A38,'MA Engine'!$H$6:$H$1110,8) -> 79273556 | O38: =SUMIFS('MA Engine'!$W$6:$W$1110,'MA Engine'!$B$6:$B$1110,$A38,'MA Engine'!$H$6:$H$1110,8) -> 5642.2 | P38: =Q38+R38 -> 5642.2 | Q38: =SUMIFS('MA Engine'!$W$6:$W$1110,'MA Engine'!$B$6:$B$1110,$A38,'MA Engine'!$H$6:$H$1110,8,'MA Engine'!$I$6:$I$1110,"DO",'MA Engine'!$P$6:$P$1110,"<>Y") -> 5642.2 | R38: =SUMIFS('MA Engine'!$W$6:$W$1110,'MA Engine'!$B$6:$B$1110,$A38,'MA Engine'!$H$6:$H$1110,8,'MA Engine'!$I$6:$I$1110,"Unbilled") -> 0 | S38: =SUMIFS('MA Engine'!$W$6:$W$1110,'MA Engine'!$B$6:$B$1110,$A38,'MA Engine'!$H$6:$H$1110,8,'MA Engine'!$P$6:$P$1110,"Y") -> 0 | T38: =O38-P38-S38 -> 0 | U38: =MAX(0,H38-J38) -> 768.5 | V38: =MAX(0,K38-U38) -> 0 | W38: =MIN(U38,O38) -> 768.5 | X38: =MIN(V38,O38-W38) -> 0 | Y38: =O38-W38-X38 -> 4873.7 | Z38: =IF(O38=0,0,P38/O38) -> 1 | AA38: =SUMIFS('MA Engine'!$AH$6:$AH$1110,'MA Engine'!$B$6:$B$1110,$A38,'MA Engine'!$H$6:$H$1110,8,'MA Engine'!$I$6:$I$1110,"DO",'MA Engine'!$P$6:$P$1110,"<>Y")+SUMIFS('MA Engine'!$AH$6:$AH$1110,'MA Engine'!$B$6:$B$1110,$A38,'MA Engine'!$H$6:$H$1110,8,'MA Engine'!$I$6:$I$1110,"Unbilled") -> 768.5 | AB38: =SUMIFS('MA Engine'!$AI$6:$AI$1110,'MA Engine'!$B$6:$B$1110,$A38,'MA Engine'!$H$6:$H$1110,8,'MA Engine'!$I$6:$I$1110,"DO",'MA Engine'!$P$6:$P$1110,"<>Y")+SUMIFS('MA Engine'!$AI$6:$AI$1110,'MA Engine'!$B$6:$B$1110,$A38,'MA Engine'!$H$6:$H$1110,8,'MA Engine'!$I$6:$I$1110,"Unbilled") -> 0 | AC38: =SUMIFS('MA Engine'!$AJ$6:$AJ$1110,'MA Engine'!$B$6:$B$1110,$A38,'MA Engine'!$H$6:$H$1110,8,'MA Engine'!$I$6:$I$1110,"DO",'MA Engine'!$P$6:$P$1110,"<>Y")+SUMIFS('MA Engine'!$AJ$6:$AJ$1110,'MA Engine'!$B$6:$B$1110,$A38,'MA Engine'!$H$6:$H$1110,8,'MA Engine'!$I$6:$I$1110,"Unbilled") -> 4873.7 | AD38: =SUMIFS('MA Engine'!$L$6:$L$1110,'MA Engine'!$B$6:$B$1110,$A38,'MA Engine'!$H$6:$H$1110,7,'MA Engine'!$I$6:$I$1110,"<>Opening") -> 0 | AE38: =IF(AND(U38>0.0001,(L38-V38*IF(I38>0,AD38/I38,IF(K38>0,L38/K38,0)))<0),IF(K38>0,L38/K38,0),IF(I38>0,AD38/I38,IF(K38>0,L38/K38,0))) -> 12155.561 | AF38: =IF(U38<=0.0001,IF(K38>0,L38/K38,0),IF((L38-V38*IF(I38>0,AD38/I38,IF(K38>0,L38/K38,0)))<0,IF(K38>0,L38/K38,0),(L38-V38*IF(I38>0,AD38/I38,IF(K38>0,L38/K38,0)))/U38)) -> 12155.561 | AG38: =IF(M38>0,N38/M38,IF(K38>0,L38/K38,0)) -> 12862.402 | AH38: =SUMIFS('MA Engine'!$X$6:$X$1110,'MA Engine'!$B$6:$B$1110,$A38,'MA Engine'!$H$6:$H$1110,8,'MA Engine'!$I$6:$I$1110,"DO",'MA Engine'!$P$6:$P$1110,"<>Y")+SUMIFS('MA Engine'!$X$6:$X$1110,'MA Engine'!$B$6:$B$1110,$A38,'MA Engine'!$H$6:$H$1110,8,'MA Engine'!$I$6:$I$1110,"Unbilled") -> 71348083 | AI38: =SUMIFS('MA Engine'!$AK$6:$AK$1110,'MA Engine'!$B$6:$B$1110,$A38,'MA Engine'!$H$6:$H$1110,8,'MA Engine'!$I$6:$I$1110,"DO",'MA Engine'!$P$6:$P$1110,"<>Y")+SUMIFS('MA Engine'!$AK$6:$AK$1110,'MA Engine'!$B$6:$B$1110,$A38,'MA Engine'!$H$6:$H$1110,8,'MA Engine'!$I$6:$I$1110,"Unbilled") -> 8756160.6 | AJ38: =SUMIFS('MA Engine'!$AL$6:$AL$1110,'MA Engine'!$B$6:$B$1110,$A38,'MA Engine'!$H$6:$H$1110,8,'MA Engine'!$I$6:$I$1110,"DO",'MA Engine'!$P$6:$P$1110,"<>Y")+SUMIFS('MA Engine'!$AL$6:$AL$1110,'MA Engine'!$B$6:$B$1110,$A38,'MA Engine'!$H$6:$H$1110,8,'MA Engine'!$I$6:$I$1110,"Unbilled") -> 0 | AK38: =SUMIFS('MA Engine'!$AM$6:$AM$1110,'MA Engine'!$B$6:$B$1110,$A38,'MA Engine'!$H$6:$H$1110,8,'MA Engine'!$I$6:$I$1110,"DO",'MA Engine'!$P$6:$P$1110,"<>Y")+SUMIFS('MA Engine'!$AM$6:$AM$1110,'MA Engine'!$B$6:$B$1110,$A38,'MA Engine'!$H$6:$H$1110,8,'MA Engine'!$I$6:$I$1110,"Unbilled") -> 62591922 | AL38: =AH38-AI38-AJ38-AK38 -> 0 | AM38: =IF(Q38=0,0,IF($D38="Karkas",SUMIFS('Karkas Detail'!$E$6:$E$42,'Karkas Detail'!$A$6:$A$42,$C38,'Karkas Detail'!$B$6:$B$42,$F38,'Karkas Detail'!$C$6:$C$42,$E38)/SUMIFS($Q$36:$Q$127,$C$36:$C$127,$C38,$D$36:$D$127,"Karkas",$F$36:$F$127,$F38,$E$36:$E$127,$E38),SUMIFS('Data SKU'!$G$5:$G$116,'Data SKU'!$A$5:$A$116,$C38,'Data SKU'!$B$5:$B$116,$D38,'Data SKU'!$C$5:$C$116,$E38,'Data SKU'!$D$5:$D$116,8,'Data SKU'!$N$5:$N$116,"Invoiced")/SUMIFS($Q$36:$Q$127,$C$36:$C$127,$C38,$D$36:$D$127,$D38,$E$36:$E$127,$E38))*Q38)+SUMIFS(Unbilled!$U$22:$U$38,Unbilled!$E$22:$E$38,$A38) -> 22730600 | AN38: =IF(P38=0,0,AM38*AA38/P38) -> 3096038.1 | AO38: =IF(P38=0,0,AM38*AB38/P38) -> 0 | AP38: =IF(P38=0,0,AM38*AC38/P38) -> 19634562 | AQ38: =MIN(U38+V38,MAX(0,O38-M38)) -> 0 | AR38: =MAX(0,AQ38-V38)*Z38 -> 0 | AS38: =MIN(V38,AQ38)*Z38 -> 0 | AT38: =(O38-AQ38)*Z38 -> 5642.2 | AU38: =(AR38+AS38+AT38)*BA38 -> 71348083 | AV38: =IF(P38=0,0,AM38*AR38/P38) -> 0 | AW38: =IF(P38=0,0,AM38*AS38/P38) -> 0 | AX38: =IF(P38=0,0,AM38*AT38/P38) -> 22730600 | AY38: =AH38-AU38 -> 0 | AZ38: =IF(M38>0,P38*AG38,0) -> 72572244 | BA38: =IF(P38=0,0,AH38/P38) -> 12645.437 | BB38: By-product (kepala, ceker, usus, HJA, lemak) | BC38: =SUMIFS('MA Engine'!$W$6:$W$1110,'MA Engine'!$B$6:$B$1110,$A38,'MA Engine'!$H$6:$H$1110,7,'MA Engine'!$I$6:$I$1110,"DO") -> 0 | BD38: =MIN(MAX(0,H38),J38) -> 0 | BE38: =J38-BD38 -> 0 | BF38: =IF(J38=0,0,BC38/J38) -> 0 | BG38: =SUMIFS('MA Engine'!$AH$6:$AH$1110,'MA Engine'!$B$6:$B$1110,$A38,'MA Engine'!$H$6:$H$1110,7,'MA Engine'!$I$6:$I$1110,"DO") -> 0 | BH38: =SUMIFS('MA Engine'!$AI$6:$AI$1110,'MA Engine'!$B$6:$B$1110,$A38,'MA Engine'!$H$6:$H$1110,7,'MA Engine'!$I$6:$I$1110,"DO")+SUMIFS('MA Engine'!$AJ$6:$AJ$1110,'MA Engine'!$B$6:$B$1110,$A38,'MA Engine'!$H$6:$H$1110,7,'MA Engine'!$I$6:$I$1110,"DO") -> 0 | BI38: =IF(H38>0,SUMIFS('MA Engine'!$L$6:$L$1110,'MA Engine'!$B$6:$B$1110,$A38,'MA Engine'!$I$6:$I$1110,"Opening")/H38,0) -> 12155.561 | BJ38: =IF(I38>0,AD38/I38,BI38) -> 12155.561 | BK38: =SUMIFS('MA Engine'!$X$6:$X$1110,'MA Engine'!$B$6:$B$1110,$A38,'MA Engine'!$H$6:$H$1110,7,'MA Engine'!$I$6:$I$1110,"DO") -> 0 | BL38: =SUMIFS('MA Engine'!$AK$6:$AK$1110,'MA Engine'!$B$6:$B$1110,$A38,'MA Engine'!$H$6:$H$1110,7,'MA Engine'!$I$6:$I$1110,"DO") -> 0 | BM38: =SUMIFS('MA Engine'!$AL$6:$AL$1110,'MA Engine'!$B$6:$B$1110,$A38,'MA Engine'!$H$6:$H$1110,7,'MA Engine'!$I$6:$I$1110,"DO")+SUMIFS('MA Engine'!$AM$6:$AM$1110,'MA Engine'!$B$6:$B$1110,$A38,'MA Engine'!$H$6:$H$1110,7,'MA Engine'!$I$6:$I$1110,"DO") -> 0 | BN38: =BK38-BL38-BM38 -> 0 | BO38: =IF(BC38=0,0,SUMIFS('Data SKU'!$G$5:$G$116,'Data SKU'!$A$5:$A$116,$C38,'Data SKU'!$B$5:$B$116,$D38,'Data SKU'!$C$5:$C$116,$E38,'Data SKU'!$D$5:$D$116,7,'Data SKU'!$N$5:$N$116,"Invoiced")/SUMIFS($BC$36:$BC$127,$C$36:$C$127,$C38,$D$36:$D$127,$D38,$E$36:$E$127,$E38)*BC38) -> 0 | BP38: =IF(BC38=0,0,BO38*BG38/BC38) -> 0 | BQ38: =IF(BC38=0,0,BO38*BH38/BC38) -> 0
A39: JLB0118 | B39: =INDEX(I_Items!$B$5:$B$133,MATCH($A39,I_Items!$A$5:$A$133,0))&"" -> Boneless BL Fresh Lemak | C39: =INDEX(I_Items!$C$5:$C$133,MATCH($A39,I_Items!$A$5:$A$133,0))&"" -> RPA | D39: =INDEX(I_Items!$D$5:$D$133,MATCH($A39,I_Items!$A$5:$A$133,0))&"" -> Lemak | E39: =INDEX(I_Items!$F$5:$F$133,MATCH($A39,I_Items!$A$5:$A$133,0))&"" -> Fresh | F39: =INDEX(I_Items!$E$5:$E$133,MATCH($A39,I_Items!$A$5:$A$133,0))&"" | G39: =IF(P39=0,"-",IF(M39=0,"A",IF(K39<=0,"C","B"))) -> - | H39: =SUMIFS('MA Engine'!$K$6:$K$1110,'MA Engine'!$B$6:$B$1110,$A39,'MA Engine'!$I$6:$I$1110,"Opening") -> 172.5 | I39: =SUMIFS('MA Engine'!$K$6:$K$1110,'MA Engine'!$B$6:$B$1110,$A39,'MA Engine'!$H$6:$H$1110,7,'MA Engine'!$I$6:$I$1110,"<>Opening") -> 0 | J39: =SUMIFS('MA Engine'!$W$6:$W$1110,'MA Engine'!$B$6:$B$1110,$A39,'MA Engine'!$H$6:$H$1110,7) -> 0 | K39: =H39+I39-J39 -> 172.5 | L39: =SUMIFS('MA Engine'!$L$6:$L$1110,'MA Engine'!$B$6:$B$1110,$A39,'MA Engine'!$I$6:$I$1110,"Opening")+SUMIFS('MA Engine'!$L$6:$L$1110,'MA Engine'!$B$6:$B$1110,$A39,'MA Engine'!$H$6:$H$1110,7,'MA Engine'!$I$6:$I$1110,"<>Opening")-SUMIFS('MA Engine'!$X$6:$X$1110,'MA Engine'!$B$6:$B$1110,$A39,'MA Engine'!$H$6:$H$1110,7) -> 1017669.7 | M39: =SUMIFS('MA Engine'!$K$6:$K$1110,'MA Engine'!$B$6:$B$1110,$A39,'MA Engine'!$H$6:$H$1110,8) -> 64.4 | N39: =SUMIFS('MA Engine'!$L$6:$L$1110,'MA Engine'!$B$6:$B$1110,$A39,'MA Engine'!$H$6:$H$1110,8) -> 1440138.1 | O39: =SUMIFS('MA Engine'!$W$6:$W$1110,'MA Engine'!$B$6:$B$1110,$A39,'MA Engine'!$H$6:$H$1110,8) -> 11 | P39: =Q39+R39 -> 0 | Q39: =SUMIFS('MA Engine'!$W$6:$W$1110,'MA Engine'!$B$6:$B$1110,$A39,'MA Engine'!$H$6:$H$1110,8,'MA Engine'!$I$6:$I$1110,"DO",'MA Engine'!$P$6:$P$1110,"<>Y") -> 0 | R39: =SUMIFS('MA Engine'!$W$6:$W$1110,'MA Engine'!$B$6:$B$1110,$A39,'MA Engine'!$H$6:$H$1110,8,'MA Engine'!$I$6:$I$1110,"Unbilled") -> 0 | S39: =SUMIFS('MA Engine'!$W$6:$W$1110,'MA Engine'!$B$6:$B$1110,$A39,'MA Engine'!$H$6:$H$1110,8,'MA Engine'!$P$6:$P$1110,"Y") -> 11 | T39: =O39-P39-S39 -> 0 | U39: =MAX(0,H39-J39) -> 172.5 | V39: =MAX(0,K39-U39) -> 0 | W39: =MIN(U39,O39) -> 11 | X39: =MIN(V39,O39-W39) -> 0 | Y39: =O39-W39-X39 -> 0 | Z39: =IF(O39=0,0,P39/O39) -> 0 | AA39: =SUMIFS('MA Engine'!$AH$6:$AH$1110,'MA Engine'!$B$6:$B$1110,$A39,'MA Engine'!$H$6:$H$1110,8,'MA Engine'!$I$6:$I$1110,"DO",'MA Engine'!$P$6:$P$1110,"<>Y")+SUMIFS('MA Engine'!$AH$6:$AH$1110,'MA Engine'!$B$6:$B$1110,$A39,'MA Engine'!$H$6:$H$1110,8,'MA Engine'!$I$6:$I$1110,"Unbilled") -> 0 | AB39: =SUMIFS('MA Engine'!$AI$6:$AI$1110,'MA Engine'!$B$6:$B$1110,$A39,'MA Engine'!$H$6:$H$1110,8,'MA Engine'!$I$6:$I$1110,"DO",'MA Engine'!$P$6:$P$1110,"<>Y")+SUMIFS('MA Engine'!$AI$6:$AI$1110,'MA Engine'!$B$6:$B$1110,$A39,'MA Engine'!$H$6:$H$1110,8,'MA Engine'!$I$6:$I$1110,"Unbilled") -> 0 | AC39: =SUMIFS('MA Engine'!$AJ$6:$AJ$1110,'MA Engine'!$B$6:$B$1110,$A39,'MA Engine'!$H$6:$H$1110,8,'MA Engine'!$I$6:$I$1110,"DO",'MA Engine'!$P$6:$P$1110,"<>Y")+SUMIFS('MA Engine'!$AJ$6:$AJ$1110,'MA Engine'!$B$6:$B$1110,$A39,'MA Engine'!$H$6:$H$1110,8,'MA Engine'!$I$6:$I$1110,"Unbilled") -> 0 | AD39: =SUMIFS('MA Engine'!$L$6:$L$1110,'MA Engine'!$B$6:$B$1110,$A39,'MA Engine'!$H$6:$H$1110,7,'MA Engine'!$I$6:$I$1110,"<>Opening") -> 0 | AE39: =IF(AND(U39>0.0001,(L39-V39*IF(I39>0,AD39/I39,IF(K39>0,L39/K39,0)))<0),IF(K39>0,L39/K39,0),IF(I39>0,AD39/I39,IF(K39>0,L39/K39,0))) -> 5899.5347 | AF39: =IF(U39<=0.0001,IF(K39>0,L39/K39,0),IF((L39-V39*IF(I39>0,AD39/I39,IF(K39>0,L39/K39,0)))<0,IF(K39>0,L39/K39,0),(L39-V39*IF(I39>0,AD39/I39,IF(K39>0,L39/K39,0)))/U39)) -> 5899.5347 | AG39: =IF(M39>0,N39/M39,IF(K39>0,L39/K39,0)) -> 22362.392 | AH39: =SUMIFS('MA Engine'!$X$6:$X$1110,'MA Engine'!$B$6:$B$1110,$A39,'MA Engine'!$H$6:$H$1110,8,'MA Engine'!$I$6:$I$1110,"DO",'MA Engine'!$P$6:$P$1110,"<>Y")+SUMIFS('MA Engine'!$X$6:$X$1110,'MA Engine'!$B$6:$B$1110,$A39,'MA Engine'!$H$6:$H$1110,8,'MA Engine'!$I$6:$I$1110,"Unbilled") -> 0 | AI39: =SUMIFS('MA Engine'!$AK$6:$AK$1110,'MA Engine'!$B$6:$B$1110,$A39,'MA Engine'!$H$6:$H$1110,8,'MA Engine'!$I$6:$I$1110,"DO",'MA Engine'!$P$6:$P$1110,"<>Y")+SUMIFS('MA Engine'!$AK$6:$AK$1110,'MA Engine'!$B$6:$B$1110,$A39,'MA Engine'!$H$6:$H$1110,8,'MA Engine'!$I$6:$I$1110,"Unbilled") -> 0 | AJ39: =SUMIFS('MA Engine'!$AL$6:$AL$1110,'MA Engine'!$B$6:$B$1110,$A39,'MA Engine'!$H$6:$H$1110,8,'MA Engine'!$I$6:$I$1110,"DO",'MA Engine'!$P$6:$P$1110,"<>Y")+SUMIFS('MA Engine'!$AL$6:$AL$1110,'MA Engine'!$B$6:$B$1110,$A39,'MA Engine'!$H$6:$H$1110,8,'MA Engine'!$I$6:$I$1110,"Unbilled") -> 0 | AK39: =SUMIFS('MA Engine'!$AM$6:$AM$1110,'MA Engine'!$B$6:$B$1110,$A39,'MA Engine'!$H$6:$H$1110,8,'MA Engine'!$I$6:$I$1110,"DO",'MA Engine'!$P$6:$P$1110,"<>Y")+SUMIFS('MA Engine'!$AM$6:$AM$1110,'MA Engine'!$B$6:$B$1110,$A39,'MA Engine'!$H$6:$H$1110,8,'MA Engine'!$I$6:$I$1110,"Unbilled") -> 0 | AL39: =AH39-AI39-AJ39-AK39 -> 0 | AM39: =IF(Q39=0,0,IF($D39="Karkas",SUMIFS('Karkas Detail'!$E$6:$E$42,'Karkas Detail'!$A$6:$A$42,$C39,'Karkas Detail'!$B$6:$B$42,$F39,'Karkas Detail'!$C$6:$C$42,$E39)/SUMIFS($Q$36:$Q$127,$C$36:$C$127,$C39,$D$36:$D$127,"Karkas",$F$36:$F$127,$F39,$E$36:$E$127,$E39),SUMIFS('Data SKU'!$G$5:$G$116,'Data SKU'!$A$5:$A$116,$C39,'Data SKU'!$B$5:$B$116,$D39,'Data SKU'!$C$5:$C$116,$E39,'Data SKU'!$D$5:$D$116,8,'Data SKU'!$N$5:$N$116,"Invoiced")/SUMIFS($Q$36:$Q$127,$C$36:$C$127,$C39,$D$36:$D$127,$D39,$E$36:$E$127,$E39))*Q39)+SUMIFS(Unbilled!$U$22:$U$38,Unbilled!$E$22:$E$38,$A39) -> 0 | AN39: =IF(P39=0,0,AM39*AA39/P39) -> 0 | AO39: =IF(P39=0,0,AM39*AB39/P39) -> 0 | AP39: =IF(P39=0,0,AM39*AC39/P39) -> 0 | AQ39: =MIN(U39+V39,MAX(0,O39-M39)) -> 0 | AR39: =MAX(0,AQ39-V39)*Z39 -> 0 | AS39: =MIN(V39,AQ39)*Z39 -> 0 | AT39: =(O39-AQ39)*Z39 -> 0 | AU39: =(AR39+AS39+AT39)*BA39 -> 0 | AV39: =IF(P39=0,0,AM39*AR39/P39) -> 0 | AW39: =IF(P39=0,0,AM39*AS39/P39) -> 0 | AX39: =IF(P39=0,0,AM39*AT39/P39) -> 0 | AY39: =AH39-AU39 -> 0 | AZ39: =IF(M39>0,P39*AG39,0) -> 0 | BA39: =IF(P39=0,0,AH39/P39) -> 0 | BB39: By-product (kepala, ceker, usus, HJA, lemak) | BC39: =SUMIFS('MA Engine'!$W$6:$W$1110,'MA Engine'!$B$6:$B$1110,$A39,'MA Engine'!$H$6:$H$1110,7,'MA Engine'!$I$6:$I$1110,"DO") -> 0 | BD39: =MIN(MAX(0,H39),J39) -> 0 | BE39: =J39-BD39 -> 0 | BF39: =IF(J39=0,0,BC39/J39) -> 0 | BG39: =SUMIFS('MA Engine'!$AH$6:$AH$1110,'MA Engine'!$B$6:$B$1110,$A39,'MA Engine'!$H$6:$H$1110,7,'MA Engine'!$I$6:$I$1110,"DO") -> 0 | BH39: =SUMIFS('MA Engine'!$AI$6:$AI$1110,'MA Engine'!$B$6:$B$1110,$A39,'MA Engine'!$H$6:$H$1110,7,'MA Engine'!$I$6:$I$1110,"DO")+SUMIFS('MA Engine'!$AJ$6:$AJ$1110,'MA Engine'!$B$6:$B$1110,$A39,'MA Engine'!$H$6:$H$1110,7,'MA Engine'!$I$6:$I$1110,"DO") -> 0 | BI39: =IF(H39>0,SUMIFS('MA Engine'!$L$6:$L$1110,'MA Engine'!$B$6:$B$1110,$A39,'MA Engine'!$I$6:$I$1110,"Opening")/H39,0) -> 5899.5347 | BJ39: =IF(I39>0,AD39/I39,BI39) -> 5899.5347 | BK39: =SUMIFS('MA Engine'!$X$6:$X$1110,'MA Engine'!$B$6:$B$1110,$A39,'MA Engine'!$H$6:$H$1110,7,'MA Engine'!$I$6:$I$1110,"DO") -> 0 | BL39: =SUMIFS('MA Engine'!$AK$6:$AK$1110,'MA Engine'!$B$6:$B$1110,$A39,'MA Engine'!$H$6:$H$1110,7,'MA Engine'!$I$6:$I$1110,"DO") -> 0 | BM39: =SUMIFS('MA Engine'!$AL$6:$AL$1110,'MA Engine'!$B$6:$B$1110,$A39,'MA Engine'!$H$6:$H$1110,7,'MA Engine'!$I$6:$I$1110,"DO")+SUMIFS('MA Engine'!$AM$6:$AM$1110,'MA Engine'!$B$6:$B$1110,$A39,'MA Engine'!$H$6:$H$1110,7,'MA Engine'!$I$6:$I$1110,"DO") -> 0 | BN39: =BK39-BL39-BM39 -> 0 | BO39: =IF(BC39=0,0,SUMIFS('Data SKU'!$G$5:$G$116,'Data SKU'!$A$5:$A$116,$C39,'Data SKU'!$B$5:$B$116,$D39,'Data SKU'!$C$5:$C$116,$E39,'Data SKU'!$D$5:$D$116,7,'Data SKU'!$N$5:$N$116,"Invoiced")/SUMIFS($BC$36:$BC$127,$C$36:$C$127,$C39,$D$36:$D$127,$D39,$E$36:$E$127,$E39)*BC39) -> 0 | BP39: =IF(BC39=0,0,BO39*BG39/BC39) -> 0 | BQ39: =IF(BC39=0,0,BO39*BH39/BC39) -> 0
