Workbook

Sheet Model_Details
A1: KGR GROUP — Demand Forecast & Inventory Optimizer (Working Paper)
A3: Joint-Production Optimizer
A5: MODEL INFORMATION
A6: Entity | B6: KGR (perusahaan trading & potong ayam)
A7: Model purpose | B7: Demand forecast per potongan + keputusan beli ayam hidup (joint production)
A8: Methodology | B8: Overlay stack + scenario (Bear/Base/Bull) + multi-product newsvendor (joint supply)
A9: Basis | B9: Unit fisik - kg per potongan & ekor ayam
A10: Forecast horizon | B10: 7 hari ke depan (harian), window beli mingguan
A11: Historical data | B11: Penjualan harian per SKU (dummy 3 minggu pada skeleton)
A12: Scenarios | B12: Bear / Base / Bull
A14: SHEET MAP
A15: Sheet | B15: Purpose | C15: Type | D15: Status
A16: I_Products | B16: Master potongan/SKU: harga, shelf life, tier | G16: Input | H16: Edit
A17: I_Yield | B17: Yield matrix: 1 ekor → kg tiap potongan (KOPLING) | G17: Input | H17: Paste aktual RPA
A18: I_Live_Bird | B18: Biaya ayam hidup + constraint + model controls | G18: Input | H18: Edit
A19: I_Sales_History | B19: Penjualan harian per SKU (kg) + flag stockout | G19: Input | H19: Paste data riil
A20: I_Market_Intelligence | B20: Seasonality DOW + override Lebaran/hari libur | G20: Input | H20: Isi judgment
A21: I_MEV | B21: Driver makro ayam (pakan, DOC, harga hidup) | G21: Input | H21: TBC — overlay OFF
A22: O_Demand_Rate | B22: Demand rate historis per SKU (censored) | G22: Calc | H22: Auto
A23: O_Scenario_Multipliers | B23: Multiplier skenario per SKU via tier | G23: Calc | H23: Auto
A24: O_Monte_Carlo | B24: Band probabilistik P10/P50/P90 per SKU | G24: Calc | H24: Auto
A25: O_Granger_Test | B25: Validasi MEV (placeholder) | G25: Calc | H25: TBC
A26: O_Demand_Forecast | B26: LAYER 1 — forecast kg per SKU × skenario | G26: Output | H26: Auto
A27: O_Optimizer | B27: LAYER 2 — beli berapa ekor (joint production) | G27: Output | H27: Auto + 1 decision
... A30: Z_Model_Governance | B30: Versi, sign-off, disclosure | G30: Reference | H30: Active
A32: COLOR LEGEND
A33: Sample | B33: Teks biru = input aktual (hardcode) — edit
A34: Sample | B34: Kuning = asumsi/judgment yang harus diisi
A35: Sample | B35: Teks hitam = output formula — jangan edit
A36: Sample | B36: Oranye = flag / perlu review
A37: Sample | B37: Biru muda + tebal = baris total
A39: OPEN ITEMS
A40: Item | B40: Owner | C40: Status | D40: Notes
A41: Yield aktual per kelas bobot | B41: RPA / Ops | C41: Pending | D41: Skeleton pakai 1 kelas bobot + yield placeholder
A42: Data penjualan harian riil per SKU | B42: Sales | C42: Pending | D42: Skeleton pakai dummy 3 minggu
A43: Harga jual aktual per potongan | B43: Finance | C43: Pending | D43: I_Products kolom harga
A44: Seasonality DOW + uplift Lebaran | B44: Head of Sales | C44: Pending | D44: I_Market_Intelligence — paling fondasional
A45: Validasi MEV (Granger ≥60 obs) | B45: Finance | C45: Pending | D45: Pakai indeks harga ayam/pakan seri panjang
A46: Optimizer stokastik harian + perishability | B46: Analytics | C46: Pending | D46: Excel = aproksimasi mingguan; versi rigor di Python
A47: Jalur potong alternatif (jual karkas utuh) | B47: Ops | C47: Pending | D47: Skeleton asumsikan semua dideboning

Sheet I_Products
A1: I_Products — Master Potongan / SKU
A2: Input aktual KGR. Harga & shelf life = placeholder; ganti dengan angka riil.
A3: SKU Code | B3: SKU Name | C3: Cut Type | D3: Fresh Shelf (hari) | E3: Frozen-Capable | F3: Frozen Shelf (hari) | G3: Sell Price (IDR/kg) | H3: Frozen Price Factor | I3: Tier | J3: Notes
A4: BLD | B4: Boneless Dada (fillet) | C4: Boneless | D4: 2 | E4: Y | F4: 90 | G4: 55000 | H4: 0.9 | I4: Neutral | J4: Binding cut — demand tertinggi
A5: BLP | B5: Boneless Paha (fillet) | C5: Boneless | D5: 2 | E5: Y | F5: 90 | G5: 48000 | H5: 0.9 | I5: Neutral
A6: SYP | B6: Sayap | C6: Bone-in | D6: 2 | E6: Y | F6: 90 | G6: 38000 | H6: 0.92 | I6: Neutral
A7: CKR | B7: Ceker | C7: Byproduct | D7: 2 | E7: Y | F7: 120 | G7: 28000 | H7: 0.95 | I7: Cyclical | J7: Demand ekspor-sensitif
A8: KPL | B8: Kepala | C8: Byproduct | D8: 1 | E8: Y | F8: 90 | G8: 12000 | H8: 0.95 | I8: Cyclical
A9: KLT | B9: Kulit | C9: Byproduct | D9: 1 | E9: Y | F9: 90 | G9: 25000 | H9: 0.92 | I9: Cyclical
A10: JRN | B10: Jeroan (ati ampela) | C10: Byproduct | D10: 1 | E10: Y | F10: 60 | G10: 22000 | H10: 0.9 | I10: Cyclical
A11: TLG | B11: Tulang / carcass frame | C11: Byproduct | D11: 2 | E11: Y | F11: 90 | G11: 8000 | H11: 0.95 | I11: Defensive | J11: Stok / pakan

Sheet I_Live_Bird
A1: I_Live_Bird — Biaya Ayam Hidup, Constraint & Model Controls
A2: Kuning = isi/ubah. Putih hitam = otomatis.
A3: Avg bobot ayam hidup (kg/ekor) | B3: 2
A4: Harga beli ayam hidup (IDR/kg) | B4: 19000
A5: Harga beli per ekor (IDR/ekor) | B5: =B3*B4 -> 38000 | C5: Otomatis: bobot × harga/kg
A6: Biaya potong RPA (IDR/ekor) | B6: 3000
A7: Total biaya per ekor (IDR/ekor) | B7: =B5+B6 -> 41000
A8: Kapasitas freezer (kg) | B8: 5000
A9: Biaya handling beku (IDR/kg) | B9: 500
A10: Nilai salvage unsold non-beku (IDR/kg) | B10: 1000
A11: Kapasitas potong harian (ekor/hari) | B11: 1500
A13: MODEL CONTROLS
A14: Planning window (hari) | B14: 7
A15: Trend mode (Flat / Clamped) | B15: Flat | C15: Flat = aman untuk data pendek
A16: Trend clamp (+/-) | B16: 0.1 | C16: Batas trend bila mode=Clamped
A17: MEV overlay (Off / On) | B17: Off | C17: Off sampai Granger-validated

Sheet I_Yield
A1: I_Yield — Yield Matrix
A2: Ganti % dengan rendemen aktual RPA. kg/ekor = % × bobot hidup. Total % harus = 100%.
A3: Bobot hidup acuan (kg/ekor) | B3: =I_Live_Bird!$B$3 -> 2
A5: Part Code | B5: Part Name | C5: Sellable | D5: Yield % Live Wt | E5: kg per Ekor | F5: Notes
A6: BLD | B6: Boneless Dada (fillet) | C6: Y | D6: 0.18 | E6: =D6*$B$3 -> 0.36 | F6: Binding cut — demand tertinggi
A7: BLP | B7: Boneless Paha (fillet) | C7: Y | D7: 0.13 | E7: =D7*$B$3 -> 0.26
A8: SYP | B8: Sayap | C8: Y | D8: 0.09 | E8: =D8*$B$3 -> 0.18
A9: CKR | B9: Ceker | C9: Y | D9: 0.04 | E9: =D9*$B$3 -> 0.08 | F9: Demand ekspor-sensitif
A10: KPL | B10: Kepala | C10: Y | D10: 0.03 | E10: =D10*$B$3 -> 0.06
A11: KLT | B11: Kulit | C11: Y | D11: 0.06 | E11: =D11*$B$3 -> 0.12
A12: JRN | B12: Jeroan (ati ampela) | C12: Y | D12: 0.05 | E12: =D12*$B$3 -> 0.1
A13: TLG | B13: Tulang / carcass frame | C13: Y | D13: 0.28 | E13: =D13*$B$3 -> 0.56 | F13: Stok / pakan
A14: SUSUT | B14: Susut (darah, bulu, drip, loss proses) | C14: N | D14: =1-SUM(D6:D13) -> 0.14 | E14: =D14*$B$3 -> 0.28 | F14: Penyeimbang ke 100%
A15: TOTAL | D15: =SUM(D6:D14) -> 1 | E15: =SUM(E6:E14) -> 2 | F15: Cek: % = 100%, kg = bobot hidup

Sheet I_Sales_History
A1: I_Sales_History — Penjualan Harian per SKU (kg)
A2: Data aktual (dummy pada skeleton). Flag "Stockout" = hari kehabisan stok → DIKECUALIKAN dari demand rate (censored).
A3: Tanggal | B3: SKU Code | C3: SKU Name | D3: Qty Sold (kg) | E3: Stockout Flag | F3: Notes
A4: 46174 | B4: BLD | C4: Boneless Dada (fillet) | D4: 319.3 | E4: Normal
A5: 46174 | B5: BLP | C5: Boneless Paha (fillet) | D5: 215.5 | E5: Normal
A6: 46174 | B6: SYP | C6: Sayap | D6: 141.2 | E6: Normal
A7: 46174 | B7: CKR | C7: Ceker | D7: 60.2 | E7: Normal
A8: 46174 | B8: KPL | C8: Kepala | D8: 28.2 | E8: Normal
A9: 46174 | B9: KLT | C9: Kulit | D9: 58.5 | E9: Normal
A10: 46174 | B10: JRN | C10: Jeroan (ati ampela) | D10: 53.6 | E10: Normal
A11: 46174 | B11: TLG | C11: Tulang / carcass frame | D11: 185.9 | E11: Normal
A12: 46175 | B12: BLD | C12: Boneless Dada (fillet) | D12: 310.7 | E12: Normal
A13: 46175 | B13: BLP | C13: Boneless Paha (fillet) | D13: 215.9 | E13: Normal
A14: 46175 | B14: SYP | C14: Sayap | D14: 142.1 | E14: Normal
A15: 46175 | B15: CKR | C15: Ceker | D15: 61 | E15: Normal
... A43: 46178 | B43: TLG | C43: Tulang / carcass frame | D43: 202.4 | E43: Normal
A44: 46179 | B44: BLD | C44: Boneless Dada (fillet) | D44: 187 | E44: Stockout | F44: Habis stok siang
A45: 46179 | B45: BLP | C45: Boneless Paha (fillet) | D45: 269.5 | E45: Normal
A46: 46179 | B46: SYP | C46: Sayap | D46: 181.6 | E46: Normal
A47: 46179 | B47: CKR | C47: Ceker | D47: 76.7 | E47: Normal
A48: 46179 | B48: KPL | C48: Kepala | D48: 37.8 | E48: Normal
A49: 46179 | B49: KLT | C49: Kulit | D49: 86.4 | E49: Normal
A50: 46179 | B50: JRN | C50: Jeroan (ati ampela) | D50: 69.4 | E50: Normal
A51: 46179 | B51: TLG | C51: Tulang / carcass frame | D51: 249.2 | E51: Normal
A52: 46180 | B52: BLD | C52: Boneless Dada (fillet) | D52: 371.4 | E52: Normal
A53: 46180 | B53: BLP | C53: Boneless Paha (fillet) | D53: 249.3 | E53: Normal
A54: 46180 | B54: SYP | C54: Sayap | D54: 166 | E54: Normal
A55: 46180 | B55: CKR | C55: Ceker | D55: 71.8 | E55: Normal
A56: 46180 | B56: KPL | C56: Kepala | D56: 33.8 | E56: Normal
... A99: 46185 | B99: TLG | C99: Tulang / carcass frame | D99: 226.7 | E99: Normal
A100: 46186 | B100: BLD | C100: Boneless Dada (fillet) | D100: 187 | E100: Stockout | F100: Habis stok siang
A101: 46186 | B101: BLP | C101: Boneless Paha (fillet) | D101: 275.3 | E101: Normal
A102: 46186 | B102: SYP | C102: Sayap | D102: 208.1 | E102: Normal
A103: 46186 | B103: CKR | C103: Ceker | D103: 69.9 | E103: Normal
A104: 46186 | B104: KPL | C104: Kepala | D104: 40.6 | E104: Normal
A105: 46186 | B105: KLT | C105: Kulit | D105: 84.8 | E105: Normal
A106: 46186 | B106: JRN | C106: Jeroan (ati ampela) | D106: 63.3 | E106: Normal
A107: 46186 | B107: TLG | C107: Tulang / carcass frame | D107: 218.3 | E107: Normal
A108: 46187 | B108: BLD | C108: Boneless Dada (fillet) | D108: 386.3 | E108: Normal
A109: 46187 | B109: BLP | C109: Boneless Paha (fillet) | D109: 294.6 | E109: Normal
A110: 46187 | B110: SYP | C110: Sayap | D110: 183.8 | E110: Normal
A111: 46187 | B111: CKR | C111: Ceker | D111: 72.8 | E111: Normal
A112: 46187 | B112: KPL | C112: Kepala | D112: 27.9 | E112: Normal
... A171: 46194 | B171: TLG | C171: Tulang / carcass frame | D171: 257.3 | E171: Normal

Sheet I_Market_Intelligence
A1: I_Market_Intelligence — Judgment Interface (seasonality & event)
A2: Sheet yang diisi Head of Sales. Semua angka kuning = override pengetahuan pasar.
A3: SECTION 1 — SEASONALITY HARI (berlaku semua potongan)
A4: Index: 1.00 = rata-rata. 1.15 = 15% di atas, 0.85 = 15% di bawah.
A5: Hari | B5: Seasonality Index
A6: Monday | B6: 0.95
A7: Tuesday | B7: 0.93
A8: Wednesday | B8: 0.95
A9: Thursday | B9: 1
A10: Friday | B10: 1.1
A11: Saturday | B11: 1.2
A12: Sunday | B12: 1.15
A14: SECTION 2 — OVERRIDE HARI LIBUR / RAMADAN / LEBARAN
A15: Lebaran ikut kalender Hijriah (geser ~11 hari/thn) → harus disuntik manual, model tak bisa pelajari dari data pendek.
A16: Tanggal | B16: Uplift Factor | C16: Catatan
A17: 46466 | B17: 1.35 | C17: Contoh: H-2 Lebaran (di luar window skeleton)

Sheet I_MEV
A1: I_MEV — Driver Makro (overlay OFF sampai Granger-validated)
A2: Variabel relevan untuk ayam. Proyeksi = TBC.
A3: Variabel | B3: Unit | C3: Nilai Terbaru | D3: Sumber | E3: Proj Bear | F3: Proj Base | G3: Proj Bull
A4: Harga jagung (pakan) | B4: IDR/kg | C4: TBC | D4: BPS / BI / pasar | E4: TBC | F4: TBC | G4: TBC
A5: Harga DOC | B5: IDR/ekor | C5: TBC | D5: BPS / BI / pasar | E5: TBC | F5: TBC | G5: TBC
A6: Harga ayam hidup | B6: IDR/kg | C6: TBC | D6: BPS / BI / pasar | E6: TBC | F6: TBC | G6: TBC
A7: CPI Pangan | B7: index | C7: TBC | D7: BPS / BI / pasar | E7: TBC | F7: TBC | G7: TBC
A8: BI Rate | B8: % | C8: TBC | D8: BPS / BI / pasar | E8: TBC | F8: TBC | G8: TBC

Sheet O_Demand_Rate
A1: O_Demand_Rate — Demand Rate Historis per SKU (censored)
A2: Avg harian DIHITUNG HANYA dari hari "Normal" → koreksi censored demand (stockout tak menyeret rata-rata turun).
A3: SKU Code | B3: SKU Name | C3: Avg Daily Demand (kg, hari Normal) | D3: Hari Tercatat | E3: Hari Stockout | F3: Manual WoW Trend % | G3: Notes
A4: BLD | B4: Boneless Dada (fillet) | C4: =IFERROR(AVERAGEIFS(I_Sales_History!$D:$D,I_Sales_History!$B:$B,A4,I_Sales_History!$E:$E,"Normal"),0) -> 348.65263 | D4: =COUNTIFS(I_Sales_History!$B:$B,A4) -> 21 | E4: =COUNTIFS(I_Sales_History!$B:$B,A4,I_Sales_History!$E:$E,"Stockout") -> 2 | F4: 0 | G4: Stockout dikecualikan
A5: BLP | B5: Boneless Paha (fillet) | C5: =IFERROR(AVERAGEIFS(I_Sales_History!$D:$D,I_Sales_History!$B:$B,A5,I_Sales_History!$E:$E,"Normal"),0) -> 239.15238 | D5: =COUNTIFS(I_Sales_History!$B:$B,A5) -> 21 | E5: =COUNTIFS(I_Sales_History!$B:$B,A5,I_Sales_History!$E:$E,"Stockout") -> 0 | F5: 0
A6: SYP | B6: Sayap | C6: =IFERROR(AVERAGEIFS(I_Sales_History!$D:$D,I_Sales_History!$B:$B,A6,I_Sales_History!$E:$E,"Normal"),0) -> 157.5619 | D6: =COUNTIFS(I_Sales_History!$B:$B,A6) -> 21 | E6: =COUNTIFS(I_Sales_History!$B:$B,A6,I_Sales_History!$E:$E,"Stockout") -> 0 | F6: 0
A7: CKR | B7: Ceker | C7: =IFERROR(AVERAGEIFS(I_Sales_History!$D:$D,I_Sales_History!$B:$B,A7,I_Sales_History!$E:$E,"Normal"),0) -> 63.585714 | D7: =COUNTIFS(I_Sales_History!$B:$B,A7) -> 21 | E7: =COUNTIFS(I_Sales_History!$B:$B,A7,I_Sales_History!$E:$E,"Stockout") -> 0 | F7: 0
A8: KPL | B8: Kepala | C8: =IFERROR(AVERAGEIFS(I_Sales_History!$D:$D,I_Sales_History!$B:$B,A8,I_Sales_History!$E:$E,"Normal"),0) -> 31.709524 | D8: =COUNTIFS(I_Sales_History!$B:$B,A8) -> 21 | E8: =COUNTIFS(I_Sales_History!$B:$B,A8,I_Sales_History!$E:$E,"Stockout") -> 0 | F8: 0
A9: KLT | B9: Kulit | C9: =IFERROR(AVERAGEIFS(I_Sales_History!$D:$D,I_Sales_History!$B:$B,A9,I_Sales_History!$E:$E,"Normal"),0) -> 72.828571 | D9: =COUNTIFS(I_Sales_History!$B:$B,A9) -> 21 | E9: =COUNTIFS(I_Sales_History!$B:$B,A9,I_Sales_History!$E:$E,"Stockout") -> 0 | F9: 0
A10: JRN | B10: Jeroan (ati ampela) | C10: =IFERROR(AVERAGEIFS(I_Sales_History!$D:$D,I_Sales_History!$B:$B,A10,I_Sales_History!$E:$E,"Normal"),0) -> 58.519048 | D10: =COUNTIFS(I_Sales_History!$B:$B,A10) -> 21 | E10: =COUNTIFS(I_Sales_History!$B:$B,A10,I_Sales_History!$E:$E,"Stockout") -> 0 | F10: 0
A11: TLG | B11: Tulang / carcass frame | C11: =IFERROR(AVERAGEIFS(I_Sales_History!$D:$D,I_Sales_History!$B:$B,A11,I_Sales_History!$E:$E,"Normal"),0) -> 209.32381 | D11: =COUNTIFS(I_Sales_History!$B:$B,A11) -> 21 | E11: =COUNTIFS(I_Sales_History!$B:$B,A11,I_Sales_History!$E:$E,"Stockout") -> 0 | F11: 0

Sheet O_Scenario_Multipliers
A1: O_Scenario_Multipliers — Multiplier Skenario per SKU
A3: SECTION 1 — ELASTISITAS TIER (spread skenario)
A4: Tier | B4: Bear Factor | C4: Bull Factor | D4: Makna
A5: Defensive | B5: 0.97 | C5: 1.03 | D5: Inelastis (tulang/stok)
A6: Neutral | B6: 0.93 | C6: 1.07 | D6: Default
A7: Cyclical | B7: 0.85 | C7: 1.15 | D7: Diskresioner (byproduct/ekspor)
A9: SECTION 1b — MULTIPLIER MEV GABUNGAN (Off = 1.000)
A10: Bear MEV | B10: =IF(I_Live_Bird!$B$17="On",1,1) -> 1
A11: Base MEV | B11: 1
A12: Bull MEV | B12: =IF(I_Live_Bird!$B$17="On",1,1) -> 1
A14: SECTION 2 — MULTIPLIER PER SKU
A15: SKU Code | B15: SKU Name | C15: Tier | D15: Bear | E15: Base | F15: Bull
A16: BLD | B16: Boneless Dada (fillet) | C16: =I_Products!$I$4 -> Neutral | D16: =IFERROR(VLOOKUP(C16,O_Scenario_Multipliers!$A$5:$C$7,2,FALSE()),1) -> 0.93 | E16: 1 | F16: =IFERROR(VLOOKUP(C16,O_Scenario_Multipliers!$A$5:$C$7,3,FALSE()),1) -> 1.07
A17: BLP | B17: Boneless Paha (fillet) | C17: =I_Products!$I$5 -> Neutral | D17: =IFERROR(VLOOKUP(C17,O_Scenario_Multipliers!$A$5:$C$7,2,FALSE()),1) -> 0.93 | E17: 1 | F17: =IFERROR(VLOOKUP(C17,O_Scenario_Multipliers!$A$5:$C$7,3,FALSE()),1) -> 1.07
A18: SYP | B18: Sayap | C18: =I_Products!$I$6 -> Neutral | D18: =IFERROR(VLOOKUP(C18,O_Scenario_Multipliers!$A$5:$C$7,2,FALSE()),1) -> 0.93 | E18: 1 | F18: =IFERROR(VLOOKUP(C18,O_Scenario_Multipliers!$A$5:$C$7,3,FALSE()),1) -> 1.07
A19: CKR | B19: Ceker | C19: =I_Products!$I$7 -> Cyclical | D19: =IFERROR(VLOOKUP(C19,O_Scenario_Multipliers!$A$5:$C$7,2,FALSE()),1) -> 0.85 | E19: 1 | F19: =IFERROR(VLOOKUP(C19,O_Scenario_Multipliers!$A$5:$C$7,3,FALSE()),1) -> 1.15
A20: KPL | B20: Kepala | C20: =I_Products!$I$8 -> Cyclical | D20: =IFERROR(VLOOKUP(C20,O_Scenario_Multipliers!$A$5:$C$7,2,FALSE()),1) -> 0.85 | E20: 1 | F20: =IFERROR(VLOOKUP(C20,O_Scenario_Multipliers!$A$5:$C$7,3,FALSE()),1) -> 1.15
A21: KLT | B21: Kulit | C21: =I_Products!$I$9 -> Cyclical | D21: =IFERROR(VLOOKUP(C21,O_Scenario_Multipliers!$A$5:$C$7,2,FALSE()),1) -> 0.85 | E21: 1 | F21: =IFERROR(VLOOKUP(C21,O_Scenario_Multipliers!$A$5:$C$7,3,FALSE()),1) -> 1.15
A22: JRN | B22: Jeroan (ati ampela) | C22: =I_Products!$I$10 -> Cyclical | D22: =IFERROR(VLOOKUP(C22,O_Scenario_Multipliers!$A$5:$C$7,2,FALSE()),1) -> 0.85 | E22: 1 | F22: =IFERROR(VLOOKUP(C22,O_Scenario_Multipliers!$A$5:$C$7,3,FALSE()),1) -> 1.15
A23: TLG | B23: Tulang / carcass frame | C23: =I_Products!$I$11 -> Defensive | D23: =IFERROR(VLOOKUP(C23,O_Scenario_Multipliers!$A$5:$C$7,2,FALSE()),1) -> 0.97 | E23: 1 | F23: =IFERROR(VLOOKUP(C23,O_Scenario_Multipliers!$A$5:$C$7,3,FALSE()),1) -> 1.03

Sheet O_Monte_Carlo
A1: O_Monte_Carlo — Band Probabilistik per SKU
A2: P10/P50/P90 deterministik via NORMINV (stabil, tak volatile). Untuk simulasi penuh jalankan di Python (scipy).
A3: SKU Code | B3: SKU Name | C3: Avg Daily (kg) | D3: CV % | E3: Std Dev | F3: P10 (kg) | G3: P90 (kg)
A4: BLD | B4: Boneless Dada (fillet) | C4: =O_Demand_Rate!$C$4 -> 348.65263 | D4: 0.12 | E4: =C4*D4 -> 41.838316 | F4: =IFERROR(NORMINV(0.1,C4,E4),0) -> 295.03467 | G4: =IFERROR(NORMINV(0.9,C4,E4),0) -> 402.27059
A5: BLP | B5: Boneless Paha (fillet) | C5: =O_Demand_Rate!$C$5 -> 239.15238 | D5: 0.12 | E5: =C5*D5 -> 28.698286 | F5: =IFERROR(NORMINV(0.1,C5,E5),0) -> 202.37405 | G5: =IFERROR(NORMINV(0.9,C5,E5),0) -> 275.93071
A6: SYP | B6: Sayap | C6: =O_Demand_Rate!$C$6 -> 157.5619 | D6: 0.12 | E6: =C6*D6 -> 18.907429 | F6: =IFERROR(NORMINV(0.1,C6,E6),0) -> 133.33106 | G6: =IFERROR(NORMINV(0.9,C6,E6),0) -> 181.79275
A7: CKR | B7: Ceker | C7: =O_Demand_Rate!$C$7 -> 63.585714 | D7: 0.12 | E7: =C7*D7 -> 7.6302857 | F7: =IFERROR(NORMINV(0.1,C7,E7),0) -> 53.80711 | G7: =IFERROR(NORMINV(0.9,C7,E7),0) -> 73.364319
A8: KPL | B8: Kepala | C8: =O_Demand_Rate!$C$8 -> 31.709524 | D8: 0.12 | E8: =C8*D8 -> 3.8051429 | F8: =IFERROR(NORMINV(0.1,C8,E8),0) -> 26.833037 | G8: =IFERROR(NORMINV(0.9,C8,E8),0) -> 36.586011
A9: KLT | B9: Kulit | C9: =O_Demand_Rate!$C$9 -> 72.828571 | D9: 0.12 | E9: =C9*D9 -> 8.7394286 | F9: =IFERROR(NORMINV(0.1,C9,E9),0) -> 61.628543 | G9: =IFERROR(NORMINV(0.9,C9,E9),0) -> 84.0286
A10: JRN | B10: Jeroan (ati ampela) | C10: =O_Demand_Rate!$C$10 -> 58.519048 | D10: 0.12 | E10: =C10*D10 -> 7.0222857 | F10: =IFERROR(NORMINV(0.1,C10,E10),0) -> 49.519626 | G10: =IFERROR(NORMINV(0.9,C10,E10),0) -> 67.518469
A11: TLG | B11: Tulang / carcass frame | C11: =O_Demand_Rate!$C$11 -> 209.32381 | D11: 0.12 | E11: =C11*D11 -> 25.118857 | F11: =IFERROR(NORMINV(0.1,C11,E11),0) -> 177.1327 | G11: =IFERROR(NORMINV(0.9,C11,E11),0) -> 241.51492

Sheet O_Granger_Test
A1: O_Granger_Test — Validasi MEV (PLACEHOLDER)
A2: Butuh ≥60 observasi bulanan seri eksternal (mis. indeks harga ayam/pakan). Jalankan grangercausalitytests, paste F/p di sini.
A3: MEV Variable | B3: Lag (bln) | C3: F-Stat | D3: P-Value | E3: Significant? | F3: Arah Kausal | G3: Notes
A4: Harga jagung | B4: 1 | C4: TBC | D4: TBC | E4: TBC
A5: Harga jagung | B5: 2 | C5: TBC | D5: TBC | E5: TBC
A6: Harga jagung | B6: 3 | C6: TBC | D6: TBC | E6: TBC
A7: Harga DOC | B7: 1 | C7: TBC | D7: TBC | E7: TBC
A8: Harga DOC | B8: 2 | C8: TBC | D8: TBC | E8: TBC
A9: Harga DOC | B9: 3 | C9: TBC | D9: TBC | E9: TBC
A10: Harga ayam hidup | B10: 1 | C10: TBC | D10: TBC | E10: TBC
A11: Harga ayam hidup | B11: 2 | C11: TBC | D11: TBC | E11: TBC
A12: Harga ayam hidup | B12: 3 | C12: TBC | D12: TBC | E12: TBC
A13: CPI Pangan | B13: 1 | C13: TBC | D13: TBC | E13: TBC
A14: CPI Pangan | B14: 2 | C14: TBC | D14: TBC | E14: TBC
A15: CPI Pangan | B15: 3 | C15: TBC | D15: TBC | E15: TBC
... A18: BI Rate | B18: 3 | C18: TBC | D18: TBC | E18: TBC

Sheet O_Demand_Forecast
A1: O_Demand_Forecast — LAYER 1: Forecast kg per SKU × Skenario (7 hari)
A2: Cell = base rate × seasonality(hari) × multiplier skenario × MEV × trend.
A4: Seasonality (×) | D4: =IFERROR(VLOOKUP(TEXT(D6,"dddd"),I_Market_Intelligence!$A$6:$B$12,2,FALSE()),1)*IFERROR(VLOOKUP(D6,I_Market_Intelligence!$A$17:$B$19,2,FALSE()),1) -> 0.93 | E4: =IFERROR(VLOOKUP(TEXT(E6,"dddd"),I_Market_Intelligence!$A$6:$B$12,2,FALSE()),1)*IFERROR(VLOOKUP(E6,I_Market_Intelligence!$A$17:$B$19,2,FALSE()),1) -> 0.95 | F4: =IFERROR(VLOOKUP(TEXT(F6,"dddd"),I_Market_Intelligence!$A$6:$B$12,2,FALSE()),1)*IFERROR(VLOOKUP(F6,I_Market_Intelligence!$A$17:$B$19,2,FALSE()),1) -> 1 | G4: =IFERROR(VLOOKUP(TEXT(G6,"dddd"),I_Market_Intelligence!$A$6:$B$12,2,FALSE()),1)*IFERROR(VLOOKUP(G6,I_Market_Intelligence!$A$17:$B$19,2,FALSE()),1) -> 1.1 | H4: =IFERROR(VLOOKUP(TEXT(H6,"dddd"),I_Market_Intelligence!$A$6:$B$12,2,FALSE()),1)*IFERROR(VLOOKUP(H6,I_Market_Intelligence!$A$17:$B$19,2,FALSE()),1) -> 1.2 | I4: =IFERROR(VLOOKUP(TEXT(I6,"dddd"),I_Market_Intelligence!$A$6:$B$12,2,FALSE()),1)*IFERROR(VLOOKUP(I6,I_Market_Intelligence!$A$17:$B$19,2,FALSE()),1) -> 1.15 | J4: =IFERROR(VLOOKUP(TEXT(J6,"dddd"),I_Market_Intelligence!$A$6:$B$12,2,FALSE()),1)*IFERROR(VLOOKUP(J6,I_Market_Intelligence!$A$17:$B$19,2,FALSE()),1) -> 0.95
A5: Hari | D5: =TEXT(D6,"dddd") -> Tuesday | E5: =TEXT(E6,"dddd") -> Wednesday | F5: =TEXT(F6,"dddd") -> Thursday | G5: =TEXT(G6,"dddd") -> Friday | H5: =TEXT(H6,"dddd") -> Saturday | I5: =TEXT(I6,"dddd") -> Sunday | J5: =TEXT(J6,"dddd") -> Monday
A6: SKU Code | B6: SKU Name | C6: Scenario | D6: 46196 | E6: 46197 | F6: 46198 | G6: 46199 | H6: 46200 | I6: 46201 | J6: 46202 | K6: 7-Hari Total (kg)
A7: BLD | B7: Boneless Dada (fillet) | C7: Bear | D7: =ROUND(O_Demand_Rate!$C$4*D$4*O_Scenario_Multipliers!$D$16*O_Scenario_Multipliers!$B$10*(IF(I_Live_Bird!$B$15="Flat",1,1+MAX(MIN(O_Demand_Rate!$F$4,I_Live_Bird!$B$16),-I_Live_Bird!$B$16))),1) -> 301.5 | E7: =ROUND(O_Demand_Rate!$C$4*E$4*O_Scenario_Multipliers!$D$16*O_Scenario_Multipliers!$B$10*(IF(I_Live_Bird!$B$15="Flat",1,1+MAX(MIN(O_Demand_Rate!$F$4,I_Live_Bird!$B$16),-I_Live_Bird!$B$16))),1) -> 308 | F7: =ROUND(O_Demand_Rate!$C$4*F$4*O_Scenario_Multipliers!$D$16*O_Scenario_Multipliers!$B$10*(IF(I_Live_Bird!$B$15="Flat",1,1+MAX(MIN(O_Demand_Rate!$F$4,I_Live_Bird!$B$16),-I_Live_Bird!$B$16))),1) -> 324.2 | G7: =ROUND(O_Demand_Rate!$C$4*G$4*O_Scenario_Multipliers!$D$16*O_Scenario_Multipliers!$B$10*(IF(I_Live_Bird!$B$15="Flat",1,1+MAX(MIN(O_Demand_Rate!$F$4,I_Live_Bird!$B$16),-I_Live_Bird!$B$16))),1) -> 356.7 | H7: =ROUND(O_Demand_Rate!$C$4*H$4*O_Scenario_Multipliers!$D$16*O_Scenario_Multipliers!$B$10*(IF(I_Live_Bird!$B$15="Flat",1,1+MAX(MIN(O_Demand_Rate!$F$4,I_Live_Bird!$B$16),-I_Live_Bird!$B$16))),1) -> 389.1 | I7: =ROUND(O_Demand_Rate!$C$4*I$4*O_Scenario_Multipliers!$D$16*O_Scenario_Multipliers!$B$10*(IF(I_Live_Bird!$B$15="Flat",1,1+MAX(MIN(O_Demand_Rate!$F$4,I_Live_Bird!$B$16),-I_Live_Bird!$B$16))),1) -> 372.9 | J7: =ROUND(O_Demand_Rate!$C$4*J$4*O_Scenario_Multipliers!$D$16*O_Scenario_Multipliers!$B$10*(IF(I_Live_Bird!$B$15="Flat",1,1+MAX(MIN(O_Demand_Rate!$F$4,I_Live_Bird!$B$16),-I_Live_Bird!$B$16))),1) -> 308 | K7: =SUM(D7:J7) -> 2360.4
A8: BLD | B8: Boneless Dada (fillet) | C8: Base | D8: =ROUND(O_Demand_Rate!$C$4*D$4*O_Scenario_Multipliers!$E$16*O_Scenario_Multipliers!$B$11*(IF(I_Live_Bird!$B$15="Flat",1,1+MAX(MIN(O_Demand_Rate!$F$4,I_Live_Bird!$B$16),-I_Live_Bird!$B$16))),1) -> 324.2 | E8: =ROUND(O_Demand_Rate!$C$4*E$4*O_Scenario_Multipliers!$E$16*O_Scenario_Multipliers!$B$11*(IF(I_Live_Bird!$B$15="Flat",1,1+MAX(MIN(O_Demand_Rate!$F$4,I_Live_Bird!$B$16),-I_Live_Bird!$B$16))),1) -> 331.2 | F8: =ROUND(O_Demand_Rate!$C$4*F$4*O_Scenario_Multipliers!$E$16*O_Scenario_Multipliers!$B$11*(IF(I_Live_Bird!$B$15="Flat",1,1+MAX(MIN(O_Demand_Rate!$F$4,I_Live_Bird!$B$16),-I_Live_Bird!$B$16))),1) -> 348.7 | G8: =ROUND(O_Demand_Rate!$C$4*G$4*O_Scenario_Multipliers!$E$16*O_Scenario_Multipliers!$B$11*(IF(I_Live_Bird!$B$15="Flat",1,1+MAX(MIN(O_Demand_Rate!$F$4,I_Live_Bird!$B$16),-I_Live_Bird!$B$16))),1) -> 383.5 | H8: =ROUND(O_Demand_Rate!$C$4*H$4*O_Scenario_Multipliers!$E$16*O_Scenario_Multipliers!$B$11*(IF(I_Live_Bird!$B$15="Flat",1,1+MAX(MIN(O_Demand_Rate!$F$4,I_Live_Bird!$B$16),-I_Live_Bird!$B$16))),1) -> 418.4 | I8: =ROUND(O_Demand_Rate!$C$4*I$4*O_Scenario_Multipliers!$E$16*O_Scenario_Multipliers!$B$11*(IF(I_Live_Bird!$B$15="Flat",1,1+MAX(MIN(O_Demand_Rate!$F$4,I_Live_Bird!$B$16),-I_Live_Bird!$B$16))),1) -> 401 | J8: =ROUND(O_Demand_Rate!$C$4*J$4*O_Scenario_Multipliers!$E$16*O_Scenario_Multipliers!$B$11*(IF(I_Live_Bird!$B$15="Flat",1,1+MAX(MIN(O_Demand_Rate!$F$4,I_Live_Bird!$B$16),-I_Live_Bird!$B$16))),1) -> 331.2 | K8: =SUM(D8:J8) -> 2538.2
A9: BLD | B9: Boneless Dada (fillet) | C9: Bull | D9: =ROUND(O_Demand_Rate!$C$4*D$4*O_Scenario_Multipliers!$F$16*O_Scenario_Multipliers!$B$12*(IF(I_Live_Bird!$B$15="Flat",1,1+MAX(MIN(O_Demand_Rate!$F$4,I_Live_Bird!$B$16),-I_Live_Bird!$B$16))),1) -> 346.9 | E9: =ROUND(O_Demand_Rate!$C$4*E$4*O_Scenario_Multipliers!$F$16*O_Scenario_Multipliers!$B$12*(IF(I_Live_Bird!$B$15="Flat",1,1+MAX(MIN(O_Demand_Rate!$F$4,I_Live_Bird!$B$16),-I_Live_Bird!$B$16))),1) -> 354.4 | F9: =ROUND(O_Demand_Rate!$C$4*F$4*O_Scenario_Multipliers!$F$16*O_Scenario_Multipliers!$B$12*(IF(I_Live_Bird!$B$15="Flat",1,1+MAX(MIN(O_Demand_Rate!$F$4,I_Live_Bird!$B$16),-I_Live_Bird!$B$16))),1) -> 373.1 | G9: =ROUND(O_Demand_Rate!$C$4*G$4*O_Scenario_Multipliers!$F$16*O_Scenario_Multipliers!$B$12*(IF(I_Live_Bird!$B$15="Flat",1,1+MAX(MIN(O_Demand_Rate!$F$4,I_Live_Bird!$B$16),-I_Live_Bird!$B$16))),1) -> 410.4 | H9: =ROUND(O_Demand_Rate!$C$4*H$4*O_Scenario_Multipliers!$F$16*O_Scenario_Multipliers!$B$12*(IF(I_Live_Bird!$B$15="Flat",1,1+MAX(MIN(O_Demand_Rate!$F$4,I_Live_Bird!$B$16),-I_Live_Bird!$B$16))),1) -> 447.7 | I9: =ROUND(O_Demand_Rate!$C$4*I$4*O_Scenario_Multipliers!$F$16*O_Scenario_Multipliers!$B$12*(IF(I_Live_Bird!$B$15="Flat",1,1+MAX(MIN(O_Demand_Rate!$F$4,I_Live_Bird!$B$16),-I_Live_Bird!$B$16))),1) -> 429 | J9: =ROUND(O_Demand_Rate!$C$4*J$4*O_Scenario_Multipliers!$F$16*O_Scenario_Multipliers!$B$12*(IF(I_Live_Bird!$B$15="Flat",1,1+MAX(MIN(O_Demand_Rate!$F$4,I_Live_Bird!$B$16),-I_Live_Bird!$B$16))),1) -> 354.4 | K9: =SUM(D9:J9) -> 2715.9
A10: BLP | B10: Boneless Paha (fillet) | C10: Bear | D10: =ROUND(O_Demand_Rate!$C$5*D$4*O_Scenario_Multipliers!$D$17*O_Scenario_Multipliers!$B$10*(IF(I_Live_Bird!$B$15="Flat",1,1+MAX(MIN(O_Demand_Rate!$F$5,I_Live_Bird!$B$16),-I_Live_Bird!$B$16))),1) -> 206.8 | E10: =ROUND(O_Demand_Rate!$C$5*E$4*O_Scenario_Multipliers!$D$17*O_Scenario_Multipliers!$B$10*(IF(I_Live_Bird!$B$15="Flat",1,1+MAX(MIN(O_Demand_Rate!$F$5,I_Live_Bird!$B$16),-I_Live_Bird!$B$16))),1) -> 211.3 | F10: =ROUND(O_Demand_Rate!$C$5*F$4*O_Scenario_Multipliers!$D$17*O_Scenario_Multipliers!$B$10*(IF(I_Live_Bird!$B$15="Flat",1,1+MAX(MIN(O_Demand_Rate!$F$5,I_Live_Bird!$B$16),-I_Live_Bird!$B$16))),1) -> 222.4 | G10: =ROUND(O_Demand_Rate!$C$5*G$4*O_Scenario_Multipliers!$D$17*O_Scenario_Multipliers!$B$10*(IF(I_Live_Bird!$B$15="Flat",1,1+MAX(MIN(O_Demand_Rate!$F$5,I_Live_Bird!$B$16),-I_Live_Bird!$B$16))),1) -> 244.7 | H10: =ROUND(O_Demand_Rate!$C$5*H$4*O_Scenario_Multipliers!$D$17*O_Scenario_Multipliers!$B$10*(IF(I_Live_Bird!$B$15="Flat",1,1+MAX(MIN(O_Demand_Rate!$F$5,I_Live_Bird!$B$16),-I_Live_Bird!$B$16))),1) -> 266.9 | I10: =ROUND(O_Demand_Rate!$C$5*I$4*O_Scenario_Multipliers!$D$17*O_Scenario_Multipliers!$B$10*(IF(I_Live_Bird!$B$15="Flat",1,1+MAX(MIN(O_Demand_Rate!$F$5,I_Live_Bird!$B$16),-I_Live_Bird!$B$16))),1) -> 255.8 | J10: =ROUND(O_Demand_Rate!$C$5*J$4*O_Scenario_Multipliers!$D$17*O_Scenario_Multipliers!$B$10*(IF(I_Live_Bird!$B$15="Flat",1,1+MAX(MIN(O_Demand_Rate!$F$5,I_Live_Bird!$B$16),-I_Live_Bird!$B$16))),1) -> 211.3 | K10: =SUM(D10:J10) -> 1619.2
A11: BLP | B11: Boneless Paha (fillet) | C11: Base | D11: =ROUND(O_Demand_Rate!$C$5*D$4*O_Scenario_Multipliers!$E$17*O_Scenario_Multipliers!$B$11*(IF(I_Live_Bird!$B$15="Flat",1,1+MAX(MIN(O_Demand_Rate!$F$5,I_Live_Bird!$B$16),-I_Live_Bird!$B$16))),1) -> 222.4 | E11: =ROUND(O_Demand_Rate!$C$5*E$4*O_Scenario_Multipliers!$E$17*O_Scenario_Multipliers!$B$11*(IF(I_Live_Bird!$B$15="Flat",1,1+MAX(MIN(O_Demand_Rate!$F$5,I_Live_Bird!$B$16),-I_Live_Bird!$B$16))),1) -> 227.2 | F11: =ROUND(O_Demand_Rate!$C$5*F$4*O_Scenario_Multipliers!$E$17*O_Scenario_Multipliers!$B$11*(IF(I_Live_Bird!$B$15="Flat",1,1+MAX(MIN(O_Demand_Rate!$F$5,I_Live_Bird!$B$16),-I_Live_Bird!$B$16))),1) -> 239.2 | G11: =ROUND(O_Demand_Rate!$C$5*G$4*O_Scenario_Multipliers!$E$17*O_Scenario_Multipliers!$B$11*(IF(I_Live_Bird!$B$15="Flat",1,1+MAX(MIN(O_Demand_Rate!$F$5,I_Live_Bird!$B$16),-I_Live_Bird!$B$16))),1) -> 263.1 | H11: =ROUND(O_Demand_Rate!$C$5*H$4*O_Scenario_Multipliers!$E$17*O_Scenario_Multipliers!$B$11*(IF(I_Live_Bird!$B$15="Flat",1,1+MAX(MIN(O_Demand_Rate!$F$5,I_Live_Bird!$B$16),-I_Live_Bird!$B$16))),1) -> 287 | I11: =ROUND(O_Demand_Rate!$C$5*I$4*O_Scenario_Multipliers!$E$17*O_Scenario_Multipliers!$B$11*(IF(I_Live_Bird!$B$15="Flat",1,1+MAX(MIN(O_Demand_Rate!$F$5,I_Live_Bird!$B$16),-I_Live_Bird!$B$16))),1) -> 275 | J11: =ROUND(O_Demand_Rate!$C$5*J$4*O_Scenario_Multipliers!$E$17*O_Scenario_Multipliers!$B$11*(IF(I_Live_Bird!$B$15="Flat",1,1+MAX(MIN(O_Demand_Rate!$F$5,I_Live_Bird!$B$16),-I_Live_Bird!$B$16))),1) -> 227.2 | K11: =SUM(D11:J11) -> 1741.1
A12: BLP | B12: Boneless Paha (fillet) | C12: Bull | D12: =ROUND(O_Demand_Rate!$C$5*D$4*O_Scenario_Multipliers!$F$17*O_Scenario_Multipliers!$B$12*(IF(I_Live_Bird!$B$15="Flat",1,1+MAX(MIN(O_Demand_Rate!$F$5,I_Live_Bird!$B$16),-I_Live_Bird!$B$16))),1) -> 238 | E12: =ROUND(O_Demand_Rate!$C$5*E$4*O_Scenario_Multipliers!$F$17*O_Scenario_Multipliers!$B$12*(IF(I_Live_Bird!$B$15="Flat",1,1+MAX(MIN(O_Demand_Rate!$F$5,I_Live_Bird!$B$16),-I_Live_Bird!$B$16))),1) -> 243.1 | F12: =ROUND(O_Demand_Rate!$C$5*F$4*O_Scenario_Multipliers!$F$17*O_Scenario_Multipliers!$B$12*(IF(I_Live_Bird!$B$15="Flat",1,1+MAX(MIN(O_Demand_Rate!$F$5,I_Live_Bird!$B$16),-I_Live_Bird!$B$16))),1) -> 255.9 | G12: =ROUND(O_Demand_Rate!$C$5*G$4*O_Scenario_Multipliers!$F$17*O_Scenario_Multipliers!$B$12*(IF(I_Live_Bird!$B$15="Flat",1,1+MAX(MIN(O_Demand_Rate!$F$5,I_Live_Bird!$B$16),-I_Live_Bird!$B$16))),1) -> 281.5 | H12: =ROUND(O_Demand_Rate!$C$5*H$4*O_Scenario_Multipliers!$F$17*O_Scenario_Multipliers!$B$12*(IF(I_Live_Bird!$B$15="Flat",1,1+MAX(MIN(O_Demand_Rate!$F$5,I_Live_Bird!$B$16),-I_Live_Bird!$B$16))),1) -> 307.1 | I12: =ROUND(O_Demand_Rate!$C$5*I$4*O_Scenario_Multipliers!$F$17*O_Scenario_Multipliers!$B$12*(IF(I_Live_Bird!$B$15="Flat",1,1+MAX(MIN(O_Demand_Rate!$F$5,I_Live_Bird!$B$16),-I_Live_Bird!$B$16))),1) -> 294.3 | J12: =ROUND(O_Demand_Rate!$C$5*J$4*O_Scenario_Multipliers!$F$17*O_Scenario_Multipliers!$B$12*(IF(I_Live_Bird!$B$15="Flat",1,1+MAX(MIN(O_Demand_Rate!$F$5,I_Live_Bird!$B$16),-I_Live_Bird!$B$16))),1) -> 243.1 | K12: =SUM(D12:J12) -> 1863
A13: SYP | B13: Sayap | C13: Bear | D13: =ROUND(O_Demand_Rate!$C$6*D$4*O_Scenario_Multipliers!$D$18*O_Scenario_Multipliers!$B$10*(IF(I_Live_Bird!$B$15="Flat",1,1+MAX(MIN(O_Demand_Rate!$F$6,I_Live_Bird!$B$16),-I_Live_Bird!$B$16))),1) -> 136.3 | E13: =ROUND(O_Demand_Rate!$C$6*E$4*O_Scenario_Multipliers!$D$18*O_Scenario_Multipliers!$B$10*(IF(I_Live_Bird!$B$15="Flat",1,1+MAX(MIN(O_Demand_Rate!$F$6,I_Live_Bird!$B$16),-I_Live_Bird!$B$16))),1) -> 139.2 | F13: =ROUND(O_Demand_Rate!$C$6*F$4*O_Scenario_Multipliers!$D$18*O_Scenario_Multipliers!$B$10*(IF(I_Live_Bird!$B$15="Flat",1,1+MAX(MIN(O_Demand_Rate!$F$6,I_Live_Bird!$B$16),-I_Live_Bird!$B$16))),1) -> 146.5 | G13: =ROUND(O_Demand_Rate!$C$6*G$4*O_Scenario_Multipliers!$D$18*O_Scenario_Multipliers!$B$10*(IF(I_Live_Bird!$B$15="Flat",1,1+MAX(MIN(O_Demand_Rate!$F$6,I_Live_Bird!$B$16),-I_Live_Bird!$B$16))),1) -> 161.2 | H13: =ROUND(O_Demand_Rate!$C$6*H$4*O_Scenario_Multipliers!$D$18*O_Scenario_Multipliers!$B$10*(IF(I_Live_Bird!$B$15="Flat",1,1+MAX(MIN(O_Demand_Rate!$F$6,I_Live_Bird!$B$16),-I_Live_Bird!$B$16))),1) -> 175.8 | I13: =ROUND(O_Demand_Rate!$C$6*I$4*O_Scenario_Multipliers!$D$18*O_Scenario_Multipliers!$B$10*(IF(I_Live_Bird!$B$15="Flat",1,1+MAX(MIN(O_Demand_Rate!$F$6,I_Live_Bird!$B$16),-I_Live_Bird!$B$16))),1) -> 168.5 | J13: =ROUND(O_Demand_Rate!$C$6*J$4*O_Scenario_Multipliers!$D$18*O_Scenario_Multipliers!$B$10*(IF(I_Live_Bird!$B$15="Flat",1,1+MAX(MIN(O_Demand_Rate!$F$6,I_Live_Bird!$B$16),-I_Live_Bird!$B$16))),1) -> 139.2 | K13: =SUM(D13:J13) -> 1066.7
A14: SYP | B14: Sayap | C14: Base | D14: =ROUND(O_Demand_Rate!$C$6*D$4*O_Scenario_Multipliers!$E$18*O_Scenario_Multipliers!$B$11*(IF(I_Live_Bird!$B$15="Flat",1,1+MAX(MIN(O_Demand_Rate!$F$6,I_Live_Bird!$B$16),-I_Live_Bird!$B$16))),1) -> 146.5 | E14: =ROUND(O_Demand_Rate!$C$6*E$4*O_Scenario_Multipliers!$E$18*O_Scenario_Multipliers!$B$11*(IF(I_Live_Bird!$B$15="Flat",1,1+MAX(MIN(O_Demand_Rate!$F$6,I_Live_Bird!$B$16),-I_Live_Bird!$B$16))),1) -> 149.7 | F14: =ROUND(O_Demand_Rate!$C$6*F$4*O_Scenario_Multipliers!$E$18*O_Scenario_Multipliers!$B$11*(IF(I_Live_Bird!$B$15="Flat",1,1+MAX(MIN(O_Demand_Rate!$F$6,I_Live_Bird!$B$16),-I_Live_Bird!$B$16))),1) -> 157.6 | G14: =ROUND(O_Demand_Rate!$C$6*G$4*O_Scenario_Multipliers!$E$18*O_Scenario_Multipliers!$B$11*(IF(I_Live_Bird!$B$15="Flat",1,1+MAX(MIN(O_Demand_Rate!$F$6,I_Live_Bird!$B$16),-I_Live_Bird!$B$16))),1) -> 173.3 | H14: =ROUND(O_Demand_Rate!$C$6*H$4*O_Scenario_Multipliers!$E$18*O_Scenario_Multipliers!$B$11*(IF(I_Live_Bird!$B$15="Flat",1,1+MAX(MIN(O_Demand_Rate!$F$6,I_Live_Bird!$B$16),-I_Live_Bird!$B$16))),1) -> 189.1 | I14: =ROUND(O_Demand_Rate!$C$6*I$4*O_Scenario_Multipliers!$E$18*O_Scenario_Multipliers!$B$11*(IF(I_Live_Bird!$B$15="Flat",1,1+MAX(MIN(O_Demand_Rate!$F$6,I_Live_Bird!$B$16),-I_Live_Bird!$B$16))),1) -> 181.2 | J14: =ROUND(O_Demand_Rate!$C$6*J$4*O_Scenario_Multipliers!$E$18*O_Scenario_Multipliers!$B$11*(IF(I_Live_Bird!$B$15="Flat",1,1+MAX(MIN(O_Demand_Rate!$F$6,I_Live_Bird!$B$16),-I_Live_Bird!$B$16))),1) -> 149.7 | K14: =SUM(D14:J14) -> 1147.1
A15: SYP | B15: Sayap | C15: Bull | D15: =ROUND(O_Demand_Rate!$C$6*D$4*O_Scenario_Multipliers!$F$18*O_Scenario_Multipliers!$B$12*(IF(I_Live_Bird!$B$15="Flat",1,1+MAX(MIN(O_Demand_Rate!$F$6,I_Live_Bird!$B$16),-I_Live_Bird!$B$16))),1) -> 156.8 | E15: =ROUND(O_Demand_Rate!$C$6*E$4*O_Scenario_Multipliers!$F$18*O_Scenario_Multipliers!$B$12*(IF(I_Live_Bird!$B$15="Flat",1,1+MAX(MIN(O_Demand_Rate!$F$6,I_Live_Bird!$B$16),-I_Live_Bird!$B$16))),1) -> 160.2 | F15: =ROUND(O_Demand_Rate!$C$6*F$4*O_Scenario_Multipliers!$F$18*O_Scenario_Multipliers!$B$12*(IF(I_Live_Bird!$B$15="Flat",1,1+MAX(MIN(O_Demand_Rate!$F$6,I_Live_Bird!$B$16),-I_Live_Bird!$B$16))),1) -> 168.6 | G15: =ROUND(O_Demand_Rate!$C$6*G$4*O_Scenario_Multipliers!$F$18*O_Scenario_Multipliers!$B$12*(IF(I_Live_Bird!$B$15="Flat",1,1+MAX(MIN(O_Demand_Rate!$F$6,I_Live_Bird!$B$16),-I_Live_Bird!$B$16))),1) -> 185.5 | H15: =ROUND(O_Demand_Rate!$C$6*H$4*O_Scenario_Multipliers!$F$18*O_Scenario_Multipliers!$B$12*(IF(I_Live_Bird!$B$15="Flat",1,1+MAX(MIN(O_Demand_Rate!$F$6,I_Live_Bird!$B$16),-I_Live_Bird!$B$16))),1) -> 202.3 | I15: =ROUND(O_Demand_Rate!$C$6*I$4*O_Scenario_Multipliers!$F$18*O_Scenario_Multipliers!$B$12*(IF(I_Live_Bird!$B$15="Flat",1,1+MAX(MIN(O_Demand_Rate!$F$6,I_Live_Bird!$B$16),-I_Live_Bird!$B$16))),1) -> 193.9 | J15: =ROUND(O_Demand_Rate!$C$6*J$4*O_Scenario_Multipliers!$F$18*O_Scenario_Multipliers!$B$12*(IF(I_Live_Bird!$B$15="Flat",1,1+MAX(MIN(O_Demand_Rate!$F$6,I_Live_Bird!$B$16),-I_Live_Bird!$B$16))),1) -> 160.2 | K15: =SUM(D15:J15) -> 1227.5
A16: CKR | B16: Ceker | C16: Bear | D16: =ROUND(O_Demand_Rate!$C$7*D$4*O_Scenario_Multipliers!$D$19*O_Scenario_Multipliers!$B$10*(IF(I_Live_Bird!$B$15="Flat",1,1+MAX(MIN(O_Demand_Rate!$F$7,I_Live_Bird!$B$16),-I_Live_Bird!$B$16))),1) -> 50.3 | E16: =ROUND(O_Demand_Rate!$C$7*E$4*O_Scenario_Multipliers!$D$19*O_Scenario_Multipliers!$B$10*(IF(I_Live_Bird!$B$15="Flat",1,1+MAX(MIN(O_Demand_Rate!$F$7,I_Live_Bird!$B$16),-I_Live_Bird!$B$16))),1) -> 51.3 | F16: =ROUND(O_Demand_Rate!$C$7*F$4*O_Scenario_Multipliers!$D$19*O_Scenario_Multipliers!$B$10*(IF(I_Live_Bird!$B$15="Flat",1,1+MAX(MIN(O_Demand_Rate!$F$7,I_Live_Bird!$B$16),-I_Live_Bird!$B$16))),1) -> 54 | G16: =ROUND(O_Demand_Rate!$C$7*G$4*O_Scenario_Multipliers!$D$19*O_Scenario_Multipliers!$B$10*(IF(I_Live_Bird!$B$15="Flat",1,1+MAX(MIN(O_Demand_Rate!$F$7,I_Live_Bird!$B$16),-I_Live_Bird!$B$16))),1) -> 59.5 | H16: =ROUND(O_Demand_Rate!$C$7*H$4*O_Scenario_Multipliers!$D$19*O_Scenario_Multipliers!$B$10*(IF(I_Live_Bird!$B$15="Flat",1,1+MAX(MIN(O_Demand_Rate!$F$7,I_Live_Bird!$B$16),-I_Live_Bird!$B$16))),1) -> 64.9 | I16: =ROUND(O_Demand_Rate!$C$7*I$4*O_Scenario_Multipliers!$D$19*O_Scenario_Multipliers!$B$10*(IF(I_Live_Bird!$B$15="Flat",1,1+MAX(MIN(O_Demand_Rate!$F$7,I_Live_Bird!$B$16),-I_Live_Bird!$B$16))),1) -> 62.2 | J16: =ROUND(O_Demand_Rate!$C$7*J$4*O_Scenario_Multipliers!$D$19*O_Scenario_Multipliers!$B$10*(IF(I_Live_Bird!$B$15="Flat",1,1+MAX(MIN(O_Demand_Rate!$F$7,I_Live_Bird!$B$16),-I_Live_Bird!$B$16))),1) -> 51.3 | K16: =SUM(D16:J16) -> 393.5
A17: CKR | B17: Ceker | C17: Base | D17: =ROUND(O_Demand_Rate!$C$7*D$4*O_Scenario_Multipliers!$E$19*O_Scenario_Multipliers!$B$11*(IF(I_Live_Bird!$B$15="Flat",1,1+MAX(MIN(O_Demand_Rate!$F$7,I_Live_Bird!$B$16),-I_Live_Bird!$B$16))),1) -> 59.1 | E17: =ROUND(O_Demand_Rate!$C$7*E$4*O_Scenario_Multipliers!$E$19*O_Scenario_Multipliers!$B$11*(IF(I_Live_Bird!$B$15="Flat",1,1+MAX(MIN(O_Demand_Rate!$F$7,I_Live_Bird!$B$16),-I_Live_Bird!$B$16))),1) -> 60.4 | F17: =ROUND(O_Demand_Rate!$C$7*F$4*O_Scenario_Multipliers!$E$19*O_Scenario_Multipliers!$B$11*(IF(I_Live_Bird!$B$15="Flat",1,1+MAX(MIN(O_Demand_Rate!$F$7,I_Live_Bird!$B$16),-I_Live_Bird!$B$16))),1) -> 63.6 | G17: =ROUND(O_Demand_Rate!$C$7*G$4*O_Scenario_Multipliers!$E$19*O_Scenario_Multipliers!$B$11*(IF(I_Live_Bird!$B$15="Flat",1,1+MAX(MIN(O_Demand_Rate!$F$7,I_Live_Bird!$B$16),-I_Live_Bird!$B$16))),1) -> 69.9 | H17: =ROUND(O_Demand_Rate!$C$7*H$4*O_Scenario_Multipliers!$E$19*O_Scenario_Multipliers!$B$11*(IF(I_Live_Bird!$B$15="Flat",1,1+MAX(MIN(O_Demand_Rate!$F$7,I_Live_Bird!$B$16),-I_Live_Bird!$B$16))),1) -> 76.3 | I17: =ROUND(O_Demand_Rate!$C$7*I$4*O_Scenario_Multipliers!$E$19*O_Scenario_Multipliers!$B$11*(IF(I_Live_Bird!$B$15="Flat",1,1+MAX(MIN(O_Demand_Rate!$F$7,I_Live_Bird!$B$16),-I_Live_Bird!$B$16))),1) -> 73.1 | J17: =ROUND(O_Demand_Rate!$C$7*J$4*O_Scenario_Multipliers!$E$19*O_Scenario_Multipliers!$B$11*(IF(I_Live_Bird!$B$15="Flat",1,1+MAX(MIN(O_Demand_Rate!$F$7,I_Live_Bird!$B$16),-I_Live_Bird!$B$16))),1) -> 60.4 | K17: =SUM(D17:J17) -> 462.8
A18: CKR | B18: Ceker | C18: Bull | D18: =ROUND(O_Demand_Rate!$C$7*D$4*O_Scenario_Multipliers!$F$19*O_Scenario_Multipliers!$B$12*(IF(I_Live_Bird!$B$15="Flat",1,1+MAX(MIN(O_Demand_Rate!$F$7,I_Live_Bird!$B$16),-I_Live_Bird!$B$16))),1) -> 68 | E18: =ROUND(O_Demand_Rate!$C$7*E$4*O_Scenario_Multipliers!$F$19*O_Scenario_Multipliers!$B$12*(IF(I_Live_Bird!$B$15="Flat",1,1+MAX(MIN(O_Demand_Rate!$F$7,I_Live_Bird!$B$16),-I_Live_Bird!$B$16))),1) -> 69.5 | F18: =ROUND(O_Demand_Rate!$C$7*F$4*O_Scenario_Multipliers!$F$19*O_Scenario_Multipliers!$B$12*(IF(I_Live_Bird!$B$15="Flat",1,1+MAX(MIN(O_Demand_Rate!$F$7,I_Live_Bird!$B$16),-I_Live_Bird!$B$16))),1) -> 73.1 | G18: =ROUND(O_Demand_Rate!$C$7*G$4*O_Scenario_Multipliers!$F$19*O_Scenario_Multipliers!$B$12*(IF(I_Live_Bird!$B$15="Flat",1,1+MAX(MIN(O_Demand_Rate!$F$7,I_Live_Bird!$B$16),-I_Live_Bird!$B$16))),1) -> 80.4 | H18: =ROUND(O_Demand_Rate!$C$7*H$4*O_Scenario_Multipliers!$F$19*O_Scenario_Multipliers!$B$12*(IF(I_Live_Bird!$B$15="Flat",1,1+MAX(MIN(O_Demand_Rate!$F$7,I_Live_Bird!$B$16),-I_Live_Bird!$B$16))),1) -> 87.7 | I18: =ROUND(O_Demand_Rate!$C$7*I$4*O_Scenario_Multipliers!$F$19*O_Scenario_Multipliers!$B$12*(IF(I_Live_Bird!$B$15="Flat",1,1+MAX(MIN(O_Demand_Rate!$F$7,I_Live_Bird!$B$16),-I_Live_Bird!$B$16))),1) -> 84.1 | J18: =ROUND(O_Demand_Rate!$C$7*J$4*O_Scenario_Multipliers!$F$19*O_Scenario_Multipliers!$B$12*(IF(I_Live_Bird!$B$15="Flat",1,1+MAX(MIN(O_Demand_Rate!$F$7,I_Live_Bird!$B$16),-I_Live_Bird!$B$16))),1) -> 69.5 | K18: =SUM(D18:J18) -> 532.3
A19: KPL | B19: Kepala | C19: Bear | D19: =ROUND(O_Demand_Rate!$C$8*D$4*O_Scenario_Multipliers!$D$20*O_Scenario_Multipliers!$B$10*(IF(I_Live_Bird!$B$15="Flat",1,1+MAX(MIN(O_Demand_Rate!$F$8,I_Live_Bird!$B$16),-I_Live_Bird!$B$16))),1) -> 25.1 | E19: =ROUND(O_Demand_Rate!$C$8*E$4*O_Scenario_Multipliers!$D$20*O_Scenario_Multipliers!$B$10*(IF(I_Live_Bird!$B$15="Flat",1,1+MAX(MIN(O_Demand_Rate!$F$8,I_Live_Bird!$B$16),-I_Live_Bird!$B$16))),1) -> 25.6 | F19: =ROUND(O_Demand_Rate!$C$8*F$4*O_Scenario_Multipliers!$D$20*O_Scenario_Multipliers!$B$10*(IF(I_Live_Bird!$B$15="Flat",1,1+MAX(MIN(O_Demand_Rate!$F$8,I_Live_Bird!$B$16),-I_Live_Bird!$B$16))),1) -> 27 | G19: =ROUND(O_Demand_Rate!$C$8*G$4*O_Scenario_Multipliers!$D$20*O_Scenario_Multipliers!$B$10*(IF(I_Live_Bird!$B$15="Flat",1,1+MAX(MIN(O_Demand_Rate!$F$8,I_Live_Bird!$B$16),-I_Live_Bird!$B$16))),1) -> 29.6 | H19: =ROUND(O_Demand_Rate!$C$8*H$4*O_Scenario_Multipliers!$D$20*O_Scenario_Multipliers!$B$10*(IF(I_Live_Bird!$B$15="Flat",1,1+MAX(MIN(O_Demand_Rate!$F$8,I_Live_Bird!$B$16),-I_Live_Bird!$B$16))),1) -> 32.3 | I19: =ROUND(O_Demand_Rate!$C$8*I$4*O_Scenario_Multipliers!$D$20*O_Scenario_Multipliers!$B$10*(IF(I_Live_Bird!$B$15="Flat",1,1+MAX(MIN(O_Demand_Rate!$F$8,I_Live_Bird!$B$16),-I_Live_Bird!$B$16))),1) -> 31 | J19: =ROUND(O_Demand_Rate!$C$8*J$4*O_Scenario_Multipliers!$D$20*O_Scenario_Multipliers!$B$10*(IF(I_Live_Bird!$B$15="Flat",1,1+MAX(MIN(O_Demand_Rate!$F$8,I_Live_Bird!$B$16),-I_Live_Bird!$B$16))),1) -> 25.6 | K19: =SUM(D19:J19) -> 196.2
A20: KPL | B20: Kepala | C20: Base | D20: =ROUND(O_Demand_Rate!$C$8*D$4*O_Scenario_Multipliers!$E$20*O_Scenario_Multipliers!$B$11*(IF(I_Live_Bird!$B$15="Flat",1,1+MAX(MIN(O_Demand_Rate!$F$8,I_Live_Bird!$B$16),-I_Live_Bird!$B$16))),1) -> 29.5 | E20: =ROUND(O_Demand_Rate!$C$8*E$4*O_Scenario_Multipliers!$E$20*O_Scenario_Multipliers!$B$11*(IF(I_Live_Bird!$B$15="Flat",1,1+MAX(MIN(O_Demand_Rate!$F$8,I_Live_Bird!$B$16),-I_Live_Bird!$B$16))),1) -> 30.1 | F20: =ROUND(O_Demand_Rate!$C$8*F$4*O_Scenario_Multipliers!$E$20*O_Scenario_Multipliers!$B$11*(IF(I_Live_Bird!$B$15="Flat",1,1+MAX(MIN(O_Demand_Rate!$F$8,I_Live_Bird!$B$16),-I_Live_Bird!$B$16))),1) -> 31.7 | G20: =ROUND(O_Demand_Rate!$C$8*G$4*O_Scenario_Multipliers!$E$20*O_Scenario_Multipliers!$B$11*(IF(I_Live_Bird!$B$15="Flat",1,1+MAX(MIN(O_Demand_Rate!$F$8,I_Live_Bird!$B$16),-I_Live_Bird!$B$16))),1) -> 34.9 | H20: =ROUND(O_Demand_Rate!$C$8*H$4*O_Scenario_Multipliers!$E$20*O_Scenario_Multipliers!$B$11*(IF(I_Live_Bird!$B$15="Flat",1,1+MAX(MIN(O_Demand_Rate!$F$8,I_Live_Bird!$B$16),-I_Live_Bird!$B$16))),1) -> 38.1 | I20: =ROUND(O_Demand_Rate!$C$8*I$4*O_Scenario_Multipliers!$E$20*O_Scenario_Multipliers!$B$11*(IF(I_Live_Bird!$B$15="Flat",1,1+MAX(MIN(O_Demand_Rate!$F$8,I_Live_Bird!$B$16),-I_Live_Bird!$B$16))),1) -> 36.5 | J20: =ROUND(O_Demand_Rate!$C$8*J$4*O_Scenario_Multipliers!$E$20*O_Scenario_Multipliers!$B$11*(IF(I_Live_Bird!$B$15="Flat",1,1+MAX(MIN(O_Demand_Rate!$F$8,I_Live_Bird!$B$16),-I_Live_Bird!$B$16))),1) -> 30.1 | K20: =SUM(D20:J20) -> 230.9
A21: KPL | B21: Kepala | C21: Bull | D21: =ROUND(O_Demand_Rate!$C$8*D$4*O_Scenario_Multipliers!$F$20*O_Scenario_Multipliers!$B$12*(IF(I_Live_Bird!$B$15="Flat",1,1+MAX(MIN(O_Demand_Rate!$F$8,I_Live_Bird!$B$16),-I_Live_Bird!$B$16))),1) -> 33.9 | E21: =ROUND(O_Demand_Rate!$C$8*E$4*O_Scenario_Multipliers!$F$20*O_Scenario_Multipliers!$B$12*(IF(I_Live_Bird!$B$15="Flat",1,1+MAX(MIN(O_Demand_Rate!$F$8,I_Live_Bird!$B$16),-I_Live_Bird!$B$16))),1) -> 34.6 | F21: =ROUND(O_Demand_Rate!$C$8*F$4*O_Scenario_Multipliers!$F$20*O_Scenario_Multipliers!$B$12*(IF(I_Live_Bird!$B$15="Flat",1,1+MAX(MIN(O_Demand_Rate!$F$8,I_Live_Bird!$B$16),-I_Live_Bird!$B$16))),1) -> 36.5 | G21: =ROUND(O_Demand_Rate!$C$8*G$4*O_Scenario_Multipliers!$F$20*O_Scenario_Multipliers!$B$12*(IF(I_Live_Bird!$B$15="Flat",1,1+MAX(MIN(O_Demand_Rate!$F$8,I_Live_Bird!$B$16),-I_Live_Bird!$B$16))),1) -> 40.1 | H21: =ROUND(O_Demand_Rate!$C$8*H$4*O_Scenario_Multipliers!$F$20*O_Scenario_Multipliers!$B$12*(IF(I_Live_Bird!$B$15="Flat",1,1+MAX(MIN(O_Demand_Rate!$F$8,I_Live_Bird!$B$16),-I_Live_Bird!$B$16))),1) -> 43.8 | I21: =ROUND(O_Demand_Rate!$C$8*I$4*O_Scenario_Multipliers!$F$20*O_Scenario_Multipliers!$B$12*(IF(I_Live_Bird!$B$15="Flat",1,1+MAX(MIN(O_Demand_Rate!$F$8,I_Live_Bird!$B$16),-I_Live_Bird!$B$16))),1) -> 41.9 | J21: =ROUND(O_Demand_Rate!$C$8*J$4*O_Scenario_Multipliers!$F$20*O_Scenario_Multipliers!$B$12*(IF(I_Live_Bird!$B$15="Flat",1,1+MAX(MIN(O_Demand_Rate!$F$8,I_Live_Bird!$B$16),-I_Live_Bird!$B$16))),1) -> 34.6 | K21: =SUM(D21:J21) -> 265.4
A22: KLT | B22: Kulit | C22: Bear | D22: =ROUND(O_Demand_Rate!$C$9*D$4*O_Scenario_Multipliers!$D$21*O_Scenario_Multipliers!$B$10*(IF(I_Live_Bird!$B$15="Flat",1,1+MAX(MIN(O_Demand_Rate!$F$9,I_Live_Bird!$B$16),-I_Live_Bird!$B$16))),1) -> 57.6 | E22: =ROUND(O_Demand_Rate!$C$9*E$4*O_Scenario_Multipliers!$D$21*O_Scenario_Multipliers!$B$10*(IF(I_Live_Bird!$B$15="Flat",1,1+MAX(MIN(O_Demand_Rate!$F$9,I_Live_Bird!$B$16),-I_Live_Bird!$B$16))),1) -> 58.8 | F22: =ROUND(O_Demand_Rate!$C$9*F$4*O_Scenario_Multipliers!$D$21*O_Scenario_Multipliers!$B$10*(IF(I_Live_Bird!$B$15="Flat",1,1+MAX(MIN(O_Demand_Rate!$F$9,I_Live_Bird!$B$16),-I_Live_Bird!$B$16))),1) -> 61.9 | G22: =ROUND(O_Demand_Rate!$C$9*G$4*O_Scenario_Multipliers!$D$21*O_Scenario_Multipliers!$B$10*(IF(I_Live_Bird!$B$15="Flat",1,1+MAX(MIN(O_Demand_Rate!$F$9,I_Live_Bird!$B$16),-I_Live_Bird!$B$16))),1) -> 68.1 | H22: =ROUND(O_Demand_Rate!$C$9*H$4*O_Scenario_Multipliers!$D$21*O_Scenario_Multipliers!$B$10*(IF(I_Live_Bird!$B$15="Flat",1,1+MAX(MIN(O_Demand_Rate!$F$9,I_Live_Bird!$B$16),-I_Live_Bird!$B$16))),1) -> 74.3 | I22: =ROUND(O_Demand_Rate!$C$9*I$4*O_Scenario_Multipliers!$D$21*O_Scenario_Multipliers!$B$10*(IF(I_Live_Bird!$B$15="Flat",1,1+MAX(MIN(O_Demand_Rate!$F$9,I_Live_Bird!$B$16),-I_Live_Bird!$B$16))),1) -> 71.2 | J22: =ROUND(O_Demand_Rate!$C$9*J$4*O_Scenario_Multipliers!$D$21*O_Scenario_Multipliers!$B$10*(IF(I_Live_Bird!$B$15="Flat",1,1+MAX(MIN(O_Demand_Rate!$F$9,I_Live_Bird!$B$16),-I_Live_Bird!$B$16))),1) -> 58.8 | K22: =SUM(D22:J22) -> 450.7
A23: KLT | B23: Kulit | C23: Base | D23: =ROUND(O_Demand_Rate!$C$9*D$4*O_Scenario_Multipliers!$E$21*O_Scenario_Multipliers!$B$11*(IF(I_Live_Bird!$B$15="Flat",1,1+MAX(MIN(O_Demand_Rate!$F$9,I_Live_Bird!$B$16),-I_Live_Bird!$B$16))),1) -> 67.7 | E23: =ROUND(O_Demand_Rate!$C$9*E$4*O_Scenario_Multipliers!$E$21*O_Scenario_Multipliers!$B$11*(IF(I_Live_Bird!$B$15="Flat",1,1+MAX(MIN(O_Demand_Rate!$F$9,I_Live_Bird!$B$16),-I_Live_Bird!$B$16))),1) -> 69.2 | F23: =ROUND(O_Demand_Rate!$C$9*F$4*O_Scenario_Multipliers!$E$21*O_Scenario_Multipliers!$B$11*(IF(I_Live_Bird!$B$15="Flat",1,1+MAX(MIN(O_Demand_Rate!$F$9,I_Live_Bird!$B$16),-I_Live_Bird!$B$16))),1) -> 72.8 | G23: =ROUND(O_Demand_Rate!$C$9*G$4*O_Scenario_Multipliers!$E$21*O_Scenario_Multipliers!$B$11*(IF(I_Live_Bird!$B$15="Flat",1,1+MAX(MIN(O_Demand_Rate!$F$9,I_Live_Bird!$B$16),-I_Live_Bird!$B$16))),1) -> 80.1 | H23: =ROUND(O_Demand_Rate!$C$9*H$4*O_Scenario_Multipliers!$E$21*O_Scenario_Multipliers!$B$11*(IF(I_Live_Bird!$B$15="Flat",1,1+MAX(MIN(O_Demand_Rate!$F$9,I_Live_Bird!$B$16),-I_Live_Bird!$B$16))),1) -> 87.4 | I23: =ROUND(O_Demand_Rate!$C$9*I$4*O_Scenario_Multipliers!$E$21*O_Scenario_Multipliers!$B$11*(IF(I_Live_Bird!$B$15="Flat",1,1+MAX(MIN(O_Demand_Rate!$F$9,I_Live_Bird!$B$16),-I_Live_Bird!$B$16))),1) -> 83.8 | J23: =ROUND(O_Demand_Rate!$C$9*J$4*O_Scenario_Multipliers!$E$21*O_Scenario_Multipliers!$B$11*(IF(I_Live_Bird!$B$15="Flat",1,1+MAX(MIN(O_Demand_Rate!$F$9,I_Live_Bird!$B$16),-I_Live_Bird!$B$16))),1) -> 69.2 | K23: =SUM(D23:J23) -> 530.2
A24: KLT | B24: Kulit | C24: Bull | D24: =ROUND(O_Demand_Rate!$C$9*D$4*O_Scenario_Multipliers!$F$21*O_Scenario_Multipliers!$B$12*(IF(I_Live_Bird!$B$15="Flat",1,1+MAX(MIN(O_Demand_Rate!$F$9,I_Live_Bird!$B$16),-I_Live_Bird!$B$16))),1) -> 77.9 | E24: =ROUND(O_Demand_Rate!$C$9*E$4*O_Scenario_Multipliers!$F$21*O_Scenario_Multipliers!$B$12*(IF(I_Live_Bird!$B$15="Flat",1,1+MAX(MIN(O_Demand_Rate!$F$9,I_Live_Bird!$B$16),-I_Live_Bird!$B$16))),1) -> 79.6 | F24: =ROUND(O_Demand_Rate!$C$9*F$4*O_Scenario_Multipliers!$F$21*O_Scenario_Multipliers!$B$12*(IF(I_Live_Bird!$B$15="Flat",1,1+MAX(MIN(O_Demand_Rate!$F$9,I_Live_Bird!$B$16),-I_Live_Bird!$B$16))),1) -> 83.8 | G24: =ROUND(O_Demand_Rate!$C$9*G$4*O_Scenario_Multipliers!$F$21*O_Scenario_Multipliers!$B$12*(IF(I_Live_Bird!$B$15="Flat",1,1+MAX(MIN(O_Demand_Rate!$F$9,I_Live_Bird!$B$16),-I_Live_Bird!$B$16))),1) -> 92.1 | H24: =ROUND(O_Demand_Rate!$C$9*H$4*O_Scenario_Multipliers!$F$21*O_Scenario_Multipliers!$B$12*(IF(I_Live_Bird!$B$15="Flat",1,1+MAX(MIN(O_Demand_Rate!$F$9,I_Live_Bird!$B$16),-I_Live_Bird!$B$16))),1) -> 100.5 | I24: =ROUND(O_Demand_Rate!$C$9*I$4*O_Scenario_Multipliers!$F$21*O_Scenario_Multipliers!$B$12*(IF(I_Live_Bird!$B$15="Flat",1,1+MAX(MIN(O_Demand_Rate!$F$9,I_Live_Bird!$B$16),-I_Live_Bird!$B$16))),1) -> 96.3 | J24: =ROUND(O_Demand_Rate!$C$9*J$4*O_Scenario_Multipliers!$F$21*O_Scenario_Multipliers!$B$12*(IF(I_Live_Bird!$B$15="Flat",1,1+MAX(MIN(O_Demand_Rate!$F$9,I_Live_Bird!$B$16),-I_Live_Bird!$B$16))),1) -> 79.6 | K24: =SUM(D24:J24) -> 609.8
A25: JRN | B25: Jeroan (ati ampela) | C25: Bear | D25: =ROUND(O_Demand_Rate!$C$10*D$4*O_Scenario_Multipliers!$D$22*O_Scenario_Multipliers!$B$10*(IF(I_Live_Bird!$B$15="Flat",1,1+MAX(MIN(O_Demand_Rate!$F$10,I_Live_Bird!$B$16),-I_Live_Bird!$B$16))),1) -> 46.3 | E25: =ROUND(O_Demand_Rate!$C$10*E$4*O_Scenario_Multipliers!$D$22*O_Scenario_Multipliers!$B$10*(IF(I_Live_Bird!$B$15="Flat",1,1+MAX(MIN(O_Demand_Rate!$F$10,I_Live_Bird!$B$16),-I_Live_Bird!$B$16))),1) -> 47.3 | F25: =ROUND(O_Demand_Rate!$C$10*F$4*O_Scenario_Multipliers!$D$22*O_Scenario_Multipliers!$B$10*(IF(I_Live_Bird!$B$15="Flat",1,1+MAX(MIN(O_Demand_Rate!$F$10,I_Live_Bird!$B$16),-I_Live_Bird!$B$16))),1) -> 49.7 | G25: =ROUND(O_Demand_Rate!$C$10*G$4*O_Scenario_Multipliers!$D$22*O_Scenario_Multipliers!$B$10*(IF(I_Live_Bird!$B$15="Flat",1,1+MAX(MIN(O_Demand_Rate!$F$10,I_Live_Bird!$B$16),-I_Live_Bird!$B$16))),1) -> 54.7 | H25: =ROUND(O_Demand_Rate!$C$10*H$4*O_Scenario_Multipliers!$D$22*O_Scenario_Multipliers!$B$10*(IF(I_Live_Bird!$B$15="Flat",1,1+MAX(MIN(O_Demand_Rate!$F$10,I_Live_Bird!$B$16),-I_Live_Bird!$B$16))),1) -> 59.7 | I25: =ROUND(O_Demand_Rate!$C$10*I$4*O_Scenario_Multipliers!$D$22*O_Scenario_Multipliers!$B$10*(IF(I_Live_Bird!$B$15="Flat",1,1+MAX(MIN(O_Demand_Rate!$F$10,I_Live_Bird!$B$16),-I_Live_Bird!$B$16))),1) -> 57.2 | J25: =ROUND(O_Demand_Rate!$C$10*J$4*O_Scenario_Multipliers!$D$22*O_Scenario_Multipliers!$B$10*(IF(I_Live_Bird!$B$15="Flat",1,1+MAX(MIN(O_Demand_Rate!$F$10,I_Live_Bird!$B$16),-I_Live_Bird!$B$16))),1) -> 47.3 | K25: =SUM(D25:J25) -> 362.2
A26: JRN | B26: Jeroan (ati ampela) | C26: Base | D26: =ROUND(O_Demand_Rate!$C$10*D$4*O_Scenario_Multipliers!$E$22*O_Scenario_Multipliers!$B$11*(IF(I_Live_Bird!$B$15="Flat",1,1+MAX(MIN(O_Demand_Rate!$F$10,I_Live_Bird!$B$16),-I_Live_Bird!$B$16))),1) -> 54.4 | E26: =ROUND(O_Demand_Rate!$C$10*E$4*O_Scenario_Multipliers!$E$22*O_Scenario_Multipliers!$B$11*(IF(I_Live_Bird!$B$15="Flat",1,1+MAX(MIN(O_Demand_Rate!$F$10,I_Live_Bird!$B$16),-I_Live_Bird!$B$16))),1) -> 55.6 | F26: =ROUND(O_Demand_Rate!$C$10*F$4*O_Scenario_Multipliers!$E$22*O_Scenario_Multipliers!$B$11*(IF(I_Live_Bird!$B$15="Flat",1,1+MAX(MIN(O_Demand_Rate!$F$10,I_Live_Bird!$B$16),-I_Live_Bird!$B$16))),1) -> 58.5 | G26: =ROUND(O_Demand_Rate!$C$10*G$4*O_Scenario_Multipliers!$E$22*O_Scenario_Multipliers!$B$11*(IF(I_Live_Bird!$B$15="Flat",1,1+MAX(MIN(O_Demand_Rate!$F$10,I_Live_Bird!$B$16),-I_Live_Bird!$B$16))),1) -> 64.4 | H26: =ROUND(O_Demand_Rate!$C$10*H$4*O_Scenario_Multipliers!$E$22*O_Scenario_Multipliers!$B$11*(IF(I_Live_Bird!$B$15="Flat",1,1+MAX(MIN(O_Demand_Rate!$F$10,I_Live_Bird!$B$16),-I_Live_Bird!$B$16))),1) -> 70.2 | I26: =ROUND(O_Demand_Rate!$C$10*I$4*O_Scenario_Multipliers!$E$22*O_Scenario_Multipliers!$B$11*(IF(I_Live_Bird!$B$15="Flat",1,1+MAX(MIN(O_Demand_Rate!$F$10,I_Live_Bird!$B$16),-I_Live_Bird!$B$16))),1) -> 67.3 | J26: =ROUND(O_Demand_Rate!$C$10*J$4*O_Scenario_Multipliers!$E$22*O_Scenario_Multipliers!$B$11*(IF(I_Live_Bird!$B$15="Flat",1,1+MAX(MIN(O_Demand_Rate!$F$10,I_Live_Bird!$B$16),-I_Live_Bird!$B$16))),1) -> 55.6 | K26: =SUM(D26:J26) -> 426
A27: JRN | B27: Jeroan (ati ampela) | C27: Bull | D27: =ROUND(O_Demand_Rate!$C$10*D$4*O_Scenario_Multipliers!$F$22*O_Scenario_Multipliers!$B$12*(IF(I_Live_Bird!$B$15="Flat",1,1+MAX(MIN(O_Demand_Rate!$F$10,I_Live_Bird!$B$16),-I_Live_Bird!$B$16))),1) -> 62.6 | E27: =ROUND(O_Demand_Rate!$C$10*E$4*O_Scenario_Multipliers!$F$22*O_Scenario_Multipliers!$B$12*(IF(I_Live_Bird!$B$15="Flat",1,1+MAX(MIN(O_Demand_Rate!$F$10,I_Live_Bird!$B$16),-I_Live_Bird!$B$16))),1) -> 63.9 | F27: =ROUND(O_Demand_Rate!$C$10*F$4*O_Scenario_Multipliers!$F$22*O_Scenario_Multipliers!$B$12*(IF(I_Live_Bird!$B$15="Flat",1,1+MAX(MIN(O_Demand_Rate!$F$10,I_Live_Bird!$B$16),-I_Live_Bird!$B$16))),1) -> 67.3 | G27: =ROUND(O_Demand_Rate!$C$10*G$4*O_Scenario_Multipliers!$F$22*O_Scenario_Multipliers!$B$12*(IF(I_Live_Bird!$B$15="Flat",1,1+MAX(MIN(O_Demand_Rate!$F$10,I_Live_Bird!$B$16),-I_Live_Bird!$B$16))),1) -> 74 | H27: =ROUND(O_Demand_Rate!$C$10*H$4*O_Scenario_Multipliers!$F$22*O_Scenario_Multipliers!$B$12*(IF(I_Live_Bird!$B$15="Flat",1,1+MAX(MIN(O_Demand_Rate!$F$10,I_Live_Bird!$B$16),-I_Live_Bird!$B$16))),1) -> 80.8 | I27: =ROUND(O_Demand_Rate!$C$10*I$4*O_Scenario_Multipliers!$F$22*O_Scenario_Multipliers!$B$12*(IF(I_Live_Bird!$B$15="Flat",1,1+MAX(MIN(O_Demand_Rate!$F$10,I_Live_Bird!$B$16),-I_Live_Bird!$B$16))),1) -> 77.4 | J27: =ROUND(O_Demand_Rate!$C$10*J$4*O_Scenario_Multipliers!$F$22*O_Scenario_Multipliers!$B$12*(IF(I_Live_Bird!$B$15="Flat",1,1+MAX(MIN(O_Demand_Rate!$F$10,I_Live_Bird!$B$16),-I_Live_Bird!$B$16))),1) -> 63.9 | K27: =SUM(D27:J27) -> 489.9
A28: TLG | B28: Tulang / carcass frame | C28: Bear | D28: =ROUND(O_Demand_Rate!$C$11*D$4*O_Scenario_Multipliers!$D$23*O_Scenario_Multipliers!$B$10*(IF(I_Live_Bird!$B$15="Flat",1,1+MAX(MIN(O_Demand_Rate!$F$11,I_Live_Bird!$B$16),-I_Live_Bird!$B$16))),1) -> 188.8 | E28: =ROUND(O_Demand_Rate!$C$11*E$4*O_Scenario_Multipliers!$D$23*O_Scenario_Multipliers!$B$10*(IF(I_Live_Bird!$B$15="Flat",1,1+MAX(MIN(O_Demand_Rate!$F$11,I_Live_Bird!$B$16),-I_Live_Bird!$B$16))),1) -> 192.9 | F28: =ROUND(O_Demand_Rate!$C$11*F$4*O_Scenario_Multipliers!$D$23*O_Scenario_Multipliers!$B$10*(IF(I_Live_Bird!$B$15="Flat",1,1+MAX(MIN(O_Demand_Rate!$F$11,I_Live_Bird!$B$16),-I_Live_Bird!$B$16))),1) -> 203 | G28: =ROUND(O_Demand_Rate!$C$11*G$4*O_Scenario_Multipliers!$D$23*O_Scenario_Multipliers!$B$10*(IF(I_Live_Bird!$B$15="Flat",1,1+MAX(MIN(O_Demand_Rate!$F$11,I_Live_Bird!$B$16),-I_Live_Bird!$B$16))),1) -> 223.3 | H28: =ROUND(O_Demand_Rate!$C$11*H$4*O_Scenario_Multipliers!$D$23*O_Scenario_Multipliers!$B$10*(IF(I_Live_Bird!$B$15="Flat",1,1+MAX(MIN(O_Demand_Rate!$F$11,I_Live_Bird!$B$16),-I_Live_Bird!$B$16))),1) -> 243.7 | I28: =ROUND(O_Demand_Rate!$C$11*I$4*O_Scenario_Multipliers!$D$23*O_Scenario_Multipliers!$B$10*(IF(I_Live_Bird!$B$15="Flat",1,1+MAX(MIN(O_Demand_Rate!$F$11,I_Live_Bird!$B$16),-I_Live_Bird!$B$16))),1) -> 233.5 | J28: =ROUND(O_Demand_Rate!$C$11*J$4*O_Scenario_Multipliers!$D$23*O_Scenario_Multipliers!$B$10*(IF(I_Live_Bird!$B$15="Flat",1,1+MAX(MIN(O_Demand_Rate!$F$11,I_Live_Bird!$B$16),-I_Live_Bird!$B$16))),1) -> 192.9 | K28: =SUM(D28:J28) -> 1478.1
A29: TLG | B29: Tulang / carcass frame | C29: Base | D29: =ROUND(O_Demand_Rate!$C$11*D$4*O_Scenario_Multipliers!$E$23*O_Scenario_Multipliers!$B$11*(IF(I_Live_Bird!$B$15="Flat",1,1+MAX(MIN(O_Demand_Rate!$F$11,I_Live_Bird!$B$16),-I_Live_Bird!$B$16))),1) -> 194.7 | E29: =ROUND(O_Demand_Rate!$C$11*E$4*O_Scenario_Multipliers!$E$23*O_Scenario_Multipliers!$B$11*(IF(I_Live_Bird!$B$15="Flat",1,1+MAX(MIN(O_Demand_Rate!$F$11,I_Live_Bird!$B$16),-I_Live_Bird!$B$16))),1) -> 198.9 | F29: =ROUND(O_Demand_Rate!$C$11*F$4*O_Scenario_Multipliers!$E$23*O_Scenario_Multipliers!$B$11*(IF(I_Live_Bird!$B$15="Flat",1,1+MAX(MIN(O_Demand_Rate!$F$11,I_Live_Bird!$B$16),-I_Live_Bird!$B$16))),1) -> 209.3 | G29: =ROUND(O_Demand_Rate!$C$11*G$4*O_Scenario_Multipliers!$E$23*O_Scenario_Multipliers!$B$11*(IF(I_Live_Bird!$B$15="Flat",1,1+MAX(MIN(O_Demand_Rate!$F$11,I_Live_Bird!$B$16),-I_Live_Bird!$B$16))),1) -> 230.3 | H29: =ROUND(O_Demand_Rate!$C$11*H$4*O_Scenario_Multipliers!$E$23*O_Scenario_Multipliers!$B$11*(IF(I_Live_Bird!$B$15="Flat",1,1+MAX(MIN(O_Demand_Rate!$F$11,I_Live_Bird!$B$16),-I_Live_Bird!$B$16))),1) -> 251.2 | I29: =ROUND(O_Demand_Rate!$C$11*I$4*O_Scenario_Multipliers!$E$23*O_Scenario_Multipliers!$B$11*(IF(I_Live_Bird!$B$15="Flat",1,1+MAX(MIN(O_Demand_Rate!$F$11,I_Live_Bird!$B$16),-I_Live_Bird!$B$16))),1) -> 240.7 | J29: =ROUND(O_Demand_Rate!$C$11*J$4*O_Scenario_Multipliers!$E$23*O_Scenario_Multipliers!$B$11*(IF(I_Live_Bird!$B$15="Flat",1,1+MAX(MIN(O_Demand_Rate!$F$11,I_Live_Bird!$B$16),-I_Live_Bird!$B$16))),1) -> 198.9 | K29: =SUM(D29:J29) -> 1524
A30: TLG | B30: Tulang / carcass frame | C30: Bull | D30: =ROUND(O_Demand_Rate!$C$11*D$4*O_Scenario_Multipliers!$F$23*O_Scenario_Multipliers!$B$12*(IF(I_Live_Bird!$B$15="Flat",1,1+MAX(MIN(O_Demand_Rate!$F$11,I_Live_Bird!$B$16),-I_Live_Bird!$B$16))),1) -> 200.5 | E30: =ROUND(O_Demand_Rate!$C$11*E$4*O_Scenario_Multipliers!$F$23*O_Scenario_Multipliers!$B$12*(IF(I_Live_Bird!$B$15="Flat",1,1+MAX(MIN(O_Demand_Rate!$F$11,I_Live_Bird!$B$16),-I_Live_Bird!$B$16))),1) -> 204.8 | F30: =ROUND(O_Demand_Rate!$C$11*F$4*O_Scenario_Multipliers!$F$23*O_Scenario_Multipliers!$B$12*(IF(I_Live_Bird!$B$15="Flat",1,1+MAX(MIN(O_Demand_Rate!$F$11,I_Live_Bird!$B$16),-I_Live_Bird!$B$16))),1) -> 215.6 | G30: =ROUND(O_Demand_Rate!$C$11*G$4*O_Scenario_Multipliers!$F$23*O_Scenario_Multipliers!$B$12*(IF(I_Live_Bird!$B$15="Flat",1,1+MAX(MIN(O_Demand_Rate!$F$11,I_Live_Bird!$B$16),-I_Live_Bird!$B$16))),1) -> 237.2 | H30: =ROUND(O_Demand_Rate!$C$11*H$4*O_Scenario_Multipliers!$F$23*O_Scenario_Multipliers!$B$12*(IF(I_Live_Bird!$B$15="Flat",1,1+MAX(MIN(O_Demand_Rate!$F$11,I_Live_Bird!$B$16),-I_Live_Bird!$B$16))),1) -> 258.7 | I30: =ROUND(O_Demand_Rate!$C$11*I$4*O_Scenario_Multipliers!$F$23*O_Scenario_Multipliers!$B$12*(IF(I_Live_Bird!$B$15="Flat",1,1+MAX(MIN(O_Demand_Rate!$F$11,I_Live_Bird!$B$16),-I_Live_Bird!$B$16))),1) -> 247.9 | J30: =ROUND(O_Demand_Rate!$C$11*J$4*O_Scenario_Multipliers!$F$23*O_Scenario_Multipliers!$B$12*(IF(I_Live_Bird!$B$15="Flat",1,1+MAX(MIN(O_Demand_Rate!$F$11,I_Live_Bird!$B$16),-I_Live_Bird!$B$16))),1) -> 204.8 | K30: =SUM(D30:J30) -> 1569.5

Sheet O_Optimizer
A1: O_Optimizer — LAYER 2: Keputusan Beli Ayam (Joint Production)
A2: Window 7 hari. Implied ekor per potongan = demand / (kg per ekor). Binding cut = ekor terbanyak.
A4: BAGIAN A — DEMAND 7-HARI & IMPLIED EKOR
A5: SKU Code | B5: SKU Name | C5: kg/Ekor | D5: Demand Bear | E5: Demand Base | F5: Demand Bull | G5: Ekor Bear | H5: Ekor Base | I5: Ekor Bull
A6: BLD | B6: Boneless Dada (fillet) | C6: =I_Yield!$E$6 -> 0.36 | D6: =O_Demand_Forecast!$K$7 -> 2360.4 | E6: =O_Demand_Forecast!$K$8 -> 2538.2 | F6: =O_Demand_Forecast!$K$9 -> 2715.9 | G6: =IFERROR(D6/C6,0) -> 6556.6667 | H6: =IFERROR(E6/C6,0) -> 7050.5556 | I6: =IFERROR(F6/C6,0) -> 7544.1667
A7: BLP | B7: Boneless Paha (fillet) | C7: =I_Yield!$E$7 -> 0.26 | D7: =O_Demand_Forecast!$K$10 -> 1619.2 | E7: =O_Demand_Forecast!$K$11 -> 1741.1 | F7: =O_Demand_Forecast!$K$12 -> 1863 | G7: =IFERROR(D7/C7,0) -> 6227.6923 | H7: =IFERROR(E7/C7,0) -> 6696.5385 | I7: =IFERROR(F7/C7,0) -> 7165.3846
A8: SYP | B8: Sayap | C8: =I_Yield!$E$8 -> 0.18 | D8: =O_Demand_Forecast!$K$13 -> 1066.7 | E8: =O_Demand_Forecast!$K$14 -> 1147.1 | F8: =O_Demand_Forecast!$K$15 -> 1227.5 | G8: =IFERROR(D8/C8,0) -> 5926.1111 | H8: =IFERROR(E8/C8,0) -> 6372.7778 | I8: =IFERROR(F8/C8,0) -> 6819.4444
A9: CKR | B9: Ceker | C9: =I_Yield!$E$9 -> 0.08 | D9: =O_Demand_Forecast!$K$16 -> 393.5 | E9: =O_Demand_Forecast!$K$17 -> 462.8 | F9: =O_Demand_Forecast!$K$18 -> 532.3 | G9: =IFERROR(D9/C9,0) -> 4918.75 | H9: =IFERROR(E9/C9,0) -> 5785 | I9: =IFERROR(F9/C9,0) -> 6653.75
A10: KPL | B10: Kepala | C10: =I_Yield!$E$10 -> 0.06 | D10: =O_Demand_Forecast!$K$19 -> 196.2 | E10: =O_Demand_Forecast!$K$20 -> 230.9 | F10: =O_Demand_Forecast!$K$21 -> 265.4 | G10: =IFERROR(D10/C10,0) -> 3270 | H10: =IFERROR(E10/C10,0) -> 3848.3333 | I10: =IFERROR(F10/C10,0) -> 4423.3333
A11: KLT | B11: Kulit | C11: =I_Yield!$E$11 -> 0.12 | D11: =O_Demand_Forecast!$K$22 -> 450.7 | E11: =O_Demand_Forecast!$K$23 -> 530.2 | F11: =O_Demand_Forecast!$K$24 -> 609.8 | G11: =IFERROR(D11/C11,0) -> 3755.8333 | H11: =IFERROR(E11/C11,0) -> 4418.3333 | I11: =IFERROR(F11/C11,0) -> 5081.6667
A12: JRN | B12: Jeroan (ati ampela) | C12: =I_Yield!$E$12 -> 0.1 | D12: =O_Demand_Forecast!$K$25 -> 362.2 | E12: =O_Demand_Forecast!$K$26 -> 426 | F12: =O_Demand_Forecast!$K$27 -> 489.9 | G12: =IFERROR(D12/C12,0) -> 3622 | H12: =IFERROR(E12/C12,0) -> 4260 | I12: =IFERROR(F12/C12,0) -> 4899
A13: TLG | B13: Tulang / carcass frame | C13: =I_Yield!$E$13 -> 0.56 | D13: =O_Demand_Forecast!$K$28 -> 1478.1 | E13: =O_Demand_Forecast!$K$29 -> 1524 | F13: =O_Demand_Forecast!$K$30 -> 1569.5 | G13: =IFERROR(D13/C13,0) -> 2639.4643 | H13: =IFERROR(E13/C13,0) -> 2721.4286 | I13: =IFERROR(F13/C13,0) -> 2802.6786
A15: BAGIAN B
A16: Binding cut (Base) | B16: =INDEX(B6:B13,MATCH(MAX(H6:H13),H6:H13,0)) -> Boneless Dada (fillet)
A17: Max implied ekor (Base) — penuhi semua demand | B17: =MAX(H6:H13) -> 7050.5556
A18: Min implied ekor (Base) | B18: =MIN(H6:H13) -> 2721.4286
A19: Kapasitas potong mingguan (ekor) | B19: =I_Live_Bird!$B$11*7 -> 10500
A20: EKOR DIBELI — DECISION (7 hari) | B20: =ROUND(MAX(H6:H13),0) -> 7051 | C20: default = penuhi binding cut; timpa dengan angkamu untuk trade-off surplus vs service
A22: BAGIAN C — EKONOMI @ DECISION N (Base) + kontribusi Bear/Bull
A23: SKU | B23: kg/Ekor | C23: Supply (kg) | D23: Demand Base | E23: Sold | F23: Surplus | G23: Shortfall | H23: Fill % | I23: Beku? | J23: Nilai Surplus (IDR) | K23: Revenue (IDR) | L23: Kontrib Bear | M23: Kontrib Bull
A24: BLD | B24: =I_Yield!$E$6 -> 0.36 | C24: =$B$20*B24 -> 2538.36 | D24: =O_Optimizer!$E$6 -> 2538.2 | E24: =MIN(C24,D24) -> 2538.2 | F24: =MAX(C24-D24,0) -> 0.16 | G24: =MAX(D24-C24,0) -> 0 | H24: =IFERROR(E24/D24,0) -> 1 | I24: =I_Products!$E$4 -> Y | J24: =IF(I24="Y",F24*I_Products!$G$4*I_Products!$H$4-F24*I_Live_Bird!$B$9,F24*I_Live_Bird!$B$10) -> 7840 | K24: =E24*I_Products!$G$4 -> 139601000 | L24: =MIN(C24,O_Optimizer!$D$6)*I_Products!$G$4+IF(I24="Y",MAX(C24-O_Optimizer!$D$6,0)*I_Products!$G$4*I_Products!$H$4-MAX(C24-O_Optimizer!$D$6,0)*I_Live_Bird!$B$9,MAX(C24-O_Optimizer!$D$6,0)*I_Live_Bird!$B$10) -> 138542040 | M24: =MIN(C24,O_Optimizer!$F$6)*I_Products!$G$4+IF(I24="Y",MAX(C24-O_Optimizer!$F$6,0)*I_Products!$G$4*I_Products!$H$4-MAX(C24-O_Optimizer!$F$6,0)*I_Live_Bird!$B$9,MAX(C24-O_Optimizer!$F$6,0)*I_Live_Bird!$B$10) -> 139609800
A25: BLP | B25: =I_Yield!$E$7 -> 0.26 | C25: =$B$20*B25 -> 1833.26 | D25: =O_Optimizer!$E$7 -> 1741.1 | E25: =MIN(C25,D25) -> 1741.1 | F25: =MAX(C25-D25,0) -> 92.16 | G25: =MAX(D25-C25,0) -> 0 | H25: =IFERROR(E25/D25,0) -> 1 | I25: =I_Products!$E$5 -> Y | J25: =IF(I25="Y",F25*I_Products!$G$5*I_Products!$H$5-F25*I_Live_Bird!$B$9,F25*I_Live_Bird!$B$10) -> 3935232 | K25: =E25*I_Products!$G$5 -> 83572800 | L25: =MIN(C25,O_Optimizer!$D$7)*I_Products!$G$5+IF(I25="Y",MAX(C25-O_Optimizer!$D$7,0)*I_Products!$G$5*I_Products!$H$5-MAX(C25-O_Optimizer!$D$7,0)*I_Live_Bird!$B$9,MAX(C25-O_Optimizer!$D$7,0)*I_Live_Bird!$B$10) -> 86861962 | M25: =MIN(C25,O_Optimizer!$F$7)*I_Products!$G$5+IF(I25="Y",MAX(C25-O_Optimizer!$F$7,0)*I_Products!$G$5*I_Products!$H$5-MAX(C25-O_Optimizer!$F$7,0)*I_Live_Bird!$B$9,MAX(C25-O_Optimizer!$F$7,0)*I_Live_Bird!$B$10) -> 87996480
A26: SYP | B26: =I_Yield!$E$8 -> 0.18 | C26: =$B$20*B26 -> 1269.18 | D26: =O_Optimizer!$E$8 -> 1147.1 | E26: =MIN(C26,D26) -> 1147.1 | F26: =MAX(C26-D26,0) -> 122.08 | G26: =MAX(D26-C26,0) -> 0 | H26: =IFERROR(E26/D26,0) -> 1 | I26: =I_Products!$E$6 -> Y | J26: =IF(I26="Y",F26*I_Products!$G$6*I_Products!$H$6-F26*I_Live_Bird!$B$9,F26*I_Live_Bird!$B$10) -> 4206876.8 | K26: =E26*I_Products!$G$6 -> 43589800 | L26: =MIN(C26,O_Optimizer!$D$8)*I_Products!$G$6+IF(I26="Y",MAX(C26-O_Optimizer!$D$8,0)*I_Products!$G$6*I_Products!$H$6-MAX(C26-O_Optimizer!$D$8,0)*I_Live_Bird!$B$9,MAX(C26-O_Optimizer!$D$8,0)*I_Live_Bird!$B$10) -> 47512061 | M26: =MIN(C26,O_Optimizer!$F$8)*I_Products!$G$6+IF(I26="Y",MAX(C26-O_Optimizer!$F$8,0)*I_Products!$G$6*I_Products!$H$6-MAX(C26-O_Optimizer!$F$8,0)*I_Live_Bird!$B$9,MAX(C26-O_Optimizer!$F$8,0)*I_Live_Bird!$B$10) -> 48081293
A27: CKR | B27: =I_Yield!$E$9 -> 0.08 | C27: =$B$20*B27 -> 564.08 | D27: =O_Optimizer!$E$9 -> 462.8 | E27: =MIN(C27,D27) -> 462.8 | F27: =MAX(C27-D27,0) -> 101.28 | G27: =MAX(D27-C27,0) -> 0 | H27: =IFERROR(E27/D27,0) -> 1 | I27: =I_Products!$E$7 -> Y | J27: =IF(I27="Y",F27*I_Products!$G$7*I_Products!$H$7-F27*I_Live_Bird!$B$9,F27*I_Live_Bird!$B$10) -> 2643408 | K27: =E27*I_Products!$G$7 -> 12958400 | L27: =MIN(C27,O_Optimizer!$D$9)*I_Products!$G$7+IF(I27="Y",MAX(C27-O_Optimizer!$D$9,0)*I_Products!$G$7*I_Products!$H$7-MAX(C27-O_Optimizer!$D$9,0)*I_Live_Bird!$B$9,MAX(C27-O_Optimizer!$D$9,0)*I_Live_Bird!$B$10) -> 15470138 | M27: =MIN(C27,O_Optimizer!$F$9)*I_Products!$G$7+IF(I27="Y",MAX(C27-O_Optimizer!$F$9,0)*I_Products!$G$7*I_Products!$H$7-MAX(C27-O_Optimizer!$F$9,0)*I_Live_Bird!$B$9,MAX(C27-O_Optimizer!$F$9,0)*I_Live_Bird!$B$10) -> 15733858
A28: KPL | B28: =I_Yield!$E$10 -> 0.06 | C28: =$B$20*B28 -> 423.06 | D28: =O_Optimizer!$E$10 -> 230.9 | E28: =MIN(C28,D28) -> 230.9 | F28: =MAX(C28-D28,0) -> 192.16 | G28: =MAX(D28-C28,0) -> 0 | H28: =IFERROR(E28/D28,0) -> 1 | I28: =I_Products!$E$8 -> Y | J28: =IF(I28="Y",F28*I_Products!$G$8*I_Products!$H$8-F28*I_Live_Bird!$B$9,F28*I_Live_Bird!$B$10) -> 2094544 | K28: =E28*I_Products!$G$8 -> 2770800 | L28: =MIN(C28,O_Optimizer!$D$10)*I_Products!$G$8+IF(I28="Y",MAX(C28-O_Optimizer!$D$10,0)*I_Products!$G$8*I_Products!$H$8-MAX(C28-O_Optimizer!$D$10,0)*I_Live_Bird!$B$9,MAX(C28-O_Optimizer!$D$10,0)*I_Live_Bird!$B$10) -> 4827174 | M28: =MIN(C28,O_Optimizer!$F$10)*I_Products!$G$8+IF(I28="Y",MAX(C28-O_Optimizer!$F$10,0)*I_Products!$G$8*I_Products!$H$8-MAX(C28-O_Optimizer!$F$10,0)*I_Live_Bird!$B$9,MAX(C28-O_Optimizer!$F$10,0)*I_Live_Bird!$B$10) -> 4903294
A29: KLT | B29: =I_Yield!$E$11 -> 0.12 | C29: =$B$20*B29 -> 846.12 | D29: =O_Optimizer!$E$11 -> 530.2 | E29: =MIN(C29,D29) -> 530.2 | F29: =MAX(C29-D29,0) -> 315.92 | G29: =MAX(D29-C29,0) -> 0 | H29: =IFERROR(E29/D29,0) -> 1 | I29: =I_Products!$E$9 -> Y | J29: =IF(I29="Y",F29*I_Products!$G$9*I_Products!$H$9-F29*I_Live_Bird!$B$9,F29*I_Live_Bird!$B$10) -> 7108200 | K29: =E29*I_Products!$G$9 -> 13255000 | L29: =MIN(C29,O_Optimizer!$D$11)*I_Products!$G$9+IF(I29="Y",MAX(C29-O_Optimizer!$D$11,0)*I_Products!$G$9*I_Products!$H$9-MAX(C29-O_Optimizer!$D$11,0)*I_Live_Bird!$B$9,MAX(C29-O_Optimizer!$D$11,0)*I_Live_Bird!$B$10) -> 20164450 | M29: =MIN(C29,O_Optimizer!$F$11)*I_Products!$G$9+IF(I29="Y",MAX(C29-O_Optimizer!$F$11,0)*I_Products!$G$9*I_Products!$H$9-MAX(C29-O_Optimizer!$F$11,0)*I_Live_Bird!$B$9,MAX(C29-O_Optimizer!$F$11,0)*I_Live_Bird!$B$10) -> 20562200
A30: JRN | B30: =I_Yield!$E$12 -> 0.1 | C30: =$B$20*B30 -> 705.1 | D30: =O_Optimizer!$E$12 -> 426 | E30: =MIN(C30,D30) -> 426 | F30: =MAX(C30-D30,0) -> 279.1 | G30: =MAX(D30-C30,0) -> 0 | H30: =IFERROR(E30/D30,0) -> 1 | I30: =I_Products!$E$10 -> Y | J30: =IF(I30="Y",F30*I_Products!$G$10*I_Products!$H$10-F30*I_Live_Bird!$B$9,F30*I_Live_Bird!$B$10) -> 5386630 | K30: =E30*I_Products!$G$10 -> 9372000 | L30: =MIN(C30,O_Optimizer!$D$12)*I_Products!$G$10+IF(I30="Y",MAX(C30-O_Optimizer!$D$12,0)*I_Products!$G$10*I_Products!$H$10-MAX(C30-O_Optimizer!$D$12,0)*I_Live_Bird!$B$9,MAX(C30-O_Optimizer!$D$12,0)*I_Live_Bird!$B$10) -> 14586370 | M30: =MIN(C30,O_Optimizer!$F$12)*I_Products!$G$10+IF(I30="Y",MAX(C30-O_Optimizer!$F$12,0)*I_Products!$G$10*I_Products!$H$10-MAX(C30-O_Optimizer!$F$12,0)*I_Live_Bird!$B$9,MAX(C30-O_Optimizer!$F$12,0)*I_Live_Bird!$B$10) -> 14931160
A31: TLG | B31: =I_Yield!$E$13 -> 0.56 | C31: =$B$20*B31 -> 3948.56 | D31: =O_Optimizer!$E$13 -> 1524 | E31: =MIN(C31,D31) -> 1524 | F31: =MAX(C31-D31,0) -> 2424.56 | G31: =MAX(D31-C31,0) -> 0 | H31: =IFERROR(E31/D31,0) -> 1 | I31: =I_Products!$E$11 -> Y | J31: =IF(I31="Y",F31*I_Products!$G$11*I_Products!$H$11-F31*I_Live_Bird!$B$9,F31*I_Live_Bird!$B$10) -> 17214376 | K31: =E31*I_Products!$G$11 -> 12192000 | L31: =MIN(C31,O_Optimizer!$D$13)*I_Products!$G$11+IF(I31="Y",MAX(C31-O_Optimizer!$D$13,0)*I_Products!$G$11*I_Products!$H$11-MAX(C31-O_Optimizer!$D$13,0)*I_Live_Bird!$B$9,MAX(C31-O_Optimizer!$D$13,0)*I_Live_Bird!$B$10) -> 29365066 | M31: =MIN(C31,O_Optimizer!$F$13)*I_Products!$G$11+IF(I31="Y",MAX(C31-O_Optimizer!$F$13,0)*I_Products!$G$11*I_Products!$H$11-MAX(C31-O_Optimizer!$F$13,0)*I_Live_Bird!$B$9,MAX(C31-O_Optimizer!$F$13,0)*I_Live_Bird!$B$10) -> 29447326
A32: TOTAL | E32: =SUM(E24:E31) -> 8600.3 | F32: =SUM(F24:F31) -> 3527.42 | G32: =SUM(G24:G31) -> 0 | J32: =SUM(J24:J31) -> 42597107 | K32: =SUM(K24:K31) -> 317311800 | L32: =SUM(L24:L31) -> 3.5732926e+08 | M32: =SUM(M24:M31) -> 3.6126541e+08
A34: Biaya ayam total (N × biaya/ekor) | B34: =$B$20*I_Live_Bird!$B$7 -> 289091000
A35: PROFIT — Bear (IDR) | B35: =L32-$B$20*I_Live_Bird!$B$7 -> 68238261
A36: PROFIT — Base (IDR) | B36: =K32+J32-$B$20*I_Live_Bird!$B$7 -> 70817907
A37: PROFIT — Bull (IDR) | B37: =M32-$B$20*I_Live_Bird!$B$7 -> 72174411
A39: Bobot skenario (Bear/Base/Bull) | B39: 0.25 | C39: 0.5 | D39: 0.25
A40: EXPECTED PROFIT (terbobot, IDR) | B40: =B39*O_Optimizer!$B$35+C39*O_Optimizer!$B$36+D39*O_Optimizer!$B$37 -> 70512121
A42: Surplus untuk dibekukan (kg) | B42: =SUMIFS($F$24:$F$31,$I$24:$I$31,"Y") -> 3527.42
A43: Kapasitas freezer (kg) | B43: =I_Live_Bird!$B$8 -> 5000
A44: Status freezer | B44: =IF(B42>B43,"OVER — revisi N / freezer","OK") -> OK

Sheet B_Purchase_Plan
A1: B_Purchase_Plan — Ringkasan Keputusan Beli
A2: Headline output yang dipakai operasional. Semua otomatis dari O_Optimizer.
A4: KEPUTUSAN UTAMA
A5: Ekor dibeli (7 hari) | B5: =O_Optimizer!$B$20 -> 7051
A6: Ekor per hari | B6: =O_Optimizer!$B$20/7 -> 1007.2857
A7: Binding cut (penentu jumlah) | B7: =O_Optimizer!$B$16 -> Boneless Dada (fillet)
A8: Status freezer | B8: =O_Optimizer!$B$44 -> OK
A10: PROFIT 7-HARI per SKENARIO
A11: Bear | B11: =O_Optimizer!$B$35 -> 68238261
A12: Base | B12: =O_Optimizer!$B$36 -> 70817907
A13: Bull | B13: =O_Optimizer!$B$37 -> 72174411
A14: Expected (terbobot) | B14: =O_Optimizer!$B$40 -> 70512121
A16: FILL RATE & SURPLUS per POTONGAN (Base)
A17: SKU Code | B17: SKU Name | C17: Fill % | D17: Surplus (kg) | E17: Shortfall (kg) | F17: Beku?
A18: BLD | B18: Boneless Dada (fillet) | C18: =O_Optimizer!$H$24 -> 1 | D18: =O_Optimizer!$F$24 -> 0.16 | E18: =O_Optimizer!$G$24 -> 0 | F18: =O_Optimizer!$I$24 -> Y
A19: BLP | B19: Boneless Paha (fillet) | C19: =O_Optimizer!$H$25 -> 1 | D19: =O_Optimizer!$F$25 -> 92.16 | E19: =O_Optimizer!$G$25 -> 0 | F19: =O_Optimizer!$I$25 -> Y
A20: SYP | B20: Sayap | C20: =O_Optimizer!$H$26 -> 1 | D20: =O_Optimizer!$F$26 -> 122.08 | E20: =O_Optimizer!$G$26 -> 0 | F20: =O_Optimizer!$I$26 -> Y
A21: CKR | B21: Ceker | C21: =O_Optimizer!$H$27 -> 1 | D21: =O_Optimizer!$F$27 -> 101.28 | E21: =O_Optimizer!$G$27 -> 0 | F21: =O_Optimizer!$I$27 -> Y
A22: KPL | B22: Kepala | C22: =O_Optimizer!$H$28 -> 1 | D22: =O_Optimizer!$F$28 -> 192.16 | E22: =O_Optimizer!$G$28 -> 0 | F22: =O_Optimizer!$I$28 -> Y
A23: KLT | B23: Kulit | C23: =O_Optimizer!$H$29 -> 1 | D23: =O_Optimizer!$F$29 -> 315.92 | E23: =O_Optimizer!$G$29 -> 0 | F23: =O_Optimizer!$I$29 -> Y
A24: JRN | B24: Jeroan (ati ampela) | C24: =O_Optimizer!$H$30 -> 1 | D24: =O_Optimizer!$F$30 -> 279.1 | E24: =O_Optimizer!$G$30 -> 0 | F24: =O_Optimizer!$I$30 -> Y
A25: TLG | B25: Tulang / carcass frame | C25: =O_Optimizer!$H$31 -> 1 | D25: =O_Optimizer!$F$31 -> 2424.56 | E25: =O_Optimizer!$G$31 -> 0 | F25: =O_Optimizer!$I$31 -> Y

Sheet B_Alokasi_Stok
A1: B_Alokasi_Stok — Pemetaan Stok On-hand ke Customer
A2: Diisi ops. Petakan stok ~100 ton per SKU ke customer/buyer tujuan. Rekonsiliasi otomatis: total alokasi harus = stok on-hand (tidak over, tidak ada sisa nyangkut).
A4: SECTION 1 — STOK ON-HAND per SKU (isi kg aktual; teks biru/kuning = ganti dgn angka riil)
B5: SKU Code | C5: SKU Name | D5: Stok On-hand (kg)
B6: =I_Products!$A$4 -> BLD | C6: =I_Products!$B$4 -> Boneless Dada (fillet) | D6: 22000 | L6: KFC
B7: =I_Products!$A$5 -> BLP | C7: =I_Products!$B$5 -> Boneless Paha (fillet) | D7: 16000
B8: =I_Products!$A$6 -> SYP | C8: =I_Products!$B$6 -> Sayap | D8: 11000
B9: =I_Products!$A$7 -> CKR | C9: =I_Products!$B$7 -> Ceker | D9: 8000
B10: =I_Products!$A$8 -> KPL | C10: =I_Products!$B$8 -> Kepala | D10: 4000
B11: =I_Products!$A$9 -> KLT | C11: =I_Products!$B$9 -> Kulit | D11: 9000
B12: =I_Products!$A$10 -> JRN | C12: =I_Products!$B$10 -> Jeroan (ati ampela) | D12: 6000
B13: =I_Products!$A$11 -> TLG | C13: =I_Products!$B$11 -> Tulang / carcass frame | D13: 24000
C14: TOTAL | D14: =SUM(D6:D13) -> 100000
A16: SECTION 2 — ALOKASI KE CUSTOMER (tambah baris sesuai kebutuhan)
A17: Satu baris = satu alokasi. Stok 1 SKU boleh dipecah ke banyak customer (buat beberapa baris). Pilih SKU & Customer dari dropdown. Kolom Harga/Nilai opsional.
A18: No | B18: SKU Code | C18: SKU Name | D18: Customer / Buyer | E18: Qty Alokasi (kg) | F18: Harga Deal (IDR/kg) | G18: Nilai (IDR) | H18: Catatan
A19: =IF($B19<>"",ROW()-18,"") -> 1 | B19: BLD | C19: =IFERROR(VLOOKUP($B19,I_Products!$A$4:$B$11,2,0),"") -> Boneless Dada (fillet) | D19: CV Distribusi Nusantara | E19: 2000 | G19: =IF(AND($E19<>"",$F19<>""),$E19*$F19,"")
A20: =IF($B20<>"",ROW()-18,"") -> 2 | B20: BLD | C20: =IFERROR(VLOOKUP($B20,I_Products!$A$4:$B$11,2,0),"") -> Boneless Dada (fillet) | G20: =IF(AND($E20<>"",$F20<>""),$E20*$F20,"")
A21: =IF($B21<>"",ROW()-18,"") | C21: =IFERROR(VLOOKUP($B21,I_Products!$A$4:$B$11,2,0),"") | G21: =IF(AND($E21<>"",$F21<>""),$E21*$F21,"")
A22: =IF($B22<>"",ROW()-18,"") | C22: =IFERROR(VLOOKUP($B22,I_Products!$A$4:$B$11,2,0),"") | G22: =IF(AND($E22<>"",$F22<>""),$E22*$F22,"")
A23: =IF($B23<>"",ROW()-18,"") | C23: =IFERROR(VLOOKUP($B23,I_Products!$A$4:$B$11,2,0),"") | G23: =IF(AND($E23<>"",$F23<>""),$E23*$F23,"")
A24: =IF($B24<>"",ROW()-18,"") | C24: =IFERROR(VLOOKUP($B24,I_Products!$A$4:$B$11,2,0),"") | G24: =IF(AND($E24<>"",$F24<>""),$E24*$F24,"")
A25: =IF($B25<>"",ROW()-18,"") | C25: =IFERROR(VLOOKUP($B25,I_Products!$A$4:$B$11,2,0),"") | G25: =IF(AND($E25<>"",$F25<>""),$E25*$F25,"")
A26: =IF($B26<>"",ROW()-18,"") | C26: =IFERROR(VLOOKUP($B26,I_Products!$A$4:$B$11,2,0),"") | G26: =IF(AND($E26<>"",$F26<>""),$E26*$F26,"")
A27: =IF($B27<>"",ROW()-18,"") | C27: =IFERROR(VLOOKUP($B27,I_Products!$A$4:$B$11,2,0),"") | G27: =IF(AND($E27<>"",$F27<>""),$E27*$F27,"")
A28: =IF($B28<>"",ROW()-18,"") | C28: =IFERROR(VLOOKUP($B28,I_Products!$A$4:$B$11,2,0),"") | G28: =IF(AND($E28<>"",$F28<>""),$E28*$F28,"")
A29: =IF($B29<>"",ROW()-18,"") | C29: =IFERROR(VLOOKUP($B29,I_Products!$A$4:$B$11,2,0),"") | G29: =IF(AND($E29<>"",$F29<>""),$E29*$F29,"")
A30: =IF($B30<>"",ROW()-18,"") | C30: =IFERROR(VLOOKUP($B30,I_Products!$A$4:$B$11,2,0),"") | G30: =IF(AND($E30<>"",$F30<>""),$E30*$F30,"")
A31: =IF($B31<>"",ROW()-18,"") | C31: =IFERROR(VLOOKUP($B31,I_Products!$A$4:$B$11,2,0),"") | G31: =IF(AND($E31<>"",$F31<>""),$E31*$F31,"")
A32: =IF($B32<>"",ROW()-18,"") | C32: =IFERROR(VLOOKUP($B32,I_Products!$A$4:$B$11,2,0),"") | G32: =IF(AND($E32<>"",$F32<>""),$E32*$F32,"")
... A48: =IF($B48<>"",ROW()-18,"") | C48: =IFERROR(VLOOKUP($B48,I_Products!$A$4:$B$11,2,0),"") | G48: =IF(AND($E48<>"",$F48<>""),$E48*$F48,"")
D49: TOTAL | E49: =SUM(E19:E48) -> 2000 | G49: =SUM(G19:G48) -> 0
A51: SECTION 3 — REKONSILIASI per SKU (otomatis)
B52: SKU Code | C52: SKU Name | D52: Stok On-hand (kg) | E52: Total Dialokasi (kg) | F52: Sisa Belum Dialokasi (kg) | G52: % Teralokasi | H52: Status
B53: =B6 -> BLD | C53: =C6 -> Boneless Dada (fillet) | D53: =D6 -> 22000 | E53: =SUMIFS($E$19:$E$48,$B$19:$B$48,$B53) -> 2000 | F53: =D53-E53 -> 20000 | G53: =IFERROR(E53/D53,0) -> 0.090909091 | H53: =IF(E53>D53,"OVER — cek alokasi",IF(D53=0,"—",IF(F53>0,"Ada sisa","Full"))) -> Ada sisa
B54: =B7 -> BLP | C54: =C7 -> Boneless Paha (fillet) | D54: =D7 -> 16000 | E54: =SUMIFS($E$19:$E$48,$B$19:$B$48,$B54) -> 0 | F54: =D54-E54 -> 16000 | G54: =IFERROR(E54/D54,0) -> 0 | H54: =IF(E54>D54,"OVER — cek alokasi",IF(D54=0,"—",IF(F54>0,"Ada sisa","Full"))) -> Ada sisa
B55: =B8 -> SYP | C55: =C8 -> Sayap | D55: =D8 -> 11000 | E55: =SUMIFS($E$19:$E$48,$B$19:$B$48,$B55) -> 0 | F55: =D55-E55 -> 11000 | G55: =IFERROR(E55/D55,0) -> 0 | H55: =IF(E55>D55,"OVER — cek alokasi",IF(D55=0,"—",IF(F55>0,"Ada sisa","Full"))) -> Ada sisa
B56: =B9 -> CKR | C56: =C9 -> Ceker | D56: =D9 -> 8000 | E56: =SUMIFS($E$19:$E$48,$B$19:$B$48,$B56) -> 0 | F56: =D56-E56 -> 8000 | G56: =IFERROR(E56/D56,0) -> 0 | H56: =IF(E56>D56,"OVER — cek alokasi",IF(D56=0,"—",IF(F56>0,"Ada sisa","Full"))) -> Ada sisa
B57: =B10 -> KPL | C57: =C10 -> Kepala | D57: =D10 -> 4000 | E57: =SUMIFS($E$19:$E$48,$B$19:$B$48,$B57) -> 0 | F57: =D57-E57 -> 4000 | G57: =IFERROR(E57/D57,0) -> 0 | H57: =IF(E57>D57,"OVER — cek alokasi",IF(D57=0,"—",IF(F57>0,"Ada sisa","Full"))) -> Ada sisa
B58: =B11 -> KLT | C58: =C11 -> Kulit | D58: =D11 -> 9000 | E58: =SUMIFS($E$19:$E$48,$B$19:$B$48,$B58) -> 0 | F58: =D58-E58 -> 9000 | G58: =IFERROR(E58/D58,0) -> 0 | H58: =IF(E58>D58,"OVER — cek alokasi",IF(D58=0,"—",IF(F58>0,"Ada sisa","Full"))) -> Ada sisa
B59: =B12 -> JRN | C59: =C12 -> Jeroan (ati ampela) | D59: =D12 -> 6000 | E59: =SUMIFS($E$19:$E$48,$B$19:$B$48,$B59) -> 0 | F59: =D59-E59 -> 6000 | G59: =IFERROR(E59/D59,0) -> 0 | H59: =IF(E59>D59,"OVER — cek alokasi",IF(D59=0,"—",IF(F59>0,"Ada sisa","Full"))) -> Ada sisa
B60: =B13 -> TLG | C60: =C13 -> Tulang / carcass frame | D60: =D13 -> 24000 | E60: =SUMIFS($E$19:$E$48,$B$19:$B$48,$B60) -> 0 | F60: =D60-E60 -> 24000 | G60: =IFERROR(E60/D60,0) -> 0 | H60: =IF(E60>D60,"OVER — cek alokasi",IF(D60=0,"—",IF(F60>0,"Ada sisa","Full"))) -> Ada sisa
C61: TOTAL | D61: =SUM(D53:D60) -> 100000 | E61: =SUM(E53:E60) -> 2000 | F61: =SUM(F53:F60) -> 98000
A63: SECTION 4 — DAFTAR CUSTOMER & REKAP (isi daftar = sumber dropdown; rekap otomatis)
A64: Isi daftar customer riil di kolom Customer (baris di bawah = contoh, ganti). Dropdown alokasi ambil dari sini. Total kg & nilai per customer otomatis.
D65: Customer / Buyer | E65: Total Qty (kg) | F65: Total Nilai (IDR)
D66: Pasar Induk Cibitung | E66: =IF($D66<>"",SUMIFS($E$19:$E$48,$D$19:$D$48,$D66),"") -> 0 | F66: =IF($D66<>"",SUMIFS($G$19:$G$48,$D$19:$D$48,$D66),"") -> 0
D67: Superindo Bekasi (MT) | E67: =IF($D67<>"",SUMIFS($E$19:$E$48,$D$19:$D$48,$D67),"") -> 0 | F67: =IF($D67<>"",SUMIFS($G$19:$G$48,$D$19:$D$48,$D67),"") -> 0
D68: Katering Amanah | E68: =IF($D68<>"",SUMIFS($E$19:$E$48,$D$19:$D$48,$D68),"") -> 0 | F68: =IF($D68<>"",SUMIFS($G$19:$G$48,$D$19:$D$48,$D68),"") -> 0
D69: Bakso Jaya (industri) | E69: =IF($D69<>"",SUMIFS($E$19:$E$48,$D$19:$D$48,$D69),"") -> 0 | F69: =IF($D69<>"",SUMIFS($G$19:$G$48,$D$19:$D$48,$D69),"") -> 0
D70: CV Distribusi Nusantara | E70: =IF($D70<>"",SUMIFS($E$19:$E$48,$D$19:$D$48,$D70),"") -> 2000 | F70: =IF($D70<>"",SUMIFS($G$19:$G$48,$D$19:$D$48,$D70),"") -> 0
E71: =IF($D71<>"",SUMIFS($E$19:$E$48,$D$19:$D$48,$D71),"") | F71: =IF($D71<>"",SUMIFS($G$19:$G$48,$D$19:$D$48,$D71),"")
E72: =IF($D72<>"",SUMIFS($E$19:$E$48,$D$19:$D$48,$D72),"") | F72: =IF($D72<>"",SUMIFS($G$19:$G$48,$D$19:$D$48,$D72),"")
E73: =IF($D73<>"",SUMIFS($E$19:$E$48,$D$19:$D$48,$D73),"") | F73: =IF($D73<>"",SUMIFS($G$19:$G$48,$D$19:$D$48,$D73),"")
E74: =IF($D74<>"",SUMIFS($E$19:$E$48,$D$19:$D$48,$D74),"") | F74: =IF($D74<>"",SUMIFS($G$19:$G$48,$D$19:$D$48,$D74),"")
E75: =IF($D75<>"",SUMIFS($E$19:$E$48,$D$19:$D$48,$D75),"") | F75: =IF($D75<>"",SUMIFS($G$19:$G$48,$D$19:$D$48,$D75),"")
E76: =IF($D76<>"",SUMIFS($E$19:$E$48,$D$19:$D$48,$D76),"") | F76: =IF($D76<>"",SUMIFS($G$19:$G$48,$D$19:$D$48,$D76),"")
E77: =IF($D77<>"",SUMIFS($E$19:$E$48,$D$19:$D$48,$D77),"") | F77: =IF($D77<>"",SUMIFS($G$19:$G$48,$D$19:$D$48,$D77),"")
E78: =IF($D78<>"",SUMIFS($E$19:$E$48,$D$19:$D$48,$D78),"") | F78: =IF($D78<>"",SUMIFS($G$19:$G$48,$D$19:$D$48,$D78),"")
E79: =IF($D79<>"",SUMIFS($E$19:$E$48,$D$19:$D$48,$D79),"") | F79: =IF($D79<>"",SUMIFS($G$19:$G$48,$D$19:$D$48,$D79),"")
E80: =IF($D80<>"",SUMIFS($E$19:$E$48,$D$19:$D$48,$D80),"") | F80: =IF($D80<>"",SUMIFS($G$19:$G$48,$D$19:$D$48,$D80),"")
E81: =IF($D81<>"",SUMIFS($E$19:$E$48,$D$19:$D$48,$D81),"") | F81: =IF($D81<>"",SUMIFS($G$19:$G$48,$D$19:$D$48,$D81),"")
E82: =IF($D82<>"",SUMIFS($E$19:$E$48,$D$19:$D$48,$D82),"") | F82: =IF($D82<>"",SUMIFS($G$19:$G$48,$D$19:$D$48,$D82),"")
... E85: =IF($D85<>"",SUMIFS($E$19:$E$48,$D$19:$D$48,$D85),"") | F85: =IF($D85<>"",SUMIFS($G$19:$G$48,$D$19:$D$48,$D85),"")
D86: TOTAL | E86: =SUM(E66:E85) -> 2000 | F86: =SUM(F66:F85) -> 0

Sheet O_Accuracy_Tracker
A1: O_Accuracy_Tracker — Log Forecast vs Aktual (backtest)
A2: Catat tiap periode tutup. MAPE/bias akumulasi → backtest mulai periode ke-2.
A3: Periode | B3: SKU Code | C3: SKU Name | D3: Scenario | E3: Forecast (kg) | F3: Aktual (kg) | G3: Abs % Error | H3: Signed % Error | I3: Arah Benar?
G4: =IFERROR(ABS(F4-E4)/F4,"") | H4: =IFERROR((E4-F4)/F4,"") | I4: =IF(OR(E4="",F4=""),"",IF(SIGN(E4)=SIGN(F4),"Ya","Tidak"))
G5: =IFERROR(ABS(F5-E5)/F5,"") | H5: =IFERROR((E5-F5)/F5,"") | I5: =IF(OR(E5="",F5=""),"",IF(SIGN(E5)=SIGN(F5),"Ya","Tidak"))
G6: =IFERROR(ABS(F6-E6)/F6,"") | H6: =IFERROR((E6-F6)/F6,"") | I6: =IF(OR(E6="",F6=""),"",IF(SIGN(E6)=SIGN(F6),"Ya","Tidak"))
G7: =IFERROR(ABS(F7-E7)/F7,"") | H7: =IFERROR((E7-F7)/F7,"") | I7: =IF(OR(E7="",F7=""),"",IF(SIGN(E7)=SIGN(F7),"Ya","Tidak"))
G8: =IFERROR(ABS(F8-E8)/F8,"") | H8: =IFERROR((E8-F8)/F8,"") | I8: =IF(OR(E8="",F8=""),"",IF(SIGN(E8)=SIGN(F8),"Ya","Tidak"))
G9: =IFERROR(ABS(F9-E9)/F9,"") | H9: =IFERROR((E9-F9)/F9,"") | I9: =IF(OR(E9="",F9=""),"",IF(SIGN(E9)=SIGN(F9),"Ya","Tidak"))
G10: =IFERROR(ABS(F10-E10)/F10,"") | H10: =IFERROR((E10-F10)/F10,"") | I10: =IF(OR(E10="",F10=""),"",IF(SIGN(E10)=SIGN(F10),"Ya","Tidak"))
G11: =IFERROR(ABS(F11-E11)/F11,"") | H11: =IFERROR((E11-F11)/F11,"") | I11: =IF(OR(E11="",F11=""),"",IF(SIGN(E11)=SIGN(F11),"Ya","Tidak"))
G12: =IFERROR(ABS(F12-E12)/F12,"") | H12: =IFERROR((E12-F12)/F12,"") | I12: =IF(OR(E12="",F12=""),"",IF(SIGN(E12)=SIGN(F12),"Ya","Tidak"))
G13: =IFERROR(ABS(F13-E13)/F13,"") | H13: =IFERROR((E13-F13)/F13,"") | I13: =IF(OR(E13="",F13=""),"",IF(SIGN(E13)=SIGN(F13),"Ya","Tidak"))
A15: MAPE (rata-rata Abs % Error) | B15: =IFERROR(AVERAGE(G4:G13),"")
A16: Bias (rata-rata Signed % Error) | B16: =IFERROR(AVERAGE(H4:H13),"")

Sheet Z_Model_Governance
A1: Z_Model_Governance — Versi & Sign-off
A3: SECTION 1 — VERSION HISTORY
A4: Versi | B4: Tanggal | C4: Author | D4: Ringkasan | E4: Reviewer
A5: v0.1 | B5: Jun 2026 | C5: Analytics | D5: Skeleton awal: arsitektur overlay (adaptasi SAMB) + Layer yield + optimizer joint-production + hardening
A7: SECTION 2 — SIGN-OFF
A8: Peran | B8: Nama | C8: Scope | D8: Tanggal | E8: Status
A9: Model preparer | E9: Pending
A10: Head of Sales (input) | E10: Pending
A11: Ops / RPA (yield) | E11: Pending
A12: Finance Controller | E12: Pending
A13: CEO | E13: Pending
