Workbook

Sheet 00_Petunjuk
A1: KGR WEEKLY OUTLOOK — PETUNJUK
B4: Tujuan | C4: Satu file per minggu (Senin–Minggu), diupdate setiap pagi, untuk keputusan harian: potong berapa dan beli live bird di harga berapa (RPA), beli apa dan berapa (Trading), stok mana yang harus dijual, dan berapa kas keluar. Halaman utama: O_Outlook.
B5: Setiap pagi (±30 menit) | C5: 1) I_Parameter: ganti Tanggal update dan Harga live bird hari ini. 2) T_Penjualan: tempel penjualan kemarin dari Accurate (Status = Aktual, isi HPP aktual dari DO kalau ada); ubah order yang sudah terkirim jadi Aktual; tambah order baru dari sales (Status = Order, tanggal kirim rencana). 3) T_Penerimaan: tempel GRN kemarin (Aktual); perbarui rencana terima trading (Rencana). 4) T_Batch: isi batch kemarin dari data ops (Aktual); perbarui rencana potong (Rencana). 5) Cek Z_Kontrol = LULUS, lalu kirim O_Outlook.
B6: Setiap Senin | C6: Buat file minggu baru: isi I_Stok_Awal dari Inventory Valuation Accurate (kg, nilai, umur), isi baris "Minggu lalu" di I_Parameter dari ringkasan outlook minggu sebelumnya, kosongkan T_Penjualan / T_Penerimaan / T_Batch, perbarui harga acuan di I_Master.
B7: Siapa mengisi | C7: Senior Inventory Accounting: aktual dari Accurate (penjualan, GRN, stok awal). Sales: order. PPIC: rencana potong (T_Batch Rencana). Purchasing / Manajer Operasional: harga LB, rencana beli trading, harga beli pengganti.
B8: Cara hitung | C8: GP produk = revenue − HPP. Penjualan aktual pakai HPP dari Accurate; order dinilai di biaya rata-rata stok minggu ini (stok awal + penerimaan). Cost of sales others (angkut, blasting) dan opex tidak termasuk. Breakeven live bird = (1 − shrink) × (yield karkas × harga karkas + Σ yield by-product × harga) − angkut − maklon × (1 − shrink). Porsi fresh rencana = kebutuhan karkas fresh ÷ karkas dari potong rencana. Stok per hari = stok kemarin + terima − jual (aktual untuk hari lewat, rencana/order mulai hari ini).
B9: Warna | C9: Biru di latar krem = input. Hijau = link dari sheet lain. Hitam = rumus. Merah = peringatan.
B10: Contoh isi | C10: File ini berisi contoh minggu 24–30 Agustus 2026, update 27 Agustus: aktual dari Accurate (DO, GRN, inventory valuation), order = pengiriman aktual 27–30 Agu, rencana potong = batch ops 27–28 Agu, harga = rata-rata Agustus. Ganti dengan data minggu berjalan.
B11: Laporan keuangan mingguan | C11: O_PnL, O_BS, O_CF. Aktual dari jurnal Accurate (T_GL) di atas neraca saldo awal (I_TB). Sisa minggu: revenue dan HPP dari order, biaya lain dari run-rate (I_RunRate), kas dari T_Kas_Rencana plus pembayaran live bird / trading / angkut-maklon yang jatuh tempo sesuai termin di I_Parameter. Setiap pagi: tempel jurnal kemarin ke T_GL. Setiap awal bulan: perbarui I_RunRate dengan aktual bulan lalu. I_TB diganti bila tanggal saldo awal diganti (mis. TB akhir bulan lalu).
B12: Arus kas aktual | C12: Setiap baris kas diberi kategori dari akun lawan terbesar dalam voucher yang sama (I_COA kolom F). Kalau salah, isi Override di T_GL kolom R.

Sheet O_Outlook
A1: KGR — WEEKLY OUTLOOK DAN KEPUTUSAN HARIAN
A2: Minggu (Senin – Minggu): | B2: =I_Parameter!$C$5 -> 46258 | C2: =I_Parameter!$C$6 -> 46264 | E2: Update: | F2: =I_Parameter!$C$4 -> 46261 | H2: Aktual = transaksi s.d. kemarin; sisa minggu = order + rencana mulai hari ini.
A4: 1. RINGKASAN MINGGU — GP produk (HPP dari Accurate; order dinilai di biaya rata-rata stok minggu ini; cost of sales others tidak termasuk)
A5: Segmen | B5: kg aktual s.d. kemarin | C5: Revenue aktual Rp | D5: GP aktual Rp | E5: kg order sisa minggu | F5: Revenue order Rp | G5: GP order Rp | H5: kg proyeksi minggu | I5: Revenue proyeksi Rp | J5: GP proyeksi Rp | K5: GP/kg proyeksi | L5: GP % proyeksi | M5: GP/kg minggu lalu | N5: Δ GP/kg
A6: RPA | B6: =SUMIFS(T_Penjualan!$H$6:$H$1505,T_Penjualan!$N$6:$N$1505,"RPA",T_Penjualan!$B$6:$B$1505,"Aktual",T_Penjualan!$P$6:$P$1505,1) -> 7942.69 | C6: =SUMIFS(T_Penjualan!$J$6:$J$1505,T_Penjualan!$N$6:$N$1505,"RPA",T_Penjualan!$B$6:$B$1505,"Aktual",T_Penjualan!$P$6:$P$1505,1) -> 2.2400658e+08 | D6: =SUMIFS(T_Penjualan!$M$6:$M$1505,T_Penjualan!$N$6:$N$1505,"RPA",T_Penjualan!$B$6:$B$1505,"Aktual",T_Penjualan!$P$6:$P$1505,1) -> -10279045 | E6: =SUMIFS(T_Penjualan!$H$6:$H$1505,T_Penjualan!$N$6:$N$1505,"RPA",T_Penjualan!$B$6:$B$1505,"Order",T_Penjualan!$P$6:$P$1505,1) -> 23783.76 | F6: =SUMIFS(T_Penjualan!$J$6:$J$1505,T_Penjualan!$N$6:$N$1505,"RPA",T_Penjualan!$B$6:$B$1505,"Order",T_Penjualan!$P$6:$P$1505,1) -> 6.3161319e+08 | G6: =SUMIFS(T_Penjualan!$M$6:$M$1505,T_Penjualan!$N$6:$N$1505,"RPA",T_Penjualan!$B$6:$B$1505,"Order",T_Penjualan!$P$6:$P$1505,1) -> -52292801 | H6: =B6+E6 -> 31726.45 | I6: =C6+F6 -> 8.5561977e+08 | J6: =D6+G6 -> -62571846 | K6: =IF(H6=0,0,J6/H6) -> -1972.2297 | L6: =IF(I6=0,0,J6/I6) -> -0.073130435 | M6: =IF(I_Parameter!C38=0,0,I_Parameter!E38/I_Parameter!C38) -> -154.72464 | N6: =K6-M6 -> -1817.505
A7: Trading | B7: =SUMIFS(T_Penjualan!$H$6:$H$1505,T_Penjualan!$N$6:$N$1505,"Trading",T_Penjualan!$B$6:$B$1505,"Aktual",T_Penjualan!$P$6:$P$1505,1) -> 15645.28 | C7: =SUMIFS(T_Penjualan!$J$6:$J$1505,T_Penjualan!$N$6:$N$1505,"Trading",T_Penjualan!$B$6:$B$1505,"Aktual",T_Penjualan!$P$6:$P$1505,1) -> 3.4712513e+08 | D7: =SUMIFS(T_Penjualan!$M$6:$M$1505,T_Penjualan!$N$6:$N$1505,"Trading",T_Penjualan!$B$6:$B$1505,"Aktual",T_Penjualan!$P$6:$P$1505,1) -> 15239014 | E7: =SUMIFS(T_Penjualan!$H$6:$H$1505,T_Penjualan!$N$6:$N$1505,"Trading",T_Penjualan!$B$6:$B$1505,"Order",T_Penjualan!$P$6:$P$1505,1) -> 16653.64 | F7: =SUMIFS(T_Penjualan!$J$6:$J$1505,T_Penjualan!$N$6:$N$1505,"Trading",T_Penjualan!$B$6:$B$1505,"Order",T_Penjualan!$P$6:$P$1505,1) -> 4.3621227e+08 | G7: =SUMIFS(T_Penjualan!$M$6:$M$1505,T_Penjualan!$N$6:$N$1505,"Trading",T_Penjualan!$B$6:$B$1505,"Order",T_Penjualan!$P$6:$P$1505,1) -> -244556.72 | H7: =B7+E7 -> 32298.92 | I7: =C7+F7 -> 7.8333739e+08 | J7: =D7+G7 -> 14994457 | K7: =IF(H7=0,0,J7/H7) -> 464.24021 | L7: =IF(I7=0,0,J7/I7) -> 0.019141761 | M7: =IF(I_Parameter!C39=0,0,I_Parameter!E39/I_Parameter!C39) -> 1972.6891 | N7: =K7-M7 -> -1508.4489
A8: TOTAL KGR | B8: =B6+B7 -> 23587.97 | C8: =C6+C7 -> 5.711317e+08 | D8: =D6+D7 -> 4959969.3 | E8: =E6+E7 -> 40437.4 | F8: =F6+F7 -> 1.0678255e+09 | G8: =G6+G7 -> -52537358 | H8: =H6+H7 -> 64025.37 | I8: =I6+I7 -> 1.6389572e+09 | J8: =J6+J7 -> -47577388 | K8: =IF(H8=0,0,J8/H8) -> -743.10212 | L8: =IF(I8=0,0,J8/I8) -> -0.029029061 | M8: =IF(I_Parameter!C38+I_Parameter!C39=0,0,(I_Parameter!E38+I_Parameter!E39)/(I_Parameter!C38+I_Parameter!C39)) -> 883.35737 | N8: =K8-M8 -> -1626.4595
A10: 2. KEPUTUSAN RPA — potong berapa, beli live bird di harga berapa
A11: Indikator | B11: Nilai | C11: Satuan | D11: Cara hitung
A12: Harga live bird hari ini (penawaran) | B12: =I_Parameter!$C$11 -> 24600 | C12: Rp/kg LB | D12: I_Parameter
A13: Order karkas fresh — hari ini s.d. horizon | B13: =SUMIFS(T_Penjualan!$H$6:$H$1505,T_Penjualan!$G$6:$G$1505,"RPA|Karkas|Fresh",T_Penjualan!$B$6:$B$1505,"Order",T_Penjualan!$A$6:$A$1505,">="&I_Parameter!$C$4,T_Penjualan!$A$6:$A$1505,"<="&(I_Parameter!$C$4+I_Parameter!$C$7-1)) -> 12307.15 | C13: kg | D13: T_Penjualan: order RPA|Karkas|Fresh dalam horizon
A14: Stok karkas fresh hari ini | B14: =IFERROR(INDEX(O_Stok!$S$6:$S$85,MATCH("RPA|Karkas|Fresh",O_Stok!$A$6:$A$85,0)),0) -> 18768.21 | C14: kg | D14: O_Stok
A15: Kebutuhan bersih karkas fresh | B15: =MAX(0,B13-B14) -> 0 | C15: kg | D15: order − stok
A16: Live bird maksimum tanpa menambah karkas frozen | B16: =IF(I_Parameter!$C$19*(1-I_Parameter!$C$8)=0,0,B15/((1-I_Parameter!$C$8)*I_Parameter!$C$19)) -> 0 | C16: kg LB | D16: kebutuhan bersih ÷ ((1 − shrink) × yield karkas)
A17: Live bird yang sudah direncanakan potong (horizon) | B17: =SUMIFS(T_Batch!$E$6:$E$55,T_Batch!$B$6:$B$55,"Rencana",T_Batch!$A$6:$A$55,">="&I_Parameter!$C$4,T_Batch!$A$6:$A$55,"<="&(I_Parameter!$C$4+I_Parameter!$C$7-1)) -> 27218.6 | C17: kg LB | D17: T_Batch: Rencana
A18: Karkas yang berpotensi jadi frozen | B18: =MAX(0,B17-B16)*(1-I_Parameter!$C$8)*I_Parameter!$C$19 -> 19474.899 | C18: kg | D18: kelebihan potong × (1 − shrink) × yield karkas
A19: Porsi karkas fresh dari potong rencana | B19: =IF(B17=0,1,MIN(1,B15/(B17*(1-I_Parameter!$C$8)*I_Parameter!$C$19))) -> 0 | C19: %
A20: Nilai output per kg live bird (porsi fresh rencana) | B20: =(1-I_Parameter!$C$8)*(I_Parameter!$C$19*(B19*I_Parameter!$C$28+(1-B19)*I_Parameter!$C$29)+I_Parameter!$C$20*I_Parameter!$C$30+I_Parameter!$C$21*I_Parameter!$C$31+I_Parameter!$C$22*I_Parameter!$C$32+I_Parameter!$C$23*I_Parameter!$C$33+I_Parameter!$C$24*I_Parameter!$C$34) -> 23277.657 | C20: Rp/kg LB | D20: harga acuan × yield parameter
A21: Breakeven live bird — porsi fresh rencana | B21: =B20-I_Parameter!$C$9-I_Parameter!$C$10*(1-I_Parameter!$C$8) -> 20725.657 | C21: Rp/kg LB | D21: nilai output − angkut − maklon
A22: Breakeven live bird — 100% karkas fresh | B22: =(1-I_Parameter!$C$8)*(I_Parameter!$C$19*I_Parameter!$C$28+I_Parameter!$C$20*I_Parameter!$C$30+I_Parameter!$C$21*I_Parameter!$C$31+I_Parameter!$C$22*I_Parameter!$C$32+I_Parameter!$C$23*I_Parameter!$C$33+I_Parameter!$C$24*I_Parameter!$C$34)-I_Parameter!$C$9-I_Parameter!$C$10*(1-I_Parameter!$C$8) -> 24336.784 | C22: Rp/kg LB | D22: batas atas
A23: Margin per kg live bird di harga hari ini | B23: =B21-B12 -> -3874.3425 | C23: Rp/kg LB | D23: breakeven − harga
A24: Perkiraan margin potong rencana | B24: =B23*B17 -> -1.0545418e+08 | C24: Rp | D24: margin/kg × kg LB rencana
A25: Potensi selisih harga karkas yang jadi frozen | B25: =B18*(I_Parameter!$C$28-I_Parameter!$C$29) -> 98289817 | C25: Rp | D25: kg frozen × (harga fresh − frozen)
A26: REKOMENDASI RPA | B26: =IF(B12>B22,"TUNDA / NEGOSIASI: harga LB "&FIXED(B12,0)&" di atas breakeven 100% fresh "&FIXED(B22,0)&" — setiap kg LB rugi walau semua karkas laku fresh",IF(B17>B16+0.5,"KURANGI potong ke maksimum "&FIXED(B16,0)&" kg LB (rencana "&FIXED(B17,0)&" kg) supaya karkas tidak jadi frozen",IF(B23<0,"POTONG HANYA SESUAI ORDER: margin per kg LB negatif ("&FIXED(B23,0)&")","LANJUT sesuai rencana: harga LB di bawah breakeven dan kebutuhan fresh tertutup"))) -> TUNDA / NEGOSIASI: harga LB 24,600 di atas breakeven 100% fresh 24,337 — setiap kg LB rugi walau semua karkas laku fresh
A28: 3. KEPUTUSAN TRADING — beli apa, berapa, di spread berapa
A29: SKU (key) | B29: Stok hari ini kg | C29: Order sisa minggu kg | D29: Rencana terima sisa minggu kg | E29: Kebutuhan bersih kg | F29: Harga jual order Rp/kg | G29: Harga beli pengganti Rp/kg | H29: Spread Rp/kg | I29: Spread % | J29: Biaya stok rata-rata Rp/kg | K29: REKOMENDASI
A30: BLD|Frozen | B30: =IFERROR(INDEX(O_Stok!$S$6:$S$85,MATCH("Trading|BLD|Frozen",O_Stok!$A$6:$A$85,0)),0) -> 4848.44 | C30: =IFERROR(INDEX(O_Stok!$T$6:$T$85,MATCH("Trading|BLD|Frozen",O_Stok!$A$6:$A$85,0)),0) -> 0 | D30: =SUMIFS(T_Penerimaan!$I$6:$I$1005,T_Penerimaan!$H$6:$H$1005,"Trading|BLD|Frozen",T_Penerimaan!$B$6:$B$1005,"Rencana",T_Penerimaan!$A$6:$A$1005,">="&I_Parameter!$C$4,T_Penerimaan!$A$6:$A$1005,"<="&I_Parameter!$C$6) -> 0 | E30: =MAX(0,C30-B30-D30) -> 0 | F30: =IFERROR(SUMIFS(T_Penjualan!$J$6:$J$1505,T_Penjualan!$G$6:$G$1505,"Trading|BLD|Frozen",T_Penjualan!$B$6:$B$1505,"Order",T_Penjualan!$A$6:$A$1505,">="&I_Parameter!$C$4)/SUMIFS(T_Penjualan!$H$6:$H$1505,T_Penjualan!$G$6:$G$1505,"Trading|BLD|Frozen",T_Penjualan!$B$6:$B$1505,"Order",T_Penjualan!$A$6:$A$1505,">="&I_Parameter!$C$4),IFERROR(INDEX(I_Master!$F$6:$F$85,MATCH("Trading|BLD|Frozen",I_Master!$A$6:$A$85,0)),0)) -> 42083 | G30: =IFERROR(INDEX(I_Master!$G$6:$G$85,MATCH("Trading|BLD|Frozen",I_Master!$A$6:$A$85,0)),"") -> 38169 | H30: =IF(OR(G30="",G30=0,F30=0),"",F30-G30) -> 3914 | I30: =IF(H30="","",H30/F30) -> 0.093006677 | J30: =IFERROR(INDEX(O_Stok!$Q$6:$Q$85,MATCH("Trading|BLD|Frozen",O_Stok!$A$6:$A$85,0)),0) -> 39097.081 | K30: =IF(E30>0.5,IF(H30="","BELI "&FIXED(E30,0)&" kg — isi harga beli pengganti",IF(H30>=I_Parameter!$C$12,"BELI "&FIXED(E30,0)&" kg (spread "&FIXED(H30,0)&"/kg)","TAHAN: spread "&FIXED(H30,0)&"/kg di bawah minimum — naikkan harga jual atau cari pemasok")),IF(AND(B30>0.5,C30<=0.5),"JUAL STOK: "&FIXED(B30,0)&" kg tanpa order",IF(AND(C30>0.5,J30>0,F30<J30),"CEK HARGA: order "&FIXED(F30,0)&"/kg di bawah biaya stok "&FIXED(J30,0)&"/kg",IF(B30>0.5,"Cukup — sisa "&FIXED(B30-C30+D30,0)&" kg setelah order","-")))) -> JUAL STOK: 4,848 kg tanpa order
A31: BLD|n/a | B31: =IFERROR(INDEX(O_Stok!$S$6:$S$85,MATCH("Trading|BLD|n/a",O_Stok!$A$6:$A$85,0)),0) -> 10.2 | C31: =IFERROR(INDEX(O_Stok!$T$6:$T$85,MATCH("Trading|BLD|n/a",O_Stok!$A$6:$A$85,0)),0) -> 0 | D31: =SUMIFS(T_Penerimaan!$I$6:$I$1005,T_Penerimaan!$H$6:$H$1005,"Trading|BLD|n/a",T_Penerimaan!$B$6:$B$1005,"Rencana",T_Penerimaan!$A$6:$A$1005,">="&I_Parameter!$C$4,T_Penerimaan!$A$6:$A$1005,"<="&I_Parameter!$C$6) -> 0 | E31: =MAX(0,C31-B31-D31) -> 0 | F31: =IFERROR(SUMIFS(T_Penjualan!$J$6:$J$1505,T_Penjualan!$G$6:$G$1505,"Trading|BLD|n/a",T_Penjualan!$B$6:$B$1505,"Order",T_Penjualan!$A$6:$A$1505,">="&I_Parameter!$C$4)/SUMIFS(T_Penjualan!$H$6:$H$1505,T_Penjualan!$G$6:$G$1505,"Trading|BLD|n/a",T_Penjualan!$B$6:$B$1505,"Order",T_Penjualan!$A$6:$A$1505,">="&I_Parameter!$C$4),IFERROR(INDEX(I_Master!$F$6:$F$85,MATCH("Trading|BLD|n/a",I_Master!$A$6:$A$85,0)),0)) -> 45000 | G31: =IFERROR(INDEX(I_Master!$G$6:$G$85,MATCH("Trading|BLD|n/a",I_Master!$A$6:$A$85,0)),"") -> 0 | H31: =IF(OR(G31="",G31=0,F31=0),"",F31-G31) | I31: =IF(H31="","",H31/F31) | J31: =IFERROR(INDEX(O_Stok!$Q$6:$Q$85,MATCH("Trading|BLD|n/a",O_Stok!$A$6:$A$85,0)),0) -> 43000 | K31: =IF(E31>0.5,IF(H31="","BELI "&FIXED(E31,0)&" kg — isi harga beli pengganti",IF(H31>=I_Parameter!$C$12,"BELI "&FIXED(E31,0)&" kg (spread "&FIXED(H31,0)&"/kg)","TAHAN: spread "&FIXED(H31,0)&"/kg di bawah minimum — naikkan harga jual atau cari pemasok")),IF(AND(B31>0.5,C31<=0.5),"JUAL STOK: "&FIXED(B31,0)&" kg tanpa order",IF(AND(C31>0.5,J31>0,F31<J31),"CEK HARGA: order "&FIXED(F31,0)&"/kg di bawah biaya stok "&FIXED(J31,0)&"/kg",IF(B31>0.5,"Cukup — sisa "&FIXED(B31-C31+D31,0)&" kg setelah order","-")))) -> JUAL STOK: 10 kg tanpa order
A32: BLP|Frozen | B32: =IFERROR(INDEX(O_Stok!$S$6:$S$85,MATCH("Trading|BLP|Frozen",O_Stok!$A$6:$A$85,0)),0) -> 10141 | C32: =IFERROR(INDEX(O_Stok!$T$6:$T$85,MATCH("Trading|BLP|Frozen",O_Stok!$A$6:$A$85,0)),0) -> 3229.2 | D32: =SUMIFS(T_Penerimaan!$I$6:$I$1005,T_Penerimaan!$H$6:$H$1005,"Trading|BLP|Frozen",T_Penerimaan!$B$6:$B$1005,"Rencana",T_Penerimaan!$A$6:$A$1005,">="&I_Parameter!$C$4,T_Penerimaan!$A$6:$A$1005,"<="&I_Parameter!$C$6) -> 0 | E32: =MAX(0,C32-B32-D32) -> 0 | F32: =IFERROR(SUMIFS(T_Penjualan!$J$6:$J$1505,T_Penjualan!$G$6:$G$1505,"Trading|BLP|Frozen",T_Penjualan!$B$6:$B$1505,"Order",T_Penjualan!$A$6:$A$1505,">="&I_Parameter!$C$4)/SUMIFS(T_Penjualan!$H$6:$H$1505,T_Penjualan!$G$6:$G$1505,"Trading|BLP|Frozen",T_Penjualan!$B$6:$B$1505,"Order",T_Penjualan!$A$6:$A$1505,">="&I_Parameter!$C$4),IFERROR(INDEX(I_Master!$F$6:$F$85,MATCH("Trading|BLP|Frozen",I_Master!$A$6:$A$85,0)),0)) -> 43086 | G32: =IFERROR(INDEX(I_Master!$G$6:$G$85,MATCH("Trading|BLP|Frozen",I_Master!$A$6:$A$85,0)),"") -> 49577 | H32: =IF(OR(G32="",G32=0,F32=0),"",F32-G32) -> -6491 | I32: =IF(H32="","",H32/F32) -> -0.15065218 | J32: =IFERROR(INDEX(O_Stok!$Q$6:$Q$85,MATCH("Trading|BLP|Frozen",O_Stok!$A$6:$A$85,0)),0) -> 47198.571 | K32: =IF(E32>0.5,IF(H32="","BELI "&FIXED(E32,0)&" kg — isi harga beli pengganti",IF(H32>=I_Parameter!$C$12,"BELI "&FIXED(E32,0)&" kg (spread "&FIXED(H32,0)&"/kg)","TAHAN: spread "&FIXED(H32,0)&"/kg di bawah minimum — naikkan harga jual atau cari pemasok")),IF(AND(B32>0.5,C32<=0.5),"JUAL STOK: "&FIXED(B32,0)&" kg tanpa order",IF(AND(C32>0.5,J32>0,F32<J32),"CEK HARGA: order "&FIXED(F32,0)&"/kg di bawah biaya stok "&FIXED(J32,0)&"/kg",IF(B32>0.5,"Cukup — sisa "&FIXED(B32-C32+D32,0)&" kg setelah order","-")))) -> CEK HARGA: order 43,086/kg di bawah biaya stok 47,199/kg
A33: BLPK|Frozen | B33: =IFERROR(INDEX(O_Stok!$S$6:$S$85,MATCH("Trading|BLPK|Frozen",O_Stok!$A$6:$A$85,0)),0) -> 8.53 | C33: =IFERROR(INDEX(O_Stok!$T$6:$T$85,MATCH("Trading|BLPK|Frozen",O_Stok!$A$6:$A$85,0)),0) -> 0 | D33: =SUMIFS(T_Penerimaan!$I$6:$I$1005,T_Penerimaan!$H$6:$H$1005,"Trading|BLPK|Frozen",T_Penerimaan!$B$6:$B$1005,"Rencana",T_Penerimaan!$A$6:$A$1005,">="&I_Parameter!$C$4,T_Penerimaan!$A$6:$A$1005,"<="&I_Parameter!$C$6) -> 0 | E33: =MAX(0,C33-B33-D33) -> 0 | F33: =IFERROR(SUMIFS(T_Penjualan!$J$6:$J$1505,T_Penjualan!$G$6:$G$1505,"Trading|BLPK|Frozen",T_Penjualan!$B$6:$B$1505,"Order",T_Penjualan!$A$6:$A$1505,">="&I_Parameter!$C$4)/SUMIFS(T_Penjualan!$H$6:$H$1505,T_Penjualan!$G$6:$G$1505,"Trading|BLPK|Frozen",T_Penjualan!$B$6:$B$1505,"Order",T_Penjualan!$A$6:$A$1505,">="&I_Parameter!$C$4),IFERROR(INDEX(I_Master!$F$6:$F$85,MATCH("Trading|BLPK|Frozen",I_Master!$A$6:$A$85,0)),0)) -> 34000 | G33: =IFERROR(INDEX(I_Master!$G$6:$G$85,MATCH("Trading|BLPK|Frozen",I_Master!$A$6:$A$85,0)),"") -> 0 | H33: =IF(OR(G33="",G33=0,F33=0),"",F33-G33) | I33: =IF(H33="","",H33/F33) | J33: =IFERROR(INDEX(O_Stok!$Q$6:$Q$85,MATCH("Trading|BLPK|Frozen",O_Stok!$A$6:$A$85,0)),0) -> 32000 | K33: =IF(E33>0.5,IF(H33="","BELI "&FIXED(E33,0)&" kg — isi harga beli pengganti",IF(H33>=I_Parameter!$C$12,"BELI "&FIXED(E33,0)&" kg (spread "&FIXED(H33,0)&"/kg)","TAHAN: spread "&FIXED(H33,0)&"/kg di bawah minimum — naikkan harga jual atau cari pemasok")),IF(AND(B33>0.5,C33<=0.5),"JUAL STOK: "&FIXED(B33,0)&" kg tanpa order",IF(AND(C33>0.5,J33>0,F33<J33),"CEK HARGA: order "&FIXED(F33,0)&"/kg di bawah biaya stok "&FIXED(J33,0)&"/kg",IF(B33>0.5,"Cukup — sisa "&FIXED(B33-C33+D33,0)&" kg setelah order","-")))) -> JUAL STOK: 9 kg tanpa order
A34: HJA (Hati/Jantung/Ampela)|n/a | B34: =IFERROR(INDEX(O_Stok!$S$6:$S$85,MATCH("Trading|HJA (Hati/Jantung/Ampela)|n/a",O_Stok!$A$6:$A$85,0)),0) -> 4300.37 | C34: =IFERROR(INDEX(O_Stok!$T$6:$T$85,MATCH("Trading|HJA (Hati/Jantung/Ampela)|n/a",O_Stok!$A$6:$A$85,0)),0) -> 0 | D34: =SUMIFS(T_Penerimaan!$I$6:$I$1005,T_Penerimaan!$H$6:$H$1005,"Trading|HJA (Hati/Jantung/Ampela)|n/a",T_Penerimaan!$B$6:$B$1005,"Rencana",T_Penerimaan!$A$6:$A$1005,">="&I_Parameter!$C$4,T_Penerimaan!$A$6:$A$1005,"<="&I_Parameter!$C$6) -> 0 | E34: =MAX(0,C34-B34-D34) -> 0 | F34: =IFERROR(SUMIFS(T_Penjualan!$J$6:$J$1505,T_Penjualan!$G$6:$G$1505,"Trading|HJA (Hati/Jantung/Ampela)|n/a",T_Penjualan!$B$6:$B$1505,"Order",T_Penjualan!$A$6:$A$1505,">="&I_Parameter!$C$4)/SUMIFS(T_Penjualan!$H$6:$H$1505,T_Penjualan!$G$6:$G$1505,"Trading|HJA (Hati/Jantung/Ampela)|n/a",T_Penjualan!$B$6:$B$1505,"Order",T_Penjualan!$A$6:$A$1505,">="&I_Parameter!$C$4),IFERROR(INDEX(I_Master!$F$6:$F$85,MATCH("Trading|HJA (Hati/Jantung/Ampela)|n/a",I_Master!$A$6:$A$85,0)),0)) -> 15500 | G34: =IFERROR(INDEX(I_Master!$G$6:$G$85,MATCH("Trading|HJA (Hati/Jantung/Ampela)|n/a",I_Master!$A$6:$A$85,0)),"") -> 0 | H34: =IF(OR(G34="",G34=0,F34=0),"",F34-G34) | I34: =IF(H34="","",H34/F34) | J34: =IFERROR(INDEX(O_Stok!$Q$6:$Q$85,MATCH("Trading|HJA (Hati/Jantung/Ampela)|n/a",O_Stok!$A$6:$A$85,0)),0) -> 4860.4618 | K34: =IF(E34>0.5,IF(H34="","BELI "&FIXED(E34,0)&" kg — isi harga beli pengganti",IF(H34>=I_Parameter!$C$12,"BELI "&FIXED(E34,0)&" kg (spread "&FIXED(H34,0)&"/kg)","TAHAN: spread "&FIXED(H34,0)&"/kg di bawah minimum — naikkan harga jual atau cari pemasok")),IF(AND(B34>0.5,C34<=0.5),"JUAL STOK: "&FIXED(B34,0)&" kg tanpa order",IF(AND(C34>0.5,J34>0,F34<J34),"CEK HARGA: order "&FIXED(F34,0)&"/kg di bawah biaya stok "&FIXED(J34,0)&"/kg",IF(B34>0.5,"Cukup — sisa "&FIXED(B34-C34+D34,0)&" kg setelah order","-")))) -> JUAL STOK: 4,300 kg tanpa order
A35: KRK (Kerangka)|n/a | B35: =IFERROR(INDEX(O_Stok!$S$6:$S$85,MATCH("Trading|KRK (Kerangka)|n/a",O_Stok!$A$6:$A$85,0)),0) -> 25815.44 | C35: =IFERROR(INDEX(O_Stok!$T$6:$T$85,MATCH("Trading|KRK (Kerangka)|n/a",O_Stok!$A$6:$A$85,0)),0) -> 6011.3 | D35: =SUMIFS(T_Penerimaan!$I$6:$I$1005,T_Penerimaan!$H$6:$H$1005,"Trading|KRK (Kerangka)|n/a",T_Penerimaan!$B$6:$B$1005,"Rencana",T_Penerimaan!$A$6:$A$1005,">="&I_Parameter!$C$4,T_Penerimaan!$A$6:$A$1005,"<="&I_Parameter!$C$6) -> 0 | E35: =MAX(0,C35-B35-D35) -> 0 | F35: =IFERROR(SUMIFS(T_Penjualan!$J$6:$J$1505,T_Penjualan!$G$6:$G$1505,"Trading|KRK (Kerangka)|n/a",T_Penjualan!$B$6:$B$1505,"Order",T_Penjualan!$A$6:$A$1505,">="&I_Parameter!$C$4)/SUMIFS(T_Penjualan!$H$6:$H$1505,T_Penjualan!$G$6:$G$1505,"Trading|KRK (Kerangka)|n/a",T_Penjualan!$B$6:$B$1505,"Order",T_Penjualan!$A$6:$A$1505,">="&I_Parameter!$C$4),IFERROR(INDEX(I_Master!$F$6:$F$85,MATCH("Trading|KRK (Kerangka)|n/a",I_Master!$A$6:$A$85,0)),0)) -> 10903 | G35: =IFERROR(INDEX(I_Master!$G$6:$G$85,MATCH("Trading|KRK (Kerangka)|n/a",I_Master!$A$6:$A$85,0)),"") -> 11169 | H35: =IF(OR(G35="",G35=0,F35=0),"",F35-G35) -> -266 | I35: =IF(H35="","",H35/F35) -> -0.024396955 | J35: =IFERROR(INDEX(O_Stok!$Q$6:$Q$85,MATCH("Trading|KRK (Kerangka)|n/a",O_Stok!$A$6:$A$85,0)),0) -> 10310.872 | K35: =IF(E35>0.5,IF(H35="","BELI "&FIXED(E35,0)&" kg — isi harga beli pengganti",IF(H35>=I_Parameter!$C$12,"BELI "&FIXED(E35,0)&" kg (spread "&FIXED(H35,0)&"/kg)","TAHAN: spread "&FIXED(H35,0)&"/kg di bawah minimum — naikkan harga jual atau cari pemasok")),IF(AND(B35>0.5,C35<=0.5),"JUAL STOK: "&FIXED(B35,0)&" kg tanpa order",IF(AND(C35>0.5,J35>0,F35<J35),"CEK HARGA: order "&FIXED(F35,0)&"/kg di bawah biaya stok "&FIXED(J35,0)&"/kg",IF(B35>0.5,"Cukup — sisa "&FIXED(B35-C35+D35,0)&" kg setelah order","-")))) -> Cukup — sisa 19,804 kg setelah order
A36: Karkas|n/a | B36: =IFERROR(INDEX(O_Stok!$S$6:$S$85,MATCH("Trading|Karkas|n/a",O_Stok!$A$6:$A$85,0)),0) -> 46572.5 | C36: =IFERROR(INDEX(O_Stok!$T$6:$T$85,MATCH("Trading|Karkas|n/a",O_Stok!$A$6:$A$85,0)),0) -> 7007.77 | D36: =SUMIFS(T_Penerimaan!$I$6:$I$1005,T_Penerimaan!$H$6:$H$1005,"Trading|Karkas|n/a",T_Penerimaan!$B$6:$B$1005,"Rencana",T_Penerimaan!$A$6:$A$1005,">="&I_Parameter!$C$4,T_Penerimaan!$A$6:$A$1005,"<="&I_Parameter!$C$6) -> 0 | E36: =MAX(0,C36-B36-D36) -> 0 | F36: =IFERROR(SUMIFS(T_Penjualan!$J$6:$J$1505,T_Penjualan!$G$6:$G$1505,"Trading|Karkas|n/a",T_Penjualan!$B$6:$B$1505,"Order",T_Penjualan!$A$6:$A$1505,">="&I_Parameter!$C$4)/SUMIFS(T_Penjualan!$H$6:$H$1505,T_Penjualan!$G$6:$G$1505,"Trading|Karkas|n/a",T_Penjualan!$B$6:$B$1505,"Order",T_Penjualan!$A$6:$A$1505,">="&I_Parameter!$C$4),IFERROR(INDEX(I_Master!$F$6:$F$85,MATCH("Trading|Karkas|n/a",I_Master!$A$6:$A$85,0)),0)) -> 31277 | G36: =IFERROR(INDEX(I_Master!$G$6:$G$85,MATCH("Trading|Karkas|n/a",I_Master!$A$6:$A$85,0)),"") -> 30050 | H36: =IF(OR(G36="",G36=0,F36=0),"",F36-G36) -> 1227 | I36: =IF(H36="","",H36/F36) -> 0.039230105 | J36: =IFERROR(INDEX(O_Stok!$Q$6:$Q$85,MATCH("Trading|Karkas|n/a",O_Stok!$A$6:$A$85,0)),0) -> 30065.464 | K36: =IF(E36>0.5,IF(H36="","BELI "&FIXED(E36,0)&" kg — isi harga beli pengganti",IF(H36>=I_Parameter!$C$12,"BELI "&FIXED(E36,0)&" kg (spread "&FIXED(H36,0)&"/kg)","TAHAN: spread "&FIXED(H36,0)&"/kg di bawah minimum — naikkan harga jual atau cari pemasok")),IF(AND(B36>0.5,C36<=0.5),"JUAL STOK: "&FIXED(B36,0)&" kg tanpa order",IF(AND(C36>0.5,J36>0,F36<J36),"CEK HARGA: order "&FIXED(F36,0)&"/kg di bawah biaya stok "&FIXED(J36,0)&"/kg",IF(B36>0.5,"Cukup — sisa "&FIXED(B36-C36+D36,0)&" kg setelah order","-")))) -> Cukup — sisa 39,565 kg setelah order
A37: Kulit|Frozen | B37: =IFERROR(INDEX(O_Stok!$S$6:$S$85,MATCH("Trading|Kulit|Frozen",O_Stok!$A$6:$A$85,0)),0) -> 4067.31 | C37: =IFERROR(INDEX(O_Stok!$T$6:$T$85,MATCH("Trading|Kulit|Frozen",O_Stok!$A$6:$A$85,0)),0) -> 105.37 | D37: =SUMIFS(T_Penerimaan!$I$6:$I$1005,T_Penerimaan!$H$6:$H$1005,"Trading|Kulit|Frozen",T_Penerimaan!$B$6:$B$1005,"Rencana",T_Penerimaan!$A$6:$A$1005,">="&I_Parameter!$C$4,T_Penerimaan!$A$6:$A$1005,"<="&I_Parameter!$C$6) -> 0 | E37: =MAX(0,C37-B37-D37) -> 0 | F37: =IFERROR(SUMIFS(T_Penjualan!$J$6:$J$1505,T_Penjualan!$G$6:$G$1505,"Trading|Kulit|Frozen",T_Penjualan!$B$6:$B$1505,"Order",T_Penjualan!$A$6:$A$1505,">="&I_Parameter!$C$4)/SUMIFS(T_Penjualan!$H$6:$H$1505,T_Penjualan!$G$6:$G$1505,"Trading|Kulit|Frozen",T_Penjualan!$B$6:$B$1505,"Order",T_Penjualan!$A$6:$A$1505,">="&I_Parameter!$C$4),IFERROR(INDEX(I_Master!$F$6:$F$85,MATCH("Trading|Kulit|Frozen",I_Master!$A$6:$A$85,0)),0)) -> 29000 | G37: =IFERROR(INDEX(I_Master!$G$6:$G$85,MATCH("Trading|Kulit|Frozen",I_Master!$A$6:$A$85,0)),"") -> 29577 | H37: =IF(OR(G37="",G37=0,F37=0),"",F37-G37) -> -577 | I37: =IF(H37="","",H37/F37) -> -0.019896552 | J37: =IFERROR(INDEX(O_Stok!$Q$6:$Q$85,MATCH("Trading|Kulit|Frozen",O_Stok!$A$6:$A$85,0)),0) -> 26380.955 | K37: =IF(E37>0.5,IF(H37="","BELI "&FIXED(E37,0)&" kg — isi harga beli pengganti",IF(H37>=I_Parameter!$C$12,"BELI "&FIXED(E37,0)&" kg (spread "&FIXED(H37,0)&"/kg)","TAHAN: spread "&FIXED(H37,0)&"/kg di bawah minimum — naikkan harga jual atau cari pemasok")),IF(AND(B37>0.5,C37<=0.5),"JUAL STOK: "&FIXED(B37,0)&" kg tanpa order",IF(AND(C37>0.5,J37>0,F37<J37),"CEK HARGA: order "&FIXED(F37,0)&"/kg di bawah biaya stok "&FIXED(J37,0)&"/kg",IF(B37>0.5,"Cukup — sisa "&FIXED(B37-C37+D37,0)&" kg setelah order","-")))) -> Cukup — sisa 3,962 kg setelah order
A38: Kulit|n/a | B38: =IFERROR(INDEX(O_Stok!$S$6:$S$85,MATCH("Trading|Kulit|n/a",O_Stok!$A$6:$A$85,0)),0) -> 1395.69 | C38: =IFERROR(INDEX(O_Stok!$T$6:$T$85,MATCH("Trading|Kulit|n/a",O_Stok!$A$6:$A$85,0)),0) -> 0 | D38: =SUMIFS(T_Penerimaan!$I$6:$I$1005,T_Penerimaan!$H$6:$H$1005,"Trading|Kulit|n/a",T_Penerimaan!$B$6:$B$1005,"Rencana",T_Penerimaan!$A$6:$A$1005,">="&I_Parameter!$C$4,T_Penerimaan!$A$6:$A$1005,"<="&I_Parameter!$C$6) -> 0 | E38: =MAX(0,C38-B38-D38) -> 0 | F38: =IFERROR(SUMIFS(T_Penjualan!$J$6:$J$1505,T_Penjualan!$G$6:$G$1505,"Trading|Kulit|n/a",T_Penjualan!$B$6:$B$1505,"Order",T_Penjualan!$A$6:$A$1505,">="&I_Parameter!$C$4)/SUMIFS(T_Penjualan!$H$6:$H$1505,T_Penjualan!$G$6:$G$1505,"Trading|Kulit|n/a",T_Penjualan!$B$6:$B$1505,"Order",T_Penjualan!$A$6:$A$1505,">="&I_Parameter!$C$4),IFERROR(INDEX(I_Master!$F$6:$F$85,MATCH("Trading|Kulit|n/a",I_Master!$A$6:$A$85,0)),0)) -> 26261 | G38: =IFERROR(INDEX(I_Master!$G$6:$G$85,MATCH("Trading|Kulit|n/a",I_Master!$A$6:$A$85,0)),"") -> 0 | H38: =IF(OR(G38="",G38=0,F38=0),"",F38-G38) | I38: =IF(H38="","",H38/F38) | J38: =IFERROR(INDEX(O_Stok!$Q$6:$Q$85,MATCH("Trading|Kulit|n/a",O_Stok!$A$6:$A$85,0)),0) -> 21000 | K38: =IF(E38>0.5,IF(H38="","BELI "&FIXED(E38,0)&" kg — isi harga beli pengganti",IF(H38>=I_Parameter!$C$12,"BELI "&FIXED(E38,0)&" kg (spread "&FIXED(H38,0)&"/kg)","TAHAN: spread "&FIXED(H38,0)&"/kg di bawah minimum — naikkan harga jual atau cari pemasok")),IF(AND(B38>0.5,C38<=0.5),"JUAL STOK: "&FIXED(B38,0)&" kg tanpa order",IF(AND(C38>0.5,J38>0,F38<J38),"CEK HARGA: order "&FIXED(F38,0)&"/kg di bawah biaya stok "&FIXED(J38,0)&"/kg",IF(B38>0.5,"Cukup — sisa "&FIXED(B38-C38+D38,0)&" kg setelah order","-")))) -> JUAL STOK: 1,396 kg tanpa order
A39: Sayap|n/a | B39: =IFERROR(INDEX(O_Stok!$S$6:$S$85,MATCH("Trading|Sayap|n/a",O_Stok!$A$6:$A$85,0)),0) -> 0 | C39: =IFERROR(INDEX(O_Stok!$T$6:$T$85,MATCH("Trading|Sayap|n/a",O_Stok!$A$6:$A$85,0)),0) -> 300 | D39: =SUMIFS(T_Penerimaan!$I$6:$I$1005,T_Penerimaan!$H$6:$H$1005,"Trading|Sayap|n/a",T_Penerimaan!$B$6:$B$1005,"Rencana",T_Penerimaan!$A$6:$A$1005,">="&I_Parameter!$C$4,T_Penerimaan!$A$6:$A$1005,"<="&I_Parameter!$C$6) -> 6985 | E39: =MAX(0,C39-B39-D39) -> 0 | F39: =IFERROR(SUMIFS(T_Penjualan!$J$6:$J$1505,T_Penjualan!$G$6:$G$1505,"Trading|Sayap|n/a",T_Penjualan!$B$6:$B$1505,"Order",T_Penjualan!$A$6:$A$1505,">="&I_Parameter!$C$4)/SUMIFS(T_Penjualan!$H$6:$H$1505,T_Penjualan!$G$6:$G$1505,"Trading|Sayap|n/a",T_Penjualan!$B$6:$B$1505,"Order",T_Penjualan!$A$6:$A$1505,">="&I_Parameter!$C$4),IFERROR(INDEX(I_Master!$F$6:$F$85,MATCH("Trading|Sayap|n/a",I_Master!$A$6:$A$85,0)),0)) -> 31000 | G39: =IFERROR(INDEX(I_Master!$G$6:$G$85,MATCH("Trading|Sayap|n/a",I_Master!$A$6:$A$85,0)),"") -> 0 | H39: =IF(OR(G39="",G39=0,F39=0),"",F39-G39) | I39: =IF(H39="","",H39/F39) | J39: =IFERROR(INDEX(O_Stok!$Q$6:$Q$85,MATCH("Trading|Sayap|n/a",O_Stok!$A$6:$A$85,0)),0) -> 28632.78 | K39: =IF(E39>0.5,IF(H39="","BELI "&FIXED(E39,0)&" kg — isi harga beli pengganti",IF(H39>=I_Parameter!$C$12,"BELI "&FIXED(E39,0)&" kg (spread "&FIXED(H39,0)&"/kg)","TAHAN: spread "&FIXED(H39,0)&"/kg di bawah minimum — naikkan harga jual atau cari pemasok")),IF(AND(B39>0.5,C39<=0.5),"JUAL STOK: "&FIXED(B39,0)&" kg tanpa order",IF(AND(C39>0.5,J39>0,F39<J39),"CEK HARGA: order "&FIXED(F39,0)&"/kg di bawah biaya stok "&FIXED(J39,0)&"/kg",IF(B39>0.5,"Cukup — sisa "&FIXED(B39-C39+D39,0)&" kg setelah order","-")))) -> -
A40: Usus|Fresh | B40: =IFERROR(INDEX(O_Stok!$S$6:$S$85,MATCH("Trading|Usus|Fresh",O_Stok!$A$6:$A$85,0)),0) -> 0 | C40: =IFERROR(INDEX(O_Stok!$T$6:$T$85,MATCH("Trading|Usus|Fresh",O_Stok!$A$6:$A$85,0)),0) -> 0 | D40: =SUMIFS(T_Penerimaan!$I$6:$I$1005,T_Penerimaan!$H$6:$H$1005,"Trading|Usus|Fresh",T_Penerimaan!$B$6:$B$1005,"Rencana",T_Penerimaan!$A$6:$A$1005,">="&I_Parameter!$C$4,T_Penerimaan!$A$6:$A$1005,"<="&I_Parameter!$C$6) -> 0 | E40: =MAX(0,C40-B40-D40) -> 0 | F40: =IFERROR(SUMIFS(T_Penjualan!$J$6:$J$1505,T_Penjualan!$G$6:$G$1505,"Trading|Usus|Fresh",T_Penjualan!$B$6:$B$1505,"Order",T_Penjualan!$A$6:$A$1505,">="&I_Parameter!$C$4)/SUMIFS(T_Penjualan!$H$6:$H$1505,T_Penjualan!$G$6:$G$1505,"Trading|Usus|Fresh",T_Penjualan!$B$6:$B$1505,"Order",T_Penjualan!$A$6:$A$1505,">="&I_Parameter!$C$4),IFERROR(INDEX(I_Master!$F$6:$F$85,MATCH("Trading|Usus|Fresh",I_Master!$A$6:$A$85,0)),0)) -> 14000 | G40: =IFERROR(INDEX(I_Master!$G$6:$G$85,MATCH("Trading|Usus|Fresh",I_Master!$A$6:$A$85,0)),"") -> 0 | H40: =IF(OR(G40="",G40=0,F40=0),"",F40-G40) | I40: =IF(H40="","",H40/F40) | J40: =IFERROR(INDEX(O_Stok!$Q$6:$Q$85,MATCH("Trading|Usus|Fresh",O_Stok!$A$6:$A$85,0)),0) -> 0 | K40: =IF(E40>0.5,IF(H40="","BELI "&FIXED(E40,0)&" kg — isi harga beli pengganti",IF(H40>=I_Parameter!$C$12,"BELI "&FIXED(E40,0)&" kg (spread "&FIXED(H40,0)&"/kg)","TAHAN: spread "&FIXED(H40,0)&"/kg di bawah minimum — naikkan harga jual atau cari pemasok")),IF(AND(B40>0.5,C40<=0.5),"JUAL STOK: "&FIXED(B40,0)&" kg tanpa order",IF(AND(C40>0.5,J40>0,F40<J40),"CEK HARGA: order "&FIXED(F40,0)&"/kg di bawah biaya stok "&FIXED(J40,0)&"/kg",IF(B40>0.5,"Cukup — sisa "&FIXED(B40-C40+D40,0)&" kg setelah order","-")))) -> -
A42: 4. STOK — yang harus dijual / dibeli (detail per SKU di sheet O_Stok kolom Z)
A43: Status | B43: Jumlah SKU | C43: kg hari ini | D43: Nilai Rp
A44: KURANG (stok minus di minggu ini) | B44: =COUNTIF(O_Stok!$Z$6:$Z$85,"KURANG*") -> 0 | C44: =SUMIFS(O_Stok!$S$6:$S$85,O_Stok!$Z$6:$Z$85,"KURANG*") -> 0 | D44: =SUMIFS(O_Stok!$Y$6:$Y$85,O_Stok!$Z$6:$Z$85,"KURANG*") -> 0
A45: JUAL (tanpa order minggu ini) | B45: =COUNTIF(O_Stok!$Z$6:$Z$85,"JUAL*") -> 23 | C45: =SUMIFS(O_Stok!$S$6:$S$85,O_Stok!$Z$6:$Z$85,"JUAL*") -> 17834.26 | D45: =SUMIFS(O_Stok!$Y$6:$Y$85,O_Stok!$Z$6:$Z$85,"JUAL*") -> 3.3331952e+08
A46: PERHATIAN (di atas batas umur) | B46: =COUNTIF(O_Stok!$Z$6:$Z$85,"PERHATIAN*") -> 7 | C46: =SUMIFS(O_Stok!$S$6:$S$85,O_Stok!$Z$6:$Z$85,"PERHATIAN*") -> 116289.84 | D46: =SUMIFS(O_Stok!$Y$6:$Y$85,O_Stok!$Z$6:$Z$85,"PERHATIAN*") -> 2.7821589e+09
A48: 5. KAS KELUAR — live bird dan pembelian trading (sesuai termin di I_Parameter)
A49: Tanggal | B49: Bayar live bird Rp | C49: Bayar pembelian trading Rp | D49: Total Rp | E49: Basis
A50: =I_Parameter!$C$5+0 -> 46258 | B50: =SUMIFS(T_Batch!$R$6:$R$55,T_Batch!$A$6:$A$55,A50-I_Parameter!$C$14) -> 0 | C50: =SUMIFS(T_Penerimaan!$K$6:$K$1005,T_Penerimaan!$C$6:$C$1005,"Beli Trading",T_Penerimaan!$A$6:$A$1005,A50-I_Parameter!$C$15,T_Penerimaan!$M$6:$M$1005,1) -> 0 | D50: =B50+C50 -> 0 | E50: =IF(A50<I_Parameter!$C$4,"aktual","rencana") -> aktual
A51: =I_Parameter!$C$5+1 -> 46259 | B51: =SUMIFS(T_Batch!$R$6:$R$55,T_Batch!$A$6:$A$55,A51-I_Parameter!$C$14) -> 0 | C51: =SUMIFS(T_Penerimaan!$K$6:$K$1005,T_Penerimaan!$C$6:$C$1005,"Beli Trading",T_Penerimaan!$A$6:$A$1005,A51-I_Parameter!$C$15,T_Penerimaan!$M$6:$M$1005,1) -> 0 | D51: =B51+C51 -> 0 | E51: =IF(A51<I_Parameter!$C$4,"aktual","rencana") -> aktual
A52: =I_Parameter!$C$5+2 -> 46260 | B52: =SUMIFS(T_Batch!$R$6:$R$55,T_Batch!$A$6:$A$55,A52-I_Parameter!$C$14) -> 0 | C52: =SUMIFS(T_Penerimaan!$K$6:$K$1005,T_Penerimaan!$C$6:$C$1005,"Beli Trading",T_Penerimaan!$A$6:$A$1005,A52-I_Parameter!$C$15,T_Penerimaan!$M$6:$M$1005,1) -> 0 | D52: =B52+C52 -> 0 | E52: =IF(A52<I_Parameter!$C$4,"aktual","rencana") -> aktual
A53: =I_Parameter!$C$5+3 -> 46261 | B53: =SUMIFS(T_Batch!$R$6:$R$55,T_Batch!$A$6:$A$55,A53-I_Parameter!$C$14) -> 0 | C53: =SUMIFS(T_Penerimaan!$K$6:$K$1005,T_Penerimaan!$C$6:$C$1005,"Beli Trading",T_Penerimaan!$A$6:$A$1005,A53-I_Parameter!$C$15,T_Penerimaan!$M$6:$M$1005,1) -> 0 | D53: =B53+C53 -> 0 | E53: =IF(A53<I_Parameter!$C$4,"aktual","rencana") -> rencana
A54: =I_Parameter!$C$5+4 -> 46262 | B54: =SUMIFS(T_Batch!$R$6:$R$55,T_Batch!$A$6:$A$55,A54-I_Parameter!$C$14) -> 0 | C54: =SUMIFS(T_Penerimaan!$K$6:$K$1005,T_Penerimaan!$C$6:$C$1005,"Beli Trading",T_Penerimaan!$A$6:$A$1005,A54-I_Parameter!$C$15,T_Penerimaan!$M$6:$M$1005,1) -> 0 | D54: =B54+C54 -> 0 | E54: =IF(A54<I_Parameter!$C$4,"aktual","rencana") -> rencana
A55: =I_Parameter!$C$5+5 -> 46263 | B55: =SUMIFS(T_Batch!$R$6:$R$55,T_Batch!$A$6:$A$55,A55-I_Parameter!$C$14) -> 0 | C55: =SUMIFS(T_Penerimaan!$K$6:$K$1005,T_Penerimaan!$C$6:$C$1005,"Beli Trading",T_Penerimaan!$A$6:$A$1005,A55-I_Parameter!$C$15,T_Penerimaan!$M$6:$M$1005,1) -> 0 | D55: =B55+C55 -> 0 | E55: =IF(A55<I_Parameter!$C$4,"aktual","rencana") -> rencana
A56: =I_Parameter!$C$5+6 -> 46264 | B56: =SUMIFS(T_Batch!$R$6:$R$55,T_Batch!$A$6:$A$55,A56-I_Parameter!$C$14) -> 0 | C56: =SUMIFS(T_Penerimaan!$K$6:$K$1005,T_Penerimaan!$C$6:$C$1005,"Beli Trading",T_Penerimaan!$A$6:$A$1005,A56-I_Parameter!$C$15,T_Penerimaan!$M$6:$M$1005,1) -> 0 | D56: =B56+C56 -> 0 | E56: =IF(A56<I_Parameter!$C$4,"aktual","rencana") -> rencana
A57: Total minggu | B57: =SUM(B50:B56) -> 0 | C57: =SUM(C50:C56) -> 0 | D57: =SUM(D50:D56) -> 0 | E57: Penerimaan kas dari pelanggan belum dimodelkan
A59: 6. BATCH RPA MINGGU INI — aktual vs rencana
A60: Status | B60: Jumlah batch | C60: kg LB | D60: Harga LB rata-rata | E60: Shrink | F60: Yield karkas ÷ diproses | G60: Karkas fresh % | H60: Margin batch Rp | I60: Margin per kg LB | J60: Biaya per kg output | K60: Nilai per kg output | L60: Breakeven LB Rp/kg
A61: Aktual | B61: =COUNTIFS(T_Batch!$B$6:$B$55,"Aktual",T_Batch!$A$6:$A$55,">="&I_Parameter!$C$5,T_Batch!$A$6:$A$55,"<="&I_Parameter!$C$6) -> 2 | C61: =SUMIFS(T_Batch!$E$6:$E$55,T_Batch!$B$6:$B$55,"Aktual",T_Batch!$A$6:$A$55,">="&I_Parameter!$C$5,T_Batch!$A$6:$A$55,"<="&I_Parameter!$C$6) -> 24301.2 | D61: =IF(C61=0,"",SUMIFS(T_Batch!$R$6:$R$55,T_Batch!$B$6:$B$55,"Aktual",T_Batch!$A$6:$A$55,">="&I_Parameter!$C$5,T_Batch!$A$6:$A$55,"<="&I_Parameter!$C$6)/C61) -> 23902.799 | E61: =IF(C61=0,"",1-SUMIFS(T_Batch!$I$6:$I$55,T_Batch!$B$6:$B$55,"Aktual",T_Batch!$A$6:$A$55,">="&I_Parameter!$C$5,T_Batch!$A$6:$A$55,"<="&I_Parameter!$C$6)/C61) -> 0.06308742 | F61: =IFERROR((SUMIFS(T_Batch!$J$6:$J$55,T_Batch!$B$6:$B$55,"Aktual",T_Batch!$A$6:$A$55,">="&I_Parameter!$C$5,T_Batch!$A$6:$A$55,"<="&I_Parameter!$C$6)+SUMIFS(T_Batch!$K$6:$K$55,T_Batch!$B$6:$B$55,"Aktual",T_Batch!$A$6:$A$55,">="&I_Parameter!$C$5,T_Batch!$A$6:$A$55,"<="&I_Parameter!$C$6))/SUMIFS(T_Batch!$I$6:$I$55,T_Batch!$B$6:$B$55,"Aktual",T_Batch!$A$6:$A$55,">="&I_Parameter!$C$5,T_Batch!$A$6:$A$55,"<="&I_Parameter!$C$6),"") -> 0.73762852 | G61: =IFERROR(SUMIFS(T_Batch!$J$6:$J$55,T_Batch!$B$6:$B$55,"Aktual",T_Batch!$A$6:$A$55,">="&I_Parameter!$C$5,T_Batch!$A$6:$A$55,"<="&I_Parameter!$C$6)/(SUMIFS(T_Batch!$J$6:$J$55,T_Batch!$B$6:$B$55,"Aktual",T_Batch!$A$6:$A$55,">="&I_Parameter!$C$5,T_Batch!$A$6:$A$55,"<="&I_Parameter!$C$6)+SUMIFS(T_Batch!$K$6:$K$55,T_Batch!$B$6:$B$55,"Aktual",T_Batch!$A$6:$A$55,">="&I_Parameter!$C$5,T_Batch!$A$6:$A$55,"<="&I_Parameter!$C$6)),"") -> 0.66635307 | H61: =SUMIFS(T_Batch!$Z$6:$Z$55,T_Batch!$B$6:$B$55,"Aktual",T_Batch!$A$6:$A$55,">="&I_Parameter!$C$5,T_Batch!$A$6:$A$55,"<="&I_Parameter!$C$6) -> -57435278 | I61: =IF(C61=0,"",H61/C61) -> -2363.475 | J61: =IFERROR(SUMIFS(T_Batch!$S$6:$S$55,T_Batch!$B$6:$B$55,"Aktual",T_Batch!$A$6:$A$55,">="&I_Parameter!$C$5,T_Batch!$A$6:$A$55,"<="&I_Parameter!$C$6)/SUMIFS(T_Batch!$U$6:$U$55,T_Batch!$B$6:$B$55,"Aktual",T_Batch!$A$6:$A$55,">="&I_Parameter!$C$5,T_Batch!$A$6:$A$55,"<="&I_Parameter!$C$6),"") -> 31859.71 | K61: =IFERROR(SUMIFS(T_Batch!$Y$6:$Y$55,T_Batch!$B$6:$B$55,"Aktual",T_Batch!$A$6:$A$55,">="&I_Parameter!$C$5,T_Batch!$A$6:$A$55,"<="&I_Parameter!$C$6)/SUMIFS(T_Batch!$U$6:$U$55,T_Batch!$B$6:$B$55,"Aktual",T_Batch!$A$6:$A$55,">="&I_Parameter!$C$5,T_Batch!$A$6:$A$55,"<="&I_Parameter!$C$6),"") -> 29088.419 | L61: =IF(C61=0,"",(SUMIFS(T_Batch!$Y$6:$Y$55,T_Batch!$B$6:$B$55,"Aktual",T_Batch!$A$6:$A$55,">="&I_Parameter!$C$5,T_Batch!$A$6:$A$55,"<="&I_Parameter!$C$6)-SUMIFS(T_Batch!$G$6:$G$55,T_Batch!$B$6:$B$55,"Aktual",T_Batch!$A$6:$A$55,">="&I_Parameter!$C$5,T_Batch!$A$6:$A$55,"<="&I_Parameter!$C$6)-SUMIFS(T_Batch!$H$6:$H$55,T_Batch!$B$6:$B$55,"Aktual",T_Batch!$A$6:$A$55,">="&I_Parameter!$C$5,T_Batch!$A$6:$A$55,"<="&I_Parameter!$C$6))/C61) -> 21539.324
A62: Rencana | B62: =COUNTIFS(T_Batch!$B$6:$B$55,"Rencana",T_Batch!$A$6:$A$55,">="&I_Parameter!$C$5,T_Batch!$A$6:$A$55,"<="&I_Parameter!$C$6) -> 2 | C62: =SUMIFS(T_Batch!$E$6:$E$55,T_Batch!$B$6:$B$55,"Rencana",T_Batch!$A$6:$A$55,">="&I_Parameter!$C$5,T_Batch!$A$6:$A$55,"<="&I_Parameter!$C$6) -> 27218.6 | D62: =IF(C62=0,"",SUMIFS(T_Batch!$R$6:$R$55,T_Batch!$B$6:$B$55,"Rencana",T_Batch!$A$6:$A$55,">="&I_Parameter!$C$5,T_Batch!$A$6:$A$55,"<="&I_Parameter!$C$6)/C62) -> 25063.537 | E62: =IF(C62=0,"",1-SUMIFS(T_Batch!$I$6:$I$55,T_Batch!$B$6:$B$55,"Rencana",T_Batch!$A$6:$A$55,">="&I_Parameter!$C$5,T_Batch!$A$6:$A$55,"<="&I_Parameter!$C$6)/C62) -> 0.059418927 | F62: =IFERROR((SUMIFS(T_Batch!$J$6:$J$55,T_Batch!$B$6:$B$55,"Rencana",T_Batch!$A$6:$A$55,">="&I_Parameter!$C$5,T_Batch!$A$6:$A$55,"<="&I_Parameter!$C$6)+SUMIFS(T_Batch!$K$6:$K$55,T_Batch!$B$6:$B$55,"Rencana",T_Batch!$A$6:$A$55,">="&I_Parameter!$C$5,T_Batch!$A$6:$A$55,"<="&I_Parameter!$C$6))/SUMIFS(T_Batch!$I$6:$I$55,T_Batch!$B$6:$B$55,"Rencana",T_Batch!$A$6:$A$55,">="&I_Parameter!$C$5,T_Batch!$A$6:$A$55,"<="&I_Parameter!$C$6),"") -> 0.7442708 | G62: =IFERROR(SUMIFS(T_Batch!$J$6:$J$55,T_Batch!$B$6:$B$55,"Rencana",T_Batch!$A$6:$A$55,">="&I_Parameter!$C$5,T_Batch!$A$6:$A$55,"<="&I_Parameter!$C$6)/(SUMIFS(T_Batch!$J$6:$J$55,T_Batch!$B$6:$B$55,"Rencana",T_Batch!$A$6:$A$55,">="&I_Parameter!$C$5,T_Batch!$A$6:$A$55,"<="&I_Parameter!$C$6)+SUMIFS(T_Batch!$K$6:$K$55,T_Batch!$B$6:$B$55,"Rencana",T_Batch!$A$6:$A$55,">="&I_Parameter!$C$5,T_Batch!$A$6:$A$55,"<="&I_Parameter!$C$6)),"") -> 0.53021628 | H62: =SUMIFS(T_Batch!$Z$6:$Z$55,T_Batch!$B$6:$B$55,"Rencana",T_Batch!$A$6:$A$55,">="&I_Parameter!$C$5,T_Batch!$A$6:$A$55,"<="&I_Parameter!$C$6) -> -81242185 | I62: =IF(C62=0,"",H62/C62) -> -2984.804 | J62: =IFERROR(SUMIFS(T_Batch!$S$6:$S$55,T_Batch!$B$6:$B$55,"Rencana",T_Batch!$A$6:$A$55,">="&I_Parameter!$C$5,T_Batch!$A$6:$A$55,"<="&I_Parameter!$C$6)/SUMIFS(T_Batch!$U$6:$U$55,T_Batch!$B$6:$B$55,"Rencana",T_Batch!$A$6:$A$55,">="&I_Parameter!$C$5,T_Batch!$A$6:$A$55,"<="&I_Parameter!$C$6),"") -> 31875.83 | K62: =IFERROR(SUMIFS(T_Batch!$Y$6:$Y$55,T_Batch!$B$6:$B$55,"Rencana",T_Batch!$A$6:$A$55,">="&I_Parameter!$C$5,T_Batch!$A$6:$A$55,"<="&I_Parameter!$C$6)/SUMIFS(T_Batch!$U$6:$U$55,T_Batch!$B$6:$B$55,"Rencana",T_Batch!$A$6:$A$55,">="&I_Parameter!$C$5,T_Batch!$A$6:$A$55,"<="&I_Parameter!$C$6),"") -> 28434.677 | L62: =IF(C62=0,"",(SUMIFS(T_Batch!$Y$6:$Y$55,T_Batch!$B$6:$B$55,"Rencana",T_Batch!$A$6:$A$55,">="&I_Parameter!$C$5,T_Batch!$A$6:$A$55,"<="&I_Parameter!$C$6)-SUMIFS(T_Batch!$G$6:$G$55,T_Batch!$B$6:$B$55,"Rencana",T_Batch!$A$6:$A$55,">="&I_Parameter!$C$5,T_Batch!$A$6:$A$55,"<="&I_Parameter!$C$6)-SUMIFS(T_Batch!$H$6:$H$55,T_Batch!$B$6:$B$55,"Rencana",T_Batch!$A$6:$A$55,">="&I_Parameter!$C$5,T_Batch!$A$6:$A$55,"<="&I_Parameter!$C$6))/C62) -> 22078.733
A63: Target / benchmark | E63: =I_Parameter!$C$8 -> 0.03 | F63: =I_Parameter!D19 -> 0.7367 | L63: =B22 -> 24336.784
A65: 7. PERINGATAN
A66: =IF(COUNTIFS(T_Penjualan!$B$6:$B$1505,"Order",T_Penjualan!$A$6:$A$1505,"<"&I_Parameter!$C$4,T_Penjualan!$H$6:$H$1505,">0")>0,COUNTIFS(T_Penjualan!$B$6:$B$1505,"Order",T_Penjualan!$A$6:$A$1505,"<"&I_Parameter!$C$4,T_Penjualan!$H$6:$H$1505,">0")&" baris order sudah lewat tanggal tapi belum terkirim — ubah jadi Aktual atau geser tanggal","")
A67: =IF(COUNTIF(T_Penjualan!$G$6:$G$1505,"KODE BARU")+COUNTIF(T_Penerimaan!$H$6:$H$1005,"KODE BARU")+COUNTIF(I_Stok_Awal!$C$6:$C$305,"KODE BARU")>0,"Ada kode item baru — tambahkan ke I_Item","")
A68: =IF(COUNTIF(O_Stok!$V$6:$V$85,"<-0.5")>0,COUNTIF(O_Stok!$V$6:$V$85,"<-0.5")&" SKU diproyeksikan stok minus — lihat O_Stok","")
A69: =IF(SUMPRODUCT((O_Stok!$S$6:$S$85>0.5)*((O_Stok!$W$6:$W$85="")+(O_Stok!$W$6:$W$85=0)))>0,"Harga acuan kosong untuk SKU yang masih ada stok — isi di I_Master","") -> Harga acuan kosong untuk SKU yang masih ada stok — isi di I_Master
A70: =IF(AND(B61>0,E61<>"",E61>I_Parameter!$C$8),"Shrink aktual minggu ini "&FIXED(E61*100,1)&"% di atas target "&FIXED(I_Parameter!$C$8*100,1)&"%","") -> Shrink aktual minggu ini 6.3% di atas target 3.0%
A71: =IF(B12>B22,"Harga LB hari ini di atas breakeven 100% fresh","") -> Harga LB hari ini di atas breakeven 100% fresh
A72: =IF(COUNTIF(K30:K40,"TAHAN*")>0,COUNTIF(K30:K40,"TAHAN*")&" SKU trading butuh stok tapi spread di bawah minimum","")
A74: 8. LAPORAN KEUANGAN MINGGU INI — ringkasan (detail di O_PnL, O_BS, O_CF)
A75: Indikator | B75: Minggu lalu | C75: Proyeksi minggu ini | D75: Δ
A76: Revenue | B76: =O_PnL!B9 -> 1572306370 | C76: =O_PnL!E9 -> 1.6567983e+09 | D76: =C76-B76 -> 84491960
A77: Gross profit | B77: =O_PnL!B15 -> -4182480.4 | C77: =O_PnL!E15 -> -67528109 | D77: =C77-B77 -> -63345629
A78: Total operating expenses (excl. D&A) | B78: =O_PnL!B29 -> -106792694 | C78: =O_PnL!E29 -> -38907587 | D78: =C78-B78 -> 67885107
A79: NIBT (before D&A) | B79: =O_PnL!B35 -> -1.1096777e+08 | C79: =O_PnL!E35 -> -1.0623504e+08 | D79: =C79-B79 -> 4732728.7
A80: Net income | B80: =O_PnL!B37 -> -1.1096777e+08 | C80: =O_PnL!E37 -> -1.0757613e+08 | D80: =C80-B80 -> 3391637
A81: Saldo kas akhir minggu | B81: =O_CF!B22 -> 3.7909117e+08 | C81: =O_CF!E22 -> 8.1819823e+08 | D81: =C81-B81 -> 439107064
A82: Piutang usaha (pihak ketiga) | B82: =O_BS!C8 -> 637472980 | C82: =O_BS!E8 -> 6.2518396e+08 | D82: =C82-B82 -> -12289018
A83: Persediaan (produk + trading) | B83: =O_BS!C13+O_BS!C14 -> 3.7806064e+09 | C83: =O_BS!E13+O_BS!E14 -> 3.992408e+09 | D83: =C83-B83 -> 2.1180163e+08
A84: Utang usaha + biaya masih harus dibayar | B84: =O_BS!C23+O_BS!C27 -> -6.6552995e+08 | C84: =O_BS!E23+O_BS!E27 -> 1.4347283e+08 | D84: =C84-B84 -> 8.0900278e+08
A85: Utang afiliasi (pinjaman + utang dagang afiliasi) | B85: =O_BS!C26+O_BS!C24 -> 4400000000 | C85: =O_BS!E26+O_BS!E24 -> 5238800000 | D85: =C85-B85 -> 838800000
A86: Saldo kas terendah minggu ini (harian) | C86: =O_CF!C35 -> 2.8967211e+08

Sheet O_PnL
A1: LABA RUGI MINGGUAN (format P&L deck) — Rp
A2: Aktual = jurnal Accurate (T_GL). Sisa minggu = order × harga (revenue), order × biaya rata-rata stok (COGS), run-rate untuk biaya lain. Biaya ditampilkan negatif.
A5: Baris | B5: Minggu lalu (aktual) | C5: Minggu ini aktual s.d. kemarin | D5: Sisa minggu (outlook) | E5: Proyeksi minggu ini | F5: Δ vs minggu lalu | G5: Bulan berjalan aktual (MTD) | H5: MTD + sisa minggu | I5: Basis sisa minggu
A6: Revenue - LB Main Product | B6: =-SUMIFS(T_GL!$J$6:$J$4005,T_GL!$L$6:$L$4005,"Revenue - LB Main Product",T_GL!$A$6:$A$4005,">="&(I_Parameter!$C$5-7),T_GL!$A$6:$A$4005,"<="&(I_Parameter!$C$5-1)) -> 687779970 | C6: =-SUMIFS(T_GL!$J$6:$J$4005,T_GL!$L$6:$L$4005,"Revenue - LB Main Product",T_GL!$A$6:$A$4005,">="&I_Parameter!$C$5,T_GL!$A$6:$A$4005,"<="&(I_Parameter!$C$4-1)) -> 342934170 | D6: =SUMIFS(T_Penjualan!$J$6:$J$1505,T_Penjualan!$N$6:$N$1505,"RPA",T_Penjualan!$O$6:$O$1505,"<>By-product",T_Penjualan!$B$6:$B$1505,"Order",T_Penjualan!$P$6:$P$1505,1) -> 6.0992013e+08 | E6: =C6+D6 -> 9.528543e+08 | F6: =E6-B6 -> 2.6507433e+08 | G6: =-SUMIFS(T_GL!$J$6:$J$4005,T_GL!$L$6:$L$4005,"Revenue - LB Main Product",T_GL!$A$6:$A$4005,">="&DATE(YEAR(I_Parameter!$C$4),MONTH(I_Parameter!$C$4),1),T_GL!$A$6:$A$4005,"<="&(I_Parameter!$C$4-1)) -> 1808448555 | H6: =G6+D6 -> 2.4183687e+09 | I6: order RPA (non by-product) × harga
A7: Revenue - LB By Product | B7: =-SUMIFS(T_GL!$J$6:$J$4005,T_GL!$L$6:$L$4005,"Revenue - LB By Product",T_GL!$A$6:$A$4005,">="&(I_Parameter!$C$5-7),T_GL!$A$6:$A$4005,"<="&(I_Parameter!$C$5-1)) -> 22934700 | C7: =-SUMIFS(T_GL!$J$6:$J$4005,T_GL!$L$6:$L$4005,"Revenue - LB By Product",T_GL!$A$6:$A$4005,">="&I_Parameter!$C$5,T_GL!$A$6:$A$4005,"<="&(I_Parameter!$C$4-1)) -> 6237550 | D7: =SUMIFS(T_Penjualan!$J$6:$J$1505,T_Penjualan!$N$6:$N$1505,"RPA",T_Penjualan!$O$6:$O$1505,"By-product",T_Penjualan!$B$6:$B$1505,"Order",T_Penjualan!$P$6:$P$1505,1) -> 21693061 | E7: =C7+D7 -> 27930611 | F7: =E7-B7 -> 4995910.9 | G7: =-SUMIFS(T_GL!$J$6:$J$4005,T_GL!$L$6:$L$4005,"Revenue - LB By Product",T_GL!$A$6:$A$4005,">="&DATE(YEAR(I_Parameter!$C$4),MONTH(I_Parameter!$C$4),1),T_GL!$A$6:$A$4005,"<="&(I_Parameter!$C$4-1)) -> 44484650 | H7: =G7+D7 -> 66177711 | I7: order by-product × harga
A8: Revenue - Trading | B8: =-SUMIFS(T_GL!$J$6:$J$4005,T_GL!$L$6:$L$4005,"Revenue - Trading",T_GL!$A$6:$A$4005,">="&(I_Parameter!$C$5-7),T_GL!$A$6:$A$4005,"<="&(I_Parameter!$C$5-1)) -> 861591700 | C8: =-SUMIFS(T_GL!$J$6:$J$4005,T_GL!$L$6:$L$4005,"Revenue - Trading",T_GL!$A$6:$A$4005,">="&I_Parameter!$C$5,T_GL!$A$6:$A$4005,"<="&(I_Parameter!$C$4-1)) -> 239801150 | D8: =SUMIFS(T_Penjualan!$J$6:$J$1505,T_Penjualan!$N$6:$N$1505,"Trading",T_Penjualan!$B$6:$B$1505,"Order",T_Penjualan!$P$6:$P$1505,1) -> 4.3621227e+08 | E8: =C8+D8 -> 6.7601342e+08 | F8: =E8-B8 -> -1.8557828e+08 | G8: =-SUMIFS(T_GL!$J$6:$J$4005,T_GL!$L$6:$L$4005,"Revenue - Trading",T_GL!$A$6:$A$4005,">="&DATE(YEAR(I_Parameter!$C$4),MONTH(I_Parameter!$C$4),1),T_GL!$A$6:$A$4005,"<="&(I_Parameter!$C$4-1)) -> 4532942834 | H8: =G8+D8 -> 4.9691551e+09 | I8: order Trading × harga
A9: TOTAL REVENUE | B9: =SUM(B6:B8) -> 1572306370 | C9: =SUM(C6:C8) -> 588972870 | D9: =SUM(D6:D8) -> 1.0678255e+09 | E9: =SUM(E6:E8) -> 1.6567983e+09 | F9: =SUM(F6:F8) -> 84491960 | G9: =SUM(G6:G8) -> 6385876039 | H9: =SUM(H6:H8) -> 7.4537015e+09
A10: COGS - Live Bird | B10: =-SUMIFS(T_GL!$J$6:$J$4005,T_GL!$L$6:$L$4005,"COGS - Live Bird",T_GL!$A$6:$A$4005,">="&(I_Parameter!$C$5-7),T_GL!$A$6:$A$4005,"<="&(I_Parameter!$C$5-1)) -> -7.1068474e+08 | C10: =-SUMIFS(T_GL!$J$6:$J$4005,T_GL!$L$6:$L$4005,"COGS - Live Bird",T_GL!$A$6:$A$4005,">="&I_Parameter!$C$5,T_GL!$A$6:$A$4005,"<="&(I_Parameter!$C$4-1)) -> -3.5421495e+08 | D10: =-SUMIFS(T_Penjualan!$L$6:$L$1505,T_Penjualan!$N$6:$N$1505,"RPA",T_Penjualan!$B$6:$B$1505,"Order",T_Penjualan!$P$6:$P$1505,1) -> -6.8390599e+08 | E10: =C10+D10 -> -1.0381209e+09 | F10: =E10-B10 -> -3.2743621e+08 | G10: =-SUMIFS(T_GL!$J$6:$J$4005,T_GL!$L$6:$L$4005,"COGS - Live Bird",T_GL!$A$6:$A$4005,">="&DATE(YEAR(I_Parameter!$C$4),MONTH(I_Parameter!$C$4),1),T_GL!$A$6:$A$4005,"<="&(I_Parameter!$C$4-1)) -> -1.8551981e+09 | H10: =G10+D10 -> -2.5391041e+09 | I10: order × biaya rata-rata stok RPA
A11: COGS - Trading | B11: =-SUMIFS(T_GL!$J$6:$J$4005,T_GL!$L$6:$L$4005,"COGS - Trading",T_GL!$A$6:$A$4005,">="&(I_Parameter!$C$5-7),T_GL!$A$6:$A$4005,"<="&(I_Parameter!$C$5-1)) -> -8.2594611e+08 | C11: =-SUMIFS(T_GL!$J$6:$J$4005,T_GL!$L$6:$L$4005,"COGS - Trading",T_GL!$A$6:$A$4005,">="&I_Parameter!$C$5,T_GL!$A$6:$A$4005,"<="&(I_Parameter!$C$4-1)) -> -2.1278991e+08 | D11: =-SUMIFS(T_Penjualan!$L$6:$L$1505,T_Penjualan!$N$6:$N$1505,"Trading",T_Penjualan!$B$6:$B$1505,"Order",T_Penjualan!$P$6:$P$1505,1) -> -4.3645682e+08 | E11: =C11+D11 -> -6.4924674e+08 | F11: =E11-B11 -> 1.7669937e+08 | G11: =-SUMIFS(T_GL!$J$6:$J$4005,T_GL!$L$6:$L$4005,"COGS - Trading",T_GL!$A$6:$A$4005,">="&DATE(YEAR(I_Parameter!$C$4),MONTH(I_Parameter!$C$4),1),T_GL!$A$6:$A$4005,"<="&(I_Parameter!$C$4-1)) -> -4.083272e+09 | H11: =G11+D11 -> -4.5197288e+09 | I11: order × biaya rata-rata stok Trading
A12: Other COGS - Expedition | B12: =-SUMIFS(T_GL!$J$6:$J$4005,T_GL!$L$6:$L$4005,"Other COGS - Expedition",T_GL!$A$6:$A$4005,">="&(I_Parameter!$C$5-7),T_GL!$A$6:$A$4005,"<="&(I_Parameter!$C$5-1)) -> -29000000 | C12: =-SUMIFS(T_GL!$J$6:$J$4005,T_GL!$L$6:$L$4005,"Other COGS - Expedition",T_GL!$A$6:$A$4005,">="&I_Parameter!$C$5,T_GL!$A$6:$A$4005,"<="&(I_Parameter!$C$4-1)) -> -17000000 | D12: =-(I_RunRate!$B$6*((I_Parameter!$C$6-I_Parameter!$C$4+1)/DAY(EOMONTH(I_Parameter!$C$4,0)))+I_RunRate!$C$6) -> -3592975.2 | E12: =C12+D12 -> -20592975 | F12: =E12-B12 -> 8407024.8 | G12: =-SUMIFS(T_GL!$J$6:$J$4005,T_GL!$L$6:$L$4005,"Other COGS - Expedition",T_GL!$A$6:$A$4005,">="&DATE(YEAR(I_Parameter!$C$4),MONTH(I_Parameter!$C$4),1),T_GL!$A$6:$A$4005,"<="&(I_Parameter!$C$4-1)) -> -76800000 | H12: =G12+D12 -> -80392975 | I12: run-rate (I_RunRate)
A13: COGS - Blasting | B13: =-SUMIFS(T_GL!$J$6:$J$4005,T_GL!$L$6:$L$4005,"COGS - Blasting",T_GL!$A$6:$A$4005,">="&(I_Parameter!$C$5-7),T_GL!$A$6:$A$4005,"<="&(I_Parameter!$C$5-1)) -> -10858005 | C13: =-SUMIFS(T_GL!$J$6:$J$4005,T_GL!$L$6:$L$4005,"COGS - Blasting",T_GL!$A$6:$A$4005,">="&I_Parameter!$C$5,T_GL!$A$6:$A$4005,"<="&(I_Parameter!$C$4-1)) -> -4525920 | D13: =-(I_RunRate!$B$7*((I_Parameter!$C$6-I_Parameter!$C$4+1)/DAY(EOMONTH(I_Parameter!$C$4,0)))+I_RunRate!$C$7) -> -11839861 | E13: =C13+D13 -> -16365781 | F13: =E13-B13 -> -5507775.6 | G13: =-SUMIFS(T_GL!$J$6:$J$4005,T_GL!$L$6:$L$4005,"COGS - Blasting",T_GL!$A$6:$A$4005,">="&DATE(YEAR(I_Parameter!$C$4),MONTH(I_Parameter!$C$4),1),T_GL!$A$6:$A$4005,"<="&(I_Parameter!$C$4-1)) -> -23202730 | H13: =G13+D13 -> -35042591 | I13: run-rate (I_RunRate)
A14: TOTAL COST OF SALES | B14: =SUM(B10:B13) -> -1.5764889e+09 | C14: =SUM(C10:C13) -> -5.8853079e+08 | D14: =SUM(D10:D13) -> -1.1357957e+09 | E14: =SUM(E10:E13) -> -1.7243264e+09 | F14: =SUM(F10:F13) -> -1.4783759e+08 | G14: =SUM(G10:G13) -> -6.0384728e+09 | H14: =SUM(H10:H13) -> -7.1742684e+09
A15: GROSS PROFIT | B15: =B9+B14 -> -4182480.4 | C15: =C9+C14 -> 442084.15 | D15: =D9+D14 -> -67970193 | E15: =E9+E14 -> -67528109 | F15: =F9+F14 -> -63345629 | G15: =G9+G14 -> 3.4740325e+08 | H15: =H9+H14 -> 2.7943306e+08
A16: GP margin | B16: =IF(B9=0,0,B15/B9) -> -0.0026600925 | C16: =IF(C9=0,0,C15/C9) -> 0.00075060189 | D16: =IF(D9=0,0,D15/D9) -> -0.063652906 | E16: =IF(E9=0,0,E15/E9) -> -0.040758195 | F16: =IF(F9=0,0,F15/F9) -> -0.74972374 | G16: =IF(G9=0,0,G15/G9) -> 0.054401816 | H16: =IF(H9=0,0,H15/H9) -> 0.037489167
A17: Delivery Expenses | B17: =-SUMIFS(T_GL!$J$6:$J$4005,T_GL!$L$6:$L$4005,"Delivery Expenses",T_GL!$A$6:$A$4005,">="&(I_Parameter!$C$5-7),T_GL!$A$6:$A$4005,"<="&(I_Parameter!$C$5-1)) -> -10976006 | C17: =-SUMIFS(T_GL!$J$6:$J$4005,T_GL!$L$6:$L$4005,"Delivery Expenses",T_GL!$A$6:$A$4005,">="&I_Parameter!$C$5,T_GL!$A$6:$A$4005,"<="&(I_Parameter!$C$4-1)) -> -1400000 | D17: =-(I_RunRate!$B$8*((I_Parameter!$C$6-I_Parameter!$C$4+1)/DAY(EOMONTH(I_Parameter!$C$4,0)))+I_RunRate!$C$8) -> -1987096.8 | E17: =C17+D17 -> -3387096.8 | F17: =E17-B17 -> 7588909.2 | G17: =-SUMIFS(T_GL!$J$6:$J$4005,T_GL!$L$6:$L$4005,"Delivery Expenses",T_GL!$A$6:$A$4005,">="&DATE(YEAR(I_Parameter!$C$4),MONTH(I_Parameter!$C$4),1),T_GL!$A$6:$A$4005,"<="&(I_Parameter!$C$4-1)) -> -38821994 | H17: =G17+D17 -> -40809091 | I17: run-rate (I_RunRate)
A18: Commission Expenses | B18: =-SUMIFS(T_GL!$J$6:$J$4005,T_GL!$L$6:$L$4005,"Commission Expenses",T_GL!$A$6:$A$4005,">="&(I_Parameter!$C$5-7),T_GL!$A$6:$A$4005,"<="&(I_Parameter!$C$5-1)) -> 0 | C18: =-SUMIFS(T_GL!$J$6:$J$4005,T_GL!$L$6:$L$4005,"Commission Expenses",T_GL!$A$6:$A$4005,">="&I_Parameter!$C$5,T_GL!$A$6:$A$4005,"<="&(I_Parameter!$C$4-1)) -> 0 | D18: =-(I_RunRate!$B$9*((I_Parameter!$C$6-I_Parameter!$C$4+1)/DAY(EOMONTH(I_Parameter!$C$4,0)))+I_RunRate!$C$9) -> -467040.77 | E18: =C18+D18 -> -467040.77 | F18: =E18-B18 -> -467040.77 | G18: =-SUMIFS(T_GL!$J$6:$J$4005,T_GL!$L$6:$L$4005,"Commission Expenses",T_GL!$A$6:$A$4005,">="&DATE(YEAR(I_Parameter!$C$4),MONTH(I_Parameter!$C$4),1),T_GL!$A$6:$A$4005,"<="&(I_Parameter!$C$4-1)) -> -962000 | H18: =G18+D18 -> -1429040.8 | I18: run-rate (I_RunRate)
A19: Packaging | B19: =-SUMIFS(T_GL!$J$6:$J$4005,T_GL!$L$6:$L$4005,"Packaging",T_GL!$A$6:$A$4005,">="&(I_Parameter!$C$5-7),T_GL!$A$6:$A$4005,"<="&(I_Parameter!$C$5-1)) -> -742255 | C19: =-SUMIFS(T_GL!$J$6:$J$4005,T_GL!$L$6:$L$4005,"Packaging",T_GL!$A$6:$A$4005,">="&I_Parameter!$C$5,T_GL!$A$6:$A$4005,"<="&(I_Parameter!$C$4-1)) -> 0 | D19: =-(I_RunRate!$B$10*((I_Parameter!$C$6-I_Parameter!$C$4+1)/DAY(EOMONTH(I_Parameter!$C$4,0)))+I_RunRate!$C$10) -> -5021905.3 | E19: =C19+D19 -> -5021905.3 | F19: =E19-B19 -> -4279650.3 | G19: =-SUMIFS(T_GL!$J$6:$J$4005,T_GL!$L$6:$L$4005,"Packaging",T_GL!$A$6:$A$4005,">="&DATE(YEAR(I_Parameter!$C$4),MONTH(I_Parameter!$C$4),1),T_GL!$A$6:$A$4005,"<="&(I_Parameter!$C$4-1)) -> -11226650 | H19: =G19+D19 -> -16248555 | I19: run-rate (I_RunRate)
A20: Salaries and allowance | B20: =-SUMIFS(T_GL!$J$6:$J$4005,T_GL!$L$6:$L$4005,"Salaries and allowance",T_GL!$A$6:$A$4005,">="&(I_Parameter!$C$5-7),T_GL!$A$6:$A$4005,"<="&(I_Parameter!$C$5-1)) -> 0 | C20: =-SUMIFS(T_GL!$J$6:$J$4005,T_GL!$L$6:$L$4005,"Salaries and allowance",T_GL!$A$6:$A$4005,">="&I_Parameter!$C$5,T_GL!$A$6:$A$4005,"<="&(I_Parameter!$C$4-1)) -> 0 | D20: =-(I_RunRate!$B$11*((I_Parameter!$C$6-I_Parameter!$C$4+1)/DAY(EOMONTH(I_Parameter!$C$4,0)))+I_RunRate!$C$11) -> -6733725 | E20: =C20+D20 -> -6733725 | F20: =E20-B20 -> -6733725 | G20: =-SUMIFS(T_GL!$J$6:$J$4005,T_GL!$L$6:$L$4005,"Salaries and allowance",T_GL!$A$6:$A$4005,">="&DATE(YEAR(I_Parameter!$C$4),MONTH(I_Parameter!$C$4),1),T_GL!$A$6:$A$4005,"<="&(I_Parameter!$C$4-1)) -> 0 | H20: =G20+D20 -> -6733725 | I20: run-rate (I_RunRate)
A21: Storage Expenses | B21: =-SUMIFS(T_GL!$J$6:$J$4005,T_GL!$L$6:$L$4005,"Storage Expenses",T_GL!$A$6:$A$4005,">="&(I_Parameter!$C$5-7),T_GL!$A$6:$A$4005,"<="&(I_Parameter!$C$5-1)) -> -81094312 | C21: =-SUMIFS(T_GL!$J$6:$J$4005,T_GL!$L$6:$L$4005,"Storage Expenses",T_GL!$A$6:$A$4005,">="&I_Parameter!$C$5,T_GL!$A$6:$A$4005,"<="&(I_Parameter!$C$4-1)) -> 0 | D21: =-(I_RunRate!$B$12*((I_Parameter!$C$6-I_Parameter!$C$4+1)/DAY(EOMONTH(I_Parameter!$C$4,0)))+I_RunRate!$C$12) -> -10620868 | E21: =C21+D21 -> -10620868 | F21: =E21-B21 -> 70473444 | G21: =-SUMIFS(T_GL!$J$6:$J$4005,T_GL!$L$6:$L$4005,"Storage Expenses",T_GL!$A$6:$A$4005,">="&DATE(YEAR(I_Parameter!$C$4),MONTH(I_Parameter!$C$4),1),T_GL!$A$6:$A$4005,"<="&(I_Parameter!$C$4-1)) -> -89014384 | H21: =G21+D21 -> -99635252 | I21: run-rate (I_RunRate)
A22: Office Transportation expenses | B22: =-SUMIFS(T_GL!$J$6:$J$4005,T_GL!$L$6:$L$4005,"Office Transportation expenses",T_GL!$A$6:$A$4005,">="&(I_Parameter!$C$5-7),T_GL!$A$6:$A$4005,"<="&(I_Parameter!$C$5-1)) -> -7012864 | C22: =-SUMIFS(T_GL!$J$6:$J$4005,T_GL!$L$6:$L$4005,"Office Transportation expenses",T_GL!$A$6:$A$4005,">="&I_Parameter!$C$5,T_GL!$A$6:$A$4005,"<="&(I_Parameter!$C$4-1)) -> 0 | D22: =-(I_RunRate!$B$13*((I_Parameter!$C$6-I_Parameter!$C$4+1)/DAY(EOMONTH(I_Parameter!$C$4,0)))+I_RunRate!$C$13) -> -2433327 | E22: =C22+D22 -> -2433327 | F22: =E22-B22 -> 4579537 | G22: =-SUMIFS(T_GL!$J$6:$J$4005,T_GL!$L$6:$L$4005,"Office Transportation expenses",T_GL!$A$6:$A$4005,">="&DATE(YEAR(I_Parameter!$C$4),MONTH(I_Parameter!$C$4),1),T_GL!$A$6:$A$4005,"<="&(I_Parameter!$C$4-1)) -> -23102127 | H22: =G22+D22 -> -25535454 | I22: run-rate (I_RunRate)
A23: Rent Expenses | B23: =-SUMIFS(T_GL!$J$6:$J$4005,T_GL!$L$6:$L$4005,"Rent Expenses",T_GL!$A$6:$A$4005,">="&(I_Parameter!$C$5-7),T_GL!$A$6:$A$4005,"<="&(I_Parameter!$C$5-1)) -> 0 | C23: =-SUMIFS(T_GL!$J$6:$J$4005,T_GL!$L$6:$L$4005,"Rent Expenses",T_GL!$A$6:$A$4005,">="&I_Parameter!$C$5,T_GL!$A$6:$A$4005,"<="&(I_Parameter!$C$4-1)) -> 0 | D23: =-(I_RunRate!$B$14*((I_Parameter!$C$6-I_Parameter!$C$4+1)/DAY(EOMONTH(I_Parameter!$C$4,0)))+I_RunRate!$C$14) -> -424196.9 | E23: =C23+D23 -> -424196.9 | F23: =E23-B23 -> -424196.9 | G23: =-SUMIFS(T_GL!$J$6:$J$4005,T_GL!$L$6:$L$4005,"Rent Expenses",T_GL!$A$6:$A$4005,">="&DATE(YEAR(I_Parameter!$C$4),MONTH(I_Parameter!$C$4),1),T_GL!$A$6:$A$4005,"<="&(I_Parameter!$C$4-1)) -> 0 | H23: =G23+D23 -> -424196.9 | I23: run-rate (I_RunRate)
A24: Professional Fee | B24: =-SUMIFS(T_GL!$J$6:$J$4005,T_GL!$L$6:$L$4005,"Professional Fee",T_GL!$A$6:$A$4005,">="&(I_Parameter!$C$5-7),T_GL!$A$6:$A$4005,"<="&(I_Parameter!$C$5-1)) -> -2564102 | C24: =-SUMIFS(T_GL!$J$6:$J$4005,T_GL!$L$6:$L$4005,"Professional Fee",T_GL!$A$6:$A$4005,">="&I_Parameter!$C$5,T_GL!$A$6:$A$4005,"<="&(I_Parameter!$C$4-1)) -> -7692308 | D24: =-(I_RunRate!$B$15*((I_Parameter!$C$6-I_Parameter!$C$4+1)/DAY(EOMONTH(I_Parameter!$C$4,0)))+I_RunRate!$C$15) -> 0 | E24: =C24+D24 -> -7692308 | F24: =E24-B24 -> -5128206 | G24: =-SUMIFS(T_GL!$J$6:$J$4005,T_GL!$L$6:$L$4005,"Professional Fee",T_GL!$A$6:$A$4005,">="&DATE(YEAR(I_Parameter!$C$4),MONTH(I_Parameter!$C$4),1),T_GL!$A$6:$A$4005,"<="&(I_Parameter!$C$4-1)) -> -10256410 | H24: =G24+D24 -> -10256410 | I24: run-rate (I_RunRate)
A25: Office Supplies & Utilities | B25: =-SUMIFS(T_GL!$J$6:$J$4005,T_GL!$L$6:$L$4005,"Office Supplies & Utilities",T_GL!$A$6:$A$4005,">="&(I_Parameter!$C$5-7),T_GL!$A$6:$A$4005,"<="&(I_Parameter!$C$5-1)) -> -3034793 | C25: =-SUMIFS(T_GL!$J$6:$J$4005,T_GL!$L$6:$L$4005,"Office Supplies & Utilities",T_GL!$A$6:$A$4005,">="&I_Parameter!$C$5,T_GL!$A$6:$A$4005,"<="&(I_Parameter!$C$4-1)) -> 0 | D25: =-(I_RunRate!$B$16*((I_Parameter!$C$6-I_Parameter!$C$4+1)/DAY(EOMONTH(I_Parameter!$C$4,0)))+I_RunRate!$C$16) -> -805045.16 | E25: =C25+D25 -> -805045.16 | F25: =E25-B25 -> 2229747.8 | G25: =-SUMIFS(T_GL!$J$6:$J$4005,T_GL!$L$6:$L$4005,"Office Supplies & Utilities",T_GL!$A$6:$A$4005,">="&DATE(YEAR(I_Parameter!$C$4),MONTH(I_Parameter!$C$4),1),T_GL!$A$6:$A$4005,"<="&(I_Parameter!$C$4-1)) -> -5508133 | H25: =G25+D25 -> -6313178.2 | I25: run-rate (I_RunRate)
A26: Maintenance Expenses | B26: =-SUMIFS(T_GL!$J$6:$J$4005,T_GL!$L$6:$L$4005,"Maintenance Expenses",T_GL!$A$6:$A$4005,">="&(I_Parameter!$C$5-7),T_GL!$A$6:$A$4005,"<="&(I_Parameter!$C$5-1)) -> 0 | C26: =-SUMIFS(T_GL!$J$6:$J$4005,T_GL!$L$6:$L$4005,"Maintenance Expenses",T_GL!$A$6:$A$4005,">="&I_Parameter!$C$5,T_GL!$A$6:$A$4005,"<="&(I_Parameter!$C$4-1)) -> 0 | D26: =-(I_RunRate!$B$17*((I_Parameter!$C$6-I_Parameter!$C$4+1)/DAY(EOMONTH(I_Parameter!$C$4,0)))+I_RunRate!$C$17) -> 0 | E26: =C26+D26 -> 0 | F26: =E26-B26 -> 0 | G26: =-SUMIFS(T_GL!$J$6:$J$4005,T_GL!$L$6:$L$4005,"Maintenance Expenses",T_GL!$A$6:$A$4005,">="&DATE(YEAR(I_Parameter!$C$4),MONTH(I_Parameter!$C$4),1),T_GL!$A$6:$A$4005,"<="&(I_Parameter!$C$4-1)) -> 0 | H26: =G26+D26 -> 0 | I26: run-rate (I_RunRate)
A27: Tax expenses | B27: =-SUMIFS(T_GL!$J$6:$J$4005,T_GL!$L$6:$L$4005,"Tax expenses",T_GL!$A$6:$A$4005,">="&(I_Parameter!$C$5-7),T_GL!$A$6:$A$4005,"<="&(I_Parameter!$C$5-1)) -> -1368362 | C27: =-SUMIFS(T_GL!$J$6:$J$4005,T_GL!$L$6:$L$4005,"Tax expenses",T_GL!$A$6:$A$4005,">="&I_Parameter!$C$5,T_GL!$A$6:$A$4005,"<="&(I_Parameter!$C$4-1)) -> -1392166 | D27: =-(I_RunRate!$B$18*((I_Parameter!$C$6-I_Parameter!$C$4+1)/DAY(EOMONTH(I_Parameter!$C$4,0)))+I_RunRate!$C$18) -> 70092.129 | E27: =C27+D27 -> -1322073.9 | F27: =E27-B27 -> 46288.129 | G27: =-SUMIFS(T_GL!$J$6:$J$4005,T_GL!$L$6:$L$4005,"Tax expenses",T_GL!$A$6:$A$4005,">="&DATE(YEAR(I_Parameter!$C$4),MONTH(I_Parameter!$C$4),1),T_GL!$A$6:$A$4005,"<="&(I_Parameter!$C$4-1)) -> -4998457.7 | H27: =G27+D27 -> -4928365.5 | I27: run-rate (I_RunRate)
A28: Other operating expenses | B28: =-SUMIFS(T_GL!$J$6:$J$4005,T_GL!$L$6:$L$4005,"Other operating expenses",T_GL!$A$6:$A$4005,">="&(I_Parameter!$C$5-7),T_GL!$A$6:$A$4005,"<="&(I_Parameter!$C$5-1)) -> 0 | C28: =-SUMIFS(T_GL!$J$6:$J$4005,T_GL!$L$6:$L$4005,"Other operating expenses",T_GL!$A$6:$A$4005,">="&I_Parameter!$C$5,T_GL!$A$6:$A$4005,"<="&(I_Parameter!$C$4-1)) -> 0 | D28: =-(I_RunRate!$B$19*((I_Parameter!$C$6-I_Parameter!$C$4+1)/DAY(EOMONTH(I_Parameter!$C$4,0)))+I_RunRate!$C$19) -> 0 | E28: =C28+D28 -> 0 | F28: =E28-B28 -> 0 | G28: =-SUMIFS(T_GL!$J$6:$J$4005,T_GL!$L$6:$L$4005,"Other operating expenses",T_GL!$A$6:$A$4005,">="&DATE(YEAR(I_Parameter!$C$4),MONTH(I_Parameter!$C$4),1),T_GL!$A$6:$A$4005,"<="&(I_Parameter!$C$4-1)) -> 0 | H28: =G28+D28 -> 0 | I28: run-rate (I_RunRate)
A29: TOTAL OPERATING EXPENSES (excl. D&A) | B29: =SUM(B17:B28) -> -106792694 | C29: =SUM(C17:C28) -> -10484474 | D29: =SUM(D17:D28) -> -28423113 | E29: =SUM(E17:E28) -> -38907587 | F29: =SUM(F17:F28) -> 67885107 | G29: =SUM(G17:G28) -> -1.8389016e+08 | H29: =SUM(H17:H28) -> -2.1231327e+08
A30: OPERATING INCOME | B30: =B15+B29 -> -1.1097517e+08 | C30: =C15+C29 -> -10042390 | D30: =D15+D29 -> -96393306 | E30: =E15+E29 -> -1.064357e+08 | F30: =F15+F29 -> 4539478.5 | G30: =G15+G29 -> 1.635131e+08 | H30: =H15+H29 -> 67119793
A31: Interest Expense | B31: =-SUMIFS(T_GL!$J$6:$J$4005,T_GL!$L$6:$L$4005,"Interest Expense",T_GL!$A$6:$A$4005,">="&(I_Parameter!$C$5-7),T_GL!$A$6:$A$4005,"<="&(I_Parameter!$C$5-1)) -> 0 | C31: =-SUMIFS(T_GL!$J$6:$J$4005,T_GL!$L$6:$L$4005,"Interest Expense",T_GL!$A$6:$A$4005,">="&I_Parameter!$C$5,T_GL!$A$6:$A$4005,"<="&(I_Parameter!$C$4-1)) -> 0 | D31: =-(I_RunRate!$B$20*((I_Parameter!$C$6-I_Parameter!$C$4+1)/DAY(EOMONTH(I_Parameter!$C$4,0)))+I_RunRate!$C$20) -> -3153763.4 | E31: =C31+D31 -> -3153763.4 | F31: =E31-B31 -> -3153763.4 | G31: =-SUMIFS(T_GL!$J$6:$J$4005,T_GL!$L$6:$L$4005,"Interest Expense",T_GL!$A$6:$A$4005,">="&DATE(YEAR(I_Parameter!$C$4),MONTH(I_Parameter!$C$4),1),T_GL!$A$6:$A$4005,"<="&(I_Parameter!$C$4-1)) -> 0 | H31: =G31+D31 -> -3153763.4 | I31: run-rate (I_RunRate)
A32: Other Income | B32: =-SUMIFS(T_GL!$J$6:$J$4005,T_GL!$L$6:$L$4005,"Other Income",T_GL!$A$6:$A$4005,">="&(I_Parameter!$C$5-7),T_GL!$A$6:$A$4005,"<="&(I_Parameter!$C$5-1)) -> 19058.51 | C32: =-SUMIFS(T_GL!$J$6:$J$4005,T_GL!$L$6:$L$4005,"Other Income",T_GL!$A$6:$A$4005,">="&I_Parameter!$C$5,T_GL!$A$6:$A$4005,"<="&(I_Parameter!$C$4-1)) -> -0.21 | D32: =(I_RunRate!$B$21*((I_Parameter!$C$6-I_Parameter!$C$4+1)/DAY(EOMONTH(I_Parameter!$C$4,0)))+I_RunRate!$C$21) -> 3401693 | E32: =C32+D32 -> 3401692.8 | F32: =E32-B32 -> 3382634.3 | G32: =-SUMIFS(T_GL!$J$6:$J$4005,T_GL!$L$6:$L$4005,"Other Income",T_GL!$A$6:$A$4005,">="&DATE(YEAR(I_Parameter!$C$4),MONTH(I_Parameter!$C$4),1),T_GL!$A$6:$A$4005,"<="&(I_Parameter!$C$4-1)) -> 1753081.5 | H32: =G32+D32 -> 5154774.6 | I32: run-rate (I_RunRate)
A33: Other Expense | B33: =-SUMIFS(T_GL!$J$6:$J$4005,T_GL!$L$6:$L$4005,"Other Expense",T_GL!$A$6:$A$4005,">="&(I_Parameter!$C$5-7),T_GL!$A$6:$A$4005,"<="&(I_Parameter!$C$5-1)) -> -11650 | C33: =-SUMIFS(T_GL!$J$6:$J$4005,T_GL!$L$6:$L$4005,"Other Expense",T_GL!$A$6:$A$4005,">="&I_Parameter!$C$5,T_GL!$A$6:$A$4005,"<="&(I_Parameter!$C$4-1)) -> 0 | D33: =-(I_RunRate!$B$22*((I_Parameter!$C$6-I_Parameter!$C$4+1)/DAY(EOMONTH(I_Parameter!$C$4,0)))+I_RunRate!$C$22) -> -47270.71 | E33: =C33+D33 -> -47270.71 | F33: =E33-B33 -> -35620.71 | G33: =-SUMIFS(T_GL!$J$6:$J$4005,T_GL!$L$6:$L$4005,"Other Expense",T_GL!$A$6:$A$4005,">="&DATE(YEAR(I_Parameter!$C$4),MONTH(I_Parameter!$C$4),1),T_GL!$A$6:$A$4005,"<="&(I_Parameter!$C$4-1)) -> -16400 | H33: =G33+D33 -> -63670.71 | I33: run-rate (I_RunRate)
A34: TOTAL OTHER INCOME (EXPENSE) | B34: =SUM(B31:B33) -> 7408.51 | C34: =SUM(C31:C33) -> -0.21 | D34: =SUM(D31:D33) -> 200658.97 | E34: =SUM(E31:E33) -> 200658.76 | F34: =SUM(F31:F33) -> 193250.25 | G34: =SUM(G31:G33) -> 1736681.5 | H34: =SUM(H31:H33) -> 1937340.5
A35: NIBT (before D&A) | B35: =B30+B34 -> -1.1096777e+08 | C35: =C30+C34 -> -10042390 | D35: =D30+D34 -> -96192647 | E35: =E30+E34 -> -1.0623504e+08 | F35: =F30+F34 -> 4732728.7 | G35: =G30+G34 -> 1.6524978e+08 | H35: =H30+H34 -> 69057134
A36: Depreciation & amortisation | B36: =-SUMIFS(T_GL!$J$6:$J$4005,T_GL!$L$6:$L$4005,"Depreciation & amortisation",T_GL!$A$6:$A$4005,">="&(I_Parameter!$C$5-7),T_GL!$A$6:$A$4005,"<="&(I_Parameter!$C$5-1)) -> 0 | C36: =-SUMIFS(T_GL!$J$6:$J$4005,T_GL!$L$6:$L$4005,"Depreciation & amortisation",T_GL!$A$6:$A$4005,">="&I_Parameter!$C$5,T_GL!$A$6:$A$4005,"<="&(I_Parameter!$C$4-1)) -> 0 | D36: =-(I_RunRate!$B$23*((I_Parameter!$C$6-I_Parameter!$C$4+1)/DAY(EOMONTH(I_Parameter!$C$4,0)))+I_RunRate!$C$23) -> -1341091.7 | E36: =C36+D36 -> -1341091.7 | F36: =E36-B36 -> -1341091.7 | G36: =-SUMIFS(T_GL!$J$6:$J$4005,T_GL!$L$6:$L$4005,"Depreciation & amortisation",T_GL!$A$6:$A$4005,">="&DATE(YEAR(I_Parameter!$C$4),MONTH(I_Parameter!$C$4),1),T_GL!$A$6:$A$4005,"<="&(I_Parameter!$C$4-1)) -> 0 | H36: =G36+D36 -> -1341091.7 | I36: run-rate (I_RunRate)
A37: NET INCOME | B37: =B35+B36 -> -1.1096777e+08 | C37: =C35+C36 -> -10042390 | D37: =D35+D36 -> -97533739 | E37: =E35+E36 -> -1.0757613e+08 | F37: =F35+F36 -> 3391637 | G37: =G35+G36 -> 1.6524978e+08 | H37: =H35+H36 -> 67716042
A39: Catatan: aktual = jurnal Accurate (tanggal SI/PI); blok 1 O_Outlook = pengiriman (DO). Jurnal akhir bulan (unbilled, penyesuaian) baru masuk setelah diposting.

Sheet O_BS
A1: NERACA MINGGUAN — Rp
A2: Aktual = saldo awal TB + jurnal s.d. tanggal. Proyeksi akhir minggu = saldo kemarin + arus rencana (lihat blok "Arus rencana minggu ini" di bawah).
B4: =I_Parameter!$C$47 -> 46234 | C4: =I_Parameter!$C$5-1 -> 46257 | D4: =I_Parameter!$C$4-1 -> 46260 | E4: =I_Parameter!$C$6 -> 46264
A5: Pos | B5: Saldo awal (TB) | C5: Akhir minggu lalu | D5: Kemarin (aktual) | E5: Proyeksi akhir minggu ini | F5: Δ minggu ini (proyeksi − akhir minggu lalu) | G5: Δ rencana (debit +)
A6: ASSETS
A7: Cash and cash equivalents | B7: =(SUMIFS(I_TB!$C$6:$C$265,I_TB!$E$6:$E$265,"Cash and cash equivalents")+SUMIFS(T_GL!$J$6:$J$4005,T_GL!$M$6:$M$4005,"Cash and cash equivalents",T_GL!$A$6:$A$4005,"<="&B$4)) -> 5.9984142e+08 | C7: =(SUMIFS(I_TB!$C$6:$C$265,I_TB!$E$6:$E$265,"Cash and cash equivalents")+SUMIFS(T_GL!$J$6:$J$4005,T_GL!$M$6:$M$4005,"Cash and cash equivalents",T_GL!$A$6:$A$4005,"<="&C$4)) -> 3.7909117e+08 | D7: =(SUMIFS(I_TB!$C$6:$C$265,I_TB!$E$6:$E$265,"Cash and cash equivalents")+SUMIFS(T_GL!$J$6:$J$4005,T_GL!$M$6:$M$4005,"Cash and cash equivalents",T_GL!$A$6:$A$4005,"<="&D$4)) -> 1.2892513e+09 | E7: =D7+G7 -> 8.1819823e+08 | F7: =E7-C7 -> 439107064 | G7: =-SUMIFS(T_Kas_Rencana!$E$6:$E$305,T_Kas_Rencana!$C$6:$C$305,"Cash and cash equivalents",T_Kas_Rencana!$F$6:$F$305,1)+$B$73 -> -471053116
A8: Trade Receivables - Third Parties | B8: =(SUMIFS(I_TB!$C$6:$C$265,I_TB!$E$6:$E$265,"Trade Receivables - Third Parties")+SUMIFS(T_GL!$J$6:$J$4005,T_GL!$M$6:$M$4005,"Trade Receivables - Third Parties",T_GL!$A$6:$A$4005,"<="&B$4)) -> 310674730 | C8: =(SUMIFS(I_TB!$C$6:$C$265,I_TB!$E$6:$E$265,"Trade Receivables - Third Parties")+SUMIFS(T_GL!$J$6:$J$4005,T_GL!$M$6:$M$4005,"Trade Receivables - Third Parties",T_GL!$A$6:$A$4005,"<="&C$4)) -> 637472980 | D8: =(SUMIFS(I_TB!$C$6:$C$265,I_TB!$E$6:$E$265,"Trade Receivables - Third Parties")+SUMIFS(T_GL!$J$6:$J$4005,T_GL!$M$6:$M$4005,"Trade Receivables - Third Parties",T_GL!$A$6:$A$4005,"<="&D$4)) -> 991265050 | E8: =D8+G8 -> 6.2518396e+08 | F8: =E8-C8 -> -12289018 | G8: =-SUMIFS(T_Kas_Rencana!$E$6:$E$305,T_Kas_Rencana!$C$6:$C$305,"Trade Receivables - Third Parties",T_Kas_Rencana!$F$6:$F$305,1)+$B$67 -> -3.6608109e+08
A9: Trade Receivables - Related Parties | B9: =(SUMIFS(I_TB!$C$6:$C$265,I_TB!$E$6:$E$265,"Trade Receivables - Related Parties")+SUMIFS(T_GL!$J$6:$J$4005,T_GL!$M$6:$M$4005,"Trade Receivables - Related Parties",T_GL!$A$6:$A$4005,"<="&B$4)) -> 0 | C9: =(SUMIFS(I_TB!$C$6:$C$265,I_TB!$E$6:$E$265,"Trade Receivables - Related Parties")+SUMIFS(T_GL!$J$6:$J$4005,T_GL!$M$6:$M$4005,"Trade Receivables - Related Parties",T_GL!$A$6:$A$4005,"<="&C$4)) -> 0 | D9: =(SUMIFS(I_TB!$C$6:$C$265,I_TB!$E$6:$E$265,"Trade Receivables - Related Parties")+SUMIFS(T_GL!$J$6:$J$4005,T_GL!$M$6:$M$4005,"Trade Receivables - Related Parties",T_GL!$A$6:$A$4005,"<="&D$4)) -> 0 | E9: =D9+G9 -> 0 | F9: =E9-C9 -> 0 | G9: =-SUMIFS(T_Kas_Rencana!$E$6:$E$305,T_Kas_Rencana!$C$6:$C$305,"Trade Receivables - Related Parties",T_Kas_Rencana!$F$6:$F$305,1)+0 -> 0
A10: Other Receivable - Third Party | B10: =(SUMIFS(I_TB!$C$6:$C$265,I_TB!$E$6:$E$265,"Other Receivable - Third Party")+SUMIFS(T_GL!$J$6:$J$4005,T_GL!$M$6:$M$4005,"Other Receivable - Third Party",T_GL!$A$6:$A$4005,"<="&B$4)) -> 0 | C10: =(SUMIFS(I_TB!$C$6:$C$265,I_TB!$E$6:$E$265,"Other Receivable - Third Party")+SUMIFS(T_GL!$J$6:$J$4005,T_GL!$M$6:$M$4005,"Other Receivable - Third Party",T_GL!$A$6:$A$4005,"<="&C$4)) -> 0 | D10: =(SUMIFS(I_TB!$C$6:$C$265,I_TB!$E$6:$E$265,"Other Receivable - Third Party")+SUMIFS(T_GL!$J$6:$J$4005,T_GL!$M$6:$M$4005,"Other Receivable - Third Party",T_GL!$A$6:$A$4005,"<="&D$4)) -> 0 | E10: =D10+G10 -> 0 | F10: =E10-C10 -> 0 | G10: =-SUMIFS(T_Kas_Rencana!$E$6:$E$305,T_Kas_Rencana!$C$6:$C$305,"Other Receivable - Third Party",T_Kas_Rencana!$F$6:$F$305,1)+0 -> 0
A11: Other Receivable - Affiliated Party | B11: =(SUMIFS(I_TB!$C$6:$C$265,I_TB!$E$6:$E$265,"Other Receivable - Affiliated Party")+SUMIFS(T_GL!$J$6:$J$4005,T_GL!$M$6:$M$4005,"Other Receivable - Affiliated Party",T_GL!$A$6:$A$4005,"<="&B$4)) -> 0 | C11: =(SUMIFS(I_TB!$C$6:$C$265,I_TB!$E$6:$E$265,"Other Receivable - Affiliated Party")+SUMIFS(T_GL!$J$6:$J$4005,T_GL!$M$6:$M$4005,"Other Receivable - Affiliated Party",T_GL!$A$6:$A$4005,"<="&C$4)) -> 0 | D11: =(SUMIFS(I_TB!$C$6:$C$265,I_TB!$E$6:$E$265,"Other Receivable - Affiliated Party")+SUMIFS(T_GL!$J$6:$J$4005,T_GL!$M$6:$M$4005,"Other Receivable - Affiliated Party",T_GL!$A$6:$A$4005,"<="&D$4)) -> 0 | E11: =D11+G11 -> 0 | F11: =E11-C11 -> 0 | G11: =-SUMIFS(T_Kas_Rencana!$E$6:$E$305,T_Kas_Rencana!$C$6:$C$305,"Other Receivable - Affiliated Party",T_Kas_Rencana!$F$6:$F$305,1)+0 -> 0
A12: Advance Payment | B12: =(SUMIFS(I_TB!$C$6:$C$265,I_TB!$E$6:$E$265,"Advance Payment")+SUMIFS(T_GL!$J$6:$J$4005,T_GL!$M$6:$M$4005,"Advance Payment",T_GL!$A$6:$A$4005,"<="&B$4)) -> 1.4720445e+09 | C12: =(SUMIFS(I_TB!$C$6:$C$265,I_TB!$E$6:$E$265,"Advance Payment")+SUMIFS(T_GL!$J$6:$J$4005,T_GL!$M$6:$M$4005,"Advance Payment",T_GL!$A$6:$A$4005,"<="&C$4)) -> 6.2222191e+08 | D12: =(SUMIFS(I_TB!$C$6:$C$265,I_TB!$E$6:$E$265,"Advance Payment")+SUMIFS(T_GL!$J$6:$J$4005,T_GL!$M$6:$M$4005,"Advance Payment",T_GL!$A$6:$A$4005,"<="&D$4)) -> 6.4230947e+08 | E12: =D12+G12 -> 6.2247411e+08 | F12: =E12-C12 -> 252200 | G12: =-SUMIFS(T_Kas_Rencana!$E$6:$E$305,T_Kas_Rencana!$C$6:$C$305,"Advance Payment",T_Kas_Rencana!$F$6:$F$305,1)+0 -> -19835360
A13: Inventory - Product | B13: =(SUMIFS(I_TB!$C$6:$C$265,I_TB!$E$6:$E$265,"Inventory - Product")+SUMIFS(T_GL!$J$6:$J$4005,T_GL!$M$6:$M$4005,"Inventory - Product",T_GL!$A$6:$A$4005,"<="&B$4)) -> 7.7119464e+08 | C13: =(SUMIFS(I_TB!$C$6:$C$265,I_TB!$E$6:$E$265,"Inventory - Product")+SUMIFS(T_GL!$J$6:$J$4005,T_GL!$M$6:$M$4005,"Inventory - Product",T_GL!$A$6:$A$4005,"<="&C$4)) -> 1.2620242e+09 | D13: =(SUMIFS(I_TB!$C$6:$C$265,I_TB!$E$6:$E$265,"Inventory - Product")+SUMIFS(T_GL!$J$6:$J$4005,T_GL!$M$6:$M$4005,"Inventory - Product",T_GL!$A$6:$A$4005,"<="&D$4)) -> 1.5681049e+09 | E13: =D13+G13 -> 1.6367554e+09 | F13: =E13-C13 -> 3.747312e+08 | G13: =-SUMIFS(T_Kas_Rencana!$E$6:$E$305,T_Kas_Rencana!$C$6:$C$305,"Inventory - Product",T_Kas_Rencana!$F$6:$F$305,1)+($B$60-$B$68) -> 68650474
A14: Inventory - Trading | B14: =(SUMIFS(I_TB!$C$6:$C$265,I_TB!$E$6:$E$265,"Inventory - Trading")+SUMIFS(T_GL!$J$6:$J$4005,T_GL!$M$6:$M$4005,"Inventory - Trading",T_GL!$A$6:$A$4005,"<="&B$4)) -> 2.1245601e+09 | C14: =(SUMIFS(I_TB!$C$6:$C$265,I_TB!$E$6:$E$265,"Inventory - Trading")+SUMIFS(T_GL!$J$6:$J$4005,T_GL!$M$6:$M$4005,"Inventory - Trading",T_GL!$A$6:$A$4005,"<="&C$4)) -> 2.5185822e+09 | D14: =(SUMIFS(I_TB!$C$6:$C$265,I_TB!$E$6:$E$265,"Inventory - Trading")+SUMIFS(T_GL!$J$6:$J$4005,T_GL!$M$6:$M$4005,"Inventory - Trading",T_GL!$A$6:$A$4005,"<="&D$4)) -> 2.5921095e+09 | E14: =D14+G14 -> 2.3556527e+09 | F14: =E14-C14 -> -1.6292957e+08 | G14: =-SUMIFS(T_Kas_Rencana!$E$6:$E$305,T_Kas_Rencana!$C$6:$C$305,"Inventory - Trading",T_Kas_Rencana!$F$6:$F$305,1)+($B$63-$B$69) -> -2.3645686e+08
A15: Prepaid Tax | B15: =(SUMIFS(I_TB!$C$6:$C$265,I_TB!$E$6:$E$265,"Prepaid Tax")+SUMIFS(T_GL!$J$6:$J$4005,T_GL!$M$6:$M$4005,"Prepaid Tax",T_GL!$A$6:$A$4005,"<="&B$4)) -> 1.2366855e+08 | C15: =(SUMIFS(I_TB!$C$6:$C$265,I_TB!$E$6:$E$265,"Prepaid Tax")+SUMIFS(T_GL!$J$6:$J$4005,T_GL!$M$6:$M$4005,"Prepaid Tax",T_GL!$A$6:$A$4005,"<="&C$4)) -> 1.508409e+08 | D15: =(SUMIFS(I_TB!$C$6:$C$265,I_TB!$E$6:$E$265,"Prepaid Tax")+SUMIFS(T_GL!$J$6:$J$4005,T_GL!$M$6:$M$4005,"Prepaid Tax",T_GL!$A$6:$A$4005,"<="&D$4)) -> 1.5780993e+08 | E15: =D15+G15 -> 1.5780993e+08 | F15: =E15-C15 -> 6969037 | G15: =-SUMIFS(T_Kas_Rencana!$E$6:$E$305,T_Kas_Rencana!$C$6:$C$305,"Prepaid Tax",T_Kas_Rencana!$F$6:$F$305,1)+0 -> 0
A16: Prepaid Expenses | B16: =(SUMIFS(I_TB!$C$6:$C$265,I_TB!$E$6:$E$265,"Prepaid Expenses")+SUMIFS(T_GL!$J$6:$J$4005,T_GL!$M$6:$M$4005,"Prepaid Expenses",T_GL!$A$6:$A$4005,"<="&B$4)) -> 79400000 | C16: =(SUMIFS(I_TB!$C$6:$C$265,I_TB!$E$6:$E$265,"Prepaid Expenses")+SUMIFS(T_GL!$J$6:$J$4005,T_GL!$M$6:$M$4005,"Prepaid Expenses",T_GL!$A$6:$A$4005,"<="&C$4)) -> 79400000 | D16: =(SUMIFS(I_TB!$C$6:$C$265,I_TB!$E$6:$E$265,"Prepaid Expenses")+SUMIFS(T_GL!$J$6:$J$4005,T_GL!$M$6:$M$4005,"Prepaid Expenses",T_GL!$A$6:$A$4005,"<="&D$4)) -> 1213190000 | E16: =D16+G16 -> 1213190000 | F16: =E16-C16 -> 1133790000 | G16: =-SUMIFS(T_Kas_Rencana!$E$6:$E$305,T_Kas_Rencana!$C$6:$C$305,"Prepaid Expenses",T_Kas_Rencana!$F$6:$F$305,1)+0 -> 0
A17: Other assets | B17: =(SUMIFS(I_TB!$C$6:$C$265,I_TB!$E$6:$E$265,"Other assets")+SUMIFS(T_GL!$J$6:$J$4005,T_GL!$M$6:$M$4005,"Other assets",T_GL!$A$6:$A$4005,"<="&B$4)) -> 0 | C17: =(SUMIFS(I_TB!$C$6:$C$265,I_TB!$E$6:$E$265,"Other assets")+SUMIFS(T_GL!$J$6:$J$4005,T_GL!$M$6:$M$4005,"Other assets",T_GL!$A$6:$A$4005,"<="&C$4)) -> 0 | D17: =(SUMIFS(I_TB!$C$6:$C$265,I_TB!$E$6:$E$265,"Other assets")+SUMIFS(T_GL!$J$6:$J$4005,T_GL!$M$6:$M$4005,"Other assets",T_GL!$A$6:$A$4005,"<="&D$4)) -> 0 | E17: =D17+G17 -> 0 | F17: =E17-C17 -> 0 | G17: =-SUMIFS(T_Kas_Rencana!$E$6:$E$305,T_Kas_Rencana!$C$6:$C$305,"Other assets",T_Kas_Rencana!$F$6:$F$305,1)+0 -> 0
A18: Fixed assets - cost | B18: =(SUMIFS(I_TB!$C$6:$C$265,I_TB!$E$6:$E$265,"Fixed assets - cost")+SUMIFS(T_GL!$J$6:$J$4005,T_GL!$M$6:$M$4005,"Fixed assets - cost",T_GL!$A$6:$A$4005,"<="&B$4)) -> 1.5314512e+09 | C18: =(SUMIFS(I_TB!$C$6:$C$265,I_TB!$E$6:$E$265,"Fixed assets - cost")+SUMIFS(T_GL!$J$6:$J$4005,T_GL!$M$6:$M$4005,"Fixed assets - cost",T_GL!$A$6:$A$4005,"<="&C$4)) -> 1.5314512e+09 | D18: =(SUMIFS(I_TB!$C$6:$C$265,I_TB!$E$6:$E$265,"Fixed assets - cost")+SUMIFS(T_GL!$J$6:$J$4005,T_GL!$M$6:$M$4005,"Fixed assets - cost",T_GL!$A$6:$A$4005,"<="&D$4)) -> 1.5314512e+09 | E18: =D18+G18 -> 1.5314512e+09 | F18: =E18-C18 -> 0 | G18: =-SUMIFS(T_Kas_Rencana!$E$6:$E$305,T_Kas_Rencana!$C$6:$C$305,"Fixed assets - cost",T_Kas_Rencana!$F$6:$F$305,1)+0 -> 0
A19: Accumulated depreciation | B19: =(SUMIFS(I_TB!$C$6:$C$265,I_TB!$E$6:$E$265,"Accumulated depreciation")+SUMIFS(T_GL!$J$6:$J$4005,T_GL!$M$6:$M$4005,"Accumulated depreciation",T_GL!$A$6:$A$4005,"<="&B$4)) -> -4.2808595e+08 | C19: =(SUMIFS(I_TB!$C$6:$C$265,I_TB!$E$6:$E$265,"Accumulated depreciation")+SUMIFS(T_GL!$J$6:$J$4005,T_GL!$M$6:$M$4005,"Accumulated depreciation",T_GL!$A$6:$A$4005,"<="&C$4)) -> -4.2808595e+08 | D19: =(SUMIFS(I_TB!$C$6:$C$265,I_TB!$E$6:$E$265,"Accumulated depreciation")+SUMIFS(T_GL!$J$6:$J$4005,T_GL!$M$6:$M$4005,"Accumulated depreciation",T_GL!$A$6:$A$4005,"<="&D$4)) -> -4.2808595e+08 | E19: =D19+G19 -> -4.2942704e+08 | F19: =E19-C19 -> -1341091.7 | G19: =-SUMIFS(T_Kas_Rencana!$E$6:$E$305,T_Kas_Rencana!$C$6:$C$305,"Accumulated depreciation",T_Kas_Rencana!$F$6:$F$305,1)+(-$B$71) -> -1341091.7
A20: TOTAL ASSETS | B20: =SUM(B7:B19) -> 6.5847491e+09 | C20: =SUM(C7:C19) -> 6.7529986e+09 | D20: =SUM(D7:D19) -> 9.5574054e+09 | E20: =SUM(E7:E19) -> 8.5312884e+09 | F20: =SUM(F7:F19) -> 1.7782898e+09
A22: LIABILITIES
A23: Trade Payables - Third Parties | B23: =-(SUMIFS(I_TB!$C$6:$C$265,I_TB!$E$6:$E$265,"Trade Payables - Third Parties")+SUMIFS(T_GL!$J$6:$J$4005,T_GL!$M$6:$M$4005,"Trade Payables - Third Parties",T_GL!$A$6:$A$4005,"<="&B$4)) -> 4172730 | C23: =-(SUMIFS(I_TB!$C$6:$C$265,I_TB!$E$6:$E$265,"Trade Payables - Third Parties")+SUMIFS(T_GL!$J$6:$J$4005,T_GL!$M$6:$M$4005,"Trade Payables - Third Parties",T_GL!$A$6:$A$4005,"<="&C$4)) -> -7.0780451e+08 | D23: =-(SUMIFS(I_TB!$C$6:$C$265,I_TB!$E$6:$E$265,"Trade Payables - Third Parties")+SUMIFS(T_GL!$J$6:$J$4005,T_GL!$M$6:$M$4005,"Trade Payables - Third Parties",T_GL!$A$6:$A$4005,"<="&D$4)) -> -4.2032975e+08 | E23: =D23-G23 -> 67042607 | F23: =E23-C23 -> 7.7484712e+08 | G23: =-SUMIFS(T_Kas_Rencana!$E$6:$E$305,T_Kas_Rencana!$C$6:$C$305,"Trade Payables - Third Parties",T_Kas_Rencana!$F$6:$F$305,1)+(-$B$61-$B$63+$B$64+$B$65) -> -4.8737236e+08
A24: Trade Payables - Affiliates | B24: =-(SUMIFS(I_TB!$C$6:$C$265,I_TB!$E$6:$E$265,"Trade Payables - Affiliates")+SUMIFS(T_GL!$J$6:$J$4005,T_GL!$M$6:$M$4005,"Trade Payables - Affiliates",T_GL!$A$6:$A$4005,"<="&B$4)) -> 0 | C24: =-(SUMIFS(I_TB!$C$6:$C$265,I_TB!$E$6:$E$265,"Trade Payables - Affiliates")+SUMIFS(T_GL!$J$6:$J$4005,T_GL!$M$6:$M$4005,"Trade Payables - Affiliates",T_GL!$A$6:$A$4005,"<="&C$4)) -> 0 | D24: =-(SUMIFS(I_TB!$C$6:$C$265,I_TB!$E$6:$E$265,"Trade Payables - Affiliates")+SUMIFS(T_GL!$J$6:$J$4005,T_GL!$M$6:$M$4005,"Trade Payables - Affiliates",T_GL!$A$6:$A$4005,"<="&D$4)) -> 0 | E24: =D24-G24 -> -361200000 | F24: =E24-C24 -> -361200000 | G24: =-SUMIFS(T_Kas_Rencana!$E$6:$E$305,T_Kas_Rencana!$C$6:$C$305,"Trade Payables - Affiliates",T_Kas_Rencana!$F$6:$F$305,1)+0 -> 361200000
A25: Other Payable - Third Parties | B25: =-(SUMIFS(I_TB!$C$6:$C$265,I_TB!$E$6:$E$265,"Other Payable - Third Parties")+SUMIFS(T_GL!$J$6:$J$4005,T_GL!$M$6:$M$4005,"Other Payable - Third Parties",T_GL!$A$6:$A$4005,"<="&B$4)) -> 3.1667055e+08 | C25: =-(SUMIFS(I_TB!$C$6:$C$265,I_TB!$E$6:$E$265,"Other Payable - Third Parties")+SUMIFS(T_GL!$J$6:$J$4005,T_GL!$M$6:$M$4005,"Other Payable - Third Parties",T_GL!$A$6:$A$4005,"<="&C$4)) -> 4.626862e+08 | D25: =-(SUMIFS(I_TB!$C$6:$C$265,I_TB!$E$6:$E$265,"Other Payable - Third Parties")+SUMIFS(T_GL!$J$6:$J$4005,T_GL!$M$6:$M$4005,"Other Payable - Third Parties",T_GL!$A$6:$A$4005,"<="&D$4)) -> 1.662308e+09 | E25: =D25-G25 -> 4.927967e+08 | F25: =E25-C25 -> 30110501 | G25: =-SUMIFS(T_Kas_Rencana!$E$6:$E$305,T_Kas_Rencana!$C$6:$C$305,"Other Payable - Third Parties",T_Kas_Rencana!$F$6:$F$305,1)+0 -> 1169511318
A26: Other Payable - Related Parties | B26: =-(SUMIFS(I_TB!$C$6:$C$265,I_TB!$E$6:$E$265,"Other Payable - Related Parties")+SUMIFS(T_GL!$J$6:$J$4005,T_GL!$M$6:$M$4005,"Other Payable - Related Parties",T_GL!$A$6:$A$4005,"<="&B$4)) -> 4.4298905e+09 | C26: =-(SUMIFS(I_TB!$C$6:$C$265,I_TB!$E$6:$E$265,"Other Payable - Related Parties")+SUMIFS(T_GL!$J$6:$J$4005,T_GL!$M$6:$M$4005,"Other Payable - Related Parties",T_GL!$A$6:$A$4005,"<="&C$4)) -> 4400000000 | D26: =-(SUMIFS(I_TB!$C$6:$C$265,I_TB!$E$6:$E$265,"Other Payable - Related Parties")+SUMIFS(T_GL!$J$6:$J$4005,T_GL!$M$6:$M$4005,"Other Payable - Related Parties",T_GL!$A$6:$A$4005,"<="&D$4)) -> 5600000000 | E26: =D26-G26 -> 5600000000 | F26: =E26-C26 -> 1200000000 | G26: =-SUMIFS(T_Kas_Rencana!$E$6:$E$305,T_Kas_Rencana!$C$6:$C$305,"Other Payable - Related Parties",T_Kas_Rencana!$F$6:$F$305,1)+0 -> 0
A27: Accrued Expenses - Third Parties | B27: =-(SUMIFS(I_TB!$C$6:$C$265,I_TB!$E$6:$E$265,"Accrued Expenses - Third Parties")+SUMIFS(T_GL!$J$6:$J$4005,T_GL!$M$6:$M$4005,"Accrued Expenses - Third Parties",T_GL!$A$6:$A$4005,"<="&B$4)) -> 184202599 | C27: =-(SUMIFS(I_TB!$C$6:$C$265,I_TB!$E$6:$E$265,"Accrued Expenses - Third Parties")+SUMIFS(T_GL!$J$6:$J$4005,T_GL!$M$6:$M$4005,"Accrued Expenses - Third Parties",T_GL!$A$6:$A$4005,"<="&C$4)) -> 42274555 | D27: =-(SUMIFS(I_TB!$C$6:$C$265,I_TB!$E$6:$E$265,"Accrued Expenses - Third Parties")+SUMIFS(T_GL!$J$6:$J$4005,T_GL!$M$6:$M$4005,"Accrued Expenses - Third Parties",T_GL!$A$6:$A$4005,"<="&D$4)) -> 42274555 | E27: =D27-G27 -> 76430219 | F27: =E27-C27 -> 34155664 | G27: =-SUMIFS(T_Kas_Rencana!$E$6:$E$305,T_Kas_Rencana!$C$6:$C$305,"Accrued Expenses - Third Parties",T_Kas_Rencana!$F$6:$F$305,1)+(-$B$62+$B$66-$B$70) -> -34155664
A28: Unearned Revenue | B28: =-(SUMIFS(I_TB!$C$6:$C$265,I_TB!$E$6:$E$265,"Unearned Revenue")+SUMIFS(T_GL!$J$6:$J$4005,T_GL!$M$6:$M$4005,"Unearned Revenue",T_GL!$A$6:$A$4005,"<="&B$4)) -> 628415 | C28: =-(SUMIFS(I_TB!$C$6:$C$265,I_TB!$E$6:$E$265,"Unearned Revenue")+SUMIFS(T_GL!$J$6:$J$4005,T_GL!$M$6:$M$4005,"Unearned Revenue",T_GL!$A$6:$A$4005,"<="&C$4)) -> 727613568 | D28: =-(SUMIFS(I_TB!$C$6:$C$265,I_TB!$E$6:$E$265,"Unearned Revenue")+SUMIFS(T_GL!$J$6:$J$4005,T_GL!$M$6:$M$4005,"Unearned Revenue",T_GL!$A$6:$A$4005,"<="&D$4)) -> 850804668 | E28: =D28-G28 -> 931404668 | F28: =E28-C28 -> 203791100 | G28: =-SUMIFS(T_Kas_Rencana!$E$6:$E$305,T_Kas_Rencana!$C$6:$C$305,"Unearned Revenue",T_Kas_Rencana!$F$6:$F$305,1)+0 -> -80600000
A29: Taxes Payable | B29: =-(SUMIFS(I_TB!$C$6:$C$265,I_TB!$E$6:$E$265,"Taxes Payable")+SUMIFS(T_GL!$J$6:$J$4005,T_GL!$M$6:$M$4005,"Taxes Payable",T_GL!$A$6:$A$4005,"<="&B$4)) -> 10054484 | C29: =-(SUMIFS(I_TB!$C$6:$C$265,I_TB!$E$6:$E$265,"Taxes Payable")+SUMIFS(T_GL!$J$6:$J$4005,T_GL!$M$6:$M$4005,"Taxes Payable",T_GL!$A$6:$A$4005,"<="&C$4)) -> 13806706 | D29: =-(SUMIFS(I_TB!$C$6:$C$265,I_TB!$E$6:$E$265,"Taxes Payable")+SUMIFS(T_GL!$J$6:$J$4005,T_GL!$M$6:$M$4005,"Taxes Payable",T_GL!$A$6:$A$4005,"<="&D$4)) -> 17968278 | E29: =D29-G29 -> 17968278 | F29: =E29-C29 -> 4161571.6 | G29: =-SUMIFS(T_Kas_Rencana!$E$6:$E$305,T_Kas_Rencana!$C$6:$C$305,"Taxes Payable",T_Kas_Rencana!$F$6:$F$305,1)+0 -> 0
A30: Temporary account (to reclassify) | B30: =-(SUMIFS(I_TB!$C$6:$C$265,I_TB!$E$6:$E$265,"Temporary account (to reclassify)")+SUMIFS(T_GL!$J$6:$J$4005,T_GL!$M$6:$M$4005,"Temporary account (to reclassify)",T_GL!$A$6:$A$4005,"<="&B$4)) -> 0 | C30: =-(SUMIFS(I_TB!$C$6:$C$265,I_TB!$E$6:$E$265,"Temporary account (to reclassify)")+SUMIFS(T_GL!$J$6:$J$4005,T_GL!$M$6:$M$4005,"Temporary account (to reclassify)",T_GL!$A$6:$A$4005,"<="&C$4)) -> 0 | D30: =-(SUMIFS(I_TB!$C$6:$C$265,I_TB!$E$6:$E$265,"Temporary account (to reclassify)")+SUMIFS(T_GL!$J$6:$J$4005,T_GL!$M$6:$M$4005,"Temporary account (to reclassify)",T_GL!$A$6:$A$4005,"<="&D$4)) -> 0 | E30: =D30-G30 -> 0 | F30: =E30-C30 -> 0 | G30: =-SUMIFS(T_Kas_Rencana!$E$6:$E$305,T_Kas_Rencana!$C$6:$C$305,"Temporary account (to reclassify)",T_Kas_Rencana!$F$6:$F$305,1)+0 -> 0
A31: TOTAL LIABILITIES | B31: =SUM(B23:B30) -> 4.9456193e+09 | C31: =SUM(C23:C30) -> 4.9385765e+09 | D31: =SUM(D23:D30) -> 7.7530258e+09 | E31: =SUM(E23:E30) -> 6.8244425e+09 | F31: =SUM(F23:F30) -> 1.885866e+09
A33: EQUITY
A34: Shareholder Equity | B34: =-(SUMIFS(I_TB!$C$6:$C$265,I_TB!$E$6:$E$265,"Shareholder Equity")+SUMIFS(T_GL!$J$6:$J$4005,T_GL!$M$6:$M$4005,"Shareholder Equity",T_GL!$A$6:$A$4005,"<="&B$4)) -> 5000000000 | C34: =-(SUMIFS(I_TB!$C$6:$C$265,I_TB!$E$6:$E$265,"Shareholder Equity")+SUMIFS(T_GL!$J$6:$J$4005,T_GL!$M$6:$M$4005,"Shareholder Equity",T_GL!$A$6:$A$4005,"<="&C$4)) -> 5000000000 | D34: =-(SUMIFS(I_TB!$C$6:$C$265,I_TB!$E$6:$E$265,"Shareholder Equity")+SUMIFS(T_GL!$J$6:$J$4005,T_GL!$M$6:$M$4005,"Shareholder Equity",T_GL!$A$6:$A$4005,"<="&D$4)) -> 5000000000 | E34: =D34-G34 -> 5000000000 | F34: =E34-C34 -> 0 | G34: =-SUMIFS(T_Kas_Rencana!$E$6:$E$305,T_Kas_Rencana!$C$6:$C$305,"Shareholder Equity",T_Kas_Rencana!$F$6:$F$305,1)+0 -> 0
A35: Retained earnings | B35: =-(SUMIFS(I_TB!$C$6:$C$265,I_TB!$E$6:$E$265,"Retained earnings")+SUMIFS(T_GL!$J$6:$J$4005,T_GL!$M$6:$M$4005,"Retained earnings",T_GL!$A$6:$A$4005,"<="&B$4)) -> -2.6984347e+09 | C35: =-(SUMIFS(I_TB!$C$6:$C$265,I_TB!$E$6:$E$265,"Retained earnings")+SUMIFS(T_GL!$J$6:$J$4005,T_GL!$M$6:$M$4005,"Retained earnings",T_GL!$A$6:$A$4005,"<="&C$4)) -> -2.6984347e+09 | D35: =-(SUMIFS(I_TB!$C$6:$C$265,I_TB!$E$6:$E$265,"Retained earnings")+SUMIFS(T_GL!$J$6:$J$4005,T_GL!$M$6:$M$4005,"Retained earnings",T_GL!$A$6:$A$4005,"<="&D$4)) -> -2.6984347e+09 | E35: =D35-G35 -> -2.6984347e+09 | F35: =E35-C35 -> 0 | G35: =-SUMIFS(T_Kas_Rencana!$E$6:$E$305,T_Kas_Rencana!$C$6:$C$305,"Retained earnings",T_Kas_Rencana!$F$6:$F$305,1)+0 -> 0
A36: Current year profit | B36: =-(SUMIFS(I_TB!$C$6:$C$265,I_TB!$D$6:$D$265,"LabaRugi")+SUMIFS(T_GL!$J$6:$J$4005,T_GL!$K$6:$K$4005,"LabaRugi",T_GL!$A$6:$A$4005,"<="&B$4)) -> -6.6243546e+08 | C36: =-(SUMIFS(I_TB!$C$6:$C$265,I_TB!$D$6:$D$265,"LabaRugi")+SUMIFS(T_GL!$J$6:$J$4005,T_GL!$K$6:$K$4005,"LabaRugi",T_GL!$A$6:$A$4005,"<="&C$4)) -> -4.8714329e+08 | D36: =-(SUMIFS(I_TB!$C$6:$C$265,I_TB!$D$6:$D$265,"LabaRugi")+SUMIFS(T_GL!$J$6:$J$4005,T_GL!$K$6:$K$4005,"LabaRugi",T_GL!$A$6:$A$4005,"<="&D$4)) -> -4.9718568e+08 | E36: =D36-G36 -> -5.9471942e+08 | F36: =E36-C36 -> -1.0757613e+08 | G36: =-$B$72 -> 97533739
A37: TOTAL EQUITY | B37: =SUM(B34:B36) -> 1.6391299e+09 | C37: =SUM(C34:C36) -> 1.814422e+09 | D37: =SUM(D34:D36) -> 1.8043797e+09 | E37: =SUM(E34:E36) -> 1.7068459e+09 | F37: =SUM(F34:F36) -> -1.0757613e+08
A38: TOTAL LIABILITIES AND EQUITY | B38: =B31+B37 -> 6.5847491e+09 | C38: =C31+C37 -> 6.7529986e+09 | D38: =D31+D37 -> 9.5574054e+09 | E38: =E31+E37 -> 8.5312884e+09 | F38: =F31+F37 -> 1.7782898e+09
A39: Kontrol: aset − (liabilitas + ekuitas) (harus 0) | B39: =ROUND(B20-B38,0) -> 0 | C39: =ROUND(C20-C38,0) -> 0 | D39: =ROUND(D20-D38,0) -> 0 | E39: =ROUND(E20-E38,0) -> 0 | F39: =ROUND(F20-F38,0) -> 0
A59: ARUS RENCANA MINGGU INI (dipakai untuk proyeksi neraca dan arus kas)
A60: Biaya produksi rencana (LB + angkut + maklon) | B60: =SUMIFS(T_Batch!$S$6:$S$55,T_Batch!$B$6:$B$55,"Rencana",T_Batch!$A$6:$A$55,">="&I_Parameter!$C$4,T_Batch!$A$6:$A$55,"<="&I_Parameter!$C$6) -> 7.5255647e+08
A61: Pembelian live bird rencana | B61: =SUMIFS(T_Batch!$R$6:$R$55,T_Batch!$B$6:$B$55,"Rencana",T_Batch!$A$6:$A$55,">="&I_Parameter!$C$4,T_Batch!$A$6:$A$55,"<="&I_Parameter!$C$6) -> 6.8219439e+08
A62: Angkut + maklon rencana | B62: =SUMIFS(T_Batch!$G$6:$G$55,T_Batch!$B$6:$B$55,"Rencana",T_Batch!$A$6:$A$55,">="&I_Parameter!$C$4,T_Batch!$A$6:$A$55,"<="&I_Parameter!$C$6)+SUMIFS(T_Batch!$H$6:$H$55,T_Batch!$B$6:$B$55,"Rencana",T_Batch!$A$6:$A$55,">="&I_Parameter!$C$4,T_Batch!$A$6:$A$55,"<="&I_Parameter!$C$6) -> 70362080
A63: Pembelian trading rencana | B63: =SUMIFS(T_Penerimaan!$K$6:$K$1005,T_Penerimaan!$C$6:$C$1005,"Beli Trading",T_Penerimaan!$B$6:$B$1005,"Rencana",T_Penerimaan!$M$6:$M$1005,1) -> 1.9999997e+08
A64: Bayar live bird jatuh tempo minggu ini (rencana) | B64: =SUMIFS(T_Batch!$R$6:$R$55,T_Batch!$B$6:$B$55,"Rencana",T_Batch!$A$6:$A$55,">="&(I_Parameter!$C$4-I_Parameter!$C$14),T_Batch!$A$6:$A$55,"<="&(I_Parameter!$C$6-I_Parameter!$C$14)) -> 0
A65: Bayar pembelian trading jatuh tempo minggu ini (rencana) | B65: =SUMIFS(T_Penerimaan!$K$6:$K$1005,T_Penerimaan!$C$6:$C$1005,"Beli Trading",T_Penerimaan!$B$6:$B$1005,"Rencana",T_Penerimaan!$A$6:$A$1005,">="&(I_Parameter!$C$4-I_Parameter!$C$15),T_Penerimaan!$A$6:$A$1005,"<="&(I_Parameter!$C$6-I_Parameter!$C$15)) -> 0
A66: Bayar angkut + maklon jatuh tempo minggu ini (rencana) | B66: =SUMIFS(T_Batch!$G$6:$G$55,T_Batch!$B$6:$B$55,"Rencana",T_Batch!$A$6:$A$55,">="&(I_Parameter!$C$4-I_Parameter!$C$48),T_Batch!$A$6:$A$55,"<="&(I_Parameter!$C$6-I_Parameter!$C$48))+SUMIFS(T_Batch!$H$6:$H$55,T_Batch!$B$6:$B$55,"Rencana",T_Batch!$A$6:$A$55,">="&(I_Parameter!$C$4-I_Parameter!$C$48),T_Batch!$A$6:$A$55,"<="&(I_Parameter!$C$6-I_Parameter!$C$48)) -> 0
A67: Revenue sisa minggu | B67: =O_PnL!D9 -> 1.0678255e+09
A68: COGS live bird sisa minggu | B68: =-O_PnL!D10 -> 6.8390599e+08
A69: COGS trading sisa minggu | B69: =-O_PnL!D11 -> 4.3645682e+08
A70: Biaya run-rate (excl. D&A), net | B70: =-(O_PnL!D35-O_PnL!D9-O_PnL!D10-O_PnL!D11) -> 43655290
A71: D&A sisa minggu | B71: =-O_PnL!D36 -> 1341091.7
A72: Laba bersih sisa minggu | B72: =O_PnL!D37 -> -97533739
A73: Arus kas bersih sisa minggu (O_CF) | B73: =O_CF!D18 -> -471053116

Sheet O_CF
A1: ARUS KAS MINGGUAN (metode langsung) — Rp
A2: Aktual = baris kas di jurnal Accurate, dikategorikan dari akun lawan. Sisa minggu = T_Kas_Rencana + pembayaran live bird / trading / angkut-maklon yang jatuh tempo (dari rencana).
A5: Kategori | B5: Minggu lalu (aktual) | C5: Minggu ini aktual s.d. kemarin | D5: Sisa minggu (rencana) | E5: Proyeksi minggu ini
A6: Penerimaan dari pelanggan | B6: =SUMIFS(T_GL!$J$6:$J$4005,T_GL!$S$6:$S$4005,"Penerimaan dari pelanggan",T_GL!$A$6:$A$4005,">="&(I_Parameter!$C$5-7),T_GL!$A$6:$A$4005,"<="&(I_Parameter!$C$5-1)) -> 1602851638 | C6: =SUMIFS(T_GL!$J$6:$J$4005,T_GL!$S$6:$S$4005,"Penerimaan dari pelanggan",T_GL!$A$6:$A$4005,">="&I_Parameter!$C$5,T_GL!$A$6:$A$4005,"<="&(I_Parameter!$C$4-1)) -> 358371900 | D6: =SUMIFS(T_Kas_Rencana!$E$6:$E$305,T_Kas_Rencana!$B$6:$B$305,"Penerimaan dari pelanggan",T_Kas_Rencana!$F$6:$F$305,1) -> 1514506548 | E6: =C6+D6 -> 1872878448
A7: Penerimaan lain | B7: =SUMIFS(T_GL!$J$6:$J$4005,T_GL!$S$6:$S$4005,"Penerimaan lain",T_GL!$A$6:$A$4005,">="&(I_Parameter!$C$5-7),T_GL!$A$6:$A$4005,"<="&(I_Parameter!$C$5-1)) -> 0 | C7: =SUMIFS(T_GL!$J$6:$J$4005,T_GL!$S$6:$S$4005,"Penerimaan lain",T_GL!$A$6:$A$4005,">="&I_Parameter!$C$5,T_GL!$A$6:$A$4005,"<="&(I_Parameter!$C$4-1)) -> 0 | D7: =SUMIFS(T_Kas_Rencana!$E$6:$E$305,T_Kas_Rencana!$B$6:$B$305,"Penerimaan lain",T_Kas_Rencana!$F$6:$F$305,1) -> 0 | E7: =C7+D7 -> 0
A8: Bayar pemasok barang (live bird & trading) | B8: =SUMIFS(T_GL!$J$6:$J$4005,T_GL!$S$6:$S$4005,"Bayar pemasok barang (live bird & trading)",T_GL!$A$6:$A$4005,">="&(I_Parameter!$C$5-7),T_GL!$A$6:$A$4005,"<="&(I_Parameter!$C$5-1)) -> -2131309780 | C8: =SUMIFS(T_GL!$J$6:$J$4005,T_GL!$S$6:$S$4005,"Bayar pemasok barang (live bird & trading)",T_GL!$A$6:$A$4005,">="&I_Parameter!$C$5,T_GL!$A$6:$A$4005,"<="&(I_Parameter!$C$4-1)) -> -588766720 | D8: =SUMIFS(T_Kas_Rencana!$E$6:$E$305,T_Kas_Rencana!$B$6:$B$305,"Bayar pemasok barang (live bird & trading)",T_Kas_Rencana!$F$6:$F$305,1)-O_BS!$B$64-O_BS!$B$65 -> -736186640 | E8: =C8+D8 -> -1324953360
A9: Bayar jasa (maklon, angkut, cold storage, sewa) | B9: =SUMIFS(T_GL!$J$6:$J$4005,T_GL!$S$6:$S$4005,"Bayar jasa (maklon, angkut, cold storage, sewa)",T_GL!$A$6:$A$4005,">="&(I_Parameter!$C$5-7),T_GL!$A$6:$A$4005,"<="&(I_Parameter!$C$5-1)) -> -230971062 | C9: =SUMIFS(T_GL!$J$6:$J$4005,T_GL!$S$6:$S$4005,"Bayar jasa (maklon, angkut, cold storage, sewa)",T_GL!$A$6:$A$4005,">="&I_Parameter!$C$5,T_GL!$A$6:$A$4005,"<="&(I_Parameter!$C$4-1)) -> -59445000 | D9: =SUMIFS(T_Kas_Rencana!$E$6:$E$305,T_Kas_Rencana!$B$6:$B$305,"Bayar jasa (maklon, angkut, cold storage, sewa)",T_Kas_Rencana!$F$6:$F$305,1)-O_BS!$B$66 -> -1169511318 | E9: =C9+D9 -> -1228956318
A10: Bayar karyawan | B10: =SUMIFS(T_GL!$J$6:$J$4005,T_GL!$S$6:$S$4005,"Bayar karyawan",T_GL!$A$6:$A$4005,">="&(I_Parameter!$C$5-7),T_GL!$A$6:$A$4005,"<="&(I_Parameter!$C$5-1)) -> -5823844 | C10: =SUMIFS(T_GL!$J$6:$J$4005,T_GL!$S$6:$S$4005,"Bayar karyawan",T_GL!$A$6:$A$4005,">="&I_Parameter!$C$5,T_GL!$A$6:$A$4005,"<="&(I_Parameter!$C$4-1)) -> 0 | D10: =SUMIFS(T_Kas_Rencana!$E$6:$E$305,T_Kas_Rencana!$B$6:$B$305,"Bayar karyawan",T_Kas_Rencana!$F$6:$F$305,1) -> -79741706 | E10: =C10+D10 -> -79741706
A11: Bayar biaya operasional lain | B11: =SUMIFS(T_GL!$J$6:$J$4005,T_GL!$S$6:$S$4005,"Bayar biaya operasional lain",T_GL!$A$6:$A$4005,">="&(I_Parameter!$C$5-7),T_GL!$A$6:$A$4005,"<="&(I_Parameter!$C$5-1)) -> -20053416 | C11: =SUMIFS(T_GL!$J$6:$J$4005,T_GL!$S$6:$S$4005,"Bayar biaya operasional lain",T_GL!$A$6:$A$4005,">="&I_Parameter!$C$5,T_GL!$A$6:$A$4005,"<="&(I_Parameter!$C$4-1)) -> 0 | D11: =SUMIFS(T_Kas_Rencana!$E$6:$E$305,T_Kas_Rencana!$B$6:$B$305,"Bayar biaya operasional lain",T_Kas_Rencana!$F$6:$F$305,1) -> 0 | E11: =C11+D11 -> 0
A12: Bayar pajak | B12: =SUMIFS(T_GL!$J$6:$J$4005,T_GL!$S$6:$S$4005,"Bayar pajak",T_GL!$A$6:$A$4005,">="&(I_Parameter!$C$5-7),T_GL!$A$6:$A$4005,"<="&(I_Parameter!$C$5-1)) -> 0 | C12: =SUMIFS(T_GL!$J$6:$J$4005,T_GL!$S$6:$S$4005,"Bayar pajak",T_GL!$A$6:$A$4005,">="&I_Parameter!$C$5,T_GL!$A$6:$A$4005,"<="&(I_Parameter!$C$4-1)) -> 0 | D12: =SUMIFS(T_Kas_Rencana!$E$6:$E$305,T_Kas_Rencana!$B$6:$B$305,"Bayar pajak",T_Kas_Rencana!$F$6:$F$305,1) -> 0 | E12: =C12+D12 -> 0
A13: Bunga & biaya bank | B13: =SUMIFS(T_GL!$J$6:$J$4005,T_GL!$S$6:$S$4005,"Bunga & biaya bank",T_GL!$A$6:$A$4005,">="&(I_Parameter!$C$5-7),T_GL!$A$6:$A$4005,"<="&(I_Parameter!$C$5-1)) -> -10000 | C13: =SUMIFS(T_GL!$J$6:$J$4005,T_GL!$S$6:$S$4005,"Bunga & biaya bank",T_GL!$A$6:$A$4005,">="&I_Parameter!$C$5,T_GL!$A$6:$A$4005,"<="&(I_Parameter!$C$4-1)) -> 0 | D13: =SUMIFS(T_Kas_Rencana!$E$6:$E$305,T_Kas_Rencana!$B$6:$B$305,"Bunga & biaya bank",T_Kas_Rencana!$F$6:$F$305,1) -> -120000 | E13: =C13+D13 -> -120000
A14: Belanja aset tetap | B14: =SUMIFS(T_GL!$J$6:$J$4005,T_GL!$S$6:$S$4005,"Belanja aset tetap",T_GL!$A$6:$A$4005,">="&(I_Parameter!$C$5-7),T_GL!$A$6:$A$4005,"<="&(I_Parameter!$C$5-1)) -> 0 | C14: =SUMIFS(T_GL!$J$6:$J$4005,T_GL!$S$6:$S$4005,"Belanja aset tetap",T_GL!$A$6:$A$4005,">="&I_Parameter!$C$5,T_GL!$A$6:$A$4005,"<="&(I_Parameter!$C$4-1)) -> 0 | D14: =SUMIFS(T_Kas_Rencana!$E$6:$E$305,T_Kas_Rencana!$B$6:$B$305,"Belanja aset tetap",T_Kas_Rencana!$F$6:$F$305,1) -> 0 | E14: =C14+D14 -> 0
A15: Pinjaman afiliasi (net) | B15: =SUMIFS(T_GL!$J$6:$J$4005,T_GL!$S$6:$S$4005,"Pinjaman afiliasi (net)",T_GL!$A$6:$A$4005,">="&(I_Parameter!$C$5-7),T_GL!$A$6:$A$4005,"<="&(I_Parameter!$C$5-1)) -> 0 | C15: =SUMIFS(T_GL!$J$6:$J$4005,T_GL!$S$6:$S$4005,"Pinjaman afiliasi (net)",T_GL!$A$6:$A$4005,">="&I_Parameter!$C$5,T_GL!$A$6:$A$4005,"<="&(I_Parameter!$C$4-1)) -> 1200000000 | D15: =SUMIFS(T_Kas_Rencana!$E$6:$E$305,T_Kas_Rencana!$B$6:$B$305,"Pinjaman afiliasi (net)",T_Kas_Rencana!$F$6:$F$305,1) -> 0 | E15: =C15+D15 -> 1200000000
A16: Setoran modal | B16: =SUMIFS(T_GL!$J$6:$J$4005,T_GL!$S$6:$S$4005,"Setoran modal",T_GL!$A$6:$A$4005,">="&(I_Parameter!$C$5-7),T_GL!$A$6:$A$4005,"<="&(I_Parameter!$C$5-1)) -> 0 | C16: =SUMIFS(T_GL!$J$6:$J$4005,T_GL!$S$6:$S$4005,"Setoran modal",T_GL!$A$6:$A$4005,">="&I_Parameter!$C$5,T_GL!$A$6:$A$4005,"<="&(I_Parameter!$C$4-1)) -> 0 | D16: =SUMIFS(T_Kas_Rencana!$E$6:$E$305,T_Kas_Rencana!$B$6:$B$305,"Setoran modal",T_Kas_Rencana!$F$6:$F$305,1) -> 0 | E16: =C16+D16 -> 0
A17: Transfer antar rekening | B17: =SUMIFS(T_GL!$J$6:$J$4005,T_GL!$S$6:$S$4005,"Transfer antar rekening",T_GL!$A$6:$A$4005,">="&(I_Parameter!$C$5-7),T_GL!$A$6:$A$4005,"<="&(I_Parameter!$C$5-1)) -> 0 | C17: =SUMIFS(T_GL!$J$6:$J$4005,T_GL!$S$6:$S$4005,"Transfer antar rekening",T_GL!$A$6:$A$4005,">="&I_Parameter!$C$5,T_GL!$A$6:$A$4005,"<="&(I_Parameter!$C$4-1)) -> 0 | D17: =SUMIFS(T_Kas_Rencana!$E$6:$E$305,T_Kas_Rencana!$B$6:$B$305,"Transfer antar rekening",T_Kas_Rencana!$F$6:$F$305,1) -> 0 | E17: =C17+D17 -> 0
A18: ARUS KAS BERSIH | B18: =SUM(B6:B17) -> -785316464 | C18: =SUM(C6:C17) -> 910160180 | D18: =SUM(D6:D17) -> -471053116 | E18: =SUM(E6:E17) -> 439107064
A20: Saldo kas awal | B20: =O_BS!C7-B18 -> 1.1644076e+09 | C20: =O_BS!C7 -> 3.7909117e+08 | D20: =O_BS!D7 -> 1.2892513e+09 | E20: =C20 -> 3.7909117e+08
A21: Arus kas bersih | B21: =B18 -> -785316464 | C21: =C18 -> 910160180 | D21: =D18 -> -471053116 | E21: =E18 -> 439107064
A22: Saldo kas akhir | B22: =B20+B21 -> 3.7909117e+08 | C22: =C20+C21 -> 1.2892513e+09 | D22: =D20+D21 -> 8.1819823e+08 | E22: =E20+E21 -> 8.1819823e+08
A23: Kontrol: saldo kas akhir = neraca (harus 0) | B23: =ROUND(B22-O_BS!C7,0) -> 0 | C23: =ROUND(C22-O_BS!D7,0) -> 0 | E23: =ROUND(E22-O_BS!E7,0) -> 0
A26: SALDO KAS HARIAN — minggu ini
A27: Tanggal | B27: Arus kas bersih | C27: Saldo akhir hari | D27: Basis
A28: =I_Parameter!$C$5+0 -> 46258 | B28: =IF(A28<I_Parameter!$C$4,SUMIFS(T_GL!$J$6:$J$4005,T_GL!$N$6:$N$4005,"Y",T_GL!$A$6:$A$4005,A28),SUMIFS(T_Kas_Rencana!$E$6:$E$305,T_Kas_Rencana!$A$6:$A$305,A28)-SUMIFS(T_Batch!$R$6:$R$55,T_Batch!$B$6:$B$55,"Rencana",T_Batch!$A$6:$A$55,A28-I_Parameter!$C$14)-SUMIFS(T_Penerimaan!$K$6:$K$1005,T_Penerimaan!$C$6:$C$1005,"Beli Trading",T_Penerimaan!$B$6:$B$1005,"Rencana",T_Penerimaan!$A$6:$A$1005,A28-I_Parameter!$C$15)-SUMIFS(T_Batch!$G$6:$G$55,T_Batch!$B$6:$B$55,"Rencana",T_Batch!$A$6:$A$55,A28-I_Parameter!$C$48)-SUMIFS(T_Batch!$H$6:$H$55,T_Batch!$B$6:$B$55,"Rencana",T_Batch!$A$6:$A$55,A28-I_Parameter!$C$48)) -> 175957400 | C28: =O_BS!C7+B28 -> 5.5504857e+08 | D28: =IF(A28<I_Parameter!$C$4,"aktual","rencana") -> aktual
A29: =I_Parameter!$C$5+1 -> 46259 | B29: =IF(A29<I_Parameter!$C$4,SUMIFS(T_GL!$J$6:$J$4005,T_GL!$N$6:$N$4005,"Y",T_GL!$A$6:$A$4005,A29),SUMIFS(T_Kas_Rencana!$E$6:$E$305,T_Kas_Rencana!$A$6:$A$305,A29)-SUMIFS(T_Batch!$R$6:$R$55,T_Batch!$B$6:$B$55,"Rencana",T_Batch!$A$6:$A$55,A29-I_Parameter!$C$14)-SUMIFS(T_Penerimaan!$K$6:$K$1005,T_Penerimaan!$C$6:$C$1005,"Beli Trading",T_Penerimaan!$B$6:$B$1005,"Rencana",T_Penerimaan!$A$6:$A$1005,A29-I_Parameter!$C$15)-SUMIFS(T_Batch!$G$6:$G$55,T_Batch!$B$6:$B$55,"Rencana",T_Batch!$A$6:$A$55,A29-I_Parameter!$C$48)-SUMIFS(T_Batch!$H$6:$H$55,T_Batch!$B$6:$B$55,"Rencana",T_Batch!$A$6:$A$55,A29-I_Parameter!$C$48)) -> 96934100 | C29: =C28+B29 -> 6.5198267e+08 | D29: =IF(A29<I_Parameter!$C$4,"aktual","rencana") -> aktual
A30: =I_Parameter!$C$5+2 -> 46260 | B30: =IF(A30<I_Parameter!$C$4,SUMIFS(T_GL!$J$6:$J$4005,T_GL!$N$6:$N$4005,"Y",T_GL!$A$6:$A$4005,A30),SUMIFS(T_Kas_Rencana!$E$6:$E$305,T_Kas_Rencana!$A$6:$A$305,A30)-SUMIFS(T_Batch!$R$6:$R$55,T_Batch!$B$6:$B$55,"Rencana",T_Batch!$A$6:$A$55,A30-I_Parameter!$C$14)-SUMIFS(T_Penerimaan!$K$6:$K$1005,T_Penerimaan!$C$6:$C$1005,"Beli Trading",T_Penerimaan!$B$6:$B$1005,"Rencana",T_Penerimaan!$A$6:$A$1005,A30-I_Parameter!$C$15)-SUMIFS(T_Batch!$G$6:$G$55,T_Batch!$B$6:$B$55,"Rencana",T_Batch!$A$6:$A$55,A30-I_Parameter!$C$48)-SUMIFS(T_Batch!$H$6:$H$55,T_Batch!$B$6:$B$55,"Rencana",T_Batch!$A$6:$A$55,A30-I_Parameter!$C$48)) -> 637268680 | C30: =C29+B30 -> 1.2892513e+09 | D30: =IF(A30<I_Parameter!$C$4,"aktual","rencana") -> aktual
A31: =I_Parameter!$C$5+3 -> 46261 | B31: =IF(A31<I_Parameter!$C$4,SUMIFS(T_GL!$J$6:$J$4005,T_GL!$N$6:$N$4005,"Y",T_GL!$A$6:$A$4005,A31),SUMIFS(T_Kas_Rencana!$E$6:$E$305,T_Kas_Rencana!$A$6:$A$305,A31)-SUMIFS(T_Batch!$R$6:$R$55,T_Batch!$B$6:$B$55,"Rencana",T_Batch!$A$6:$A$55,A31-I_Parameter!$C$14)-SUMIFS(T_Penerimaan!$K$6:$K$1005,T_Penerimaan!$C$6:$C$1005,"Beli Trading",T_Penerimaan!$B$6:$B$1005,"Rencana",T_Penerimaan!$A$6:$A$1005,A31-I_Parameter!$C$15)-SUMIFS(T_Batch!$G$6:$G$55,T_Batch!$B$6:$B$55,"Rencana",T_Batch!$A$6:$A$55,A31-I_Parameter!$C$48)-SUMIFS(T_Batch!$H$6:$H$55,T_Batch!$B$6:$B$55,"Rencana",T_Batch!$A$6:$A$55,A31-I_Parameter!$C$48)) -> 59620700 | C31: =C30+B31 -> 1.348872e+09 | D31: =IF(A31<I_Parameter!$C$4,"aktual","rencana") -> rencana
A32: =I_Parameter!$C$5+4 -> 46262 | B32: =IF(A32<I_Parameter!$C$4,SUMIFS(T_GL!$J$6:$J$4005,T_GL!$N$6:$N$4005,"Y",T_GL!$A$6:$A$4005,A32),SUMIFS(T_Kas_Rencana!$E$6:$E$305,T_Kas_Rencana!$A$6:$A$305,A32)-SUMIFS(T_Batch!$R$6:$R$55,T_Batch!$B$6:$B$55,"Rencana",T_Batch!$A$6:$A$55,A32-I_Parameter!$C$14)-SUMIFS(T_Penerimaan!$K$6:$K$1005,T_Penerimaan!$C$6:$C$1005,"Beli Trading",T_Penerimaan!$B$6:$B$1005,"Rencana",T_Penerimaan!$A$6:$A$1005,A32-I_Parameter!$C$15)-SUMIFS(T_Batch!$G$6:$G$55,T_Batch!$B$6:$B$55,"Rencana",T_Batch!$A$6:$A$55,A32-I_Parameter!$C$48)-SUMIFS(T_Batch!$H$6:$H$55,T_Batch!$B$6:$B$55,"Rencana",T_Batch!$A$6:$A$55,A32-I_Parameter!$C$48)) -> -1059199936 | C32: =C31+B32 -> 2.8967211e+08 | D32: =IF(A32<I_Parameter!$C$4,"aktual","rencana") -> rencana
A33: =I_Parameter!$C$5+5 -> 46263 | B33: =IF(A33<I_Parameter!$C$4,SUMIFS(T_GL!$J$6:$J$4005,T_GL!$N$6:$N$4005,"Y",T_GL!$A$6:$A$4005,A33),SUMIFS(T_Kas_Rencana!$E$6:$E$305,T_Kas_Rencana!$A$6:$A$305,A33)-SUMIFS(T_Batch!$R$6:$R$55,T_Batch!$B$6:$B$55,"Rencana",T_Batch!$A$6:$A$55,A33-I_Parameter!$C$14)-SUMIFS(T_Penerimaan!$K$6:$K$1005,T_Penerimaan!$C$6:$C$1005,"Beli Trading",T_Penerimaan!$B$6:$B$1005,"Rencana",T_Penerimaan!$A$6:$A$1005,A33-I_Parameter!$C$15)-SUMIFS(T_Batch!$G$6:$G$55,T_Batch!$B$6:$B$55,"Rencana",T_Batch!$A$6:$A$55,A33-I_Parameter!$C$48)-SUMIFS(T_Batch!$H$6:$H$55,T_Batch!$B$6:$B$55,"Rencana",T_Batch!$A$6:$A$55,A33-I_Parameter!$C$48)) -> 528526120 | C33: =C32+B33 -> 8.1819823e+08 | D33: =IF(A33<I_Parameter!$C$4,"aktual","rencana") -> rencana
A34: =I_Parameter!$C$5+6 -> 46264 | B34: =IF(A34<I_Parameter!$C$4,SUMIFS(T_GL!$J$6:$J$4005,T_GL!$N$6:$N$4005,"Y",T_GL!$A$6:$A$4005,A34),SUMIFS(T_Kas_Rencana!$E$6:$E$305,T_Kas_Rencana!$A$6:$A$305,A34)-SUMIFS(T_Batch!$R$6:$R$55,T_Batch!$B$6:$B$55,"Rencana",T_Batch!$A$6:$A$55,A34-I_Parameter!$C$14)-SUMIFS(T_Penerimaan!$K$6:$K$1005,T_Penerimaan!$C$6:$C$1005,"Beli Trading",T_Penerimaan!$B$6:$B$1005,"Rencana",T_Penerimaan!$A$6:$A$1005,A34-I_Parameter!$C$15)-SUMIFS(T_Batch!$G$6:$G$55,T_Batch!$B$6:$B$55,"Rencana",T_Batch!$A$6:$A$55,A34-I_Parameter!$C$48)-SUMIFS(T_Batch!$H$6:$H$55,T_Batch!$B$6:$B$55,"Rencana",T_Batch!$A$6:$A$55,A34-I_Parameter!$C$48)) -> 0 | C34: =C33+B34 -> 8.1819823e+08 | D34: =IF(A34<I_Parameter!$C$4,"aktual","rencana") -> rencana
A35: Saldo kas terendah minggu ini | C35: =MIN(C28:C34) -> 2.8967211e+08

Sheet O_Stok
A1: STOK PER HARI DAN DAFTAR STOK YANG HARUS DIJUAL
A2: Stok akhir hari = stok kemarin + terima − jual. Hari yang sudah lewat pakai aktual; hari ini dan seterusnya pakai rencana terima + order.
H4: =I_Parameter!$C$5+0 -> 46258 | I4: =I_Parameter!$C$5+1 -> 46259 | J4: =I_Parameter!$C$5+2 -> 46260 | K4: =I_Parameter!$C$5+3 -> 46261 | L4: =I_Parameter!$C$5+4 -> 46262 | M4: =I_Parameter!$C$5+5 -> 46263 | N4: =I_Parameter!$C$5+6 -> 46264
A5: Key | B5: Kelompok | C5: Segmen | D5: Stok awal minggu kg | E5: Nilai stok awal Rp | F5: Umur rata -rata (hari) | G5: kg di atas batas umur | H5: Stok akhir hari 1 | I5: Stok akhir hari 2 | J5: Stok akhir hari 3 | K5: Stok akhir hari 4 | L5: Stok akhir hari 5 | M5: Stok akhir hari 6 | N5: Stok akhir hari 7 | O5: Terima minggu ini kg | P5: Nilai terima Rp | Q5: Biaya rata-rata Rp/kg | R5: Jual + order minggu kg | S5: Stok hari ini kg | T5: Order sisa minggu kg | U5: Stok − order sisa kg | V5: Stok terendah minggu kg | W5: Harga acuan Rp/kg | X5: Margin/kg di harga acuan | Y5: Nilai stok hari ini Rp | Z5: STATUS / TINDAKAN
A6: =I_Master!A6 -> RPA|BLDK|Fresh | B6: =IF(A6="","",INDEX(I_Master!$E$6:$E$85,MATCH(A6,I_Master!$A$6:$A$85,0))) -> Boneless & parting | C6: =IF(A6="","",INDEX(I_Master!$B$6:$B$85,MATCH(A6,I_Master!$A$6:$A$85,0))) -> RPA | D6: =IF(A6="","",SUMIFS(I_Stok_Awal!$D$6:$D$305,I_Stok_Awal!$C$6:$C$305,A6)) -> 0 | E6: =IF(A6="","",SUMIFS(I_Stok_Awal!$E$6:$E$305,I_Stok_Awal!$C$6:$C$305,A6)) -> 0 | F6: =IF(OR(A6="",D6<=0),"",SUMPRODUCT((I_Stok_Awal!$C$6:$C$305=A6)*I_Stok_Awal!$D$6:$D$305*I_Stok_Awal!$F$6:$F$305)/D6) | G6: =IF(A6="","",SUMIFS(I_Stok_Awal!$G$6:$G$305,I_Stok_Awal!$C$6:$C$305,A6)) -> 0 | H6: =IF($A6="","",D6+SUMIFS(T_Penerimaan!$I$6:$I$1005,T_Penerimaan!$H$6:$H$1005,$A6,T_Penerimaan!$A$6:$A$1005,H$4,T_Penerimaan!$M$6:$M$1005,1)-SUMIFS(T_Penjualan!$H$6:$H$1505,T_Penjualan!$G$6:$G$1505,$A6,T_Penjualan!$A$6:$A$1505,H$4,T_Penjualan!$P$6:$P$1505,1)) -> 0 | I6: =IF($A6="","",H6+SUMIFS(T_Penerimaan!$I$6:$I$1005,T_Penerimaan!$H$6:$H$1005,$A6,T_Penerimaan!$A$6:$A$1005,I$4,T_Penerimaan!$M$6:$M$1005,1)-SUMIFS(T_Penjualan!$H$6:$H$1505,T_Penjualan!$G$6:$G$1505,$A6,T_Penjualan!$A$6:$A$1505,I$4,T_Penjualan!$P$6:$P$1505,1)) -> 0 | J6: =IF($A6="","",I6+SUMIFS(T_Penerimaan!$I$6:$I$1005,T_Penerimaan!$H$6:$H$1005,$A6,T_Penerimaan!$A$6:$A$1005,J$4,T_Penerimaan!$M$6:$M$1005,1)-SUMIFS(T_Penjualan!$H$6:$H$1505,T_Penjualan!$G$6:$G$1505,$A6,T_Penjualan!$A$6:$A$1505,J$4,T_Penjualan!$P$6:$P$1505,1)) -> 0 | K6: =IF($A6="","",J6+SUMIFS(T_Penerimaan!$I$6:$I$1005,T_Penerimaan!$H$6:$H$1005,$A6,T_Penerimaan!$A$6:$A$1005,K$4,T_Penerimaan!$M$6:$M$1005,1)-SUMIFS(T_Penjualan!$H$6:$H$1505,T_Penjualan!$G$6:$G$1505,$A6,T_Penjualan!$A$6:$A$1505,K$4,T_Penjualan!$P$6:$P$1505,1)) -> 0 | L6: =IF($A6="","",K6+SUMIFS(T_Penerimaan!$I$6:$I$1005,T_Penerimaan!$H$6:$H$1005,$A6,T_Penerimaan!$A$6:$A$1005,L$4,T_Penerimaan!$M$6:$M$1005,1)-SUMIFS(T_Penjualan!$H$6:$H$1505,T_Penjualan!$G$6:$G$1505,$A6,T_Penjualan!$A$6:$A$1505,L$4,T_Penjualan!$P$6:$P$1505,1)) -> 0 | M6: =IF($A6="","",L6+SUMIFS(T_Penerimaan!$I$6:$I$1005,T_Penerimaan!$H$6:$H$1005,$A6,T_Penerimaan!$A$6:$A$1005,M$4,T_Penerimaan!$M$6:$M$1005,1)-SUMIFS(T_Penjualan!$H$6:$H$1505,T_Penjualan!$G$6:$G$1505,$A6,T_Penjualan!$A$6:$A$1505,M$4,T_Penjualan!$P$6:$P$1505,1)) -> 0 | N6: =IF($A6="","",M6+SUMIFS(T_Penerimaan!$I$6:$I$1005,T_Penerimaan!$H$6:$H$1005,$A6,T_Penerimaan!$A$6:$A$1005,N$4,T_Penerimaan!$M$6:$M$1005,1)-SUMIFS(T_Penjualan!$H$6:$H$1505,T_Penjualan!$G$6:$G$1505,$A6,T_Penjualan!$A$6:$A$1505,N$4,T_Penjualan!$P$6:$P$1505,1)) -> 0 | O6: =IF(A6="","",SUMIFS(T_Penerimaan!$I$6:$I$1005,T_Penerimaan!$H$6:$H$1005,A6,T_Penerimaan!$M$6:$M$1005,1)) -> 0 | P6: =IF(A6="","",SUMIFS(T_Penerimaan!$K$6:$K$1005,T_Penerimaan!$H$6:$H$1005,A6,T_Penerimaan!$M$6:$M$1005,1)) -> 0 | Q6: =IF(A6="","",IF(D6+O6<=0,0,(E6+P6)/(D6+O6))) -> 0 | R6: =IF(A6="","",SUMIFS(T_Penjualan!$H$6:$H$1505,T_Penjualan!$G$6:$G$1505,A6,T_Penjualan!$P$6:$P$1505,1)) -> 0 | S6: =IF(A6="","",IF(I_Parameter!$C$4<=I_Parameter!$C$5,D6,IF(I_Parameter!$C$4>I_Parameter!$C$6,N6,INDEX(H6:N6,I_Parameter!$C$4-I_Parameter!$C$5)))) -> 0 | T6: =IF(A6="","",SUMIFS(T_Penjualan!$H$6:$H$1505,T_Penjualan!$G$6:$G$1505,A6,T_Penjualan!$B$6:$B$1505,"Order",T_Penjualan!$A$6:$A$1505,">="&I_Parameter!$C$4,T_Penjualan!$A$6:$A$1505,"<="&I_Parameter!$C$6)) -> 0 | U6: =IF(A6="","",S6-T6) -> 0 | V6: =IF(A6="","",MIN(H6:N6)) -> 0 | W6: =IF(A6="","",INDEX(I_Master!$F$6:$F$85,MATCH(A6,I_Master!$A$6:$A$85,0))) -> 38000 | X6: =IF(OR(A6="",W6=""),"",W6-Q6) -> 38000 | Y6: =IF(A6="","",S6*Q6) -> 0 | Z6: =IF(A6="","",IF(V6<-0.5,"KURANG: stok minus "&ROUND(-V6,0)&" kg — beli/potong atau geser order",IF(AND(S6>0.5,T6<=0,G6>0.5),"JUAL: "&ROUND(S6,0)&" kg tanpa order, sebagian > batas umur",IF(AND(S6>0.5,T6<=0),"JUAL: "&ROUND(S6,0)&" kg tanpa order minggu ini",IF(G6>0.5,"PERHATIAN: "&ROUND(G6,0)&" kg di atas batas umur",IF(AND(X6<>"",X6<0,T6>0),"Order di bawah biaya rata-rata — cek harga","-")))))) -> -
A7: =I_Master!A7 -> RPA|BLD|Fresh | B7: =IF(A7="","",INDEX(I_Master!$E$6:$E$85,MATCH(A7,I_Master!$A$6:$A$85,0))) -> Boneless & parting | C7: =IF(A7="","",INDEX(I_Master!$B$6:$B$85,MATCH(A7,I_Master!$A$6:$A$85,0))) -> RPA | D7: =IF(A7="","",SUMIFS(I_Stok_Awal!$D$6:$D$305,I_Stok_Awal!$C$6:$C$305,A7)) -> 0 | E7: =IF(A7="","",SUMIFS(I_Stok_Awal!$E$6:$E$305,I_Stok_Awal!$C$6:$C$305,A7)) -> 0 | F7: =IF(OR(A7="",D7<=0),"",SUMPRODUCT((I_Stok_Awal!$C$6:$C$305=A7)*I_Stok_Awal!$D$6:$D$305*I_Stok_Awal!$F$6:$F$305)/D7) | G7: =IF(A7="","",SUMIFS(I_Stok_Awal!$G$6:$G$305,I_Stok_Awal!$C$6:$C$305,A7)) -> 0 | H7: =IF($A7="","",D7+SUMIFS(T_Penerimaan!$I$6:$I$1005,T_Penerimaan!$H$6:$H$1005,$A7,T_Penerimaan!$A$6:$A$1005,H$4,T_Penerimaan!$M$6:$M$1005,1)-SUMIFS(T_Penjualan!$H$6:$H$1505,T_Penjualan!$G$6:$G$1505,$A7,T_Penjualan!$A$6:$A$1505,H$4,T_Penjualan!$P$6:$P$1505,1)) -> 0 | I7: =IF($A7="","",H7+SUMIFS(T_Penerimaan!$I$6:$I$1005,T_Penerimaan!$H$6:$H$1005,$A7,T_Penerimaan!$A$6:$A$1005,I$4,T_Penerimaan!$M$6:$M$1005,1)-SUMIFS(T_Penjualan!$H$6:$H$1505,T_Penjualan!$G$6:$G$1505,$A7,T_Penjualan!$A$6:$A$1505,I$4,T_Penjualan!$P$6:$P$1505,1)) -> 0 | J7: =IF($A7="","",I7+SUMIFS(T_Penerimaan!$I$6:$I$1005,T_Penerimaan!$H$6:$H$1005,$A7,T_Penerimaan!$A$6:$A$1005,J$4,T_Penerimaan!$M$6:$M$1005,1)-SUMIFS(T_Penjualan!$H$6:$H$1505,T_Penjualan!$G$6:$G$1505,$A7,T_Penjualan!$A$6:$A$1505,J$4,T_Penjualan!$P$6:$P$1505,1)) -> 0 | K7: =IF($A7="","",J7+SUMIFS(T_Penerimaan!$I$6:$I$1005,T_Penerimaan!$H$6:$H$1005,$A7,T_Penerimaan!$A$6:$A$1005,K$4,T_Penerimaan!$M$6:$M$1005,1)-SUMIFS(T_Penjualan!$H$6:$H$1505,T_Penjualan!$G$6:$G$1505,$A7,T_Penjualan!$A$6:$A$1505,K$4,T_Penjualan!$P$6:$P$1505,1)) -> 0 | L7: =IF($A7="","",K7+SUMIFS(T_Penerimaan!$I$6:$I$1005,T_Penerimaan!$H$6:$H$1005,$A7,T_Penerimaan!$A$6:$A$1005,L$4,T_Penerimaan!$M$6:$M$1005,1)-SUMIFS(T_Penjualan!$H$6:$H$1505,T_Penjualan!$G$6:$G$1505,$A7,T_Penjualan!$A$6:$A$1505,L$4,T_Penjualan!$P$6:$P$1505,1)) -> 0 | M7: =IF($A7="","",L7+SUMIFS(T_Penerimaan!$I$6:$I$1005,T_Penerimaan!$H$6:$H$1005,$A7,T_Penerimaan!$A$6:$A$1005,M$4,T_Penerimaan!$M$6:$M$1005,1)-SUMIFS(T_Penjualan!$H$6:$H$1505,T_Penjualan!$G$6:$G$1505,$A7,T_Penjualan!$A$6:$A$1505,M$4,T_Penjualan!$P$6:$P$1505,1)) -> 0 | N7: =IF($A7="","",M7+SUMIFS(T_Penerimaan!$I$6:$I$1005,T_Penerimaan!$H$6:$H$1005,$A7,T_Penerimaan!$A$6:$A$1005,N$4,T_Penerimaan!$M$6:$M$1005,1)-SUMIFS(T_Penjualan!$H$6:$H$1505,T_Penjualan!$G$6:$G$1505,$A7,T_Penjualan!$A$6:$A$1505,N$4,T_Penjualan!$P$6:$P$1505,1)) -> 0 | O7: =IF(A7="","",SUMIFS(T_Penerimaan!$I$6:$I$1005,T_Penerimaan!$H$6:$H$1005,A7,T_Penerimaan!$M$6:$M$1005,1)) -> 0 | P7: =IF(A7="","",SUMIFS(T_Penerimaan!$K$6:$K$1005,T_Penerimaan!$H$6:$H$1005,A7,T_Penerimaan!$M$6:$M$1005,1)) -> 0 | Q7: =IF(A7="","",IF(D7+O7<=0,0,(E7+P7)/(D7+O7))) -> 0 | R7: =IF(A7="","",SUMIFS(T_Penjualan!$H$6:$H$1505,T_Penjualan!$G$6:$G$1505,A7,T_Penjualan!$P$6:$P$1505,1)) -> 0 | S7: =IF(A7="","",IF(I_Parameter!$C$4<=I_Parameter!$C$5,D7,IF(I_Parameter!$C$4>I_Parameter!$C$6,N7,INDEX(H7:N7,I_Parameter!$C$4-I_Parameter!$C$5)))) -> 0 | T7: =IF(A7="","",SUMIFS(T_Penjualan!$H$6:$H$1505,T_Penjualan!$G$6:$G$1505,A7,T_Penjualan!$B$6:$B$1505,"Order",T_Penjualan!$A$6:$A$1505,">="&I_Parameter!$C$4,T_Penjualan!$A$6:$A$1505,"<="&I_Parameter!$C$6)) -> 0 | U7: =IF(A7="","",S7-T7) -> 0 | V7: =IF(A7="","",MIN(H7:N7)) -> 0 | W7: =IF(A7="","",INDEX(I_Master!$F$6:$F$85,MATCH(A7,I_Master!$A$6:$A$85,0))) -> 41000 | X7: =IF(OR(A7="",W7=""),"",W7-Q7) -> 41000 | Y7: =IF(A7="","",S7*Q7) -> 0 | Z7: =IF(A7="","",IF(V7<-0.5,"KURANG: stok minus "&ROUND(-V7,0)&" kg — beli/potong atau geser order",IF(AND(S7>0.5,T7<=0,G7>0.5),"JUAL: "&ROUND(S7,0)&" kg tanpa order, sebagian > batas umur",IF(AND(S7>0.5,T7<=0),"JUAL: "&ROUND(S7,0)&" kg tanpa order minggu ini",IF(G7>0.5,"PERHATIAN: "&ROUND(G7,0)&" kg di atas batas umur",IF(AND(X7<>"",X7<0,T7>0),"Order di bawah biaya rata-rata — cek harga","-")))))) -> -
A8: =I_Master!A8 -> RPA|BLD|Frozen | B8: =IF(A8="","",INDEX(I_Master!$E$6:$E$85,MATCH(A8,I_Master!$A$6:$A$85,0))) -> Boneless & parting | C8: =IF(A8="","",INDEX(I_Master!$B$6:$B$85,MATCH(A8,I_Master!$A$6:$A$85,0))) -> RPA | D8: =IF(A8="","",SUMIFS(I_Stok_Awal!$D$6:$D$305,I_Stok_Awal!$C$6:$C$305,A8)) -> 2.45 | E8: =IF(A8="","",SUMIFS(I_Stok_Awal!$E$6:$E$305,I_Stok_Awal!$C$6:$C$305,A8)) -> 70573 | F8: =IF(OR(A8="",D8<=0),"",SUMPRODUCT((I_Stok_Awal!$C$6:$C$305=A8)*I_Stok_Awal!$D$6:$D$305*I_Stok_Awal!$F$6:$F$305)/D8) -> 96 | G8: =IF(A8="","",SUMIFS(I_Stok_Awal!$G$6:$G$305,I_Stok_Awal!$C$6:$C$305,A8)) -> 2.45 | H8: =IF($A8="","",D8+SUMIFS(T_Penerimaan!$I$6:$I$1005,T_Penerimaan!$H$6:$H$1005,$A8,T_Penerimaan!$A$6:$A$1005,H$4,T_Penerimaan!$M$6:$M$1005,1)-SUMIFS(T_Penjualan!$H$6:$H$1505,T_Penjualan!$G$6:$G$1505,$A8,T_Penjualan!$A$6:$A$1505,H$4,T_Penjualan!$P$6:$P$1505,1)) -> 2.45 | I8: =IF($A8="","",H8+SUMIFS(T_Penerimaan!$I$6:$I$1005,T_Penerimaan!$H$6:$H$1005,$A8,T_Penerimaan!$A$6:$A$1005,I$4,T_Penerimaan!$M$6:$M$1005,1)-SUMIFS(T_Penjualan!$H$6:$H$1505,T_Penjualan!$G$6:$G$1505,$A8,T_Penjualan!$A$6:$A$1505,I$4,T_Penjualan!$P$6:$P$1505,1)) -> 2.45 | J8: =IF($A8="","",I8+SUMIFS(T_Penerimaan!$I$6:$I$1005,T_Penerimaan!$H$6:$H$1005,$A8,T_Penerimaan!$A$6:$A$1005,J$4,T_Penerimaan!$M$6:$M$1005,1)-SUMIFS(T_Penjualan!$H$6:$H$1505,T_Penjualan!$G$6:$G$1505,$A8,T_Penjualan!$A$6:$A$1505,J$4,T_Penjualan!$P$6:$P$1505,1)) -> 2.45 | K8: =IF($A8="","",J8+SUMIFS(T_Penerimaan!$I$6:$I$1005,T_Penerimaan!$H$6:$H$1005,$A8,T_Penerimaan!$A$6:$A$1005,K$4,T_Penerimaan!$M$6:$M$1005,1)-SUMIFS(T_Penjualan!$H$6:$H$1505,T_Penjualan!$G$6:$G$1505,$A8,T_Penjualan!$A$6:$A$1505,K$4,T_Penjualan!$P$6:$P$1505,1)) -> 2.45 | L8: =IF($A8="","",K8+SUMIFS(T_Penerimaan!$I$6:$I$1005,T_Penerimaan!$H$6:$H$1005,$A8,T_Penerimaan!$A$6:$A$1005,L$4,T_Penerimaan!$M$6:$M$1005,1)-SUMIFS(T_Penjualan!$H$6:$H$1505,T_Penjualan!$G$6:$G$1505,$A8,T_Penjualan!$A$6:$A$1505,L$4,T_Penjualan!$P$6:$P$1505,1)) -> 2.45 | M8: =IF($A8="","",L8+SUMIFS(T_Penerimaan!$I$6:$I$1005,T_Penerimaan!$H$6:$H$1005,$A8,T_Penerimaan!$A$6:$A$1005,M$4,T_Penerimaan!$M$6:$M$1005,1)-SUMIFS(T_Penjualan!$H$6:$H$1505,T_Penjualan!$G$6:$G$1505,$A8,T_Penjualan!$A$6:$A$1505,M$4,T_Penjualan!$P$6:$P$1505,1)) -> 2.45 | N8: =IF($A8="","",M8+SUMIFS(T_Penerimaan!$I$6:$I$1005,T_Penerimaan!$H$6:$H$1005,$A8,T_Penerimaan!$A$6:$A$1005,N$4,T_Penerimaan!$M$6:$M$1005,1)-SUMIFS(T_Penjualan!$H$6:$H$1505,T_Penjualan!$G$6:$G$1505,$A8,T_Penjualan!$A$6:$A$1505,N$4,T_Penjualan!$P$6:$P$1505,1)) -> 2.45 | O8: =IF(A8="","",SUMIFS(T_Penerimaan!$I$6:$I$1005,T_Penerimaan!$H$6:$H$1005,A8,T_Penerimaan!$M$6:$M$1005,1)) -> 0 | P8: =IF(A8="","",SUMIFS(T_Penerimaan!$K$6:$K$1005,T_Penerimaan!$H$6:$H$1005,A8,T_Penerimaan!$M$6:$M$1005,1)) -> 0 | Q8: =IF(A8="","",IF(D8+O8<=0,0,(E8+P8)/(D8+O8))) -> 28805.306 | R8: =IF(A8="","",SUMIFS(T_Penjualan!$H$6:$H$1505,T_Penjualan!$G$6:$G$1505,A8,T_Penjualan!$P$6:$P$1505,1)) -> 0 | S8: =IF(A8="","",IF(I_Parameter!$C$4<=I_Parameter!$C$5,D8,IF(I_Parameter!$C$4>I_Parameter!$C$6,N8,INDEX(H8:N8,I_Parameter!$C$4-I_Parameter!$C$5)))) -> 2.45 | T8: =IF(A8="","",SUMIFS(T_Penjualan!$H$6:$H$1505,T_Penjualan!$G$6:$G$1505,A8,T_Penjualan!$B$6:$B$1505,"Order",T_Penjualan!$A$6:$A$1505,">="&I_Parameter!$C$4,T_Penjualan!$A$6:$A$1505,"<="&I_Parameter!$C$6)) -> 0 | U8: =IF(A8="","",S8-T8) -> 2.45 | V8: =IF(A8="","",MIN(H8:N8)) -> 2.45 | W8: =IF(A8="","",INDEX(I_Master!$F$6:$F$85,MATCH(A8,I_Master!$A$6:$A$85,0))) -> 41000 | X8: =IF(OR(A8="",W8=""),"",W8-Q8) -> 12194.694 | Y8: =IF(A8="","",S8*Q8) -> 70573 | Z8: =IF(A8="","",IF(V8<-0.5,"KURANG: stok minus "&ROUND(-V8,0)&" kg — beli/potong atau geser order",IF(AND(S8>0.5,T8<=0,G8>0.5),"JUAL: "&ROUND(S8,0)&" kg tanpa order, sebagian > batas umur",IF(AND(S8>0.5,T8<=0),"JUAL: "&ROUND(S8,0)&" kg tanpa order minggu ini",IF(G8>0.5,"PERHATIAN: "&ROUND(G8,0)&" kg di atas batas umur",IF(AND(X8<>"",X8<0,T8>0),"Order di bawah biaya rata-rata — cek harga","-")))))) -> JUAL: 2 kg tanpa order, sebagian > batas umur
A9: =I_Master!A9 -> RPA|BLPK|Fresh | B9: =IF(A9="","",INDEX(I_Master!$E$6:$E$85,MATCH(A9,I_Master!$A$6:$A$85,0))) -> Boneless & parting | C9: =IF(A9="","",INDEX(I_Master!$B$6:$B$85,MATCH(A9,I_Master!$A$6:$A$85,0))) -> RPA | D9: =IF(A9="","",SUMIFS(I_Stok_Awal!$D$6:$D$305,I_Stok_Awal!$C$6:$C$305,A9)) -> 64.1 | E9: =IF(A9="","",SUMIFS(I_Stok_Awal!$E$6:$E$305,I_Stok_Awal!$C$6:$C$305,A9)) -> 2916133 | F9: =IF(OR(A9="",D9<=0),"",SUMPRODUCT((I_Stok_Awal!$C$6:$C$305=A9)*I_Stok_Awal!$D$6:$D$305*I_Stok_Awal!$F$6:$F$305)/D9) -> 139 | G9: =IF(A9="","",SUMIFS(I_Stok_Awal!$G$6:$G$305,I_Stok_Awal!$C$6:$C$305,A9)) -> 64.1 | H9: =IF($A9="","",D9+SUMIFS(T_Penerimaan!$I$6:$I$1005,T_Penerimaan!$H$6:$H$1005,$A9,T_Penerimaan!$A$6:$A$1005,H$4,T_Penerimaan!$M$6:$M$1005,1)-SUMIFS(T_Penjualan!$H$6:$H$1505,T_Penjualan!$G$6:$G$1505,$A9,T_Penjualan!$A$6:$A$1505,H$4,T_Penjualan!$P$6:$P$1505,1)) -> 64.1 | I9: =IF($A9="","",H9+SUMIFS(T_Penerimaan!$I$6:$I$1005,T_Penerimaan!$H$6:$H$1005,$A9,T_Penerimaan!$A$6:$A$1005,I$4,T_Penerimaan!$M$6:$M$1005,1)-SUMIFS(T_Penjualan!$H$6:$H$1505,T_Penjualan!$G$6:$G$1505,$A9,T_Penjualan!$A$6:$A$1505,I$4,T_Penjualan!$P$6:$P$1505,1)) -> 64.1 | J9: =IF($A9="","",I9+SUMIFS(T_Penerimaan!$I$6:$I$1005,T_Penerimaan!$H$6:$H$1005,$A9,T_Penerimaan!$A$6:$A$1005,J$4,T_Penerimaan!$M$6:$M$1005,1)-SUMIFS(T_Penjualan!$H$6:$H$1505,T_Penjualan!$G$6:$G$1505,$A9,T_Penjualan!$A$6:$A$1505,J$4,T_Penjualan!$P$6:$P$1505,1)) -> 64.1 | K9: =IF($A9="","",J9+SUMIFS(T_Penerimaan!$I$6:$I$1005,T_Penerimaan!$H$6:$H$1005,$A9,T_Penerimaan!$A$6:$A$1005,K$4,T_Penerimaan!$M$6:$M$1005,1)-SUMIFS(T_Penjualan!$H$6:$H$1505,T_Penjualan!$G$6:$G$1505,$A9,T_Penjualan!$A$6:$A$1505,K$4,T_Penjualan!$P$6:$P$1505,1)) -> 64.1 | L9: =IF($A9="","",K9+SUMIFS(T_Penerimaan!$I$6:$I$1005,T_Penerimaan!$H$6:$H$1005,$A9,T_Penerimaan!$A$6:$A$1005,L$4,T_Penerimaan!$M$6:$M$1005,1)-SUMIFS(T_Penjualan!$H$6:$H$1505,T_Penjualan!$G$6:$G$1505,$A9,T_Penjualan!$A$6:$A$1505,L$4,T_Penjualan!$P$6:$P$1505,1)) -> 64.1 | M9: =IF($A9="","",L9+SUMIFS(T_Penerimaan!$I$6:$I$1005,T_Penerimaan!$H$6:$H$1005,$A9,T_Penerimaan!$A$6:$A$1005,M$4,T_Penerimaan!$M$6:$M$1005,1)-SUMIFS(T_Penjualan!$H$6:$H$1505,T_Penjualan!$G$6:$G$1505,$A9,T_Penjualan!$A$6:$A$1505,M$4,T_Penjualan!$P$6:$P$1505,1)) -> 64.1 | N9: =IF($A9="","",M9+SUMIFS(T_Penerimaan!$I$6:$I$1005,T_Penerimaan!$H$6:$H$1005,$A9,T_Penerimaan!$A$6:$A$1005,N$4,T_Penerimaan!$M$6:$M$1005,1)-SUMIFS(T_Penjualan!$H$6:$H$1505,T_Penjualan!$G$6:$G$1505,$A9,T_Penjualan!$A$6:$A$1505,N$4,T_Penjualan!$P$6:$P$1505,1)) -> 64.1 | O9: =IF(A9="","",SUMIFS(T_Penerimaan!$I$6:$I$1005,T_Penerimaan!$H$6:$H$1005,A9,T_Penerimaan!$M$6:$M$1005,1)) -> 0 | P9: =IF(A9="","",SUMIFS(T_Penerimaan!$K$6:$K$1005,T_Penerimaan!$H$6:$H$1005,A9,T_Penerimaan!$M$6:$M$1005,1)) -> 0 | Q9: =IF(A9="","",IF(D9+O9<=0,0,(E9+P9)/(D9+O9))) -> 45493.495 | R9: =IF(A9="","",SUMIFS(T_Penjualan!$H$6:$H$1505,T_Penjualan!$G$6:$G$1505,A9,T_Penjualan!$P$6:$P$1505,1)) -> 0 | S9: =IF(A9="","",IF(I_Parameter!$C$4<=I_Parameter!$C$5,D9,IF(I_Parameter!$C$4>I_Parameter!$C$6,N9,INDEX(H9:N9,I_Parameter!$C$4-I_Parameter!$C$5)))) -> 64.1 | T9: =IF(A9="","",SUMIFS(T_Penjualan!$H$6:$H$1505,T_Penjualan!$G$6:$G$1505,A9,T_Penjualan!$B$6:$B$1505,"Order",T_Penjualan!$A$6:$A$1505,">="&I_Parameter!$C$4,T_Penjualan!$A$6:$A$1505,"<="&I_Parameter!$C$6)) -> 0 | U9: =IF(A9="","",S9-T9) -> 64.1 | V9: =IF(A9="","",MIN(H9:N9)) -> 64.1 | W9: =IF(A9="","",INDEX(I_Master!$F$6:$F$85,MATCH(A9,I_Master!$A$6:$A$85,0))) -> 45004 | X9: =IF(OR(A9="",W9=""),"",W9-Q9) -> -489.49454 | Y9: =IF(A9="","",S9*Q9) -> 2916133 | Z9: =IF(A9="","",IF(V9<-0.5,"KURANG: stok minus "&ROUND(-V9,0)&" kg — beli/potong atau geser order",IF(AND(S9>0.5,T9<=0,G9>0.5),"JUAL: "&ROUND(S9,0)&" kg tanpa order, sebagian > batas umur",IF(AND(S9>0.5,T9<=0),"JUAL: "&ROUND(S9,0)&" kg tanpa order minggu ini",IF(G9>0.5,"PERHATIAN: "&ROUND(G9,0)&" kg di atas batas umur",IF(AND(X9<>"",X9<0,T9>0),"Order di bawah biaya rata-rata — cek harga","-")))))) -> JUAL: 64 kg tanpa order, sebagian > batas umur
A10: =I_Master!A10 -> RPA|BLPK|Frozen | B10: =IF(A10="","",INDEX(I_Master!$E$6:$E$85,MATCH(A10,I_Master!$A$6:$A$85,0))) -> Boneless & parting | C10: =IF(A10="","",INDEX(I_Master!$B$6:$B$85,MATCH(A10,I_Master!$A$6:$A$85,0))) -> RPA | D10: =IF(A10="","",SUMIFS(I_Stok_Awal!$D$6:$D$305,I_Stok_Awal!$C$6:$C$305,A10)) -> 0 | E10: =IF(A10="","",SUMIFS(I_Stok_Awal!$E$6:$E$305,I_Stok_Awal!$C$6:$C$305,A10)) -> 0 | F10: =IF(OR(A10="",D10<=0),"",SUMPRODUCT((I_Stok_Awal!$C$6:$C$305=A10)*I_Stok_Awal!$D$6:$D$305*I_Stok_Awal!$F$6:$F$305)/D10) | G10: =IF(A10="","",SUMIFS(I_Stok_Awal!$G$6:$G$305,I_Stok_Awal!$C$6:$C$305,A10)) -> 0 | H10: =IF($A10="","",D10+SUMIFS(T_Penerimaan!$I$6:$I$1005,T_Penerimaan!$H$6:$H$1005,$A10,T_Penerimaan!$A$6:$A$1005,H$4,T_Penerimaan!$M$6:$M$1005,1)-SUMIFS(T_Penjualan!$H$6:$H$1505,T_Penjualan!$G$6:$G$1505,$A10,T_Penjualan!$A$6:$A$1505,H$4,T_Penjualan!$P$6:$P$1505,1)) -> 0 | I10: =IF($A10="","",H10+SUMIFS(T_Penerimaan!$I$6:$I$1005,T_Penerimaan!$H$6:$H$1005,$A10,T_Penerimaan!$A$6:$A$1005,I$4,T_Penerimaan!$M$6:$M$1005,1)-SUMIFS(T_Penjualan!$H$6:$H$1505,T_Penjualan!$G$6:$G$1505,$A10,T_Penjualan!$A$6:$A$1505,I$4,T_Penjualan!$P$6:$P$1505,1)) -> 0 | J10: =IF($A10="","",I10+SUMIFS(T_Penerimaan!$I$6:$I$1005,T_Penerimaan!$H$6:$H$1005,$A10,T_Penerimaan!$A$6:$A$1005,J$4,T_Penerimaan!$M$6:$M$1005,1)-SUMIFS(T_Penjualan!$H$6:$H$1505,T_Penjualan!$G$6:$G$1505,$A10,T_Penjualan!$A$6:$A$1505,J$4,T_Penjualan!$P$6:$P$1505,1)) -> 0 | K10: =IF($A10="","",J10+SUMIFS(T_Penerimaan!$I$6:$I$1005,T_Penerimaan!$H$6:$H$1005,$A10,T_Penerimaan!$A$6:$A$1005,K$4,T_Penerimaan!$M$6:$M$1005,1)-SUMIFS(T_Penjualan!$H$6:$H$1505,T_Penjualan!$G$6:$G$1505,$A10,T_Penjualan!$A$6:$A$1505,K$4,T_Penjualan!$P$6:$P$1505,1)) -> 0 | L10: =IF($A10="","",K10+SUMIFS(T_Penerimaan!$I$6:$I$1005,T_Penerimaan!$H$6:$H$1005,$A10,T_Penerimaan!$A$6:$A$1005,L$4,T_Penerimaan!$M$6:$M$1005,1)-SUMIFS(T_Penjualan!$H$6:$H$1505,T_Penjualan!$G$6:$G$1505,$A10,T_Penjualan!$A$6:$A$1505,L$4,T_Penjualan!$P$6:$P$1505,1)) -> 0 | M10: =IF($A10="","",L10+SUMIFS(T_Penerimaan!$I$6:$I$1005,T_Penerimaan!$H$6:$H$1005,$A10,T_Penerimaan!$A$6:$A$1005,M$4,T_Penerimaan!$M$6:$M$1005,1)-SUMIFS(T_Penjualan!$H$6:$H$1505,T_Penjualan!$G$6:$G$1505,$A10,T_Penjualan!$A$6:$A$1505,M$4,T_Penjualan!$P$6:$P$1505,1)) -> 0 | N10: =IF($A10="","",M10+SUMIFS(T_Penerimaan!$I$6:$I$1005,T_Penerimaan!$H$6:$H$1005,$A10,T_Penerimaan!$A$6:$A$1005,N$4,T_Penerimaan!$M$6:$M$1005,1)-SUMIFS(T_Penjualan!$H$6:$H$1505,T_Penjualan!$G$6:$G$1505,$A10,T_Penjualan!$A$6:$A$1505,N$4,T_Penjualan!$P$6:$P$1505,1)) -> 0 | O10: =IF(A10="","",SUMIFS(T_Penerimaan!$I$6:$I$1005,T_Penerimaan!$H$6:$H$1005,A10,T_Penerimaan!$M$6:$M$1005,1)) -> 0 | P10: =IF(A10="","",SUMIFS(T_Penerimaan!$K$6:$K$1005,T_Penerimaan!$H$6:$H$1005,A10,T_Penerimaan!$M$6:$M$1005,1)) -> 0 | Q10: =IF(A10="","",IF(D10+O10<=0,0,(E10+P10)/(D10+O10))) -> 0 | R10: =IF(A10="","",SUMIFS(T_Penjualan!$H$6:$H$1505,T_Penjualan!$G$6:$G$1505,A10,T_Penjualan!$P$6:$P$1505,1)) -> 0 | S10: =IF(A10="","",IF(I_Parameter!$C$4<=I_Parameter!$C$5,D10,IF(I_Parameter!$C$4>I_Parameter!$C$6,N10,INDEX(H10:N10,I_Parameter!$C$4-I_Parameter!$C$5)))) -> 0 | T10: =IF(A10="","",SUMIFS(T_Penjualan!$H$6:$H$1505,T_Penjualan!$G$6:$G$1505,A10,T_Penjualan!$B$6:$B$1505,"Order",T_Penjualan!$A$6:$A$1505,">="&I_Parameter!$C$4,T_Penjualan!$A$6:$A$1505,"<="&I_Parameter!$C$6)) -> 0 | U10: =IF(A10="","",S10-T10) -> 0 | V10: =IF(A10="","",MIN(H10:N10)) -> 0 | W10: =IF(A10="","",INDEX(I_Master!$F$6:$F$85,MATCH(A10,I_Master!$A$6:$A$85,0))) -> 39520 | X10: =IF(OR(A10="",W10=""),"",W10-Q10) -> 39520 | Y10: =IF(A10="","",S10*Q10) -> 0 | Z10: =IF(A10="","",IF(V10<-0.5,"KURANG: stok minus "&ROUND(-V10,0)&" kg — beli/potong atau geser order",IF(AND(S10>0.5,T10<=0,G10>0.5),"JUAL: "&ROUND(S10,0)&" kg tanpa order, sebagian > batas umur",IF(AND(S10>0.5,T10<=0),"JUAL: "&ROUND(S10,0)&" kg tanpa order minggu ini",IF(G10>0.5,"PERHATIAN: "&ROUND(G10,0)&" kg di atas batas umur",IF(AND(X10<>"",X10<0,T10>0),"Order di bawah biaya rata-rata — cek harga","-")))))) -> -
A11: =I_Master!A11 -> RPA|BLP|Fresh | B11: =IF(A11="","",INDEX(I_Master!$E$6:$E$85,MATCH(A11,I_Master!$A$6:$A$85,0))) -> Boneless & parting | C11: =IF(A11="","",INDEX(I_Master!$B$6:$B$85,MATCH(A11,I_Master!$A$6:$A$85,0))) -> RPA | D11: =IF(A11="","",SUMIFS(I_Stok_Awal!$D$6:$D$305,I_Stok_Awal!$C$6:$C$305,A11)) -> 0 | E11: =IF(A11="","",SUMIFS(I_Stok_Awal!$E$6:$E$305,I_Stok_Awal!$C$6:$C$305,A11)) -> 0 | F11: =IF(OR(A11="",D11<=0),"",SUMPRODUCT((I_Stok_Awal!$C$6:$C$305=A11)*I_Stok_Awal!$D$6:$D$305*I_Stok_Awal!$F$6:$F$305)/D11) | G11: =IF(A11="","",SUMIFS(I_Stok_Awal!$G$6:$G$305,I_Stok_Awal!$C$6:$C$305,A11)) -> 0 | H11: =IF($A11="","",D11+SUMIFS(T_Penerimaan!$I$6:$I$1005,T_Penerimaan!$H$6:$H$1005,$A11,T_Penerimaan!$A$6:$A$1005,H$4,T_Penerimaan!$M$6:$M$1005,1)-SUMIFS(T_Penjualan!$H$6:$H$1505,T_Penjualan!$G$6:$G$1505,$A11,T_Penjualan!$A$6:$A$1505,H$4,T_Penjualan!$P$6:$P$1505,1)) -> 0 | I11: =IF($A11="","",H11+SUMIFS(T_Penerimaan!$I$6:$I$1005,T_Penerimaan!$H$6:$H$1005,$A11,T_Penerimaan!$A$6:$A$1005,I$4,T_Penerimaan!$M$6:$M$1005,1)-SUMIFS(T_Penjualan!$H$6:$H$1505,T_Penjualan!$G$6:$G$1505,$A11,T_Penjualan!$A$6:$A$1505,I$4,T_Penjualan!$P$6:$P$1505,1)) -> 0 | J11: =IF($A11="","",I11+SUMIFS(T_Penerimaan!$I$6:$I$1005,T_Penerimaan!$H$6:$H$1005,$A11,T_Penerimaan!$A$6:$A$1005,J$4,T_Penerimaan!$M$6:$M$1005,1)-SUMIFS(T_Penjualan!$H$6:$H$1505,T_Penjualan!$G$6:$G$1505,$A11,T_Penjualan!$A$6:$A$1505,J$4,T_Penjualan!$P$6:$P$1505,1)) -> 0 | K11: =IF($A11="","",J11+SUMIFS(T_Penerimaan!$I$6:$I$1005,T_Penerimaan!$H$6:$H$1005,$A11,T_Penerimaan!$A$6:$A$1005,K$4,T_Penerimaan!$M$6:$M$1005,1)-SUMIFS(T_Penjualan!$H$6:$H$1505,T_Penjualan!$G$6:$G$1505,$A11,T_Penjualan!$A$6:$A$1505,K$4,T_Penjualan!$P$6:$P$1505,1)) -> 0 | L11: =IF($A11="","",K11+SUMIFS(T_Penerimaan!$I$6:$I$1005,T_Penerimaan!$H$6:$H$1005,$A11,T_Penerimaan!$A$6:$A$1005,L$4,T_Penerimaan!$M$6:$M$1005,1)-SUMIFS(T_Penjualan!$H$6:$H$1505,T_Penjualan!$G$6:$G$1505,$A11,T_Penjualan!$A$6:$A$1505,L$4,T_Penjualan!$P$6:$P$1505,1)) -> 0 | M11: =IF($A11="","",L11+SUMIFS(T_Penerimaan!$I$6:$I$1005,T_Penerimaan!$H$6:$H$1005,$A11,T_Penerimaan!$A$6:$A$1005,M$4,T_Penerimaan!$M$6:$M$1005,1)-SUMIFS(T_Penjualan!$H$6:$H$1505,T_Penjualan!$G$6:$G$1505,$A11,T_Penjualan!$A$6:$A$1505,M$4,T_Penjualan!$P$6:$P$1505,1)) -> 0 | N11: =IF($A11="","",M11+SUMIFS(T_Penerimaan!$I$6:$I$1005,T_Penerimaan!$H$6:$H$1005,$A11,T_Penerimaan!$A$6:$A$1005,N$4,T_Penerimaan!$M$6:$M$1005,1)-SUMIFS(T_Penjualan!$H$6:$H$1505,T_Penjualan!$G$6:$G$1505,$A11,T_Penjualan!$A$6:$A$1505,N$4,T_Penjualan!$P$6:$P$1505,1)) -> 0 | O11: =IF(A11="","",SUMIFS(T_Penerimaan!$I$6:$I$1005,T_Penerimaan!$H$6:$H$1005,A11,T_Penerimaan!$M$6:$M$1005,1)) -> 0 | P11: =IF(A11="","",SUMIFS(T_Penerimaan!$K$6:$K$1005,T_Penerimaan!$H$6:$H$1005,A11,T_Penerimaan!$M$6:$M$1005,1)) -> 0 | Q11: =IF(A11="","",IF(D11+O11<=0,0,(E11+P11)/(D11+O11))) -> 0 | R11: =IF(A11="","",SUMIFS(T_Penjualan!$H$6:$H$1505,T_Penjualan!$G$6:$G$1505,A11,T_Penjualan!$P$6:$P$1505,1)) -> 0 | S11: =IF(A11="","",IF(I_Parameter!$C$4<=I_Parameter!$C$5,D11,IF(I_Parameter!$C$4>I_Parameter!$C$6,N11,INDEX(H11:N11,I_Parameter!$C$4-I_Parameter!$C$5)))) -> 0 | T11: =IF(A11="","",SUMIFS(T_Penjualan!$H$6:$H$1505,T_Penjualan!$G$6:$G$1505,A11,T_Penjualan!$B$6:$B$1505,"Order",T_Penjualan!$A$6:$A$1505,">="&I_Parameter!$C$4,T_Penjualan!$A$6:$A$1505,"<="&I_Parameter!$C$6)) -> 0 | U11: =IF(A11="","",S11-T11) -> 0 | V11: =IF(A11="","",MIN(H11:N11)) -> 0 | W11: =IF(A11="","",INDEX(I_Master!$F$6:$F$85,MATCH(A11,I_Master!$A$6:$A$85,0))) -> 40000 | X11: =IF(OR(A11="",W11=""),"",W11-Q11) -> 40000 | Y11: =IF(A11="","",S11*Q11) -> 0 | Z11: =IF(A11="","",IF(V11<-0.5,"KURANG: stok minus "&ROUND(-V11,0)&" kg — beli/potong atau geser order",IF(AND(S11>0.5,T11<=0,G11>0.5),"JUAL: "&ROUND(S11,0)&" kg tanpa order, sebagian > batas umur",IF(AND(S11>0.5,T11<=0),"JUAL: "&ROUND(S11,0)&" kg tanpa order minggu ini",IF(G11>0.5,"PERHATIAN: "&ROUND(G11,0)&" kg di atas batas umur",IF(AND(X11<>"",X11<0,T11>0),"Order di bawah biaya rata-rata — cek harga","-")))))) -> -
A12: =I_Master!A12 -> RPA|BLP|Frozen | B12: =IF(A12="","",INDEX(I_Master!$E$6:$E$85,MATCH(A12,I_Master!$A$6:$A$85,0))) -> Boneless & parting | C12: =IF(A12="","",INDEX(I_Master!$B$6:$B$85,MATCH(A12,I_Master!$A$6:$A$85,0))) -> RPA | D12: =IF(A12="","",SUMIFS(I_Stok_Awal!$D$6:$D$305,I_Stok_Awal!$C$6:$C$305,A12)) -> 8.68 | E12: =IF(A12="","",SUMIFS(I_Stok_Awal!$E$6:$E$305,I_Stok_Awal!$C$6:$C$305,A12)) -> 250032 | F12: =IF(OR(A12="",D12<=0),"",SUMPRODUCT((I_Stok_Awal!$C$6:$C$305=A12)*I_Stok_Awal!$D$6:$D$305*I_Stok_Awal!$F$6:$F$305)/D12) -> 111 | G12: =IF(A12="","",SUMIFS(I_Stok_Awal!$G$6:$G$305,I_Stok_Awal!$C$6:$C$305,A12)) -> 8.68 | H12: =IF($A12="","",D12+SUMIFS(T_Penerimaan!$I$6:$I$1005,T_Penerimaan!$H$6:$H$1005,$A12,T_Penerimaan!$A$6:$A$1005,H$4,T_Penerimaan!$M$6:$M$1005,1)-SUMIFS(T_Penjualan!$H$6:$H$1505,T_Penjualan!$G$6:$G$1505,$A12,T_Penjualan!$A$6:$A$1505,H$4,T_Penjualan!$P$6:$P$1505,1)) -> 8.68 | I12: =IF($A12="","",H12+SUMIFS(T_Penerimaan!$I$6:$I$1005,T_Penerimaan!$H$6:$H$1005,$A12,T_Penerimaan!$A$6:$A$1005,I$4,T_Penerimaan!$M$6:$M$1005,1)-SUMIFS(T_Penjualan!$H$6:$H$1505,T_Penjualan!$G$6:$G$1505,$A12,T_Penjualan!$A$6:$A$1505,I$4,T_Penjualan!$P$6:$P$1505,1)) -> 8.68 | J12: =IF($A12="","",I12+SUMIFS(T_Penerimaan!$I$6:$I$1005,T_Penerimaan!$H$6:$H$1005,$A12,T_Penerimaan!$A$6:$A$1005,J$4,T_Penerimaan!$M$6:$M$1005,1)-SUMIFS(T_Penjualan!$H$6:$H$1505,T_Penjualan!$G$6:$G$1505,$A12,T_Penjualan!$A$6:$A$1505,J$4,T_Penjualan!$P$6:$P$1505,1)) -> 8.68 | K12: =IF($A12="","",J12+SUMIFS(T_Penerimaan!$I$6:$I$1005,T_Penerimaan!$H$6:$H$1005,$A12,T_Penerimaan!$A$6:$A$1005,K$4,T_Penerimaan!$M$6:$M$1005,1)-SUMIFS(T_Penjualan!$H$6:$H$1505,T_Penjualan!$G$6:$G$1505,$A12,T_Penjualan!$A$6:$A$1505,K$4,T_Penjualan!$P$6:$P$1505,1)) -> 8.68 | L12: =IF($A12="","",K12+SUMIFS(T_Penerimaan!$I$6:$I$1005,T_Penerimaan!$H$6:$H$1005,$A12,T_Penerimaan!$A$6:$A$1005,L$4,T_Penerimaan!$M$6:$M$1005,1)-SUMIFS(T_Penjualan!$H$6:$H$1505,T_Penjualan!$G$6:$G$1505,$A12,T_Penjualan!$A$6:$A$1505,L$4,T_Penjualan!$P$6:$P$1505,1)) -> 8.68 | M12: =IF($A12="","",L12+SUMIFS(T_Penerimaan!$I$6:$I$1005,T_Penerimaan!$H$6:$H$1005,$A12,T_Penerimaan!$A$6:$A$1005,M$4,T_Penerimaan!$M$6:$M$1005,1)-SUMIFS(T_Penjualan!$H$6:$H$1505,T_Penjualan!$G$6:$G$1505,$A12,T_Penjualan!$A$6:$A$1505,M$4,T_Penjualan!$P$6:$P$1505,1)) -> 8.68 | N12: =IF($A12="","",M12+SUMIFS(T_Penerimaan!$I$6:$I$1005,T_Penerimaan!$H$6:$H$1005,$A12,T_Penerimaan!$A$6:$A$1005,N$4,T_Penerimaan!$M$6:$M$1005,1)-SUMIFS(T_Penjualan!$H$6:$H$1505,T_Penjualan!$G$6:$G$1505,$A12,T_Penjualan!$A$6:$A$1505,N$4,T_Penjualan!$P$6:$P$1505,1)) -> 8.68 | O12: =IF(A12="","",SUMIFS(T_Penerimaan!$I$6:$I$1005,T_Penerimaan!$H$6:$H$1005,A12,T_Penerimaan!$M$6:$M$1005,1)) -> 0 | P12: =IF(A12="","",SUMIFS(T_Penerimaan!$K$6:$K$1005,T_Penerimaan!$H$6:$H$1005,A12,T_Penerimaan!$M$6:$M$1005,1)) -> 0 | Q12: =IF(A12="","",IF(D12+O12<=0,0,(E12+P12)/(D12+O12))) -> 28805.53 | R12: =IF(A12="","",SUMIFS(T_Penjualan!$H$6:$H$1505,T_Penjualan!$G$6:$G$1505,A12,T_Penjualan!$P$6:$P$1505,1)) -> 0 | S12: =IF(A12="","",IF(I_Parameter!$C$4<=I_Parameter!$C$5,D12,IF(I_Parameter!$C$4>I_Parameter!$C$6,N12,INDEX(H12:N12,I_Parameter!$C$4-I_Parameter!$C$5)))) -> 8.68 | T12: =IF(A12="","",SUMIFS(T_Penjualan!$H$6:$H$1505,T_Penjualan!$G$6:$G$1505,A12,T_Penjualan!$B$6:$B$1505,"Order",T_Penjualan!$A$6:$A$1505,">="&I_Parameter!$C$4,T_Penjualan!$A$6:$A$1505,"<="&I_Parameter!$C$6)) -> 0 | U12: =IF(A12="","",S12-T12) -> 8.68 | V12: =IF(A12="","",MIN(H12:N12)) -> 8.68 | W12: =IF(A12="","",INDEX(I_Master!$F$6:$F$85,MATCH(A12,I_Master!$A$6:$A$85,0))) -> 40000 | X12: =IF(OR(A12="",W12=""),"",W12-Q12) -> 11194.47 | Y12: =IF(A12="","",S12*Q12) -> 250032 | Z12: =IF(A12="","",IF(V12<-0.5,"KURANG: stok minus "&ROUND(-V12,0)&" kg — beli/potong atau geser order",IF(AND(S12>0.5,T12<=0,G12>0.5),"JUAL: "&ROUND(S12,0)&" kg tanpa order, sebagian > batas umur",IF(AND(S12>0.5,T12<=0),"JUAL: "&ROUND(S12,0)&" kg tanpa order minggu ini",IF(G12>0.5,"PERHATIAN: "&ROUND(G12,0)&" kg di atas batas umur",IF(AND(X12<>"",X12<0,T12>0),"Order di bawah biaya rata-rata — cek harga","-")))))) -> JUAL: 9 kg tanpa order, sebagian > batas umur
A13: =I_Master!A13 -> RPA|KRK (Kerangka)|Fresh | B13: =IF(A13="","",INDEX(I_Master!$E$6:$E$85,MATCH(A13,I_Master!$A$6:$A$85,0))) -> Boneless & parting | C13: =IF(A13="","",INDEX(I_Master!$B$6:$B$85,MATCH(A13,I_Master!$A$6:$A$85,0))) -> RPA | D13: =IF(A13="","",SUMIFS(I_Stok_Awal!$D$6:$D$305,I_Stok_Awal!$C$6:$C$305,A13)) -> 345.47 | E13: =IF(A13="","",SUMIFS(I_Stok_Awal!$E$6:$E$305,I_Stok_Awal!$C$6:$C$305,A13)) -> 1498591 | F13: =IF(OR(A13="",D13<=0),"",SUMPRODUCT((I_Stok_Awal!$C$6:$C$305=A13)*I_Stok_Awal!$D$6:$D$305*I_Stok_Awal!$F$6:$F$305)/D13) -> 104.4566 | G13: =IF(A13="","",SUMIFS(I_Stok_Awal!$G$6:$G$305,I_Stok_Awal!$C$6:$C$305,A13)) -> 345.47 | H13: =IF($A13="","",D13+SUMIFS(T_Penerimaan!$I$6:$I$1005,T_Penerimaan!$H$6:$H$1005,$A13,T_Penerimaan!$A$6:$A$1005,H$4,T_Penerimaan!$M$6:$M$1005,1)-SUMIFS(T_Penjualan!$H$6:$H$1505,T_Penjualan!$G$6:$G$1505,$A13,T_Penjualan!$A$6:$A$1505,H$4,T_Penjualan!$P$6:$P$1505,1)) -> 345.47 | I13: =IF($A13="","",H13+SUMIFS(T_Penerimaan!$I$6:$I$1005,T_Penerimaan!$H$6:$H$1005,$A13,T_Penerimaan!$A$6:$A$1005,I$4,T_Penerimaan!$M$6:$M$1005,1)-SUMIFS(T_Penjualan!$H$6:$H$1505,T_Penjualan!$G$6:$G$1505,$A13,T_Penjualan!$A$6:$A$1505,I$4,T_Penjualan!$P$6:$P$1505,1)) -> 345.47 | J13: =IF($A13="","",I13+SUMIFS(T_Penerimaan!$I$6:$I$1005,T_Penerimaan!$H$6:$H$1005,$A13,T_Penerimaan!$A$6:$A$1005,J$4,T_Penerimaan!$M$6:$M$1005,1)-SUMIFS(T_Penjualan!$H$6:$H$1505,T_Penjualan!$G$6:$G$1505,$A13,T_Penjualan!$A$6:$A$1505,J$4,T_Penjualan!$P$6:$P$1505,1)) -> 345.47 | K13: =IF($A13="","",J13+SUMIFS(T_Penerimaan!$I$6:$I$1005,T_Penerimaan!$H$6:$H$1005,$A13,T_Penerimaan!$A$6:$A$1005,K$4,T_Penerimaan!$M$6:$M$1005,1)-SUMIFS(T_Penjualan!$H$6:$H$1505,T_Penjualan!$G$6:$G$1505,$A13,T_Penjualan!$A$6:$A$1505,K$4,T_Penjualan!$P$6:$P$1505,1)) -> 345.47 | L13: =IF($A13="","",K13+SUMIFS(T_Penerimaan!$I$6:$I$1005,T_Penerimaan!$H$6:$H$1005,$A13,T_Penerimaan!$A$6:$A$1005,L$4,T_Penerimaan!$M$6:$M$1005,1)-SUMIFS(T_Penjualan!$H$6:$H$1505,T_Penjualan!$G$6:$G$1505,$A13,T_Penjualan!$A$6:$A$1505,L$4,T_Penjualan!$P$6:$P$1505,1)) -> 345.47 | M13: =IF($A13="","",L13+SUMIFS(T_Penerimaan!$I$6:$I$1005,T_Penerimaan!$H$6:$H$1005,$A13,T_Penerimaan!$A$6:$A$1005,M$4,T_Penerimaan!$M$6:$M$1005,1)-SUMIFS(T_Penjualan!$H$6:$H$1505,T_Penjualan!$G$6:$G$1505,$A13,T_Penjualan!$A$6:$A$1505,M$4,T_Penjualan!$P$6:$P$1505,1)) -> 345.47 | N13: =IF($A13="","",M13+SUMIFS(T_Penerimaan!$I$6:$I$1005,T_Penerimaan!$H$6:$H$1005,$A13,T_Penerimaan!$A$6:$A$1005,N$4,T_Penerimaan!$M$6:$M$1005,1)-SUMIFS(T_Penjualan!$H$6:$H$1505,T_Penjualan!$G$6:$G$1505,$A13,T_Penjualan!$A$6:$A$1505,N$4,T_Penjualan!$P$6:$P$1505,1)) -> 345.47 | O13: =IF(A13="","",SUMIFS(T_Penerimaan!$I$6:$I$1005,T_Penerimaan!$H$6:$H$1005,A13,T_Penerimaan!$M$6:$M$1005,1)) -> 0 | P13: =IF(A13="","",SUMIFS(T_Penerimaan!$K$6:$K$1005,T_Penerimaan!$H$6:$H$1005,A13,T_Penerimaan!$M$6:$M$1005,1)) -> 0 | Q13: =IF(A13="","",IF(D13+O13<=0,0,(E13+P13)/(D13+O13))) -> 4337.8325 | R13: =IF(A13="","",SUMIFS(T_Penjualan!$H$6:$H$1505,T_Penjualan!$G$6:$G$1505,A13,T_Penjualan!$P$6:$P$1505,1)) -> 0 | S13: =IF(A13="","",IF(I_Parameter!$C$4<=I_Parameter!$C$5,D13,IF(I_Parameter!$C$4>I_Parameter!$C$6,N13,INDEX(H13:N13,I_Parameter!$C$4-I_Parameter!$C$5)))) -> 345.47 | T13: =IF(A13="","",SUMIFS(T_Penjualan!$H$6:$H$1505,T_Penjualan!$G$6:$G$1505,A13,T_Penjualan!$B$6:$B$1505,"Order",T_Penjualan!$A$6:$A$1505,">="&I_Parameter!$C$4,T_Penjualan!$A$6:$A$1505,"<="&I_Parameter!$C$6)) -> 0 | U13: =IF(A13="","",S13-T13) -> 345.47 | V13: =IF(A13="","",MIN(H13:N13)) -> 345.47 | W13: =IF(A13="","",INDEX(I_Master!$F$6:$F$85,MATCH(A13,I_Master!$A$6:$A$85,0))) -> 8961 | X13: =IF(OR(A13="",W13=""),"",W13-Q13) -> 4623.1675 | Y13: =IF(A13="","",S13*Q13) -> 1498591 | Z13: =IF(A13="","",IF(V13<-0.5,"KURANG: stok minus "&ROUND(-V13,0)&" kg — beli/potong atau geser order",IF(AND(S13>0.5,T13<=0,G13>0.5),"JUAL: "&ROUND(S13,0)&" kg tanpa order, sebagian > batas umur",IF(AND(S13>0.5,T13<=0),"JUAL: "&ROUND(S13,0)&" kg tanpa order minggu ini",IF(G13>0.5,"PERHATIAN: "&ROUND(G13,0)&" kg di atas batas umur",IF(AND(X13<>"",X13<0,T13>0),"Order di bawah biaya rata-rata — cek harga","-")))))) -> JUAL: 345 kg tanpa order, sebagian > batas umur
A14: =I_Master!A14 -> RPA|KRK (Kerangka)|Frozen | B14: =IF(A14="","",INDEX(I_Master!$E$6:$E$85,MATCH(A14,I_Master!$A$6:$A$85,0))) -> Boneless & parting | C14: =IF(A14="","",INDEX(I_Master!$B$6:$B$85,MATCH(A14,I_Master!$A$6:$A$85,0))) -> RPA | D14: =IF(A14="","",SUMIFS(I_Stok_Awal!$D$6:$D$305,I_Stok_Awal!$C$6:$C$305,A14)) -> 119.49 | E14: =IF(A14="","",SUMIFS(I_Stok_Awal!$E$6:$E$305,I_Stok_Awal!$C$6:$C$305,A14)) -> 2529632 | F14: =IF(OR(A14="",D14<=0),"",SUMPRODUCT((I_Stok_Awal!$C$6:$C$305=A14)*I_Stok_Awal!$D$6:$D$305*I_Stok_Awal!$F$6:$F$305)/D14) -> 53.9 | G14: =IF(A14="","",SUMIFS(I_Stok_Awal!$G$6:$G$305,I_Stok_Awal!$C$6:$C$305,A14)) -> 119.49 | H14: =IF($A14="","",D14+SUMIFS(T_Penerimaan!$I$6:$I$1005,T_Penerimaan!$H$6:$H$1005,$A14,T_Penerimaan!$A$6:$A$1005,H$4,T_Penerimaan!$M$6:$M$1005,1)-SUMIFS(T_Penjualan!$H$6:$H$1505,T_Penjualan!$G$6:$G$1505,$A14,T_Penjualan!$A$6:$A$1505,H$4,T_Penjualan!$P$6:$P$1505,1)) -> 119.49 | I14: =IF($A14="","",H14+SUMIFS(T_Penerimaan!$I$6:$I$1005,T_Penerimaan!$H$6:$H$1005,$A14,T_Penerimaan!$A$6:$A$1005,I$4,T_Penerimaan!$M$6:$M$1005,1)-SUMIFS(T_Penjualan!$H$6:$H$1505,T_Penjualan!$G$6:$G$1505,$A14,T_Penjualan!$A$6:$A$1505,I$4,T_Penjualan!$P$6:$P$1505,1)) -> 119.49 | J14: =IF($A14="","",I14+SUMIFS(T_Penerimaan!$I$6:$I$1005,T_Penerimaan!$H$6:$H$1005,$A14,T_Penerimaan!$A$6:$A$1005,J$4,T_Penerimaan!$M$6:$M$1005,1)-SUMIFS(T_Penjualan!$H$6:$H$1505,T_Penjualan!$G$6:$G$1505,$A14,T_Penjualan!$A$6:$A$1505,J$4,T_Penjualan!$P$6:$P$1505,1)) -> 119.49 | K14: =IF($A14="","",J14+SUMIFS(T_Penerimaan!$I$6:$I$1005,T_Penerimaan!$H$6:$H$1005,$A14,T_Penerimaan!$A$6:$A$1005,K$4,T_Penerimaan!$M$6:$M$1005,1)-SUMIFS(T_Penjualan!$H$6:$H$1505,T_Penjualan!$G$6:$G$1505,$A14,T_Penjualan!$A$6:$A$1505,K$4,T_Penjualan!$P$6:$P$1505,1)) -> 119.49 | L14: =IF($A14="","",K14+SUMIFS(T_Penerimaan!$I$6:$I$1005,T_Penerimaan!$H$6:$H$1005,$A14,T_Penerimaan!$A$6:$A$1005,L$4,T_Penerimaan!$M$6:$M$1005,1)-SUMIFS(T_Penjualan!$H$6:$H$1505,T_Penjualan!$G$6:$G$1505,$A14,T_Penjualan!$A$6:$A$1505,L$4,T_Penjualan!$P$6:$P$1505,1)) -> 119.49 | M14: =IF($A14="","",L14+SUMIFS(T_Penerimaan!$I$6:$I$1005,T_Penerimaan!$H$6:$H$1005,$A14,T_Penerimaan!$A$6:$A$1005,M$4,T_Penerimaan!$M$6:$M$1005,1)-SUMIFS(T_Penjualan!$H$6:$H$1505,T_Penjualan!$G$6:$G$1505,$A14,T_Penjualan!$A$6:$A$1505,M$4,T_Penjualan!$P$6:$P$1505,1)) -> 119.49 | N14: =IF($A14="","",M14+SUMIFS(T_Penerimaan!$I$6:$I$1005,T_Penerimaan!$H$6:$H$1005,$A14,T_Penerimaan!$A$6:$A$1005,N$4,T_Penerimaan!$M$6:$M$1005,1)-SUMIFS(T_Penjualan!$H$6:$H$1505,T_Penjualan!$G$6:$G$1505,$A14,T_Penjualan!$A$6:$A$1505,N$4,T_Penjualan!$P$6:$P$1505,1)) -> 119.49 | O14: =IF(A14="","",SUMIFS(T_Penerimaan!$I$6:$I$1005,T_Penerimaan!$H$6:$H$1005,A14,T_Penerimaan!$M$6:$M$1005,1)) -> 0 | P14: =IF(A14="","",SUMIFS(T_Penerimaan!$K$6:$K$1005,T_Penerimaan!$H$6:$H$1005,A14,T_Penerimaan!$M$6:$M$1005,1)) -> 0 | Q14: =IF(A14="","",IF(D14+O14<=0,0,(E14+P14)/(D14+O14))) -> 21170.24 | R14: =IF(A14="","",SUMIFS(T_Penjualan!$H$6:$H$1505,T_Penjualan!$G$6:$G$1505,A14,T_Penjualan!$P$6:$P$1505,1)) -> 0 | S14: =IF(A14="","",IF(I_Parameter!$C$4<=I_Parameter!$C$5,D14,IF(I_Parameter!$C$4>I_Parameter!$C$6,N14,INDEX(H14:N14,I_Parameter!$C$4-I_Parameter!$C$5)))) -> 119.49 | T14: =IF(A14="","",SUMIFS(T_Penjualan!$H$6:$H$1505,T_Penjualan!$G$6:$G$1505,A14,T_Penjualan!$B$6:$B$1505,"Order",T_Penjualan!$A$6:$A$1505,">="&I_Parameter!$C$4,T_Penjualan!$A$6:$A$1505,"<="&I_Parameter!$C$6)) -> 0 | U14: =IF(A14="","",S14-T14) -> 119.49 | V14: =IF(A14="","",MIN(H14:N14)) -> 119.49 | W14: =IF(A14="","",INDEX(I_Master!$F$6:$F$85,MATCH(A14,I_Master!$A$6:$A$85,0))) -> 5000 | X14: =IF(OR(A14="",W14=""),"",W14-Q14) -> -16170.24 | Y14: =IF(A14="","",S14*Q14) -> 2529632 | Z14: =IF(A14="","",IF(V14<-0.5,"KURANG: stok minus "&ROUND(-V14,0)&" kg — beli/potong atau geser order",IF(AND(S14>0.5,T14<=0,G14>0.5),"JUAL: "&ROUND(S14,0)&" kg tanpa order, sebagian > batas umur",IF(AND(S14>0.5,T14<=0),"JUAL: "&ROUND(S14,0)&" kg tanpa order minggu ini",IF(G14>0.5,"PERHATIAN: "&ROUND(G14,0)&" kg di atas batas umur",IF(AND(X14<>"",X14<0,T14>0),"Order di bawah biaya rata-rata — cek harga","-")))))) -> JUAL: 119 kg tanpa order, sebagian > batas umur
A15: =I_Master!A15 -> RPA|Kulit|Fresh | B15: =IF(A15="","",INDEX(I_Master!$E$6:$E$85,MATCH(A15,I_Master!$A$6:$A$85,0))) -> Boneless & parting | C15: =IF(A15="","",INDEX(I_Master!$B$6:$B$85,MATCH(A15,I_Master!$A$6:$A$85,0))) -> RPA | D15: =IF(A15="","",SUMIFS(I_Stok_Awal!$D$6:$D$305,I_Stok_Awal!$C$6:$C$305,A15)) -> 276.03 | E15: =IF(A15="","",SUMIFS(I_Stok_Awal!$E$6:$E$305,I_Stok_Awal!$C$6:$C$305,A15)) -> 1056932 | F15: =IF(OR(A15="",D15<=0),"",SUMPRODUCT((I_Stok_Awal!$C$6:$C$305=A15)*I_Stok_Awal!$D$6:$D$305*I_Stok_Awal!$F$6:$F$305)/D15) -> 87 | G15: =IF(A15="","",SUMIFS(I_Stok_Awal!$G$6:$G$305,I_Stok_Awal!$C$6:$C$305,A15)) -> 276.03 | H15: =IF($A15="","",D15+SUMIFS(T_Penerimaan!$I$6:$I$1005,T_Penerimaan!$H$6:$H$1005,$A15,T_Penerimaan!$A$6:$A$1005,H$4,T_Penerimaan!$M$6:$M$1005,1)-SUMIFS(T_Penjualan!$H$6:$H$1505,T_Penjualan!$G$6:$G$1505,$A15,T_Penjualan!$A$6:$A$1505,H$4,T_Penjualan!$P$6:$P$1505,1)) -> 276.03 | I15: =IF($A15="","",H15+SUMIFS(T_Penerimaan!$I$6:$I$1005,T_Penerimaan!$H$6:$H$1005,$A15,T_Penerimaan!$A$6:$A$1005,I$4,T_Penerimaan!$M$6:$M$1005,1)-SUMIFS(T_Penjualan!$H$6:$H$1505,T_Penjualan!$G$6:$G$1505,$A15,T_Penjualan!$A$6:$A$1505,I$4,T_Penjualan!$P$6:$P$1505,1)) -> 276.03 | J15: =IF($A15="","",I15+SUMIFS(T_Penerimaan!$I$6:$I$1005,T_Penerimaan!$H$6:$H$1005,$A15,T_Penerimaan!$A$6:$A$1005,J$4,T_Penerimaan!$M$6:$M$1005,1)-SUMIFS(T_Penjualan!$H$6:$H$1505,T_Penjualan!$G$6:$G$1505,$A15,T_Penjualan!$A$6:$A$1505,J$4,T_Penjualan!$P$6:$P$1505,1)) -> 276.03 | K15: =IF($A15="","",J15+SUMIFS(T_Penerimaan!$I$6:$I$1005,T_Penerimaan!$H$6:$H$1005,$A15,T_Penerimaan!$A$6:$A$1005,K$4,T_Penerimaan!$M$6:$M$1005,1)-SUMIFS(T_Penjualan!$H$6:$H$1505,T_Penjualan!$G$6:$G$1505,$A15,T_Penjualan!$A$6:$A$1505,K$4,T_Penjualan!$P$6:$P$1505,1)) -> 276.03 | L15: =IF($A15="","",K15+SUMIFS(T_Penerimaan!$I$6:$I$1005,T_Penerimaan!$H$6:$H$1005,$A15,T_Penerimaan!$A$6:$A$1005,L$4,T_Penerimaan!$M$6:$M$1005,1)-SUMIFS(T_Penjualan!$H$6:$H$1505,T_Penjualan!$G$6:$G$1505,$A15,T_Penjualan!$A$6:$A$1505,L$4,T_Penjualan!$P$6:$P$1505,1)) -> 276.03 | M15: =IF($A15="","",L15+SUMIFS(T_Penerimaan!$I$6:$I$1005,T_Penerimaan!$H$6:$H$1005,$A15,T_Penerimaan!$A$6:$A$1005,M$4,T_Penerimaan!$M$6:$M$1005,1)-SUMIFS(T_Penjualan!$H$6:$H$1505,T_Penjualan!$G$6:$G$1505,$A15,T_Penjualan!$A$6:$A$1505,M$4,T_Penjualan!$P$6:$P$1505,1)) -> 276.03 | N15: =IF($A15="","",M15+SUMIFS(T_Penerimaan!$I$6:$I$1005,T_Penerimaan!$H$6:$H$1005,$A15,T_Penerimaan!$A$6:$A$1005,N$4,T_Penerimaan!$M$6:$M$1005,1)-SUMIFS(T_Penjualan!$H$6:$H$1505,T_Penjualan!$G$6:$G$1505,$A15,T_Penjualan!$A$6:$A$1505,N$4,T_Penjualan!$P$6:$P$1505,1)) -> 276.03 | O15: =IF(A15="","",SUMIFS(T_Penerimaan!$I$6:$I$1005,T_Penerimaan!$H$6:$H$1005,A15,T_Penerimaan!$M$6:$M$1005,1)) -> 0 | P15: =IF(A15="","",SUMIFS(T_Penerimaan!$K$6:$K$1005,T_Penerimaan!$H$6:$H$1005,A15,T_Penerimaan!$M$6:$M$1005,1)) -> 0 | Q15: =IF(A15="","",IF(D15+O15<=0,0,(E15+P15)/(D15+O15))) -> 3829.0476 | R15: =IF(A15="","",SUMIFS(T_Penjualan!$H$6:$H$1505,T_Penjualan!$G$6:$G$1505,A15,T_Penjualan!$P$6:$P$1505,1)) -> 0 | S15: =IF(A15="","",IF(I_Parameter!$C$4<=I_Parameter!$C$5,D15,IF(I_Parameter!$C$4>I_Parameter!$C$6,N15,INDEX(H15:N15,I_Parameter!$C$4-I_Parameter!$C$5)))) -> 276.03 | T15: =IF(A15="","",SUMIFS(T_Penjualan!$H$6:$H$1505,T_Penjualan!$G$6:$G$1505,A15,T_Penjualan!$B$6:$B$1505,"Order",T_Penjualan!$A$6:$A$1505,">="&I_Parameter!$C$4,T_Penjualan!$A$6:$A$1505,"<="&I_Parameter!$C$6)) -> 0 | U15: =IF(A15="","",S15-T15) -> 276.03 | V15: =IF(A15="","",MIN(H15:N15)) -> 276.03 | W15: =IF(A15="","",INDEX(I_Master!$F$6:$F$85,MATCH(A15,I_Master!$A$6:$A$85,0))) -> 22478 | X15: =IF(OR(A15="",W15=""),"",W15-Q15) -> 18648.952 | Y15: =IF(A15="","",S15*Q15) -> 1056932 | Z15: =IF(A15="","",IF(V15<-0.5,"KURANG: stok minus "&ROUND(-V15,0)&" kg — beli/potong atau geser order",IF(AND(S15>0.5,T15<=0,G15>0.5),"JUAL: "&ROUND(S15,0)&" kg tanpa order, sebagian > batas umur",IF(AND(S15>0.5,T15<=0),"JUAL: "&ROUND(S15,0)&" kg tanpa order minggu ini",IF(G15>0.5,"PERHATIAN: "&ROUND(G15,0)&" kg di atas batas umur",IF(AND(X15<>"",X15<0,T15>0),"Order di bawah biaya rata-rata — cek harga","-")))))) -> JUAL: 276 kg tanpa order, sebagian > batas umur
A16: =I_Master!A16 -> RPA|Kulit|Frozen | B16: =IF(A16="","",INDEX(I_Master!$E$6:$E$85,MATCH(A16,I_Master!$A$6:$A$85,0))) -> Boneless & parting | C16: =IF(A16="","",INDEX(I_Master!$B$6:$B$85,MATCH(A16,I_Master!$A$6:$A$85,0))) -> RPA | D16: =IF(A16="","",SUMIFS(I_Stok_Awal!$D$6:$D$305,I_Stok_Awal!$C$6:$C$305,A16)) -> 1033.78 | E16: =IF(A16="","",SUMIFS(I_Stok_Awal!$E$6:$E$305,I_Stok_Awal!$C$6:$C$305,A16)) -> 25074700 | F16: =IF(OR(A16="",D16<=0),"",SUMPRODUCT((I_Stok_Awal!$C$6:$C$305=A16)*I_Stok_Awal!$D$6:$D$305*I_Stok_Awal!$F$6:$F$305)/D16) -> 53.8 | G16: =IF(A16="","",SUMIFS(I_Stok_Awal!$G$6:$G$305,I_Stok_Awal!$C$6:$C$305,A16)) -> 1033.78 | H16: =IF($A16="","",D16+SUMIFS(T_Penerimaan!$I$6:$I$1005,T_Penerimaan!$H$6:$H$1005,$A16,T_Penerimaan!$A$6:$A$1005,H$4,T_Penerimaan!$M$6:$M$1005,1)-SUMIFS(T_Penjualan!$H$6:$H$1505,T_Penjualan!$G$6:$G$1505,$A16,T_Penjualan!$A$6:$A$1505,H$4,T_Penjualan!$P$6:$P$1505,1)) -> 1033.78 | I16: =IF($A16="","",H16+SUMIFS(T_Penerimaan!$I$6:$I$1005,T_Penerimaan!$H$6:$H$1005,$A16,T_Penerimaan!$A$6:$A$1005,I$4,T_Penerimaan!$M$6:$M$1005,1)-SUMIFS(T_Penjualan!$H$6:$H$1505,T_Penjualan!$G$6:$G$1505,$A16,T_Penjualan!$A$6:$A$1505,I$4,T_Penjualan!$P$6:$P$1505,1)) -> 1033.78 | J16: =IF($A16="","",I16+SUMIFS(T_Penerimaan!$I$6:$I$1005,T_Penerimaan!$H$6:$H$1005,$A16,T_Penerimaan!$A$6:$A$1005,J$4,T_Penerimaan!$M$6:$M$1005,1)-SUMIFS(T_Penjualan!$H$6:$H$1505,T_Penjualan!$G$6:$G$1505,$A16,T_Penjualan!$A$6:$A$1505,J$4,T_Penjualan!$P$6:$P$1505,1)) -> 1033.78 | K16: =IF($A16="","",J16+SUMIFS(T_Penerimaan!$I$6:$I$1005,T_Penerimaan!$H$6:$H$1005,$A16,T_Penerimaan!$A$6:$A$1005,K$4,T_Penerimaan!$M$6:$M$1005,1)-SUMIFS(T_Penjualan!$H$6:$H$1505,T_Penjualan!$G$6:$G$1505,$A16,T_Penjualan!$A$6:$A$1505,K$4,T_Penjualan!$P$6:$P$1505,1)) -> 1033.78 | L16: =IF($A16="","",K16+SUMIFS(T_Penerimaan!$I$6:$I$1005,T_Penerimaan!$H$6:$H$1005,$A16,T_Penerimaan!$A$6:$A$1005,L$4,T_Penerimaan!$M$6:$M$1005,1)-SUMIFS(T_Penjualan!$H$6:$H$1505,T_Penjualan!$G$6:$G$1505,$A16,T_Penjualan!$A$6:$A$1505,L$4,T_Penjualan!$P$6:$P$1505,1)) -> 1033.78 | M16: =IF($A16="","",L16+SUMIFS(T_Penerimaan!$I$6:$I$1005,T_Penerimaan!$H$6:$H$1005,$A16,T_Penerimaan!$A$6:$A$1005,M$4,T_Penerimaan!$M$6:$M$1005,1)-SUMIFS(T_Penjualan!$H$6:$H$1505,T_Penjualan!$G$6:$G$1505,$A16,T_Penjualan!$A$6:$A$1505,M$4,T_Penjualan!$P$6:$P$1505,1)) -> 1033.78 | N16: =IF($A16="","",M16+SUMIFS(T_Penerimaan!$I$6:$I$1005,T_Penerimaan!$H$6:$H$1005,$A16,T_Penerimaan!$A$6:$A$1005,N$4,T_Penerimaan!$M$6:$M$1005,1)-SUMIFS(T_Penjualan!$H$6:$H$1505,T_Penjualan!$G$6:$G$1505,$A16,T_Penjualan!$A$6:$A$1505,N$4,T_Penjualan!$P$6:$P$1505,1)) -> 1033.78 | O16: =IF(A16="","",SUMIFS(T_Penerimaan!$I$6:$I$1005,T_Penerimaan!$H$6:$H$1005,A16,T_Penerimaan!$M$6:$M$1005,1)) -> 0 | P16: =IF(A16="","",SUMIFS(T_Penerimaan!$K$6:$K$1005,T_Penerimaan!$H$6:$H$1005,A16,T_Penerimaan!$M$6:$M$1005,1)) -> 0 | Q16: =IF(A16="","",IF(D16+O16<=0,0,(E16+P16)/(D16+O16))) -> 24255.354 | R16: =IF(A16="","",SUMIFS(T_Penjualan!$H$6:$H$1505,T_Penjualan!$G$6:$G$1505,A16,T_Penjualan!$P$6:$P$1505,1)) -> 0 | S16: =IF(A16="","",IF(I_Parameter!$C$4<=I_Parameter!$C$5,D16,IF(I_Parameter!$C$4>I_Parameter!$C$6,N16,INDEX(H16:N16,I_Parameter!$C$4-I_Parameter!$C$5)))) -> 1033.78 | T16: =IF(A16="","",SUMIFS(T_Penjualan!$H$6:$H$1505,T_Penjualan!$G$6:$G$1505,A16,T_Penjualan!$B$6:$B$1505,"Order",T_Penjualan!$A$6:$A$1505,">="&I_Parameter!$C$4,T_Penjualan!$A$6:$A$1505,"<="&I_Parameter!$C$6)) -> 0 | U16: =IF(A16="","",S16-T16) -> 1033.78 | V16: =IF(A16="","",MIN(H16:N16)) -> 1033.78 | W16: =IF(A16="","",INDEX(I_Master!$F$6:$F$85,MATCH(A16,I_Master!$A$6:$A$85,0))) -> 23007 | X16: =IF(OR(A16="",W16=""),"",W16-Q16) -> -1248.3541 | Y16: =IF(A16="","",S16*Q16) -> 25074700 | Z16: =IF(A16="","",IF(V16<-0.5,"KURANG: stok minus "&ROUND(-V16,0)&" kg — beli/potong atau geser order",IF(AND(S16>0.5,T16<=0,G16>0.5),"JUAL: "&ROUND(S16,0)&" kg tanpa order, sebagian > batas umur",IF(AND(S16>0.5,T16<=0),"JUAL: "&ROUND(S16,0)&" kg tanpa order minggu ini",IF(G16>0.5,"PERHATIAN: "&ROUND(G16,0)&" kg di atas batas umur",IF(AND(X16<>"",X16<0,T16>0),"Order di bawah biaya rata-rata — cek harga","-")))))) -> JUAL: 1034 kg tanpa order, sebagian > batas umur
A17: =I_Master!A17 -> RPA|Paha (parting)|Fresh | B17: =IF(A17="","",INDEX(I_Master!$E$6:$E$85,MATCH(A17,I_Master!$A$6:$A$85,0))) -> Boneless & parting | C17: =IF(A17="","",INDEX(I_Master!$B$6:$B$85,MATCH(A17,I_Master!$A$6:$A$85,0))) -> RPA | D17: =IF(A17="","",SUMIFS(I_Stok_Awal!$D$6:$D$305,I_Stok_Awal!$C$6:$C$305,A17)) -> 19.77 | E17: =IF(A17="","",SUMIFS(I_Stok_Awal!$E$6:$E$305,I_Stok_Awal!$C$6:$C$305,A17)) -> 899406 | F17: =IF(OR(A17="",D17<=0),"",SUMPRODUCT((I_Stok_Awal!$C$6:$C$305=A17)*I_Stok_Awal!$D$6:$D$305*I_Stok_Awal!$F$6:$F$305)/D17) -> 126 | G17: =IF(A17="","",SUMIFS(I_Stok_Awal!$G$6:$G$305,I_Stok_Awal!$C$6:$C$305,A17)) -> 19.77 | H17: =IF($A17="","",D17+SUMIFS(T_Penerimaan!$I$6:$I$1005,T_Penerimaan!$H$6:$H$1005,$A17,T_Penerimaan!$A$6:$A$1005,H$4,T_Penerimaan!$M$6:$M$1005,1)-SUMIFS(T_Penjualan!$H$6:$H$1505,T_Penjualan!$G$6:$G$1505,$A17,T_Penjualan!$A$6:$A$1505,H$4,T_Penjualan!$P$6:$P$1505,1)) -> 19.77 | I17: =IF($A17="","",H17+SUMIFS(T_Penerimaan!$I$6:$I$1005,T_Penerimaan!$H$6:$H$1005,$A17,T_Penerimaan!$A$6:$A$1005,I$4,T_Penerimaan!$M$6:$M$1005,1)-SUMIFS(T_Penjualan!$H$6:$H$1505,T_Penjualan!$G$6:$G$1505,$A17,T_Penjualan!$A$6:$A$1505,I$4,T_Penjualan!$P$6:$P$1505,1)) -> 19.77 | J17: =IF($A17="","",I17+SUMIFS(T_Penerimaan!$I$6:$I$1005,T_Penerimaan!$H$6:$H$1005,$A17,T_Penerimaan!$A$6:$A$1005,J$4,T_Penerimaan!$M$6:$M$1005,1)-SUMIFS(T_Penjualan!$H$6:$H$1505,T_Penjualan!$G$6:$G$1505,$A17,T_Penjualan!$A$6:$A$1505,J$4,T_Penjualan!$P$6:$P$1505,1)) -> 19.77 | K17: =IF($A17="","",J17+SUMIFS(T_Penerimaan!$I$6:$I$1005,T_Penerimaan!$H$6:$H$1005,$A17,T_Penerimaan!$A$6:$A$1005,K$4,T_Penerimaan!$M$6:$M$1005,1)-SUMIFS(T_Penjualan!$H$6:$H$1505,T_Penjualan!$G$6:$G$1505,$A17,T_Penjualan!$A$6:$A$1505,K$4,T_Penjualan!$P$6:$P$1505,1)) -> 19.77 | L17: =IF($A17="","",K17+SUMIFS(T_Penerimaan!$I$6:$I$1005,T_Penerimaan!$H$6:$H$1005,$A17,T_Penerimaan!$A$6:$A$1005,L$4,T_Penerimaan!$M$6:$M$1005,1)-SUMIFS(T_Penjualan!$H$6:$H$1505,T_Penjualan!$G$6:$G$1505,$A17,T_Penjualan!$A$6:$A$1505,L$4,T_Penjualan!$P$6:$P$1505,1)) -> 19.77 | M17: =IF($A17="","",L17+SUMIFS(T_Penerimaan!$I$6:$I$1005,T_Penerimaan!$H$6:$H$1005,$A17,T_Penerimaan!$A$6:$A$1005,M$4,T_Penerimaan!$M$6:$M$1005,1)-SUMIFS(T_Penjualan!$H$6:$H$1505,T_Penjualan!$G$6:$G$1505,$A17,T_Penjualan!$A$6:$A$1505,M$4,T_Penjualan!$P$6:$P$1505,1)) -> 19.77 | N17: =IF($A17="","",M17+SUMIFS(T_Penerimaan!$I$6:$I$1005,T_Penerimaan!$H$6:$H$1005,$A17,T_Penerimaan!$A$6:$A$1005,N$4,T_Penerimaan!$M$6:$M$1005,1)-SUMIFS(T_Penjualan!$H$6:$H$1505,T_Penjualan!$G$6:$G$1505,$A17,T_Penjualan!$A$6:$A$1505,N$4,T_Penjualan!$P$6:$P$1505,1)) -> 19.77 | O17: =IF(A17="","",SUMIFS(T_Penerimaan!$I$6:$I$1005,T_Penerimaan!$H$6:$H$1005,A17,T_Penerimaan!$M$6:$M$1005,1)) -> 0 | P17: =IF(A17="","",SUMIFS(T_Penerimaan!$K$6:$K$1005,T_Penerimaan!$H$6:$H$1005,A17,T_Penerimaan!$M$6:$M$1005,1)) -> 0 | Q17: =IF(A17="","",IF(D17+O17<=0,0,(E17+P17)/(D17+O17))) -> 45493.475 | R17: =IF(A17="","",SUMIFS(T_Penjualan!$H$6:$H$1505,T_Penjualan!$G$6:$G$1505,A17,T_Penjualan!$P$6:$P$1505,1)) -> 0 | S17: =IF(A17="","",IF(I_Parameter!$C$4<=I_Parameter!$C$5,D17,IF(I_Parameter!$C$4>I_Parameter!$C$6,N17,INDEX(H17:N17,I_Parameter!$C$4-I_Parameter!$C$5)))) -> 19.77 | T17: =IF(A17="","",SUMIFS(T_Penjualan!$H$6:$H$1505,T_Penjualan!$G$6:$G$1505,A17,T_Penjualan!$B$6:$B$1505,"Order",T_Penjualan!$A$6:$A$1505,">="&I_Parameter!$C$4,T_Penjualan!$A$6:$A$1505,"<="&I_Parameter!$C$6)) -> 0 | U17: =IF(A17="","",S17-T17) -> 19.77 | V17: =IF(A17="","",MIN(H17:N17)) -> 19.77 | W17: =IF(A17="","",INDEX(I_Master!$F$6:$F$85,MATCH(A17,I_Master!$A$6:$A$85,0))) -> 35238 | X17: =IF(OR(A17="",W17=""),"",W17-Q17) -> -10255.475 | Y17: =IF(A17="","",S17*Q17) -> 899406 | Z17: =IF(A17="","",IF(V17<-0.5,"KURANG: stok minus "&ROUND(-V17,0)&" kg — beli/potong atau geser order",IF(AND(S17>0.5,T17<=0,G17>0.5),"JUAL: "&ROUND(S17,0)&" kg tanpa order, sebagian > batas umur",IF(AND(S17>0.5,T17<=0),"JUAL: "&ROUND(S17,0)&" kg tanpa order minggu ini",IF(G17>0.5,"PERHATIAN: "&ROUND(G17,0)&" kg di atas batas umur",IF(AND(X17<>"",X17<0,T17>0),"Order di bawah biaya rata-rata — cek harga","-")))))) -> JUAL: 20 kg tanpa order, sebagian > batas umur
... A46: =I_Master!A46 -> Trading|Usus|Fresh | B46: =IF(A46="","",INDEX(I_Master!$E$6:$E$85,MATCH(A46,I_Master!$A$6:$A$85,0))) -> Usus | C46: =IF(A46="","",INDEX(I_Master!$B$6:$B$85,MATCH(A46,I_Master!$A$6:$A$85,0))) -> Trading | D46: =IF(A46="","",SUMIFS(I_Stok_Awal!$D$6:$D$305,I_Stok_Awal!$C$6:$C$305,A46)) -> 0 | E46: =IF(A46="","",SUMIFS(I_Stok_Awal!$E$6:$E$305,I_Stok_Awal!$C$6:$C$305,A46)) -> 0 | F46: =IF(OR(A46="",D46<=0),"",SUMPRODUCT((I_Stok_Awal!$C$6:$C$305=A46)*I_Stok_Awal!$D$6:$D$305*I_Stok_Awal!$F$6:$F$305)/D46) | G46: =IF(A46="","",SUMIFS(I_Stok_Awal!$G$6:$G$305,I_Stok_Awal!$C$6:$C$305,A46)) -> 0 | H46: =IF($A46="","",D46+SUMIFS(T_Penerimaan!$I$6:$I$1005,T_Penerimaan!$H$6:$H$1005,$A46,T_Penerimaan!$A$6:$A$1005,H$4,T_Penerimaan!$M$6:$M$1005,1)-SUMIFS(T_Penjualan!$H$6:$H$1505,T_Penjualan!$G$6:$G$1505,$A46,T_Penjualan!$A$6:$A$1505,H$4,T_Penjualan!$P$6:$P$1505,1)) -> 0 | I46: =IF($A46="","",H46+SUMIFS(T_Penerimaan!$I$6:$I$1005,T_Penerimaan!$H$6:$H$1005,$A46,T_Penerimaan!$A$6:$A$1005,I$4,T_Penerimaan!$M$6:$M$1005,1)-SUMIFS(T_Penjualan!$H$6:$H$1505,T_Penjualan!$G$6:$G$1505,$A46,T_Penjualan!$A$6:$A$1505,I$4,T_Penjualan!$P$6:$P$1505,1)) -> 0 | J46: =IF($A46="","",I46+SUMIFS(T_Penerimaan!$I$6:$I$1005,T_Penerimaan!$H$6:$H$1005,$A46,T_Penerimaan!$A$6:$A$1005,J$4,T_Penerimaan!$M$6:$M$1005,1)-SUMIFS(T_Penjualan!$H$6:$H$1505,T_Penjualan!$G$6:$G$1505,$A46,T_Penjualan!$A$6:$A$1505,J$4,T_Penjualan!$P$6:$P$1505,1)) -> 0 | K46: =IF($A46="","",J46+SUMIFS(T_Penerimaan!$I$6:$I$1005,T_Penerimaan!$H$6:$H$1005,$A46,T_Penerimaan!$A$6:$A$1005,K$4,T_Penerimaan!$M$6:$M$1005,1)-SUMIFS(T_Penjualan!$H$6:$H$1505,T_Penjualan!$G$6:$G$1505,$A46,T_Penjualan!$A$6:$A$1505,K$4,T_Penjualan!$P$6:$P$1505,1)) -> 0 | L46: =IF($A46="","",K46+SUMIFS(T_Penerimaan!$I$6:$I$1005,T_Penerimaan!$H$6:$H$1005,$A46,T_Penerimaan!$A$6:$A$1005,L$4,T_Penerimaan!$M$6:$M$1005,1)-SUMIFS(T_Penjualan!$H$6:$H$1505,T_Penjualan!$G$6:$G$1505,$A46,T_Penjualan!$A$6:$A$1505,L$4,T_Penjualan!$P$6:$P$1505,1)) -> 0 | M46: =IF($A46="","",L46+SUMIFS(T_Penerimaan!$I$6:$I$1005,T_Penerimaan!$H$6:$H$1005,$A46,T_Penerimaan!$A$6:$A$1005,M$4,T_Penerimaan!$M$6:$M$1005,1)-SUMIFS(T_Penjualan!$H$6:$H$1505,T_Penjualan!$G$6:$G$1505,$A46,T_Penjualan!$A$6:$A$1505,M$4,T_Penjualan!$P$6:$P$1505,1)) -> 0 | N46: =IF($A46="","",M46+SUMIFS(T_Penerimaan!$I$6:$I$1005,T_Penerimaan!$H$6:$H$1005,$A46,T_Penerimaan!$A$6:$A$1005,N$4,T_Penerimaan!$M$6:$M$1005,1)-SUMIFS(T_Penjualan!$H$6:$H$1505,T_Penjualan!$G$6:$G$1505,$A46,T_Penjualan!$A$6:$A$1505,N$4,T_Penjualan!$P$6:$P$1505,1)) -> 0 | O46: =IF(A46="","",SUMIFS(T_Penerimaan!$I$6:$I$1005,T_Penerimaan!$H$6:$H$1005,A46,T_Penerimaan!$M$6:$M$1005,1)) -> 0 | P46: =IF(A46="","",SUMIFS(T_Penerimaan!$K$6:$K$1005,T_Penerimaan!$H$6:$H$1005,A46,T_Penerimaan!$M$6:$M$1005,1)) -> 0 | Q46: =IF(A46="","",IF(D46+O46<=0,0,(E46+P46)/(D46+O46))) -> 0 | R46: =IF(A46="","",SUMIFS(T_Penjualan!$H$6:$H$1505,T_Penjualan!$G$6:$G$1505,A46,T_Penjualan!$P$6:$P$1505,1)) -> 0 | S46: =IF(A46="","",IF(I_Parameter!$C$4<=I_Parameter!$C$5,D46,IF(I_Parameter!$C$4>I_Parameter!$C$6,N46,INDEX(H46:N46,I_Parameter!$C$4-I_Parameter!$C$5)))) -> 0 | T46: =IF(A46="","",SUMIFS(T_Penjualan!$H$6:$H$1505,T_Penjualan!$G$6:$G$1505,A46,T_Penjualan!$B$6:$B$1505,"Order",T_Penjualan!$A$6:$A$1505,">="&I_Parameter!$C$4,T_Penjualan!$A$6:$A$1505,"<="&I_Parameter!$C$6)) -> 0 | U46: =IF(A46="","",S46-T46) -> 0 | V46: =IF(A46="","",MIN(H46:N46)) -> 0 | W46: =IF(A46="","",INDEX(I_Master!$F$6:$F$85,MATCH(A46,I_Master!$A$6:$A$85,0))) -> 14000 | X46: =IF(OR(A46="",W46=""),"",W46-Q46) -> 14000 | Y46: =IF(A46="","",S46*Q46) -> 0 | Z46: =IF(A46="","",IF(V46<-0.5,"KURANG: stok minus "&ROUND(-V46,0)&" kg — beli/potong atau geser order",IF(AND(S46>0.5,T46<=0,G46>0.5),"JUAL: "&ROUND(S46,0)&" kg tanpa order, sebagian > batas umur",IF(AND(S46>0.5,T46<=0),"JUAL: "&ROUND(S46,0)&" kg tanpa order minggu ini",IF(G46>0.5,"PERHATIAN: "&ROUND(G46,0)&" kg di atas batas umur",IF(AND(X46<>"",X46<0,T46>0),"Order di bawah biaya rata-rata — cek harga","-")))))) -> -
A47: =IF(I_Master!A47="","",I_Master!A47) | B47: =IF(A47="","",INDEX(I_Master!$E$6:$E$85,MATCH(A47,I_Master!$A$6:$A$85,0))) | C47: =IF(A47="","",INDEX(I_Master!$B$6:$B$85,MATCH(A47,I_Master!$A$6:$A$85,0))) | D47: =IF(A47="","",SUMIFS(I_Stok_Awal!$D$6:$D$305,I_Stok_Awal!$C$6:$C$305,A47)) | E47: =IF(A47="","",SUMIFS(I_Stok_Awal!$E$6:$E$305,I_Stok_Awal!$C$6:$C$305,A47)) | F47: =IF(OR(A47="",D47<=0),"",SUMPRODUCT((I_Stok_Awal!$C$6:$C$305=A47)*I_Stok_Awal!$D$6:$D$305*I_Stok_Awal!$F$6:$F$305)/D47) | G47: =IF(A47="","",SUMIFS(I_Stok_Awal!$G$6:$G$305,I_Stok_Awal!$C$6:$C$305,A47)) | H47: =IF($A47="","",D47+SUMIFS(T_Penerimaan!$I$6:$I$1005,T_Penerimaan!$H$6:$H$1005,$A47,T_Penerimaan!$A$6:$A$1005,H$4,T_Penerimaan!$M$6:$M$1005,1)-SUMIFS(T_Penjualan!$H$6:$H$1505,T_Penjualan!$G$6:$G$1505,$A47,T_Penjualan!$A$6:$A$1505,H$4,T_Penjualan!$P$6:$P$1505,1)) | I47: =IF($A47="","",H47+SUMIFS(T_Penerimaan!$I$6:$I$1005,T_Penerimaan!$H$6:$H$1005,$A47,T_Penerimaan!$A$6:$A$1005,I$4,T_Penerimaan!$M$6:$M$1005,1)-SUMIFS(T_Penjualan!$H$6:$H$1505,T_Penjualan!$G$6:$G$1505,$A47,T_Penjualan!$A$6:$A$1505,I$4,T_Penjualan!$P$6:$P$1505,1)) | J47: =IF($A47="","",I47+SUMIFS(T_Penerimaan!$I$6:$I$1005,T_Penerimaan!$H$6:$H$1005,$A47,T_Penerimaan!$A$6:$A$1005,J$4,T_Penerimaan!$M$6:$M$1005,1)-SUMIFS(T_Penjualan!$H$6:$H$1505,T_Penjualan!$G$6:$G$1505,$A47,T_Penjualan!$A$6:$A$1505,J$4,T_Penjualan!$P$6:$P$1505,1)) | K47: =IF($A47="","",J47+SUMIFS(T_Penerimaan!$I$6:$I$1005,T_Penerimaan!$H$6:$H$1005,$A47,T_Penerimaan!$A$6:$A$1005,K$4,T_Penerimaan!$M$6:$M$1005,1)-SUMIFS(T_Penjualan!$H$6:$H$1505,T_Penjualan!$G$6:$G$1505,$A47,T_Penjualan!$A$6:$A$1505,K$4,T_Penjualan!$P$6:$P$1505,1)) | L47: =IF($A47="","",K47+SUMIFS(T_Penerimaan!$I$6:$I$1005,T_Penerimaan!$H$6:$H$1005,$A47,T_Penerimaan!$A$6:$A$1005,L$4,T_Penerimaan!$M$6:$M$1005,1)-SUMIFS(T_Penjualan!$H$6:$H$1505,T_Penjualan!$G$6:$G$1505,$A47,T_Penjualan!$A$6:$A$1505,L$4,T_Penjualan!$P$6:$P$1505,1)) | M47: =IF($A47="","",L47+SUMIFS(T_Penerimaan!$I$6:$I$1005,T_Penerimaan!$H$6:$H$1005,$A47,T_Penerimaan!$A$6:$A$1005,M$4,T_Penerimaan!$M$6:$M$1005,1)-SUMIFS(T_Penjualan!$H$6:$H$1505,T_Penjualan!$G$6:$G$1505,$A47,T_Penjualan!$A$6:$A$1505,M$4,T_Penjualan!$P$6:$P$1505,1)) | N47: =IF($A47="","",M47+SUMIFS(T_Penerimaan!$I$6:$I$1005,T_Penerimaan!$H$6:$H$1005,$A47,T_Penerimaan!$A$6:$A$1005,N$4,T_Penerimaan!$M$6:$M$1005,1)-SUMIFS(T_Penjualan!$H$6:$H$1505,T_Penjualan!$G$6:$G$1505,$A47,T_Penjualan!$A$6:$A$1505,N$4,T_Penjualan!$P$6:$P$1505,1)) | O47: =IF(A47="","",SUMIFS(T_Penerimaan!$I$6:$I$1005,T_Penerimaan!$H$6:$H$1005,A47,T_Penerimaan!$M$6:$M$1005,1)) | P47: =IF(A47="","",SUMIFS(T_Penerimaan!$K$6:$K$1005,T_Penerimaan!$H$6:$H$1005,A47,T_Penerimaan!$M$6:$M$1005,1)) | Q47: =IF(A47="","",IF(D47+O47<=0,0,(E47+P47)/(D47+O47))) | R47: =IF(A47="","",SUMIFS(T_Penjualan!$H$6:$H$1505,T_Penjualan!$G$6:$G$1505,A47,T_Penjualan!$P$6:$P$1505,1)) | S47: =IF(A47="","",IF(I_Parameter!$C$4<=I_Parameter!$C$5,D47,IF(I_Parameter!$C$4>I_Parameter!$C$6,N47,INDEX(H47:N47,I_Parameter!$C$4-I_Parameter!$C$5)))) | T47: =IF(A47="","",SUMIFS(T_Penjualan!$H$6:$H$1505,T_Penjualan!$G$6:$G$1505,A47,T_Penjualan!$B$6:$B$1505,"Order",T_Penjualan!$A$6:$A$1505,">="&I_Parameter!$C$4,T_Penjualan!$A$6:$A$1505,"<="&I_Parameter!$C$6)) | U47: =IF(A47="","",S47-T47) | V47: =IF(A47="","",MIN(H47:N47)) | W47: =IF(A47="","",INDEX(I_Master!$F$6:$F$85,MATCH(A47,I_Master!$A$6:$A$85,0))) | X47: =IF(OR(A47="",W47=""),"",W47-Q47) | Y47: =IF(A47="","",S47*Q47) | Z47: =IF(A47="","",IF(V47<-0.5,"KURANG: stok minus "&ROUND(-V47,0)&" kg — beli/potong atau geser order",IF(AND(S47>0.5,T47<=0,G47>0.5),"JUAL: "&ROUND(S47,0)&" kg tanpa order, sebagian > batas umur",IF(AND(S47>0.5,T47<=0),"JUAL: "&ROUND(S47,0)&" kg tanpa order minggu ini",IF(G47>0.5,"PERHATIAN: "&ROUND(G47,0)&" kg di atas batas umur",IF(AND(X47<>"",X47<0,T47>0),"Order di bawah biaya rata-rata — cek harga","-"))))))
A48: =IF(I_Master!A48="","",I_Master!A48) | B48: =IF(A48="","",INDEX(I_Master!$E$6:$E$85,MATCH(A48,I_Master!$A$6:$A$85,0))) | C48: =IF(A48="","",INDEX(I_Master!$B$6:$B$85,MATCH(A48,I_Master!$A$6:$A$85,0))) | D48: =IF(A48="","",SUMIFS(I_Stok_Awal!$D$6:$D$305,I_Stok_Awal!$C$6:$C$305,A48)) | E48: =IF(A48="","",SUMIFS(I_Stok_Awal!$E$6:$E$305,I_Stok_Awal!$C$6:$C$305,A48)) | F48: =IF(OR(A48="",D48<=0),"",SUMPRODUCT((I_Stok_Awal!$C$6:$C$305=A48)*I_Stok_Awal!$D$6:$D$305*I_Stok_Awal!$F$6:$F$305)/D48) | G48: =IF(A48="","",SUMIFS(I_Stok_Awal!$G$6:$G$305,I_Stok_Awal!$C$6:$C$305,A48)) | H48: =IF($A48="","",D48+SUMIFS(T_Penerimaan!$I$6:$I$1005,T_Penerimaan!$H$6:$H$1005,$A48,T_Penerimaan!$A$6:$A$1005,H$4,T_Penerimaan!$M$6:$M$1005,1)-SUMIFS(T_Penjualan!$H$6:$H$1505,T_Penjualan!$G$6:$G$1505,$A48,T_Penjualan!$A$6:$A$1505,H$4,T_Penjualan!$P$6:$P$1505,1)) | I48: =IF($A48="","",H48+SUMIFS(T_Penerimaan!$I$6:$I$1005,T_Penerimaan!$H$6:$H$1005,$A48,T_Penerimaan!$A$6:$A$1005,I$4,T_Penerimaan!$M$6:$M$1005,1)-SUMIFS(T_Penjualan!$H$6:$H$1505,T_Penjualan!$G$6:$G$1505,$A48,T_Penjualan!$A$6:$A$1505,I$4,T_Penjualan!$P$6:$P$1505,1)) | J48: =IF($A48="","",I48+SUMIFS(T_Penerimaan!$I$6:$I$1005,T_Penerimaan!$H$6:$H$1005,$A48,T_Penerimaan!$A$6:$A$1005,J$4,T_Penerimaan!$M$6:$M$1005,1)-SUMIFS(T_Penjualan!$H$6:$H$1505,T_Penjualan!$G$6:$G$1505,$A48,T_Penjualan!$A$6:$A$1505,J$4,T_Penjualan!$P$6:$P$1505,1)) | K48: =IF($A48="","",J48+SUMIFS(T_Penerimaan!$I$6:$I$1005,T_Penerimaan!$H$6:$H$1005,$A48,T_Penerimaan!$A$6:$A$1005,K$4,T_Penerimaan!$M$6:$M$1005,1)-SUMIFS(T_Penjualan!$H$6:$H$1505,T_Penjualan!$G$6:$G$1505,$A48,T_Penjualan!$A$6:$A$1505,K$4,T_Penjualan!$P$6:$P$1505,1)) | L48: =IF($A48="","",K48+SUMIFS(T_Penerimaan!$I$6:$I$1005,T_Penerimaan!$H$6:$H$1005,$A48,T_Penerimaan!$A$6:$A$1005,L$4,T_Penerimaan!$M$6:$M$1005,1)-SUMIFS(T_Penjualan!$H$6:$H$1505,T_Penjualan!$G$6:$G$1505,$A48,T_Penjualan!$A$6:$A$1505,L$4,T_Penjualan!$P$6:$P$1505,1)) | M48: =IF($A48="","",L48+SUMIFS(T_Penerimaan!$I$6:$I$1005,T_Penerimaan!$H$6:$H$1005,$A48,T_Penerimaan!$A$6:$A$1005,M$4,T_Penerimaan!$M$6:$M$1005,1)-SUMIFS(T_Penjualan!$H$6:$H$1505,T_Penjualan!$G$6:$G$1505,$A48,T_Penjualan!$A$6:$A$1505,M$4,T_Penjualan!$P$6:$P$1505,1)) | N48: =IF($A48="","",M48+SUMIFS(T_Penerimaan!$I$6:$I$1005,T_Penerimaan!$H$6:$H$1005,$A48,T_Penerimaan!$A$6:$A$1005,N$4,T_Penerimaan!$M$6:$M$1005,1)-SUMIFS(T_Penjualan!$H$6:$H$1505,T_Penjualan!$G$6:$G$1505,$A48,T_Penjualan!$A$6:$A$1505,N$4,T_Penjualan!$P$6:$P$1505,1)) | O48: =IF(A48="","",SUMIFS(T_Penerimaan!$I$6:$I$1005,T_Penerimaan!$H$6:$H$1005,A48,T_Penerimaan!$M$6:$M$1005,1)) | P48: =IF(A48="","",SUMIFS(T_Penerimaan!$K$6:$K$1005,T_Penerimaan!$H$6:$H$1005,A48,T_Penerimaan!$M$6:$M$1005,1)) | Q48: =IF(A48="","",IF(D48+O48<=0,0,(E48+P48)/(D48+O48))) | R48: =IF(A48="","",SUMIFS(T_Penjualan!$H$6:$H$1505,T_Penjualan!$G$6:$G$1505,A48,T_Penjualan!$P$6:$P$1505,1)) | S48: =IF(A48="","",IF(I_Parameter!$C$4<=I_Parameter!$C$5,D48,IF(I_Parameter!$C$4>I_Parameter!$C$6,N48,INDEX(H48:N48,I_Parameter!$C$4-I_Parameter!$C$5)))) | T48: =IF(A48="","",SUMIFS(T_Penjualan!$H$6:$H$1505,T_Penjualan!$G$6:$G$1505,A48,T_Penjualan!$B$6:$B$1505,"Order",T_Penjualan!$A$6:$A$1505,">="&I_Parameter!$C$4,T_Penjualan!$A$6:$A$1505,"<="&I_Parameter!$C$6)) | U48: =IF(A48="","",S48-T48) | V48: =IF(A48="","",MIN(H48:N48)) | W48: =IF(A48="","",INDEX(I_Master!$F$6:$F$85,MATCH(A48,I_Master!$A$6:$A$85,0))) | X48: =IF(OR(A48="",W48=""),"",W48-Q48) | Y48: =IF(A48="","",S48*Q48) | Z48: =IF(A48="","",IF(V48<-0.5,"KURANG: stok minus "&ROUND(-V48,0)&" kg — beli/potong atau geser order",IF(AND(S48>0.5,T48<=0,G48>0.5),"JUAL: "&ROUND(S48,0)&" kg tanpa order, sebagian > batas umur",IF(AND(S48>0.5,T48<=0),"JUAL: "&ROUND(S48,0)&" kg tanpa order minggu ini",IF(G48>0.5,"PERHATIAN: "&ROUND(G48,0)&" kg di atas batas umur",IF(AND(X48<>"",X48<0,T48>0),"Order di bawah biaya rata-rata — cek harga","-"))))))
A49: =IF(I_Master!A49="","",I_Master!A49) | B49: =IF(A49="","",INDEX(I_Master!$E$6:$E$85,MATCH(A49,I_Master!$A$6:$A$85,0))) | C49: =IF(A49="","",INDEX(I_Master!$B$6:$B$85,MATCH(A49,I_Master!$A$6:$A$85,0))) | D49: =IF(A49="","",SUMIFS(I_Stok_Awal!$D$6:$D$305,I_Stok_Awal!$C$6:$C$305,A49)) | E49: =IF(A49="","",SUMIFS(I_Stok_Awal!$E$6:$E$305,I_Stok_Awal!$C$6:$C$305,A49)) | F49: =IF(OR(A49="",D49<=0),"",SUMPRODUCT((I_Stok_Awal!$C$6:$C$305=A49)*I_Stok_Awal!$D$6:$D$305*I_Stok_Awal!$F$6:$F$305)/D49) | G49: =IF(A49="","",SUMIFS(I_Stok_Awal!$G$6:$G$305,I_Stok_Awal!$C$6:$C$305,A49)) | H49: =IF($A49="","",D49+SUMIFS(T_Penerimaan!$I$6:$I$1005,T_Penerimaan!$H$6:$H$1005,$A49,T_Penerimaan!$A$6:$A$1005,H$4,T_Penerimaan!$M$6:$M$1005,1)-SUMIFS(T_Penjualan!$H$6:$H$1505,T_Penjualan!$G$6:$G$1505,$A49,T_Penjualan!$A$6:$A$1505,H$4,T_Penjualan!$P$6:$P$1505,1)) | I49: =IF($A49="","",H49+SUMIFS(T_Penerimaan!$I$6:$I$1005,T_Penerimaan!$H$6:$H$1005,$A49,T_Penerimaan!$A$6:$A$1005,I$4,T_Penerimaan!$M$6:$M$1005,1)-SUMIFS(T_Penjualan!$H$6:$H$1505,T_Penjualan!$G$6:$G$1505,$A49,T_Penjualan!$A$6:$A$1505,I$4,T_Penjualan!$P$6:$P$1505,1)) | J49: =IF($A49="","",I49+SUMIFS(T_Penerimaan!$I$6:$I$1005,T_Penerimaan!$H$6:$H$1005,$A49,T_Penerimaan!$A$6:$A$1005,J$4,T_Penerimaan!$M$6:$M$1005,1)-SUMIFS(T_Penjualan!$H$6:$H$1505,T_Penjualan!$G$6:$G$1505,$A49,T_Penjualan!$A$6:$A$1505,J$4,T_Penjualan!$P$6:$P$1505,1)) | K49: =IF($A49="","",J49+SUMIFS(T_Penerimaan!$I$6:$I$1005,T_Penerimaan!$H$6:$H$1005,$A49,T_Penerimaan!$A$6:$A$1005,K$4,T_Penerimaan!$M$6:$M$1005,1)-SUMIFS(T_Penjualan!$H$6:$H$1505,T_Penjualan!$G$6:$G$1505,$A49,T_Penjualan!$A$6:$A$1505,K$4,T_Penjualan!$P$6:$P$1505,1)) | L49: =IF($A49="","",K49+SUMIFS(T_Penerimaan!$I$6:$I$1005,T_Penerimaan!$H$6:$H$1005,$A49,T_Penerimaan!$A$6:$A$1005,L$4,T_Penerimaan!$M$6:$M$1005,1)-SUMIFS(T_Penjualan!$H$6:$H$1505,T_Penjualan!$G$6:$G$1505,$A49,T_Penjualan!$A$6:$A$1505,L$4,T_Penjualan!$P$6:$P$1505,1)) | M49: =IF($A49="","",L49+SUMIFS(T_Penerimaan!$I$6:$I$1005,T_Penerimaan!$H$6:$H$1005,$A49,T_Penerimaan!$A$6:$A$1005,M$4,T_Penerimaan!$M$6:$M$1005,1)-SUMIFS(T_Penjualan!$H$6:$H$1505,T_Penjualan!$G$6:$G$1505,$A49,T_Penjualan!$A$6:$A$1505,M$4,T_Penjualan!$P$6:$P$1505,1)) | N49: =IF($A49="","",M49+SUMIFS(T_Penerimaan!$I$6:$I$1005,T_Penerimaan!$H$6:$H$1005,$A49,T_Penerimaan!$A$6:$A$1005,N$4,T_Penerimaan!$M$6:$M$1005,1)-SUMIFS(T_Penjualan!$H$6:$H$1505,T_Penjualan!$G$6:$G$1505,$A49,T_Penjualan!$A$6:$A$1505,N$4,T_Penjualan!$P$6:$P$1505,1)) | O49: =IF(A49="","",SUMIFS(T_Penerimaan!$I$6:$I$1005,T_Penerimaan!$H$6:$H$1005,A49,T_Penerimaan!$M$6:$M$1005,1)) | P49: =IF(A49="","",SUMIFS(T_Penerimaan!$K$6:$K$1005,T_Penerimaan!$H$6:$H$1005,A49,T_Penerimaan!$M$6:$M$1005,1)) | Q49: =IF(A49="","",IF(D49+O49<=0,0,(E49+P49)/(D49+O49))) | R49: =IF(A49="","",SUMIFS(T_Penjualan!$H$6:$H$1505,T_Penjualan!$G$6:$G$1505,A49,T_Penjualan!$P$6:$P$1505,1)) | S49: =IF(A49="","",IF(I_Parameter!$C$4<=I_Parameter!$C$5,D49,IF(I_Parameter!$C$4>I_Parameter!$C$6,N49,INDEX(H49:N49,I_Parameter!$C$4-I_Parameter!$C$5)))) | T49: =IF(A49="","",SUMIFS(T_Penjualan!$H$6:$H$1505,T_Penjualan!$G$6:$G$1505,A49,T_Penjualan!$B$6:$B$1505,"Order",T_Penjualan!$A$6:$A$1505,">="&I_Parameter!$C$4,T_Penjualan!$A$6:$A$1505,"<="&I_Parameter!$C$6)) | U49: =IF(A49="","",S49-T49) | V49: =IF(A49="","",MIN(H49:N49)) | W49: =IF(A49="","",INDEX(I_Master!$F$6:$F$85,MATCH(A49,I_Master!$A$6:$A$85,0))) | X49: =IF(OR(A49="",W49=""),"",W49-Q49) | Y49: =IF(A49="","",S49*Q49) | Z49: =IF(A49="","",IF(V49<-0.5,"KURANG: stok minus "&ROUND(-V49,0)&" kg — beli/potong atau geser order",IF(AND(S49>0.5,T49<=0,G49>0.5),"JUAL: "&ROUND(S49,0)&" kg tanpa order, sebagian > batas umur",IF(AND(S49>0.5,T49<=0),"JUAL: "&ROUND(S49,0)&" kg tanpa order minggu ini",IF(G49>0.5,"PERHATIAN: "&ROUND(G49,0)&" kg di atas batas umur",IF(AND(X49<>"",X49<0,T49>0),"Order di bawah biaya rata-rata — cek harga","-"))))))
A50: =IF(I_Master!A50="","",I_Master!A50) | B50: =IF(A50="","",INDEX(I_Master!$E$6:$E$85,MATCH(A50,I_Master!$A$6:$A$85,0))) | C50: =IF(A50="","",INDEX(I_Master!$B$6:$B$85,MATCH(A50,I_Master!$A$6:$A$85,0))) | D50: =IF(A50="","",SUMIFS(I_Stok_Awal!$D$6:$D$305,I_Stok_Awal!$C$6:$C$305,A50)) | E50: =IF(A50="","",SUMIFS(I_Stok_Awal!$E$6:$E$305,I_Stok_Awal!$C$6:$C$305,A50)) | F50: =IF(OR(A50="",D50<=0),"",SUMPRODUCT((I_Stok_Awal!$C$6:$C$305=A50)*I_Stok_Awal!$D$6:$D$305*I_Stok_Awal!$F$6:$F$305)/D50) | G50: =IF(A50="","",SUMIFS(I_Stok_Awal!$G$6:$G$305,I_Stok_Awal!$C$6:$C$305,A50)) | H50: =IF($A50="","",D50+SUMIFS(T_Penerimaan!$I$6:$I$1005,T_Penerimaan!$H$6:$H$1005,$A50,T_Penerimaan!$A$6:$A$1005,H$4,T_Penerimaan!$M$6:$M$1005,1)-SUMIFS(T_Penjualan!$H$6:$H$1505,T_Penjualan!$G$6:$G$1505,$A50,T_Penjualan!$A$6:$A$1505,H$4,T_Penjualan!$P$6:$P$1505,1)) | I50: =IF($A50="","",H50+SUMIFS(T_Penerimaan!$I$6:$I$1005,T_Penerimaan!$H$6:$H$1005,$A50,T_Penerimaan!$A$6:$A$1005,I$4,T_Penerimaan!$M$6:$M$1005,1)-SUMIFS(T_Penjualan!$H$6:$H$1505,T_Penjualan!$G$6:$G$1505,$A50,T_Penjualan!$A$6:$A$1505,I$4,T_Penjualan!$P$6:$P$1505,1)) | J50: =IF($A50="","",I50+SUMIFS(T_Penerimaan!$I$6:$I$1005,T_Penerimaan!$H$6:$H$1005,$A50,T_Penerimaan!$A$6:$A$1005,J$4,T_Penerimaan!$M$6:$M$1005,1)-SUMIFS(T_Penjualan!$H$6:$H$1505,T_Penjualan!$G$6:$G$1505,$A50,T_Penjualan!$A$6:$A$1505,J$4,T_Penjualan!$P$6:$P$1505,1)) | K50: =IF($A50="","",J50+SUMIFS(T_Penerimaan!$I$6:$I$1005,T_Penerimaan!$H$6:$H$1005,$A50,T_Penerimaan!$A$6:$A$1005,K$4,T_Penerimaan!$M$6:$M$1005,1)-SUMIFS(T_Penjualan!$H$6:$H$1505,T_Penjualan!$G$6:$G$1505,$A50,T_Penjualan!$A$6:$A$1505,K$4,T_Penjualan!$P$6:$P$1505,1)) | L50: =IF($A50="","",K50+SUMIFS(T_Penerimaan!$I$6:$I$1005,T_Penerimaan!$H$6:$H$1005,$A50,T_Penerimaan!$A$6:$A$1005,L$4,T_Penerimaan!$M$6:$M$1005,1)-SUMIFS(T_Penjualan!$H$6:$H$1505,T_Penjualan!$G$6:$G$1505,$A50,T_Penjualan!$A$6:$A$1505,L$4,T_Penjualan!$P$6:$P$1505,1)) | M50: =IF($A50="","",L50+SUMIFS(T_Penerimaan!$I$6:$I$1005,T_Penerimaan!$H$6:$H$1005,$A50,T_Penerimaan!$A$6:$A$1005,M$4,T_Penerimaan!$M$6:$M$1005,1)-SUMIFS(T_Penjualan!$H$6:$H$1505,T_Penjualan!$G$6:$G$1505,$A50,T_Penjualan!$A$6:$A$1505,M$4,T_Penjualan!$P$6:$P$1505,1)) | N50: =IF($A50="","",M50+SUMIFS(T_Penerimaan!$I$6:$I$1005,T_Penerimaan!$H$6:$H$1005,$A50,T_Penerimaan!$A$6:$A$1005,N$4,T_Penerimaan!$M$6:$M$1005,1)-SUMIFS(T_Penjualan!$H$6:$H$1505,T_Penjualan!$G$6:$G$1505,$A50,T_Penjualan!$A$6:$A$1505,N$4,T_Penjualan!$P$6:$P$1505,1)) | O50: =IF(A50="","",SUMIFS(T_Penerimaan!$I$6:$I$1005,T_Penerimaan!$H$6:$H$1005,A50,T_Penerimaan!$M$6:$M$1005,1)) | P50: =IF(A50="","",SUMIFS(T_Penerimaan!$K$6:$K$1005,T_Penerimaan!$H$6:$H$1005,A50,T_Penerimaan!$M$6:$M$1005,1)) | Q50: =IF(A50="","",IF(D50+O50<=0,0,(E50+P50)/(D50+O50))) | R50: =IF(A50="","",SUMIFS(T_Penjualan!$H$6:$H$1505,T_Penjualan!$G$6:$G$1505,A50,T_Penjualan!$P$6:$P$1505,1)) | S50: =IF(A50="","",IF(I_Parameter!$C$4<=I_Parameter!$C$5,D50,IF(I_Parameter!$C$4>I_Parameter!$C$6,N50,INDEX(H50:N50,I_Parameter!$C$4-I_Parameter!$C$5)))) | T50: =IF(A50="","",SUMIFS(T_Penjualan!$H$6:$H$1505,T_Penjualan!$G$6:$G$1505,A50,T_Penjualan!$B$6:$B$1505,"Order",T_Penjualan!$A$6:$A$1505,">="&I_Parameter!$C$4,T_Penjualan!$A$6:$A$1505,"<="&I_Parameter!$C$6)) | U50: =IF(A50="","",S50-T50) | V50: =IF(A50="","",MIN(H50:N50)) | W50: =IF(A50="","",INDEX(I_Master!$F$6:$F$85,MATCH(A50,I_Master!$A$6:$A$85,0))) | X50: =IF(OR(A50="",W50=""),"",W50-Q50) | Y50: =IF(A50="","",S50*Q50) | Z50: =IF(A50="","",IF(V50<-0.5,"KURANG: stok minus "&ROUND(-V50,0)&" kg — beli/potong atau geser order",IF(AND(S50>0.5,T50<=0,G50>0.5),"JUAL: "&ROUND(S50,0)&" kg tanpa order, sebagian > batas umur",IF(AND(S50>0.5,T50<=0),"JUAL: "&ROUND(S50,0)&" kg tanpa order minggu ini",IF(G50>0.5,"PERHATIAN: "&ROUND(G50,0)&" kg di atas batas umur",IF(AND(X50<>"",X50<0,T50>0),"Order di bawah biaya rata-rata — cek harga","-"))))))
A51: =IF(I_Master!A51="","",I_Master!A51) | B51: =IF(A51="","",INDEX(I_Master!$E$6:$E$85,MATCH(A51,I_Master!$A$6:$A$85,0))) | C51: =IF(A51="","",INDEX(I_Master!$B$6:$B$85,MATCH(A51,I_Master!$A$6:$A$85,0))) | D51: =IF(A51="","",SUMIFS(I_Stok_Awal!$D$6:$D$305,I_Stok_Awal!$C$6:$C$305,A51)) | E51: =IF(A51="","",SUMIFS(I_Stok_Awal!$E$6:$E$305,I_Stok_Awal!$C$6:$C$305,A51)) | F51: =IF(OR(A51="",D51<=0),"",SUMPRODUCT((I_Stok_Awal!$C$6:$C$305=A51)*I_Stok_Awal!$D$6:$D$305*I_Stok_Awal!$F$6:$F$305)/D51) | G51: =IF(A51="","",SUMIFS(I_Stok_Awal!$G$6:$G$305,I_Stok_Awal!$C$6:$C$305,A51)) | H51: =IF($A51="","",D51+SUMIFS(T_Penerimaan!$I$6:$I$1005,T_Penerimaan!$H$6:$H$1005,$A51,T_Penerimaan!$A$6:$A$1005,H$4,T_Penerimaan!$M$6:$M$1005,1)-SUMIFS(T_Penjualan!$H$6:$H$1505,T_Penjualan!$G$6:$G$1505,$A51,T_Penjualan!$A$6:$A$1505,H$4,T_Penjualan!$P$6:$P$1505,1)) | I51: =IF($A51="","",H51+SUMIFS(T_Penerimaan!$I$6:$I$1005,T_Penerimaan!$H$6:$H$1005,$A51,T_Penerimaan!$A$6:$A$1005,I$4,T_Penerimaan!$M$6:$M$1005,1)-SUMIFS(T_Penjualan!$H$6:$H$1505,T_Penjualan!$G$6:$G$1505,$A51,T_Penjualan!$A$6:$A$1505,I$4,T_Penjualan!$P$6:$P$1505,1)) | J51: =IF($A51="","",I51+SUMIFS(T_Penerimaan!$I$6:$I$1005,T_Penerimaan!$H$6:$H$1005,$A51,T_Penerimaan!$A$6:$A$1005,J$4,T_Penerimaan!$M$6:$M$1005,1)-SUMIFS(T_Penjualan!$H$6:$H$1505,T_Penjualan!$G$6:$G$1505,$A51,T_Penjualan!$A$6:$A$1505,J$4,T_Penjualan!$P$6:$P$1505,1)) | K51: =IF($A51="","",J51+SUMIFS(T_Penerimaan!$I$6:$I$1005,T_Penerimaan!$H$6:$H$1005,$A51,T_Penerimaan!$A$6:$A$1005,K$4,T_Penerimaan!$M$6:$M$1005,1)-SUMIFS(T_Penjualan!$H$6:$H$1505,T_Penjualan!$G$6:$G$1505,$A51,T_Penjualan!$A$6:$A$1505,K$4,T_Penjualan!$P$6:$P$1505,1)) | L51: =IF($A51="","",K51+SUMIFS(T_Penerimaan!$I$6:$I$1005,T_Penerimaan!$H$6:$H$1005,$A51,T_Penerimaan!$A$6:$A$1005,L$4,T_Penerimaan!$M$6:$M$1005,1)-SUMIFS(T_Penjualan!$H$6:$H$1505,T_Penjualan!$G$6:$G$1505,$A51,T_Penjualan!$A$6:$A$1505,L$4,T_Penjualan!$P$6:$P$1505,1)) | M51: =IF($A51="","",L51+SUMIFS(T_Penerimaan!$I$6:$I$1005,T_Penerimaan!$H$6:$H$1005,$A51,T_Penerimaan!$A$6:$A$1005,M$4,T_Penerimaan!$M$6:$M$1005,1)-SUMIFS(T_Penjualan!$H$6:$H$1505,T_Penjualan!$G$6:$G$1505,$A51,T_Penjualan!$A$6:$A$1505,M$4,T_Penjualan!$P$6:$P$1505,1)) | N51: =IF($A51="","",M51+SUMIFS(T_Penerimaan!$I$6:$I$1005,T_Penerimaan!$H$6:$H$1005,$A51,T_Penerimaan!$A$6:$A$1005,N$4,T_Penerimaan!$M$6:$M$1005,1)-SUMIFS(T_Penjualan!$H$6:$H$1505,T_Penjualan!$G$6:$G$1505,$A51,T_Penjualan!$A$6:$A$1505,N$4,T_Penjualan!$P$6:$P$1505,1)) | O51: =IF(A51="","",SUMIFS(T_Penerimaan!$I$6:$I$1005,T_Penerimaan!$H$6:$H$1005,A51,T_Penerimaan!$M$6:$M$1005,1)) | P51: =IF(A51="","",SUMIFS(T_Penerimaan!$K$6:$K$1005,T_Penerimaan!$H$6:$H$1005,A51,T_Penerimaan!$M$6:$M$1005,1)) | Q51: =IF(A51="","",IF(D51+O51<=0,0,(E51+P51)/(D51+O51))) | R51: =IF(A51="","",SUMIFS(T_Penjualan!$H$6:$H$1505,T_Penjualan!$G$6:$G$1505,A51,T_Penjualan!$P$6:$P$1505,1)) | S51: =IF(A51="","",IF(I_Parameter!$C$4<=I_Parameter!$C$5,D51,IF(I_Parameter!$C$4>I_Parameter!$C$6,N51,INDEX(H51:N51,I_Parameter!$C$4-I_Parameter!$C$5)))) | T51: =IF(A51="","",SUMIFS(T_Penjualan!$H$6:$H$1505,T_Penjualan!$G$6:$G$1505,A51,T_Penjualan!$B$6:$B$1505,"Order",T_Penjualan!$A$6:$A$1505,">="&I_Parameter!$C$4,T_Penjualan!$A$6:$A$1505,"<="&I_Parameter!$C$6)) | U51: =IF(A51="","",S51-T51) | V51: =IF(A51="","",MIN(H51:N51)) | W51: =IF(A51="","",INDEX(I_Master!$F$6:$F$85,MATCH(A51,I_Master!$A$6:$A$85,0))) | X51: =IF(OR(A51="",W51=""),"",W51-Q51) | Y51: =IF(A51="","",S51*Q51) | Z51: =IF(A51="","",IF(V51<-0.5,"KURANG: stok minus "&ROUND(-V51,0)&" kg — beli/potong atau geser order",IF(AND(S51>0.5,T51<=0,G51>0.5),"JUAL: "&ROUND(S51,0)&" kg tanpa order, sebagian > batas umur",IF(AND(S51>0.5,T51<=0),"JUAL: "&ROUND(S51,0)&" kg tanpa order minggu ini",IF(G51>0.5,"PERHATIAN: "&ROUND(G51,0)&" kg di atas batas umur",IF(AND(X51<>"",X51<0,T51>0),"Order di bawah biaya rata-rata — cek harga","-"))))))
A52: =IF(I_Master!A52="","",I_Master!A52) | B52: =IF(A52="","",INDEX(I_Master!$E$6:$E$85,MATCH(A52,I_Master!$A$6:$A$85,0))) | C52: =IF(A52="","",INDEX(I_Master!$B$6:$B$85,MATCH(A52,I_Master!$A$6:$A$85,0))) | D52: =IF(A52="","",SUMIFS(I_Stok_Awal!$D$6:$D$305,I_Stok_Awal!$C$6:$C$305,A52)) | E52: =IF(A52="","",SUMIFS(I_Stok_Awal!$E$6:$E$305,I_Stok_Awal!$C$6:$C$305,A52)) | F52: =IF(OR(A52="",D52<=0),"",SUMPRODUCT((I_Stok_Awal!$C$6:$C$305=A52)*I_Stok_Awal!$D$6:$D$305*I_Stok_Awal!$F$6:$F$305)/D52) | G52: =IF(A52="","",SUMIFS(I_Stok_Awal!$G$6:$G$305,I_Stok_Awal!$C$6:$C$305,A52)) | H52: =IF($A52="","",D52+SUMIFS(T_Penerimaan!$I$6:$I$1005,T_Penerimaan!$H$6:$H$1005,$A52,T_Penerimaan!$A$6:$A$1005,H$4,T_Penerimaan!$M$6:$M$1005,1)-SUMIFS(T_Penjualan!$H$6:$H$1505,T_Penjualan!$G$6:$G$1505,$A52,T_Penjualan!$A$6:$A$1505,H$4,T_Penjualan!$P$6:$P$1505,1)) | I52: =IF($A52="","",H52+SUMIFS(T_Penerimaan!$I$6:$I$1005,T_Penerimaan!$H$6:$H$1005,$A52,T_Penerimaan!$A$6:$A$1005,I$4,T_Penerimaan!$M$6:$M$1005,1)-SUMIFS(T_Penjualan!$H$6:$H$1505,T_Penjualan!$G$6:$G$1505,$A52,T_Penjualan!$A$6:$A$1505,I$4,T_Penjualan!$P$6:$P$1505,1)) | J52: =IF($A52="","",I52+SUMIFS(T_Penerimaan!$I$6:$I$1005,T_Penerimaan!$H$6:$H$1005,$A52,T_Penerimaan!$A$6:$A$1005,J$4,T_Penerimaan!$M$6:$M$1005,1)-SUMIFS(T_Penjualan!$H$6:$H$1505,T_Penjualan!$G$6:$G$1505,$A52,T_Penjualan!$A$6:$A$1505,J$4,T_Penjualan!$P$6:$P$1505,1)) | K52: =IF($A52="","",J52+SUMIFS(T_Penerimaan!$I$6:$I$1005,T_Penerimaan!$H$6:$H$1005,$A52,T_Penerimaan!$A$6:$A$1005,K$4,T_Penerimaan!$M$6:$M$1005,1)-SUMIFS(T_Penjualan!$H$6:$H$1505,T_Penjualan!$G$6:$G$1505,$A52,T_Penjualan!$A$6:$A$1505,K$4,T_Penjualan!$P$6:$P$1505,1)) | L52: =IF($A52="","",K52+SUMIFS(T_Penerimaan!$I$6:$I$1005,T_Penerimaan!$H$6:$H$1005,$A52,T_Penerimaan!$A$6:$A$1005,L$4,T_Penerimaan!$M$6:$M$1005,1)-SUMIFS(T_Penjualan!$H$6:$H$1505,T_Penjualan!$G$6:$G$1505,$A52,T_Penjualan!$A$6:$A$1505,L$4,T_Penjualan!$P$6:$P$1505,1)) | M52: =IF($A52="","",L52+SUMIFS(T_Penerimaan!$I$6:$I$1005,T_Penerimaan!$H$6:$H$1005,$A52,T_Penerimaan!$A$6:$A$1005,M$4,T_Penerimaan!$M$6:$M$1005,1)-SUMIFS(T_Penjualan!$H$6:$H$1505,T_Penjualan!$G$6:$G$1505,$A52,T_Penjualan!$A$6:$A$1505,M$4,T_Penjualan!$P$6:$P$1505,1)) | N52: =IF($A52="","",M52+SUMIFS(T_Penerimaan!$I$6:$I$1005,T_Penerimaan!$H$6:$H$1005,$A52,T_Penerimaan!$A$6:$A$1005,N$4,T_Penerimaan!$M$6:$M$1005,1)-SUMIFS(T_Penjualan!$H$6:$H$1505,T_Penjualan!$G$6:$G$1505,$A52,T_Penjualan!$A$6:$A$1505,N$4,T_Penjualan!$P$6:$P$1505,1)) | O52: =IF(A52="","",SUMIFS(T_Penerimaan!$I$6:$I$1005,T_Penerimaan!$H$6:$H$1005,A52,T_Penerimaan!$M$6:$M$1005,1)) | P52: =IF(A52="","",SUMIFS(T_Penerimaan!$K$6:$K$1005,T_Penerimaan!$H$6:$H$1005,A52,T_Penerimaan!$M$6:$M$1005,1)) | Q52: =IF(A52="","",IF(D52+O52<=0,0,(E52+P52)/(D52+O52))) | R52: =IF(A52="","",SUMIFS(T_Penjualan!$H$6:$H$1505,T_Penjualan!$G$6:$G$1505,A52,T_Penjualan!$P$6:$P$1505,1)) | S52: =IF(A52="","",IF(I_Parameter!$C$4<=I_Parameter!$C$5,D52,IF(I_Parameter!$C$4>I_Parameter!$C$6,N52,INDEX(H52:N52,I_Parameter!$C$4-I_Parameter!$C$5)))) | T52: =IF(A52="","",SUMIFS(T_Penjualan!$H$6:$H$1505,T_Penjualan!$G$6:$G$1505,A52,T_Penjualan!$B$6:$B$1505,"Order",T_Penjualan!$A$6:$A$1505,">="&I_Parameter!$C$4,T_Penjualan!$A$6:$A$1505,"<="&I_Parameter!$C$6)) | U52: =IF(A52="","",S52-T52) | V52: =IF(A52="","",MIN(H52:N52)) | W52: =IF(A52="","",INDEX(I_Master!$F$6:$F$85,MATCH(A52,I_Master!$A$6:$A$85,0))) | X52: =IF(OR(A52="",W52=""),"",W52-Q52) | Y52: =IF(A52="","",S52*Q52) | Z52: =IF(A52="","",IF(V52<-0.5,"KURANG: stok minus "&ROUND(-V52,0)&" kg — beli/potong atau geser order",IF(AND(S52>0.5,T52<=0,G52>0.5),"JUAL: "&ROUND(S52,0)&" kg tanpa order, sebagian > batas umur",IF(AND(S52>0.5,T52<=0),"JUAL: "&ROUND(S52,0)&" kg tanpa order minggu ini",IF(G52>0.5,"PERHATIAN: "&ROUND(G52,0)&" kg di atas batas umur",IF(AND(X52<>"",X52<0,T52>0),"Order di bawah biaya rata-rata — cek harga","-"))))))
A53: =IF(I_Master!A53="","",I_Master!A53) | B53: =IF(A53="","",INDEX(I_Master!$E$6:$E$85,MATCH(A53,I_Master!$A$6:$A$85,0))) | C53: =IF(A53="","",INDEX(I_Master!$B$6:$B$85,MATCH(A53,I_Master!$A$6:$A$85,0))) | D53: =IF(A53="","",SUMIFS(I_Stok_Awal!$D$6:$D$305,I_Stok_Awal!$C$6:$C$305,A53)) | E53: =IF(A53="","",SUMIFS(I_Stok_Awal!$E$6:$E$305,I_Stok_Awal!$C$6:$C$305,A53)) | F53: =IF(OR(A53="",D53<=0),"",SUMPRODUCT((I_Stok_Awal!$C$6:$C$305=A53)*I_Stok_Awal!$D$6:$D$305*I_Stok_Awal!$F$6:$F$305)/D53) | G53: =IF(A53="","",SUMIFS(I_Stok_Awal!$G$6:$G$305,I_Stok_Awal!$C$6:$C$305,A53)) | H53: =IF($A53="","",D53+SUMIFS(T_Penerimaan!$I$6:$I$1005,T_Penerimaan!$H$6:$H$1005,$A53,T_Penerimaan!$A$6:$A$1005,H$4,T_Penerimaan!$M$6:$M$1005,1)-SUMIFS(T_Penjualan!$H$6:$H$1505,T_Penjualan!$G$6:$G$1505,$A53,T_Penjualan!$A$6:$A$1505,H$4,T_Penjualan!$P$6:$P$1505,1)) | I53: =IF($A53="","",H53+SUMIFS(T_Penerimaan!$I$6:$I$1005,T_Penerimaan!$H$6:$H$1005,$A53,T_Penerimaan!$A$6:$A$1005,I$4,T_Penerimaan!$M$6:$M$1005,1)-SUMIFS(T_Penjualan!$H$6:$H$1505,T_Penjualan!$G$6:$G$1505,$A53,T_Penjualan!$A$6:$A$1505,I$4,T_Penjualan!$P$6:$P$1505,1)) | J53: =IF($A53="","",I53+SUMIFS(T_Penerimaan!$I$6:$I$1005,T_Penerimaan!$H$6:$H$1005,$A53,T_Penerimaan!$A$6:$A$1005,J$4,T_Penerimaan!$M$6:$M$1005,1)-SUMIFS(T_Penjualan!$H$6:$H$1505,T_Penjualan!$G$6:$G$1505,$A53,T_Penjualan!$A$6:$A$1505,J$4,T_Penjualan!$P$6:$P$1505,1)) | K53: =IF($A53="","",J53+SUMIFS(T_Penerimaan!$I$6:$I$1005,T_Penerimaan!$H$6:$H$1005,$A53,T_Penerimaan!$A$6:$A$1005,K$4,T_Penerimaan!$M$6:$M$1005,1)-SUMIFS(T_Penjualan!$H$6:$H$1505,T_Penjualan!$G$6:$G$1505,$A53,T_Penjualan!$A$6:$A$1505,K$4,T_Penjualan!$P$6:$P$1505,1)) | L53: =IF($A53="","",K53+SUMIFS(T_Penerimaan!$I$6:$I$1005,T_Penerimaan!$H$6:$H$1005,$A53,T_Penerimaan!$A$6:$A$1005,L$4,T_Penerimaan!$M$6:$M$1005,1)-SUMIFS(T_Penjualan!$H$6:$H$1505,T_Penjualan!$G$6:$G$1505,$A53,T_Penjualan!$A$6:$A$1505,L$4,T_Penjualan!$P$6:$P$1505,1)) | M53: =IF($A53="","",L53+SUMIFS(T_Penerimaan!$I$6:$I$1005,T_Penerimaan!$H$6:$H$1005,$A53,T_Penerimaan!$A$6:$A$1005,M$4,T_Penerimaan!$M$6:$M$1005,1)-SUMIFS(T_Penjualan!$H$6:$H$1505,T_Penjualan!$G$6:$G$1505,$A53,T_Penjualan!$A$6:$A$1505,M$4,T_Penjualan!$P$6:$P$1505,1)) | N53: =IF($A53="","",M53+SUMIFS(T_Penerimaan!$I$6:$I$1005,T_Penerimaan!$H$6:$H$1005,$A53,T_Penerimaan!$A$6:$A$1005,N$4,T_Penerimaan!$M$6:$M$1005,1)-SUMIFS(T_Penjualan!$H$6:$H$1505,T_Penjualan!$G$6:$G$1505,$A53,T_Penjualan!$A$6:$A$1505,N$4,T_Penjualan!$P$6:$P$1505,1)) | O53: =IF(A53="","",SUMIFS(T_Penerimaan!$I$6:$I$1005,T_Penerimaan!$H$6:$H$1005,A53,T_Penerimaan!$M$6:$M$1005,1)) | P53: =IF(A53="","",SUMIFS(T_Penerimaan!$K$6:$K$1005,T_Penerimaan!$H$6:$H$1005,A53,T_Penerimaan!$M$6:$M$1005,1)) | Q53: =IF(A53="","",IF(D53+O53<=0,0,(E53+P53)/(D53+O53))) | R53: =IF(A53="","",SUMIFS(T_Penjualan!$H$6:$H$1505,T_Penjualan!$G$6:$G$1505,A53,T_Penjualan!$P$6:$P$1505,1)) | S53: =IF(A53="","",IF(I_Parameter!$C$4<=I_Parameter!$C$5,D53,IF(I_Parameter!$C$4>I_Parameter!$C$6,N53,INDEX(H53:N53,I_Parameter!$C$4-I_Parameter!$C$5)))) | T53: =IF(A53="","",SUMIFS(T_Penjualan!$H$6:$H$1505,T_Penjualan!$G$6:$G$1505,A53,T_Penjualan!$B$6:$B$1505,"Order",T_Penjualan!$A$6:$A$1505,">="&I_Parameter!$C$4,T_Penjualan!$A$6:$A$1505,"<="&I_Parameter!$C$6)) | U53: =IF(A53="","",S53-T53) | V53: =IF(A53="","",MIN(H53:N53)) | W53: =IF(A53="","",INDEX(I_Master!$F$6:$F$85,MATCH(A53,I_Master!$A$6:$A$85,0))) | X53: =IF(OR(A53="",W53=""),"",W53-Q53) | Y53: =IF(A53="","",S53*Q53) | Z53: =IF(A53="","",IF(V53<-0.5,"KURANG: stok minus "&ROUND(-V53,0)&" kg — beli/potong atau geser order",IF(AND(S53>0.5,T53<=0,G53>0.5),"JUAL: "&ROUND(S53,0)&" kg tanpa order, sebagian > batas umur",IF(AND(S53>0.5,T53<=0),"JUAL: "&ROUND(S53,0)&" kg tanpa order minggu ini",IF(G53>0.5,"PERHATIAN: "&ROUND(G53,0)&" kg di atas batas umur",IF(AND(X53<>"",X53<0,T53>0),"Order di bawah biaya rata-rata — cek harga","-"))))))
A54: =IF(I_Master!A54="","",I_Master!A54) | B54: =IF(A54="","",INDEX(I_Master!$E$6:$E$85,MATCH(A54,I_Master!$A$6:$A$85,0))) | C54: =IF(A54="","",INDEX(I_Master!$B$6:$B$85,MATCH(A54,I_Master!$A$6:$A$85,0))) | D54: =IF(A54="","",SUMIFS(I_Stok_Awal!$D$6:$D$305,I_Stok_Awal!$C$6:$C$305,A54)) | E54: =IF(A54="","",SUMIFS(I_Stok_Awal!$E$6:$E$305,I_Stok_Awal!$C$6:$C$305,A54)) | F54: =IF(OR(A54="",D54<=0),"",SUMPRODUCT((I_Stok_Awal!$C$6:$C$305=A54)*I_Stok_Awal!$D$6:$D$305*I_Stok_Awal!$F$6:$F$305)/D54) | G54: =IF(A54="","",SUMIFS(I_Stok_Awal!$G$6:$G$305,I_Stok_Awal!$C$6:$C$305,A54)) | H54: =IF($A54="","",D54+SUMIFS(T_Penerimaan!$I$6:$I$1005,T_Penerimaan!$H$6:$H$1005,$A54,T_Penerimaan!$A$6:$A$1005,H$4,T_Penerimaan!$M$6:$M$1005,1)-SUMIFS(T_Penjualan!$H$6:$H$1505,T_Penjualan!$G$6:$G$1505,$A54,T_Penjualan!$A$6:$A$1505,H$4,T_Penjualan!$P$6:$P$1505,1)) | I54: =IF($A54="","",H54+SUMIFS(T_Penerimaan!$I$6:$I$1005,T_Penerimaan!$H$6:$H$1005,$A54,T_Penerimaan!$A$6:$A$1005,I$4,T_Penerimaan!$M$6:$M$1005,1)-SUMIFS(T_Penjualan!$H$6:$H$1505,T_Penjualan!$G$6:$G$1505,$A54,T_Penjualan!$A$6:$A$1505,I$4,T_Penjualan!$P$6:$P$1505,1)) | J54: =IF($A54="","",I54+SUMIFS(T_Penerimaan!$I$6:$I$1005,T_Penerimaan!$H$6:$H$1005,$A54,T_Penerimaan!$A$6:$A$1005,J$4,T_Penerimaan!$M$6:$M$1005,1)-SUMIFS(T_Penjualan!$H$6:$H$1505,T_Penjualan!$G$6:$G$1505,$A54,T_Penjualan!$A$6:$A$1505,J$4,T_Penjualan!$P$6:$P$1505,1)) | K54: =IF($A54="","",J54+SUMIFS(T_Penerimaan!$I$6:$I$1005,T_Penerimaan!$H$6:$H$1005,$A54,T_Penerimaan!$A$6:$A$1005,K$4,T_Penerimaan!$M$6:$M$1005,1)-SUMIFS(T_Penjualan!$H$6:$H$1505,T_Penjualan!$G$6:$G$1505,$A54,T_Penjualan!$A$6:$A$1505,K$4,T_Penjualan!$P$6:$P$1505,1)) | L54: =IF($A54="","",K54+SUMIFS(T_Penerimaan!$I$6:$I$1005,T_Penerimaan!$H$6:$H$1005,$A54,T_Penerimaan!$A$6:$A$1005,L$4,T_Penerimaan!$M$6:$M$1005,1)-SUMIFS(T_Penjualan!$H$6:$H$1505,T_Penjualan!$G$6:$G$1505,$A54,T_Penjualan!$A$6:$A$1505,L$4,T_Penjualan!$P$6:$P$1505,1)) | M54: =IF($A54="","",L54+SUMIFS(T_Penerimaan!$I$6:$I$1005,T_Penerimaan!$H$6:$H$1005,$A54,T_Penerimaan!$A$6:$A$1005,M$4,T_Penerimaan!$M$6:$M$1005,1)-SUMIFS(T_Penjualan!$H$6:$H$1505,T_Penjualan!$G$6:$G$1505,$A54,T_Penjualan!$A$6:$A$1505,M$4,T_Penjualan!$P$6:$P$1505,1)) | N54: =IF($A54="","",M54+SUMIFS(T_Penerimaan!$I$6:$I$1005,T_Penerimaan!$H$6:$H$1005,$A54,T_Penerimaan!$A$6:$A$1005,N$4,T_Penerimaan!$M$6:$M$1005,1)-SUMIFS(T_Penjualan!$H$6:$H$1505,T_Penjualan!$G$6:$G$1505,$A54,T_Penjualan!$A$6:$A$1505,N$4,T_Penjualan!$P$6:$P$1505,1)) | O54: =IF(A54="","",SUMIFS(T_Penerimaan!$I$6:$I$1005,T_Penerimaan!$H$6:$H$1005,A54,T_Penerimaan!$M$6:$M$1005,1)) | P54: =IF(A54="","",SUMIFS(T_Penerimaan!$K$6:$K$1005,T_Penerimaan!$H$6:$H$1005,A54,T_Penerimaan!$M$6:$M$1005,1)) | Q54: =IF(A54="","",IF(D54+O54<=0,0,(E54+P54)/(D54+O54))) | R54: =IF(A54="","",SUMIFS(T_Penjualan!$H$6:$H$1505,T_Penjualan!$G$6:$G$1505,A54,T_Penjualan!$P$6:$P$1505,1)) | S54: =IF(A54="","",IF(I_Parameter!$C$4<=I_Parameter!$C$5,D54,IF(I_Parameter!$C$4>I_Parameter!$C$6,N54,INDEX(H54:N54,I_Parameter!$C$4-I_Parameter!$C$5)))) | T54: =IF(A54="","",SUMIFS(T_Penjualan!$H$6:$H$1505,T_Penjualan!$G$6:$G$1505,A54,T_Penjualan!$B$6:$B$1505,"Order",T_Penjualan!$A$6:$A$1505,">="&I_Parameter!$C$4,T_Penjualan!$A$6:$A$1505,"<="&I_Parameter!$C$6)) | U54: =IF(A54="","",S54-T54) | V54: =IF(A54="","",MIN(H54:N54)) | W54: =IF(A54="","",INDEX(I_Master!$F$6:$F$85,MATCH(A54,I_Master!$A$6:$A$85,0))) | X54: =IF(OR(A54="",W54=""),"",W54-Q54) | Y54: =IF(A54="","",S54*Q54) | Z54: =IF(A54="","",IF(V54<-0.5,"KURANG: stok minus "&ROUND(-V54,0)&" kg — beli/potong atau geser order",IF(AND(S54>0.5,T54<=0,G54>0.5),"JUAL: "&ROUND(S54,0)&" kg tanpa order, sebagian > batas umur",IF(AND(S54>0.5,T54<=0),"JUAL: "&ROUND(S54,0)&" kg tanpa order minggu ini",IF(G54>0.5,"PERHATIAN: "&ROUND(G54,0)&" kg di atas batas umur",IF(AND(X54<>"",X54<0,T54>0),"Order di bawah biaya rata-rata — cek harga","-"))))))
A55: =IF(I_Master!A55="","",I_Master!A55) | B55: =IF(A55="","",INDEX(I_Master!$E$6:$E$85,MATCH(A55,I_Master!$A$6:$A$85,0))) | C55: =IF(A55="","",INDEX(I_Master!$B$6:$B$85,MATCH(A55,I_Master!$A$6:$A$85,0))) | D55: =IF(A55="","",SUMIFS(I_Stok_Awal!$D$6:$D$305,I_Stok_Awal!$C$6:$C$305,A55)) | E55: =IF(A55="","",SUMIFS(I_Stok_Awal!$E$6:$E$305,I_Stok_Awal!$C$6:$C$305,A55)) | F55: =IF(OR(A55="",D55<=0),"",SUMPRODUCT((I_Stok_Awal!$C$6:$C$305=A55)*I_Stok_Awal!$D$6:$D$305*I_Stok_Awal!$F$6:$F$305)/D55) | G55: =IF(A55="","",SUMIFS(I_Stok_Awal!$G$6:$G$305,I_Stok_Awal!$C$6:$C$305,A55)) | H55: =IF($A55="","",D55+SUMIFS(T_Penerimaan!$I$6:$I$1005,T_Penerimaan!$H$6:$H$1005,$A55,T_Penerimaan!$A$6:$A$1005,H$4,T_Penerimaan!$M$6:$M$1005,1)-SUMIFS(T_Penjualan!$H$6:$H$1505,T_Penjualan!$G$6:$G$1505,$A55,T_Penjualan!$A$6:$A$1505,H$4,T_Penjualan!$P$6:$P$1505,1)) | I55: =IF($A55="","",H55+SUMIFS(T_Penerimaan!$I$6:$I$1005,T_Penerimaan!$H$6:$H$1005,$A55,T_Penerimaan!$A$6:$A$1005,I$4,T_Penerimaan!$M$6:$M$1005,1)-SUMIFS(T_Penjualan!$H$6:$H$1505,T_Penjualan!$G$6:$G$1505,$A55,T_Penjualan!$A$6:$A$1505,I$4,T_Penjualan!$P$6:$P$1505,1)) | J55: =IF($A55="","",I55+SUMIFS(T_Penerimaan!$I$6:$I$1005,T_Penerimaan!$H$6:$H$1005,$A55,T_Penerimaan!$A$6:$A$1005,J$4,T_Penerimaan!$M$6:$M$1005,1)-SUMIFS(T_Penjualan!$H$6:$H$1505,T_Penjualan!$G$6:$G$1505,$A55,T_Penjualan!$A$6:$A$1505,J$4,T_Penjualan!$P$6:$P$1505,1)) | K55: =IF($A55="","",J55+SUMIFS(T_Penerimaan!$I$6:$I$1005,T_Penerimaan!$H$6:$H$1005,$A55,T_Penerimaan!$A$6:$A$1005,K$4,T_Penerimaan!$M$6:$M$1005,1)-SUMIFS(T_Penjualan!$H$6:$H$1505,T_Penjualan!$G$6:$G$1505,$A55,T_Penjualan!$A$6:$A$1505,K$4,T_Penjualan!$P$6:$P$1505,1)) | L55: =IF($A55="","",K55+SUMIFS(T_Penerimaan!$I$6:$I$1005,T_Penerimaan!$H$6:$H$1005,$A55,T_Penerimaan!$A$6:$A$1005,L$4,T_Penerimaan!$M$6:$M$1005,1)-SUMIFS(T_Penjualan!$H$6:$H$1505,T_Penjualan!$G$6:$G$1505,$A55,T_Penjualan!$A$6:$A$1505,L$4,T_Penjualan!$P$6:$P$1505,1)) | M55: =IF($A55="","",L55+SUMIFS(T_Penerimaan!$I$6:$I$1005,T_Penerimaan!$H$6:$H$1005,$A55,T_Penerimaan!$A$6:$A$1005,M$4,T_Penerimaan!$M$6:$M$1005,1)-SUMIFS(T_Penjualan!$H$6:$H$1505,T_Penjualan!$G$6:$G$1505,$A55,T_Penjualan!$A$6:$A$1505,M$4,T_Penjualan!$P$6:$P$1505,1)) | N55: =IF($A55="","",M55+SUMIFS(T_Penerimaan!$I$6:$I$1005,T_Penerimaan!$H$6:$H$1005,$A55,T_Penerimaan!$A$6:$A$1005,N$4,T_Penerimaan!$M$6:$M$1005,1)-SUMIFS(T_Penjualan!$H$6:$H$1505,T_Penjualan!$G$6:$G$1505,$A55,T_Penjualan!$A$6:$A$1505,N$4,T_Penjualan!$P$6:$P$1505,1)) | O55: =IF(A55="","",SUMIFS(T_Penerimaan!$I$6:$I$1005,T_Penerimaan!$H$6:$H$1005,A55,T_Penerimaan!$M$6:$M$1005,1)) | P55: =IF(A55="","",SUMIFS(T_Penerimaan!$K$6:$K$1005,T_Penerimaan!$H$6:$H$1005,A55,T_Penerimaan!$M$6:$M$1005,1)) | Q55: =IF(A55="","",IF(D55+O55<=0,0,(E55+P55)/(D55+O55))) | R55: =IF(A55="","",SUMIFS(T_Penjualan!$H$6:$H$1505,T_Penjualan!$G$6:$G$1505,A55,T_Penjualan!$P$6:$P$1505,1)) | S55: =IF(A55="","",IF(I_Parameter!$C$4<=I_Parameter!$C$5,D55,IF(I_Parameter!$C$4>I_Parameter!$C$6,N55,INDEX(H55:N55,I_Parameter!$C$4-I_Parameter!$C$5)))) | T55: =IF(A55="","",SUMIFS(T_Penjualan!$H$6:$H$1505,T_Penjualan!$G$6:$G$1505,A55,T_Penjualan!$B$6:$B$1505,"Order",T_Penjualan!$A$6:$A$1505,">="&I_Parameter!$C$4,T_Penjualan!$A$6:$A$1505,"<="&I_Parameter!$C$6)) | U55: =IF(A55="","",S55-T55) | V55: =IF(A55="","",MIN(H55:N55)) | W55: =IF(A55="","",INDEX(I_Master!$F$6:$F$85,MATCH(A55,I_Master!$A$6:$A$85,0))) | X55: =IF(OR(A55="",W55=""),"",W55-Q55) | Y55: =IF(A55="","",S55*Q55) | Z55: =IF(A55="","",IF(V55<-0.5,"KURANG: stok minus "&ROUND(-V55,0)&" kg — beli/potong atau geser order",IF(AND(S55>0.5,T55<=0,G55>0.5),"JUAL: "&ROUND(S55,0)&" kg tanpa order, sebagian > batas umur",IF(AND(S55>0.5,T55<=0),"JUAL: "&ROUND(S55,0)&" kg tanpa order minggu ini",IF(G55>0.5,"PERHATIAN: "&ROUND(G55,0)&" kg di atas batas umur",IF(AND(X55<>"",X55<0,T55>0),"Order di bawah biaya rata-rata — cek harga","-"))))))
A56: =IF(I_Master!A56="","",I_Master!A56) | B56: =IF(A56="","",INDEX(I_Master!$E$6:$E$85,MATCH(A56,I_Master!$A$6:$A$85,0))) | C56: =IF(A56="","",INDEX(I_Master!$B$6:$B$85,MATCH(A56,I_Master!$A$6:$A$85,0))) | D56: =IF(A56="","",SUMIFS(I_Stok_Awal!$D$6:$D$305,I_Stok_Awal!$C$6:$C$305,A56)) | E56: =IF(A56="","",SUMIFS(I_Stok_Awal!$E$6:$E$305,I_Stok_Awal!$C$6:$C$305,A56)) | F56: =IF(OR(A56="",D56<=0),"",SUMPRODUCT((I_Stok_Awal!$C$6:$C$305=A56)*I_Stok_Awal!$D$6:$D$305*I_Stok_Awal!$F$6:$F$305)/D56) | G56: =IF(A56="","",SUMIFS(I_Stok_Awal!$G$6:$G$305,I_Stok_Awal!$C$6:$C$305,A56)) | H56: =IF($A56="","",D56+SUMIFS(T_Penerimaan!$I$6:$I$1005,T_Penerimaan!$H$6:$H$1005,$A56,T_Penerimaan!$A$6:$A$1005,H$4,T_Penerimaan!$M$6:$M$1005,1)-SUMIFS(T_Penjualan!$H$6:$H$1505,T_Penjualan!$G$6:$G$1505,$A56,T_Penjualan!$A$6:$A$1505,H$4,T_Penjualan!$P$6:$P$1505,1)) | I56: =IF($A56="","",H56+SUMIFS(T_Penerimaan!$I$6:$I$1005,T_Penerimaan!$H$6:$H$1005,$A56,T_Penerimaan!$A$6:$A$1005,I$4,T_Penerimaan!$M$6:$M$1005,1)-SUMIFS(T_Penjualan!$H$6:$H$1505,T_Penjualan!$G$6:$G$1505,$A56,T_Penjualan!$A$6:$A$1505,I$4,T_Penjualan!$P$6:$P$1505,1)) | J56: =IF($A56="","",I56+SUMIFS(T_Penerimaan!$I$6:$I$1005,T_Penerimaan!$H$6:$H$1005,$A56,T_Penerimaan!$A$6:$A$1005,J$4,T_Penerimaan!$M$6:$M$1005,1)-SUMIFS(T_Penjualan!$H$6:$H$1505,T_Penjualan!$G$6:$G$1505,$A56,T_Penjualan!$A$6:$A$1505,J$4,T_Penjualan!$P$6:$P$1505,1)) | K56: =IF($A56="","",J56+SUMIFS(T_Penerimaan!$I$6:$I$1005,T_Penerimaan!$H$6:$H$1005,$A56,T_Penerimaan!$A$6:$A$1005,K$4,T_Penerimaan!$M$6:$M$1005,1)-SUMIFS(T_Penjualan!$H$6:$H$1505,T_Penjualan!$G$6:$G$1505,$A56,T_Penjualan!$A$6:$A$1505,K$4,T_Penjualan!$P$6:$P$1505,1)) | L56: =IF($A56="","",K56+SUMIFS(T_Penerimaan!$I$6:$I$1005,T_Penerimaan!$H$6:$H$1005,$A56,T_Penerimaan!$A$6:$A$1005,L$4,T_Penerimaan!$M$6:$M$1005,1)-SUMIFS(T_Penjualan!$H$6:$H$1505,T_Penjualan!$G$6:$G$1505,$A56,T_Penjualan!$A$6:$A$1505,L$4,T_Penjualan!$P$6:$P$1505,1)) | M56: =IF($A56="","",L56+SUMIFS(T_Penerimaan!$I$6:$I$1005,T_Penerimaan!$H$6:$H$1005,$A56,T_Penerimaan!$A$6:$A$1005,M$4,T_Penerimaan!$M$6:$M$1005,1)-SUMIFS(T_Penjualan!$H$6:$H$1505,T_Penjualan!$G$6:$G$1505,$A56,T_Penjualan!$A$6:$A$1505,M$4,T_Penjualan!$P$6:$P$1505,1)) | N56: =IF($A56="","",M56+SUMIFS(T_Penerimaan!$I$6:$I$1005,T_Penerimaan!$H$6:$H$1005,$A56,T_Penerimaan!$A$6:$A$1005,N$4,T_Penerimaan!$M$6:$M$1005,1)-SUMIFS(T_Penjualan!$H$6:$H$1505,T_Penjualan!$G$6:$G$1505,$A56,T_Penjualan!$A$6:$A$1505,N$4,T_Penjualan!$P$6:$P$1505,1)) | O56: =IF(A56="","",SUMIFS(T_Penerimaan!$I$6:$I$1005,T_Penerimaan!$H$6:$H$1005,A56,T_Penerimaan!$M$6:$M$1005,1)) | P56: =IF(A56="","",SUMIFS(T_Penerimaan!$K$6:$K$1005,T_Penerimaan!$H$6:$H$1005,A56,T_Penerimaan!$M$6:$M$1005,1)) | Q56: =IF(A56="","",IF(D56+O56<=0,0,(E56+P56)/(D56+O56))) | R56: =IF(A56="","",SUMIFS(T_Penjualan!$H$6:$H$1505,T_Penjualan!$G$6:$G$1505,A56,T_Penjualan!$P$6:$P$1505,1)) | S56: =IF(A56="","",IF(I_Parameter!$C$4<=I_Parameter!$C$5,D56,IF(I_Parameter!$C$4>I_Parameter!$C$6,N56,INDEX(H56:N56,I_Parameter!$C$4-I_Parameter!$C$5)))) | T56: =IF(A56="","",SUMIFS(T_Penjualan!$H$6:$H$1505,T_Penjualan!$G$6:$G$1505,A56,T_Penjualan!$B$6:$B$1505,"Order",T_Penjualan!$A$6:$A$1505,">="&I_Parameter!$C$4,T_Penjualan!$A$6:$A$1505,"<="&I_Parameter!$C$6)) | U56: =IF(A56="","",S56-T56) | V56: =IF(A56="","",MIN(H56:N56)) | W56: =IF(A56="","",INDEX(I_Master!$F$6:$F$85,MATCH(A56,I_Master!$A$6:$A$85,0))) | X56: =IF(OR(A56="",W56=""),"",W56-Q56) | Y56: =IF(A56="","",S56*Q56) | Z56: =IF(A56="","",IF(V56<-0.5,"KURANG: stok minus "&ROUND(-V56,0)&" kg — beli/potong atau geser order",IF(AND(S56>0.5,T56<=0,G56>0.5),"JUAL: "&ROUND(S56,0)&" kg tanpa order, sebagian > batas umur",IF(AND(S56>0.5,T56<=0),"JUAL: "&ROUND(S56,0)&" kg tanpa order minggu ini",IF(G56>0.5,"PERHATIAN: "&ROUND(G56,0)&" kg di atas batas umur",IF(AND(X56<>"",X56<0,T56>0),"Order di bawah biaya rata-rata — cek harga","-"))))))
A57: =IF(I_Master!A57="","",I_Master!A57) | B57: =IF(A57="","",INDEX(I_Master!$E$6:$E$85,MATCH(A57,I_Master!$A$6:$A$85,0))) | C57: =IF(A57="","",INDEX(I_Master!$B$6:$B$85,MATCH(A57,I_Master!$A$6:$A$85,0))) | D57: =IF(A57="","",SUMIFS(I_Stok_Awal!$D$6:$D$305,I_Stok_Awal!$C$6:$C$305,A57)) | E57: =IF(A57="","",SUMIFS(I_Stok_Awal!$E$6:$E$305,I_Stok_Awal!$C$6:$C$305,A57)) | F57: =IF(OR(A57="",D57<=0),"",SUMPRODUCT((I_Stok_Awal!$C$6:$C$305=A57)*I_Stok_Awal!$D$6:$D$305*I_Stok_Awal!$F$6:$F$305)/D57) | G57: =IF(A57="","",SUMIFS(I_Stok_Awal!$G$6:$G$305,I_Stok_Awal!$C$6:$C$305,A57)) | H57: =IF($A57="","",D57+SUMIFS(T_Penerimaan!$I$6:$I$1005,T_Penerimaan!$H$6:$H$1005,$A57,T_Penerimaan!$A$6:$A$1005,H$4,T_Penerimaan!$M$6:$M$1005,1)-SUMIFS(T_Penjualan!$H$6:$H$1505,T_Penjualan!$G$6:$G$1505,$A57,T_Penjualan!$A$6:$A$1505,H$4,T_Penjualan!$P$6:$P$1505,1)) | I57: =IF($A57="","",H57+SUMIFS(T_Penerimaan!$I$6:$I$1005,T_Penerimaan!$H$6:$H$1005,$A57,T_Penerimaan!$A$6:$A$1005,I$4,T_Penerimaan!$M$6:$M$1005,1)-SUMIFS(T_Penjualan!$H$6:$H$1505,T_Penjualan!$G$6:$G$1505,$A57,T_Penjualan!$A$6:$A$1505,I$4,T_Penjualan!$P$6:$P$1505,1)) | J57: =IF($A57="","",I57+SUMIFS(T_Penerimaan!$I$6:$I$1005,T_Penerimaan!$H$6:$H$1005,$A57,T_Penerimaan!$A$6:$A$1005,J$4,T_Penerimaan!$M$6:$M$1005,1)-SUMIFS(T_Penjualan!$H$6:$H$1505,T_Penjualan!$G$6:$G$1505,$A57,T_Penjualan!$A$6:$A$1505,J$4,T_Penjualan!$P$6:$P$1505,1)) | K57: =IF($A57="","",J57+SUMIFS(T_Penerimaan!$I$6:$I$1005,T_Penerimaan!$H$6:$H$1005,$A57,T_Penerimaan!$A$6:$A$1005,K$4,T_Penerimaan!$M$6:$M$1005,1)-SUMIFS(T_Penjualan!$H$6:$H$1505,T_Penjualan!$G$6:$G$1505,$A57,T_Penjualan!$A$6:$A$1505,K$4,T_Penjualan!$P$6:$P$1505,1)) | L57: =IF($A57="","",K57+SUMIFS(T_Penerimaan!$I$6:$I$1005,T_Penerimaan!$H$6:$H$1005,$A57,T_Penerimaan!$A$6:$A$1005,L$4,T_Penerimaan!$M$6:$M$1005,1)-SUMIFS(T_Penjualan!$H$6:$H$1505,T_Penjualan!$G$6:$G$1505,$A57,T_Penjualan!$A$6:$A$1505,L$4,T_Penjualan!$P$6:$P$1505,1)) | M57: =IF($A57="","",L57+SUMIFS(T_Penerimaan!$I$6:$I$1005,T_Penerimaan!$H$6:$H$1005,$A57,T_Penerimaan!$A$6:$A$1005,M$4,T_Penerimaan!$M$6:$M$1005,1)-SUMIFS(T_Penjualan!$H$6:$H$1505,T_Penjualan!$G$6:$G$1505,$A57,T_Penjualan!$A$6:$A$1505,M$4,T_Penjualan!$P$6:$P$1505,1)) | N57: =IF($A57="","",M57+SUMIFS(T_Penerimaan!$I$6:$I$1005,T_Penerimaan!$H$6:$H$1005,$A57,T_Penerimaan!$A$6:$A$1005,N$4,T_Penerimaan!$M$6:$M$1005,1)-SUMIFS(T_Penjualan!$H$6:$H$1505,T_Penjualan!$G$6:$G$1505,$A57,T_Penjualan!$A$6:$A$1505,N$4,T_Penjualan!$P$6:$P$1505,1)) | O57: =IF(A57="","",SUMIFS(T_Penerimaan!$I$6:$I$1005,T_Penerimaan!$H$6:$H$1005,A57,T_Penerimaan!$M$6:$M$1005,1)) | P57: =IF(A57="","",SUMIFS(T_Penerimaan!$K$6:$K$1005,T_Penerimaan!$H$6:$H$1005,A57,T_Penerimaan!$M$6:$M$1005,1)) | Q57: =IF(A57="","",IF(D57+O57<=0,0,(E57+P57)/(D57+O57))) | R57: =IF(A57="","",SUMIFS(T_Penjualan!$H$6:$H$1505,T_Penjualan!$G$6:$G$1505,A57,T_Penjualan!$P$6:$P$1505,1)) | S57: =IF(A57="","",IF(I_Parameter!$C$4<=I_Parameter!$C$5,D57,IF(I_Parameter!$C$4>I_Parameter!$C$6,N57,INDEX(H57:N57,I_Parameter!$C$4-I_Parameter!$C$5)))) | T57: =IF(A57="","",SUMIFS(T_Penjualan!$H$6:$H$1505,T_Penjualan!$G$6:$G$1505,A57,T_Penjualan!$B$6:$B$1505,"Order",T_Penjualan!$A$6:$A$1505,">="&I_Parameter!$C$4,T_Penjualan!$A$6:$A$1505,"<="&I_Parameter!$C$6)) | U57: =IF(A57="","",S57-T57) | V57: =IF(A57="","",MIN(H57:N57)) | W57: =IF(A57="","",INDEX(I_Master!$F$6:$F$85,MATCH(A57,I_Master!$A$6:$A$85,0))) | X57: =IF(OR(A57="",W57=""),"",W57-Q57) | Y57: =IF(A57="","",S57*Q57) | Z57: =IF(A57="","",IF(V57<-0.5,"KURANG: stok minus "&ROUND(-V57,0)&" kg — beli/potong atau geser order",IF(AND(S57>0.5,T57<=0,G57>0.5),"JUAL: "&ROUND(S57,0)&" kg tanpa order, sebagian > batas umur",IF(AND(S57>0.5,T57<=0),"JUAL: "&ROUND(S57,0)&" kg tanpa order minggu ini",IF(G57>0.5,"PERHATIAN: "&ROUND(G57,0)&" kg di atas batas umur",IF(AND(X57<>"",X57<0,T57>0),"Order di bawah biaya rata-rata — cek harga","-"))))))
